Workbook
Name \a: #REF!
Name \a: #REF!
Name \a: #REF!
Name \a: #REF!
Name \c: [1]FLASH!#REF!
Name \c: [1]FLASH!#REF!
Name \c: [1]FLASH!#REF!
Name \c: [1]FLASH!#REF!
Name \f: [1]FLASH!#REF!
Name \f: [1]FLASH!#REF!
Name \f: [1]FLASH!#REF!
Name \f: [1]FLASH!#REF!
Name \q: [1]FLASH!#REF!
Name \q: [1]FLASH!#REF!
Name \q: [1]FLASH!#REF!
Name \q: [1]FLASH!#REF!
Name \s: #REF!
Name \s: #REF!
Name \s: #REF!
Name \s: #REF!
Name \t: [1]FLASH!#REF!
Name \t: [1]FLASH!#REF!
Name \t: [1]FLASH!#REF!
Name \t: [1]FLASH!#REF!
Name \u: #REF!
Name \u: #REF!
Name \u: #REF!
Name \u: #REF!
Name \z: #REF!
Name _1: #REF!
Name _1: #REF!
Name _1: #REF!
Name _1: #REF!
Name _2: #REF!
Name _2: #REF!
Name _2: #REF!
Name _2: #REF!
Name _3: #REF!
Name _3: #REF!
Name _3: #REF!
Name _3: #REF!
Name A: #REF!
Name A: #REF!
Name A: #REF!
Name A: #REF!
Name Audit_adj: [2]validation!$I$9
Name Audit_adj_LY: [2]validation_LY!$I$9
Name Axis: OFFSET(#REF!,0,0,MAX(#REF!),1)
Name Axis: OFFSET(#REF!,0,0,MAX(#REF!),1)
Name Axis: OFFSET(#REF!,0,0,MAX(#REF!),1)
Name Axis: OFFSET(#REF!,0,0,MAX(#REF!),1)
Name Axis1: OFFSET(#REF!,0,0,MAX(#REF!),1)
Name Axis1: OFFSET(#REF!,0,0,MAX(#REF!),1)
Name Axis1: OFFSET(#REF!,0,0,MAX(#REF!),1)
Name Axis1: OFFSET(#REF!,0,0,MAX(#REF!),1)
Name B: #REF!
Name B: #REF!
Name B: #REF!
Name B: #REF!
Name BUDGETM: '[3]Budget By Month'!$E$7:$R$83

Sheet IS Feb KSA
I4: 8980975.6 | Z4: 8980975.6
I5: =I4-I12 -> 8980975.6 | Z5: =Z4-Z12 -> 1267.92
B7: INCOME STATEMENT (KSA SAR) | C7: YTD | D7: Q4 | E7: MTD | F7: MTD | G7: MTD | H7: Q3 | I7: MTD | J7: MTD | K7: MTD | L7: Q2 | M7: MTD | N7: MTD | O7: MTD | P7: Q1 | Q7: MTD | R7: MTD | S7: MTD | T7: YTD | U7: Q4 | V7: MTD | W7: MTD | X7: MTD | Y7: Q3 | Z7: MTD | AA7: MTD | AB7: MTD | AC7: Q2 | AD7: MTD | AE7: MTD | AF7: MTD | AG7: Q1 | AH7: MTD | AI7: MTD | AJ7: MTD | AL7: MTD | AM7: YTD
B8: FOR THE PERIOD 28 Feb 2026 | C8: 2026 | D8: 2026 | E8: 46387 | F8: 46356 | G8: 46326 | H8: 2026 | I8: 46295 | J8: 46265 | K8: 46234 | L8: 2026 | M8: 46203 | N8: 46173 | O8: 46142 | P8: 2026 | Q8: 46112 | R8: 46081 | S8: 46053 | T8: 2025 | U8: 2025 | V8: 46022 | W8: 45991 | X8: 45961 | Y8: 2025 | Z8: 45930 | AA8: 45900 | AB8: 45869 | AC8: 2025 | AD8: 45838 | AE8: 45808 | AF8: 45777 | AG8: 2025 | AH8: 45747 | AI8: 45716 | AJ8: 45688 | AL8: 45657 | AM8: 2024
B10: Sales | C10: =SUM(D10:S10)-P10-L10-H10-D10 -> 32825790 | D10: =SUM(E10:G10) -> 0 | H10: =SUM(I10:K10) -> 0 | L10: =SUM(M10:O10) -> 0 | P10: =SUM(Q10:S10) -> 32825790 | R10: 16439013 | S10: 16386777 | T10: =SUM(U10:AJ10)-AG10-AC10-Y10-U10 -> 1.578257e+08 | U10: =SUM(V10:X10) -> 54905864 | V10: 20791023 | W10: 18885652 | X10: =15268743.82-39555.14 -> 15229189 | Y10: =SUM(Z10:AB10) -> 37535436 | Z10: 9966234.8 | AA10: 7379008.3 | AB10: 20190193 | AC10: =SUM(AD10:AF10) -> 32972335 | AD10: 11726376 | AE10: 11371331 | AF10: 9874628.2 | AG10: =SUM(AH10:AJ10) -> 32412070 | AH10: 13667110 | AI10: 10659013 | AJ10: 8085946.4 | AL10: 10080211 | AM10: 76420880
B11: Sales Discount | C11: =SUM(D11:S11)-P11-L11-H11-D11 -> 14516.1 | H11: =SUM(I11:K11) -> 0 | L11: =SUM(M11:O11) -> 0 | P11: =SUM(Q11:S11) -> 14516.1 | R11: 14516.1 | S11: 0 | T11: =SUM(U11:AJ11)-AG11-AC11-Y11-U11 -> 82363.38 | V11: 0 | X11: 0 | Y11: =SUM(Z11:AB11) -> 0 | Z11: 0 | AA11: 0 | AB11: 0 | AC11: =SUM(AD11:AF11) -> 82363.38 | AD11: -7558.83 | AE11: 78283.38 | AF11: 11638.83
B12: Cost of Goods Sold | C12: =SUM(D12:S12)-P12-L12-H12-D12 -> 29328846 | D12: =SUM(E12:G12) -> 0 | H12: =SUM(I12:K12) -> 0 | L12: =SUM(M12:O12) -> 0 | P12: =SUM(Q12:S12) -> 29328846 | R12: 14552433 | S12: 14776413 | T12: =SUM(U12:AJ12)-AG12-AC12-Y12-U12 -> 1.4091252e+08 | U12: =SUM(V12:X12) -> 48616545 | V12: 18140835 | W12: 16962082 | X12: 13513628 | Y12: =SUM(Z12:AB12) -> 33436502 | Z12: 8979707.7 | AA12: 6625405.5 | AB12: 17831388 | AC12: =SUM(AD12:AF12) -> 29582790 | AD12: 10608445 | AE12: 10128323 | AF12: 8846021.3 | AG12: =SUM(AH12:AJ12) -> 29276685 | AH12: 12403281 | AI12: 9631833 | AJ12: 7241571.2 | AL12: 9065157.9 | AM12: 69127802
B13: Purchase Discounts | C13: =SUM(D13:S13)-P13-L13-H13-D13 -> -88806.57 | D13: =SUM(E13:G13) -> 0 | H13: =SUM(I13:K13) -> 0 | I13: 0 | J13: 0 | K13: 0 | L13: =SUM(M13:O13) -> 0 | P13: =SUM(Q13:S13) -> -88806.57 | R13: -12857.77 | S13: -75948.8 | T13: =SUM(U13:AJ13)-AG13-AC13-Y13-U13 -> -222027.19 | U13: =SUM(V13:X13) -> -148153.36 | V13: -131612.06 | W13: -14990.36 | X13: -1550.94 | Y13: =SUM(Z13:AB13) -> 0 | Z13: 0 | AA13: 0 | AB13: 0 | AC13: =SUM(AD13:AF13) -> -62005.67 | AD13: 0 | AE13: -62005.67 | AF13: 0 | AG13: =SUM(AH13:AJ13) -> -11868.16 | AH13: -7728.16 | AI13: -4140 | AJ13: 0 | AL13: 0 | AM13: -93226.45
B14: Gross Profit / (Loss) | C14: =+C10-C11-(C12+C13) -> 3571235 | D14: =+D10-D11-(D12+D13) -> 0 | E14: =+E10-E11-(E12+E13) -> 0 | F14: =+F10-F11-(F12+F13) -> 0 | G14: =+G10-G11-(G12+G13) -> 0 | H14: =+H10-H11-(H12+H13) -> 0 | I14: =+I10-I11-(I12+I13) -> 0 | J14: =+J10-J11-(J12+J13) -> 0 | ... U14: =+U10-U11-(U12+U13) -> 6437472.5 | V14: =+V10-(V12+V13) -> 2781799.7 | W14: =+W10-(W12+W13) -> 1938560.6 | X14: =+X10-(X12+X13) -> 1717112.1 | Y14: =+Y10-(Y12+Y13) -> 4098934.8 | Z14: =+Z10-(Z12+Z13) -> 986527.13 | AA14: =+AA10-(AA12+AA13) -> 753602.78 | AB14: =+AB10-AB11-(AB12+AB13) -> 2358804.9 | AC14: =+AC10-AC11-(AC12+AC13) -> 3369187.1 | AD14: =+AD10-AD11-(AD12+AD13) -> 1125489.3 | AE14: =+AE10-AE11-(AE12+AE13) -> 1226729.8 | AF14: =+AF10-AF11-(AF12+AF13) -> 1016968 | AG14: =+AG10-(AG12+AG13) -> 3147252.4 | AH14: =+AH10-(AH12+AH13) -> 1271557.3 | AI14: =+AI10-(AI12+AI13) -> 1031319.9 | AJ14: =+AJ10-(AJ12+AJ13) -> 844375.15 | AL14: =+AL10-(AL12+AL13) -> 1015053.3 | AM14: =+AM10-(AM12+AM13) -> 7386304.4
B15: Other Income | C15: =SUM(D15:S15)-P15-L15-H15-D15 -> 0 | D15: =SUM(E15:G15) -> 0 | E15: 0 | G15: 0 | H15: =SUM(I15:K15) -> 0 | I15: 0 | J15: 0 | K15: 0 | L15: =SUM(M15:O15) -> 0 | M15: 0 | N15: 0 | O15: 0 | P15: =SUM(Q15:S15) -> 0 | T15: =SUM(U15:AJ15)-AG15-AC15-Y15-U15 -> 18000 | U15: =SUM(V15:X15) -> 0 | V15: 0 | X15: 0 | Y15: =SUM(Z15:AB15) -> 0 | Z15: 0 | AA15: 0 | AB15: 0 | AC15: =SUM(AD15:AF15) -> 0 | AD15: 0 | AE15: 0 | AF15: 0 | AG15: =SUM(AH15:AJ15) -> 18000 | AH15: 12000 | AI15: 6000 | AJ15: 0
B16: Consultation Income | C16: =+D16+H16+L16+P16 -> 0 | D16: =SUM(E16:G16) -> 0 | E16: 0 | G16: 0 | H16: =SUM(I16:K16) -> 0 | I16: 0 | J16: 0 | K16: 0 | L16: =SUM(M16:O16) -> 0 | M16: 0 | N16: 0 | O16: 0 | P16: =SUM(Q16:S16) -> 0 | T16: =+U16+Y16+AC16+AG16 -> 65217.39 | U16: =SUM(V16:X16) -> 0 | V16: 0 | X16: 0 | Y16: =SUM(Z16:AB16) -> 0 | Z16: 0 | AA16: 0 | AB16: 0 | AC16: =SUM(AD16:AF16) -> 0 | AD16: 0 | AE16: 0 | AF16: 0 | AG16: =SUM(AH16:AJ16) -> 65217.39 | AH16: 0 | AI16: 0 | AJ16: 65217.39 | AL16: 26086.96 | AM16: 293478.27
B17: Gross Income | C17: =+D17+H17+L17+P17 -> 3571235 | D17: =+D16+D14 -> 0 | E17: =+E16+E14 -> 0 | F17: =+F16+F14 -> 0 | G17: =+G16+G14 -> 0 | H17: =SUM(I17:K17) -> 0 | I17: =+I16+I14 -> 0 | J17: =+J16+J14 -> 0 | K17: =+K16+K14 -> 0 | L17: =SUM(M17:O17) -> 0 | M17: =+M16+M14 -> 0 | N17: =+N16+N14 -> 0 | O17: =+O16+O14+O15 -> 0 | P17: =+P16+P14+P15 -> 3571235 | Q17: =+Q16+Q14+Q15 -> 0 | R17: =+R16+R14+R15 -> 1884921.5 | S17: =+S16+S14 -> 1686313.6 | T17: =+U17+Y17+AC17+AG17 -> 17136064 | U17: =+U16+U14 -> 6437472.5 | V17: =+V16+V14 -> 2781799.7 | W17: =+W16+W14 -> 1938560.6 | X17: =+X16+X14 -> 1717112.1 | Y17: =SUM(Z17:AB17) -> 4098934.8 | Z17: =+Z16+Z14 -> 986527.13 | AA17: =+AA16+AA14 -> 753602.78 | AB17: =+AB16+AB14 -> 2358804.9 | AC17: =SUM(AD17:AF17) -> 3369187.1 | AD17: =+AD16+AD14 -> 1125489.3 | AE17: =+AE16+AE14 -> 1226729.8 | AF17: =+AF16+AF14+AF15 -> 1016968 | AG17: =+AG16+AG14+AG15 -> 3230469.8 | AH17: =+AH16+AH14+AH15 -> 1283557.3 | AI17: =+AI16+AI14+AI15 -> 1037319.9 | AJ17: =+AJ16+AJ14 -> 909592.54 | AL17: =+AL16+AL14 -> 1041140.2 | AM17: =+AM16+AM14 -> 7679782.7
B19: General and Administrative Expenses | C19: =SUM(C20:C38) -> 330689.42 | D19: =SUM(D20:D38) -> 0 | E19: =SUM(E20:E38) -> 0 | F19: =SUM(F20:F38) -> 0 | G19: =SUM(G20:G38) -> 0 | H19: =SUM(H20:H38) -> 0 | I19: =SUM(I20:I38) -> 0 | J19: =SUM(J20:J38) -> 0 | ... AJ19: =SUM(AJ20:AJ38) -> 88485.15 | AL19: =SUM(AL20:AL38) -> 293429.8 | AM19: =SUM(AM20:AM38) -> 865548.78
B20: Bad Debt | C20: =SUM(D20:S20)-P20-L20-H20-D20 -> 114105.01 | D20: =SUM(E20:G20) -> 0 | H20: =SUM(I20:K20) -> 0 | L20: =SUM(M20:O20) -> 0 | P20: =SUM(Q20:S20) -> 114105.01 | R20: 0 | S20: 114105.01 | T20: =SUM(U20:AJ20)-AG20-AC20-Y20-U20 -> 2044438.5 | U20: =SUM(V20:X20) -> 1820446.2 | V20: 526062.9 | W20: 857099.96 | X20: 437283.39 | Y20: =SUM(Z20:AB20) -> 75000 | Z20: 25000 | AA20: 25000 | AB20: 25000 | AC20: =SUM(AD20:AF20) -> 73991.16 | AD20: 25000 | AE20: 23991.16 | AF20: 25000 | AG20: =SUM(AH20:AJ20) -> 75001.1 | AH20: 25000.8 | AI20: 25000.3 | AJ20: 25000 | AL20: 203009.5 | AM20: 203016.64
B21: Bank Fees and Charges | C21: =SUM(D21:S21)-P21-L21-H21-D21 -> 954.62 | D21: =SUM(E21:G21) -> 0 | H21: =SUM(I21:K21) -> 0 | L21: =SUM(M21:O21) -> 0 | P21: =SUM(Q21:S21) -> 954.62 | R21: 152.63 | S21: 801.99 | T21: =SUM(U21:AJ21)-AG21-AC21-Y21-U21 -> 10168.59 | U21: =SUM(V21:X21) -> 2486.04 | V21: 884.94 | W21: 797.09 | X21: 804.01 | Y21: =SUM(Z21:AB21) -> 1887.04 | Z21: 545.34 | AA21: 530.48 | AB21: 811.22 | AC21: =SUM(AD21:AF21) -> 3285.83 | AD21: 672.17 | AE21: 688.09 | AF21: 1925.57 | AG21: =SUM(AH21:AJ21) -> 2509.68 | AH21: 1049.44 | AI21: 852.65 | AJ21: 607.59 | AL21: 354.16 | AM21: 7108.25
B22: Office Supplies | C22: =SUM(D22:S22)-P22-L22-H22-D22 -> 11778.03 | D22: =SUM(E22:G22) -> 0 | H22: =SUM(I22:K22) -> 0 | L22: =SUM(M22:O22) -> 0 | P22: =SUM(Q22:S22) -> 11778.03 | R22: 5544.51 | S22: 6233.52 | T22: =SUM(U22:AJ22)-AG22-AC22-Y22-U22 -> 75454.71 | U22: =SUM(V22:X22) -> 18760.53 | V22: 4745.27 | W22: 6432.08 | X22: =47138.32-39555.14 -> 7583.18 | Y22: =SUM(Z22:AB22) -> 26652.27 | Z22: 9026.58 | AA22: 10858.29 | AB22: 6767.4 | AC22: =SUM(AD22:AF22) -> 17661.99 | AD22: 5457.01 | AE22: 9625.38 | AF22: 2579.6 | AG22: =SUM(AH22:AJ22) -> 12379.92 | AH22: 2845.92 | AI22: 5694.16 | AJ22: 3839.84 | AL22: 819.32 | AM22: 25690.34
B23: Office Utilities - Electricity/Water/Janitorial | C23: =SUM(D23:S23)-P23-L23-H23-D23 -> 0 | D23: =SUM(E23:G23) -> 0 | H23: =SUM(I23:K23) -> 0 | L23: =SUM(M23:O23) -> 0 | P23: =SUM(Q23:S23) -> 0 | R23: 0 | S23: 0 | T23: =SUM(U23:AJ23)-AG23-AC23-Y23-U23 -> 3541.19 | U23: =SUM(V23:X23) -> 0 | V23: 0 | W23: 0 | X23: 0 | Y23: =SUM(Z23:AB23) -> 1649.27 | Z23: 165.22 | AA23: 949.15 | AB23: 534.9 | AC23: =SUM(AD23:AF23) -> 1459.95 | AD23: 985.5 | AE23: 474.45 | AF23: 0 | AG23: =SUM(AH23:AJ23) -> 431.97 | AH23: 0 | AI23: 99.3 | AJ23: 332.67 | AL23: 4705.55 | AM23: 24609.21
B24: Office Expenses | C24: =SUM(D24:S24)-P24-L24-H24-D24 -> 24907.84 | D24: =SUM(E24:G24) -> 0 | H24: =SUM(I24:K24) -> 0 | L24: =SUM(M24:O24) -> 0 | P24: =SUM(Q24:S24) -> 24907.84 | R24: 7342.16 | S24: 17565.68 | T24: =SUM(U24:AJ24)-AG24-AC24-Y24-U24 -> 46991.43 | U24: =SUM(V24:X24) -> 23520.55 | V24: 3827.91 | W24: 9629.94 | X24: 10062.7 | Y24: =SUM(Z24:AB24) -> 12223.31 | Z24: 641.74 | AA24: 2711.91 | AB24: 8869.66 | AC24: =SUM(AD24:AF24) -> 11113.66 | AD24: 3687.1 | AE24: 3555.84 | AF24: 3870.72 | AG24: =SUM(AH24:AJ24) -> 133.91 | AH24: 0 | AI24: 133.91 | AJ24: 0 | AL24: 0 | AM24: 481
B25: Office Repair & Maintenance Expense | C25: =SUM(D25:S25)-P25-L25-H25-D25 -> 2985 | D25: =SUM(E25:G25) -> 0 | H25: =SUM(I25:K25) -> 0 | L25: =SUM(M25:O25) -> 0 | P25: =SUM(Q25:S25) -> 2985 | R25: 1560 | S25: 1425 | T25: =SUM(U25:AJ25)-AG25-AC25-Y25-U25 -> 16428.24 | U25: =SUM(V25:X25) -> 8126.67 | V25: 3560 | W25: 760 | X25: 3806.67 | Y25: =SUM(Z25:AB25) -> 8301.57 | Z25: 4237.61 | AA25: 4063.96
B26: Travel Expense | C26: =SUM(D26:S26)-P26-L26-H26-D26 -> 3957.14 | D26: =SUM(E26:G26) -> 0 | H26: =SUM(I26:K26) -> 0 | L26: =SUM(M26:O26) -> 0 | P26: =SUM(Q26:S26) -> 3957.14 | R26: 1007.81 | S26: 2949.33 | T26: =SUM(U26:AJ26)-AG26-AC26-Y26-U26 -> 17063.53 | U26: =SUM(V26:X26) -> 4459.33 | V26: 1943.78 | W26: 1292.13 | X26: 1223.42 | Y26: =SUM(Z26:AB26) -> 857.98 | Z26: 812.75 | AA26: 0 | AB26: 45.23 | AC26: =SUM(AD26:AF26) -> 3180.56 | AD26: 343.75 | AE26: 457.09 | AF26: 2379.72 | AG26: =SUM(AH26:AJ26) -> 8565.66 | AH26: 5067 | AI26: 3498.66 | AJ26: 0 | AL26: 3750 | AM26: 29931.99
B27: Printing and Stationery | C27: =SUM(D27:S27)-P27-L27-H27-D27 -> 702.7 | D27: =SUM(E27:G27) -> 0 | H27: =SUM(I27:K27) -> 0 | L27: =SUM(M27:O27) -> 0 | P27: =SUM(Q27:S27) -> 702.7 | R27: 359.54 | S27: 343.16 | T27: =SUM(U27:AJ27)-AG27-AC27-Y27-U27 -> 8193.6 | U27: =SUM(V27:X27) -> 2051 | V27: 0 | W27: 671 | X27: 1380 | Y27: =SUM(Z27:AB27) -> 4360.61 | Z27: 46 | AA27: 3717.22 | AB27: 597.39 | AC27: =SUM(AD27:AF27) -> 1671.99 | AD27: 1219.99 | AE27: 452 | AF27: 0 | AG27: =SUM(AH27:AJ27) -> 110 | AH27: 0 | AI27: 0 | AJ27: 110 | AL27: 241 | AM27: 4591.36
B28: Rent Expense (G&A) | C28: =SUM(D28:S28)-P28-L28-H28-D28 -> 33396.49 | D28: =SUM(E28:G28) -> 0 | H28: =SUM(I28:K28) -> 0 | L28: =SUM(M28:O28) -> 0 | P28: =SUM(Q28:S28) -> 33396.49 | R28: 10311.48 | S28: 23085.01 | T28: =SUM(U28:AJ28)-AG28-AC28-Y28-U28 -> 303572.58 | U28: =SUM(V28:X28) -> 71280.02 | V28: 23085.01 | W28: 24097.51 | X28: 24097.5 | Y28: =SUM(Z28:AB28) -> 74907.58 | Z28: 24097.5 | AA28: 24579.25 | AB28: 26230.83 | AC28: =SUM(AD28:AF28) -> 78692.49 | AD28: 26230.83 | AE28: 26230.83 | AF28: 26230.83 | AG28: =SUM(AH28:AJ28) -> 78692.49 | AH28: 26230.83 | AI28: 26230.83 | AJ28: 26230.83 | AL28: 32096.09 | AM28: 127377.94
B29: Meals and Entertainment | C29: =SUM(D29:S29)-P29-L29-H29-D29 -> 8019.85 | D29: =SUM(E29:G29) -> 0 | H29: =SUM(I29:K29) -> 0 | L29: =SUM(M29:O29) -> 0 | P29: =SUM(Q29:S29) -> 8019.85 | R29: 4127.03 | S29: 3892.82 | T29: =SUM(U29:AJ29)-AG29-AC29-Y29-U29 -> 84957.26 | U29: =SUM(V29:X29) -> 14808.57 | V29: 5215.28 | W29: 4527.88 | X29: 5065.41 | Y29: =SUM(Z29:AB29) -> 21110.6 | Z29: 10439.41 | AA29: 6048.24 | AB29: 4622.95 | AC29: =SUM(AD29:AF29) -> 18776.74 | AD29: 5737.6 | AE29: 5781.48 | AF29: 7257.66 | AG29: =SUM(AH29:AJ29) -> 30261.35 | AH29: 14668.43 | AI29: 5604.42 | AJ29: 9988.5 | AL29: 3897.75 | AM29: 84744.32
B30: Audit & Consultancy expense | C30: =SUM(D30:S30)-P30-L30-H30-D30 -> 0 | D30: =SUM(E30:G30) -> 0 | H30: =SUM(I30:K30) -> 0 | L30: =SUM(M30:O30) -> 0 | P30: =SUM(Q30:S30) -> 0 | R30: 0 | S30: 0 | T30: =SUM(U30:AJ30)-AG30-AC30-Y30-U30 -> 35000 | U30: =SUM(V30:X30) -> 35000 | V30: 35000 | W30: 0 | X30: 0 | Y30: =SUM(Z30:AB30) -> 0 | Z30: 0 | AA30: 0 | AB30: 0 | AC30: =SUM(AD30:AF30) -> 0 | AD30: 0 | AE30: 0 | AF30: 0 | AG30: =SUM(AH30:AJ30) -> 0 | AH30: 0 | AI30: 0 | AJ30: 0 | AL30: 17500 | AM30: 42500
B31: Communication Exp - Mobile & Internet | C31: =SUM(D31:S31)-P31-L31-H31-D31 -> 18883.31 | D31: =SUM(E31:G31) -> 0 | H31: =SUM(I31:K31) -> 0 | L31: =SUM(M31:O31) -> 0 | P31: =SUM(Q31:S31) -> 18883.31 | R31: 6771.94 | S31: 12111.37 | T31: =SUM(U31:AJ31)-AG31-AC31-Y31-U31 -> 63743.66 | U31: =SUM(V31:X31) -> 29094.34 | V31: 8861 | W31: 6890.44 | X31: 13342.9 | Y31: =SUM(Z31:AB31) -> 17709.52 | Z31: 9880.72 | AA31: 4099.12 | AB31: 3729.68 | AC31: =SUM(AD31:AF31) -> 8861.41 | AD31: 3298.5 | AE31: 2802.08 | AF31: 2760.83 | AG31: =SUM(AH31:AJ31) -> 8078.39 | AH31: 5361.89 | AI31: 0 | AJ31: 2716.5 | AL31: 2142.64 | AM31: 24754.9
B32: Subscriptions & Memberships | C32: =SUM(D32:S32)-P32-L32-H32-D32 -> 92577.27 | D32: =SUM(E32:G32) -> 0 | H32: =SUM(I32:K32) -> 0 | L32: =SUM(M32:O32) -> 0 | P32: =SUM(Q32:S32) -> 92577.27 | R32: 52003.09 | S32: 40574.18 | T32: =SUM(U32:AJ32)-AG32-AC32-Y32-U32 -> 479512.13 | U32: =SUM(V32:X32) -> 189181.08 | V32: 73293.74 | W32: 26969.17 | X32: 88918.17 | Y32: =SUM(Z32:AB32) -> 151194.2 | Z32: 63284.6 | AA32: 20005.06 | AB32: 67904.54 | AC32: =SUM(AD32:AF32) -> 80100.2 | AD32: 38653.92 | AE32: 24451.97 | AF32: 16994.31 | AG32: =SUM(AH32:AJ32) -> 59036.65 | AH32: 10881.39 | AI32: 35723.87 | AJ32: 12431.39 | AL32: 22184.55 | AM32: 227892.91
B33: Events & Activity Expense | C33: =SUM(D33:S33)-P33-L33-H33-D33 -> 13566.86 | D33: =SUM(E33:G33) -> 0 | L33: =SUM(M33:O33) -> 0 | P33: =SUM(Q33:S33) -> 13566.86 | R33: 4007.5 | S33: 9559.36 | T33: =SUM(U33:AJ33)-AG33-AC33-Y33-U33 -> 43313.02 | U33: =SUM(V33:X33) -> 43313.02 | V33: 22232.75 | W33: 2237.35 | X33: 18842.92
B34: Team Building Activities | C34: =SUM(D34:S34)-P34-L34-H34-D34 -> 0 | D34: =SUM(E34:G34) -> 0 | L34: =SUM(M34:O34) -> 0 | P34: =SUM(Q34:S34) -> 0 | R34: 0 | S34: 0 | T34: =SUM(U34:AJ34)-AG34-AC34-Y34-U34 -> 1200 | U34: =SUM(V34:X34) -> 1200 | V34: 0 | W34: 0 | X34: 1200
B35: Penny Difference | C35: =SUM(D35:S35)-P35-L35-H35-D35 -> 6.3 | D35: =SUM(E35:G35) -> 0 | H35: =SUM(I35:K35) -> 0 | L35: =SUM(M35:O35) -> 0 | P35: =SUM(Q35:S35) -> 6.3 | R35: 0 | S35: 6.3 | T35: =SUM(U35:AJ35)-AG35-AC35-Y35-U35 -> 8.16 | U35: =SUM(V35:X35) -> 0.65 | V35: 0 | W35: 0 | X35: 0.65 | Y35: =SUM(Z35:AB35) -> 3.51 | Z35: 0.77 | AA35: 2.77 | AB35: -0.03 | AC35: =SUM(AD35:AF35) -> 4 | AD35: 2.94 | AE35: 0.01 | AF35: 1.05 | AG35: =SUM(AH35:AJ35) -> 0 | AH35: 0 | AI35: 0 | AJ35: 0 | AL35: 0.24 | AM35: -103.77
B36: Low Value Assets | C36: =SUM(D36:S36)-P36-L36-H36-D36 -> 849 | D36: =SUM(E36:G36) -> 0 | H36: =SUM(I36:K36) -> 0 | L36: =SUM(M36:O36) -> 0 | P36: =SUM(Q36:S36) -> 849 | R36: 0 | S36: 849 | T36: =SUM(U36:AJ36)-AG36-AC36-Y36-U36 -> 56438.33 | U36: =SUM(V36:X36) -> 22771.62 | V36: 1665.09 | W36: 2350.4 | X36: 18756.13 | Y36: =SUM(Z36:AB36) -> 13695.24 | Z36: 8226.53 | AA36: 1562.62 | AB36: 3906.09 | AC36: =SUM(AD36:AF36) -> 5351.42 | AD36: 4772.18 | AE36: 157.5 | AF36: 421.74 | AG36: =SUM(AH36:AJ36) -> 14620.05 | AH36: 974.78 | AI36: 8417.44 | AJ36: 5227.83 | AL36: 729 | AM36: 5344.88
B37: Charity | C37: =SUM(D37:S37)-P37-L37-H37-D37 -> 4000 | D37: =SUM(E37:G37) -> 0 | H37: =SUM(I37:K37) -> 0 | L37: =SUM(M37:O37) -> 0 | P37: =SUM(Q37:S37) -> 4000 | R37: 2000 | S37: 2000 | T37: =SUM(U37:AJ37)-AG37-AC37-Y37-U37 -> 31000 | U37: =SUM(V37:X37) -> 13000 | V37: 2000 | W37: 2000 | X37: 9000 | Y37: =SUM(Z37:AB37) -> 6000 | Z37: 2000 | AA37: 2000 | AB37: 2000 | AC37: =SUM(AD37:AF37) -> 6000 | AD37: 2000 | AE37: 2000 | AF37: 2000 | AG37: =SUM(AH37:AJ37) -> 6000 | AH37: 2000 | AI37: 2000 | AJ37: 2000 | AL37: 2000 | AM37: 10000
B38: Witholding Tax | C38: =SUM(D38:S38)-P38-L38-H38-D38 -> 0 | D38: =SUM(E38:G38) -> 0 | H38: =SUM(I38:K38) -> 0 | L38: =SUM(M38:O38) -> 0 | P38: =SUM(Q38:S38) -> 0 | R38: 0 | S38: 0 | T38: =SUM(U38:AJ38)-AG38-AC38-Y38-U38 -> 0 | U38: =SUM(V38:X38) -> 0 | V38: 0 | W38: 0 | X38: 0 | Y38: =SUM(Z38:AB38) -> 0 | Z38: 0 | AA38: 0 | AB38: 0 | AC38: =SUM(AD38:AF38) -> 0 | AD38: 0 | AE38: 0 | AF38: 0 | AI38: 0 | AJ38: 0 | AL38: 0 | AM38: 47608.81
B39: Selling Expenses | C39: =SUM(C40:C55) -> 160268.02 | D39: =SUM(D40:D55) -> 0 | E39: =SUM(E40:E55) -> 0 | F39: =SUM(F40:F55) -> 0 | G39: =SUM(G40:G55) -> 0 | H39: =SUM(H40:H55) -> 0 | I39: =SUM(I40:I55) -> 0 | J39: =SUM(J40:J55) -> 0 | ... AJ39: =SUM(AJ40:AJ55) -> 56646.93 | AL39: =SUM(AL40:AL55) -> 58404.56 | AM39: =SUM(AM40:AM55) -> 591969.18
B40: Business travel expenses | C40: =SUM(D40:S40)-P40-L40-H40-D40 -> 17256.72 | D40: =SUM(E40:G40) -> 0 | H40: =SUM(I40:K40) -> 0 | L40: =SUM(M40:O40) -> 0 | P40: =SUM(Q40:S40) -> 17256.72 | R40: 6068.14 | S40: 11188.58 | T40: =SUM(U40:AJ40)-AG40-AC40-Y40-U40 -> 58476.06 | U40: =SUM(V40:X40) -> 17955.61 | V40: 17621.22 | W40: -11004.45 | X40: 11338.84 | Y40: =SUM(Z40:AB40) -> 11900.03 | Z40: 6977.04 | AA40: 1891.56 | AB40: 3031.43 | AC40: =SUM(AD40:AF40) -> 12382.85 | AD40: 4361 | AE40: 4405.15 | AF40: 3616.7 | AG40: =SUM(AH40:AJ40) -> 16237.57 | AH40: 952 | AI40: 4372.08 | AJ40: 10913.49 | AL40: 18271.01 | AM40: 96381.63
B41: Business Accommodation Expense | C41: =SUM(D41:S41)-P41-L41-H41-D41 -> 17753.03 | D41: =SUM(E41:G41) -> 0 | H41: =SUM(I41:K41) -> 0 | L41: =SUM(M41:O41) -> 0 | P41: =SUM(Q41:S41) -> 17753.03 | R41: 16460.27 | S41: 1292.76 | T41: =SUM(U41:AJ41)-AG41-AC41-Y41-U41 -> 127516.15 | U41: =SUM(V41:X41) -> 40679.4 | V41: 36312.33 | W41: -2227.86 | X41: 6594.93 | Y41: =SUM(Z41:AB41) -> 49747.17 | Z41: 28716.5 | AA41: 11602.53 | AB41: 9428.14 | AC41: =SUM(AD41:AF41) -> 23508.19 | AD41: 13811.06 | AE41: 8712.51 | AF41: 984.62 | AG41: =SUM(AH41:AJ41) -> 13581.39 | AH41: 22.61 | AI41: 5592.49 | AJ41: 7966.29
B42: Collection Commission | C42: =SUM(D42:S42)-P42-L42-H42-D42 -> 0 | D42: =SUM(E42:G42) -> 0 | H42: =SUM(I42:K42) -> 0 | L42: =SUM(M42:O42) -> 0 | P42: =SUM(Q42:S42) -> 0 | R42: 0 | S42: 0 | T42: =SUM(U42:AJ42)-AG42-AC42-Y42-U42 -> 0 | U42: =SUM(V42:X42) -> 0 | V42: 0 | W42: 0 | X42: 0 | Y42: =SUM(Z42:AB42) -> 0 | Z42: 0 | AA42: 0 | AB42: 0 | AC42: =SUM(AD42:AF42) -> 0 | AD42: 0 | AE42: 0 | AF42: 0 | AG42: =SUM(AH42:AJ42) -> 0 | AH42: 0 | AI42: 0 | AJ42: 0 | AL42: 4797.13 | AM42: 61150.53
B43: Dinar commission | C43: =SUM(D43:S43)-P43-L43-H43-D43 -> 0 | D43: =SUM(E43:G43) -> 0 | H43: =SUM(I43:K43) -> 0 | L43: =SUM(M43:O43) -> 0 | P43: =SUM(Q43:S43) -> 0 | R43: 0 | S43: 0 | T43: =SUM(U43:AJ43)-AG43-AC43-Y43-U43 -> 2578.26 | U43: =SUM(V43:X43) -> 0 | V43: 0 | W43: 0 | X43: 0 | Y43: =SUM(Z43:AB43) -> 0 | Z43: 0 | AA43: 0 | AB43: 0 | AC43: =SUM(AD43:AF43) -> 1600 | AD43: 0 | AE43: 0 | AF43: 1600 | AG43: =SUM(AH43:AJ43) -> 978.26 | AH43: 0 | AI43: 978.26 | AJ43: 0 | AL43: 0 | AM43: 8543.48
B44: New customer commission | C44: =SUM(D44:S44)-P44-L44-H44-D44 -> 13000 | D44: =SUM(E44:G44) -> 0 | H44: =SUM(I44:K44) -> 0 | L44: =SUM(M44:O44) -> 0 | P44: =SUM(Q44:S44) -> 13000 | R44: 5000 | S44: 8000 | T44: =SUM(U44:AJ44)-AG44-AC44-Y44-U44 -> 127000 | U44: =SUM(V44:X44) -> 39000 | V44: 7500 | W44: 21500 | X44: 10000 | Y44: =SUM(Z44:AB44) -> 35000 | Z44: 6000 | AA44: 7000 | AB44: 22000 | AC44: =SUM(AD44:AF44) -> 34000 | AD44: 13000 | AE44: 6000 | AF44: 15000 | AG44: =SUM(AH44:AJ44) -> 19000 | AH44: 7000 | AI44: 7000 | AJ44: 5000 | AL44: 5000 | AM44: 44606.18
B45: New Approved client Commission (SDA) | C45: =SUM(D45:S45)-P45-L45-H45-D45 -> 5500 | D45: =SUM(E45:G45) -> 0 | H45: =SUM(I45:K45) -> 0 | L45: =SUM(M45:O45) -> 0 | P45: =SUM(Q45:S45) -> 5500 | R45: 2500 | S45: 3000 | T45: =SUM(U45:AJ45)-AG45-AC45-Y45-U45 -> 55000 | U45: =SUM(V45:X45) -> 17200 | V45: 3400 | W45: 6300 | X45: 7500 | Y45: =SUM(Z45:AB45) -> 14200 | Z45: 4900 | AA45: 3700 | AB45: 5600 | AC45: =SUM(AD45:AF45) -> 10100 | AD45: 5400 | AE45: 1700 | AF45: 3000 | AG45: =SUM(AH45:AJ45) -> 13500 | AH45: 7000 | AI45: 5000 | AJ45: 1500
B46: Sales Commission-Employee | C46: =SUM(D46:S46)-P46-L46-H46-D46 -> 54400.79 | D46: =SUM(E46:G46) -> 0 | H46: =SUM(I46:K46) -> 0 | L46: =SUM(M46:O46) -> 0 | P46: =SUM(Q46:S46) -> 54400.79 | R46: 30932.16 | S46: 23468.63 | T46: =SUM(U46:AJ46)-AG46-AC46-Y46-U46 -> 323555.43 | U46: =SUM(V46:X46) -> 93218.17 | V46: 29491.08 | W46: 36269.68 | X46: 27457.41 | Y46: =SUM(Z46:AB46) -> 102093.22 | Z46: 19446.8 | AA46: 14722.76 | AB46: 67923.66 | AC46: =SUM(AD46:AF46) -> 71738.54 | AD46: 26518.85 | AE46: 19610.97 | AF46: 25608.72 | AG46: =SUM(AH46:AJ46) -> 56505.5 | AH46: 20701.1 | AI46: 19876.4 | AJ46: 15928
B47: Cash Purchase - Backend Margin | C47: =SUM(D47:S47)-P47-L47-H47-D47 -> 0 | D47: =SUM(E47:G47) -> 0 | H47: =SUM(I47:K47) -> 0 | L47: =SUM(M47:O47) -> 0 | P47: =SUM(Q47:S47) -> 0 | R47: 0 | S47: 0 | T47: =SUM(U47:AJ47)-AG47-AC47-Y47-U47 -> 0 | U47: =SUM(V47:X47) -> 0 | V47: 0 | W47: 0 | X47: 0 | Y47: =SUM(Z47:AB47) -> 0 | Z47: 0 | AA47: 0 | AB47: 0 | AC47: =SUM(AD47:AF47) -> 0 | AD47: 0 | AE47: 0 | AF47: 0 | AG47: =SUM(AH47:AJ47) -> 0 | AH47: 0 | AI47: 0 | AJ47: 0 | AL47: 107.5 | AM47: 4457.77
B48: Cash Sale Commission | C48: =SUM(D48:S48)-P48-L48-H48-D48 -> 0 | D48: =SUM(E48:G48) -> 0 | H48: =SUM(I48:K48) -> 0 | L48: =SUM(M48:O48) -> 0 | P48: =SUM(Q48:S48) -> 0 | R48: 0 | S48: 0 | T48: =SUM(U48:AJ48)-AG48-AC48-Y48-U48 -> 0 | U48: =SUM(V48:X48) -> 0 | V48: 0 | W48: 0 | X48: 0 | Y48: =SUM(Z48:AB48) -> 0 | Z48: 0 | AA48: 0 | AB48: 0 | AC48: =SUM(AD48:AF48) -> 0 | AD48: 0 | AE48: 0 | AF48: 0 | AG48: =SUM(AH48:AJ48) -> 0 | AI48: 0 | AJ48: 0 | AL48: 0 | AM48: 21797.18
B49: Bonus Commission | C49: =SUM(D49:S49)-P49-L49-H49-D49 -> 1500 | D49: =SUM(E49:G49) -> 0 | H49: =SUM(I49:K49) -> 0 | L49: =SUM(M49:O49) -> 0 | P49: =SUM(Q49:S49) -> 1500 | R49: 0 | S49: 1500 | T49: =SUM(U49:AJ49)-AG49-AC49-Y49-U49 -> 97386.05 | U49: =SUM(V49:X49) -> 20834.44 | V49: 3633.33 | W49: 9900 | X49: 7301.11 | Y49: =SUM(Z49:AB49) -> 65550 | Z49: 46050 | AA49: 0 | AB49: 19500 | AC49: =SUM(AD49:AF49) -> 11001.61 | AD49: 11001.61
B50: Third Party Referral Incentive | C50: =SUM(D50:S50)-P50-L50-H50-D50 -> 26991.3 | D50: =SUM(E50:G50) -> 0 | H50: =SUM(I50:K50) -> 0 | L50: =SUM(M50:O50) -> 0 | P50: =SUM(Q50:S50) -> 26991.3 | R50: 0 | S50: 26991.3 | T50: =SUM(U50:AJ50)-AG50-AC50-Y50-U50 -> 21047.54 | U50: =SUM(V50:X50) -> 17454.35 | V50: 0 | W50: 14000 | X50: 3454.35 | Y50: =SUM(Z50:AB50) -> 3593.19 | Z50: 0 | AA50: 0 | AB50: 3593.19
B51: Deal-related expenses | C51: =SUM(D51:S51)-P51-L51-H51-D51 -> 0 | D51: =SUM(E51:G51) -> 0 | H51: =SUM(I51:K51) -> 0 | L51: =SUM(M51:O51) -> 0 | P51: =SUM(Q51:S51) -> 0 | R51: 0 | S51: 0 | T51: =SUM(U51:AJ51)-AG51-AC51-Y51-U51 -> 1638.75 | U51: =SUM(V51:X51) -> 1638.75 | V51: 235.75 | W51: 299 | X51: 1104
B52: Credit Assessment Expense | C52: =SUM(D52:S52)-P52-L52-H52-D52 -> 16100 | D52: =SUM(E52:G52) -> 0 | H52: =SUM(I52:K52) -> 0 | L52: =SUM(M52:O52) -> 0 | P52: =SUM(Q52:S52) -> 16100 | R52: 8000 | S52: 8100
B53: Fuel/Mileage Expenses | C53: =SUM(D53:S53)-P53-L53-H53-D53 -> 7066.18 | D53: =SUM(E53:G53) -> 0 | H53: =SUM(I53:K53) -> 0 | L53: =SUM(M53:O53) -> 0 | P53: =SUM(Q53:S53) -> 7066.18 | R53: 3494.76 | S53: 3571.42 | T53: =SUM(U53:AJ53)-AG53-AC53-Y53-U53 -> 38416.38 | U53: =SUM(V53:X53) -> 10525.58 | V53: 3721.99 | W53: 3185.45 | X53: 3618.14 | Y53: =SUM(Z53:AB53) -> 8059.1 | Z53: 2716.95 | AA53: 2558.05 | AB53: 2784.1 | AC53: =SUM(AD53:AF53) -> 8457.52 | AD53: 3058.77 | AE53: 1991.38 | AF53: 3407.37 | AG53: =SUM(AH53:AJ53) -> 11374.18 | AH53: 3365.12 | AI53: 3084.98 | AJ53: 4924.08 | AL53: 4340.78 | AM53: 42649.18
B54: Marketing, Promotion & Advertising | C54: =SUM(D54:S54)-P54-L54-H54-D54 -> 700 | D54: =SUM(E54:G54) -> 0 | H54: =SUM(I54:K54) -> 0 | L54: =SUM(M54:O54) -> 0 | P54: =SUM(Q54:S54) -> 700 | R54: 700 | S54: 0 | T54: =SUM(U54:AJ54)-AG54-AC54-Y54-U54 -> 43062.05 | U54: =SUM(V54:X54) -> 8972.48 | V54: 1300 | W54: 7672.48 | Y54: =SUM(Z54:AB54) -> 1350 | Z54: 0 | AA54: 1350 | AB54: 0 | AC54: =SUM(AD54:AF54) -> 17361.31 | AD54: 2170 | AE54: 14765.22 | AF54: 426.09 | AG54: =SUM(AH54:AJ54) -> 15378.26 | AH54: 0 | AI54: 5478.26 | AJ54: 9900 | AL54: 0 | AM54: 93575.77
B55: Trade Credit Insurance | C55: =SUM(D55:S55)-P55-L55-H55-D55 -> 0 | D55: =SUM(E55:G55) -> 0 | H55: =SUM(I55:K55) -> 0 | I55: 0 | J55: 0 | K55: 0 | L55: =SUM(M55:O55) -> 0 | P55: =SUM(Q55:S55) -> 0 | R55: 0 | S55: 0 | T55: =SUM(U55:AJ55)-AG55-AC55-Y55-U55 -> 20113.05 | U55: =SUM(V55:X55) -> 19597.98 | V55: 0 | W55: 19597.98 | X55: 0 | Y55: =SUM(Z55:AB55) -> 0 | Z55: 0 | AA55: 0 | AB55: 0 | AC55: =SUM(AD55:AF55) -> 0 | AD55: 0 | AE55: 0 | AF55: 0 | AG55: =SUM(AH55:AJ55) -> 515.07 | AH55: 0 | AI55: 0 | AJ55: 515.07 | AL55: 25888.14 | AM55: 218807.46
B56: Legal & Consultation Expenses | C56: =SUM(C57:C59) -> 15952.91 | D56: =SUM(D57:D59) -> 0 | E56: =SUM(E57:E59) -> 0 | F56: =SUM(F57:F59) -> 0 | G56: =SUM(G57:G59) -> 0 | H56: =SUM(H57:H59) -> 0 | I56: =SUM(I57:I59) -> 0 | J56: =SUM(J57:J59) -> 0 | ... AJ56: =SUM(AJ57:AJ59) -> 23381.76 | AL56: =SUM(AL57:AL59) -> 161922.26 | AM56: =SUM(AM57:AM59) -> 408151.68
B57: Consultant Expense | C57: =SUM(D57:S57)-P57-L57-H57-D57 -> 0 | D57: =SUM(E57:G57) -> 0 | H57: =SUM(I57:K57) -> 0 | L57: =SUM(M57:O57) -> 0 | P57: =SUM(Q57:S57) -> 0 | R57: 0 | S57: 0 | T57: =SUM(U57:AJ57)-AG57-AC57-Y57-U57 -> 24330.17 | U57: =SUM(V57:X57) -> 0 | V57: 0 | W57: 0 | X57: 0 | Y57: =SUM(Z57:AB57) -> 0 | Z57: 0 | AA57: 0 | AB57: 0 | AC57: =SUM(AD57:AF57) -> 20464.86 | AD57: 0 | AE57: 16616.96 | AF57: 3847.9 | AG57: =SUM(AH57:AJ57) -> 3865.31 | AH57: -0.02 | AI57: 3865.33 | AJ57: 0 | AL57: 0 | AM57: 74533.33
B58: Government & Compliance Expense | C58: =SUM(D58:S58)-P58-L58-H58-D58 -> 952.91 | D58: =SUM(E58:G58) -> 0 | H58: =SUM(I58:K58) -> 0 | L58: =SUM(M58:O58) -> 0 | P58: =SUM(Q58:S58) -> 952.91 | R58: 584.58 | S58: 368.33 | T58: =SUM(U58:AJ58)-AG58-AC58-Y58-U58 -> 41823.9 | U58: =SUM(V58:X58) -> 10637.73 | V58: 5721.07 | W58: 1248.33 | X58: 3668.33 | Y58: =SUM(Z58:AB58) -> 15157.83 | Z58: 4867.83 | AA58: 9540.5 | AB58: =149.5+600 -> 749.5 | AC58: =SUM(AD58:AF58) -> 7098.48 | AD58: 4157.18 | AE58: 2591.3 | AF58: 350 | AG58: =SUM(AH58:AJ58) -> 8929.86 | AH58: 1.75 | AI58: 6296.36 | AJ58: 2631.75 | AL58: 1332.26 | AM58: 29073.83
B59: Legal | C59: =SUM(D59:S59)-P59-L59-H59-D59 -> 15000 | D59: =SUM(E59:G59) -> 0 | H59: =SUM(I59:K59) -> 0 | L59: =SUM(M59:O59) -> 0 | P59: =SUM(Q59:S59) -> 15000 | R59: 7500 | S59: 7500 | T59: =SUM(U59:AJ59)-AG59-AC59-Y59-U59 -> 278973.34 | U59: =SUM(V59:X59) -> 45310 | V59: 14625 | W59: 13930 | X59: 16755 | Y59: =SUM(Z59:AB59) -> 70800 | Z59: 16270 | AA59: 15610 | AB59: 38920 | AC59: =SUM(AD59:AF59) -> 130779.99 | AD59: 9576.65 | AE59: 11166.67 | AF59: 110036.67 | AG59: =SUM(AH59:AJ59) -> 32083.35 | AH59: 5416.67 | AI59: 5916.67 | AJ59: 20750.01 | AL59: 160590 | AM59: 304544.52
B60: Depreciation Expenses | C60: =SUM(C61:C64) -> 24141.47 | D60: =SUM(D61:D64) -> 0 | E60: =SUM(E61:E64) -> 0 | F60: =SUM(F61:F64) -> 0 | G60: =SUM(G61:G64) -> 0 | H60: =SUM(H61:H64) -> 0 | I60: =SUM(I61:I64) -> 0 | J60: =SUM(J61:J64) -> 0 | ... AJ60: =SUM(AJ61:AJ64) -> 7013.22 | AL60: =SUM(AL61:AL64) -> 7880.36 | AM60: =SUM(AM61:AM64) -> 85187.69
B61: Depreciation - Furniture & Fixture | C61: =SUM(D61:S61)-P61-L61-H61-D61 -> 3609.92 | D61: =SUM(E61:G61) -> 0 | H61: =SUM(I61:K61) -> 0 | L61: =SUM(M61:O61) -> 0 | P61: =SUM(Q61:S61) -> 3609.92 | R61: 1804.96 | S61: 1804.96 | T61: =SUM(U61:AJ61)-AG61-AC61-Y61-U61 -> 18962.97 | U61: =SUM(V61:X61) -> 5414.88 | V61: 1804.96 | W61: 1804.96 | X61: 1804.96 | Y61: =SUM(Z61:AB61) -> 4605.73 | Z61: 1525.8 | AA61: 1543.24 | AB61: 1536.69 | AC61: =SUM(AD61:AF61) -> 4610.07 | AD61: 1536.69 | AE61: 1536.69 | AF61: 1536.69 | AG61: =SUM(AH61:AJ61) -> 4332.29 | AH61: 1536.69 | AI61: 1397.8 | AJ61: 1397.8 | AL61: 1314.47 | AM61: 15221.76
B62: Depreciation - Motor Vehicle | C62: =SUM(D62:S62)-P62-L62-H62-D62 -> 1607.24 | D62: =SUM(E62:G62) -> 0 | H62: =SUM(I62:K62) -> 0 | L62: =SUM(M62:O62) -> 0 | P62: =SUM(Q62:S62) -> 1607.24 | R62: 803.62 | S62: 803.62 | T62: =SUM(U62:AJ62)-AG62-AC62-Y62-U62 -> 9643.44 | U62: =SUM(V62:X62) -> 2410.86 | V62: 803.62 | W62: 803.62 | X62: 803.62 | Y62: =SUM(Z62:AB62) -> 2410.86 | Z62: 803.62 | AA62: 803.62 | AB62: 803.62 | AC62: =SUM(AD62:AF62) -> 2410.86 | AD62: 803.62 | AE62: 803.62 | AF62: 803.62 | AG62: =SUM(AH62:AJ62) -> 2410.86 | AH62: 803.62 | AI62: 803.62 | AJ62: 803.62 | AL62: 1679.85 | AM62: 14526.77
B63: Depreciation-Building Improvement | C63: =SUM(D63:S63)-P63-L63-H63-D63 -> 7432.6 | D63: =SUM(E63:G63) -> 0 | H63: =SUM(I63:K63) -> 0 | P63: =SUM(Q63:S63) -> 7432.6 | R63: 3716.3 | S63: 3716.3 | T63: =SUM(U63:AJ63)-AG63-AC63-Y63-U63 -> 22297.8 | U63: =SUM(V63:X63) -> 11148.9 | V63: 3716.3 | W63: 3716.3 | X63: 3716.3 | Y63: =SUM(Z63:AB63) -> 11148.9 | Z63: 3716.3 | AA63: 3716.3 | AB63: 3716.3
B64: Depreciation - Office Equipment's | C64: =SUM(D64:S64)-P64-L64-H64-D64 -> 11491.71 | D64: =SUM(E64:G64) -> 0 | H64: =SUM(I64:K64) -> 0 | L64: =SUM(M64:O64) -> 0 | P64: =SUM(Q64:S64) -> 11491.71 | R64: 5566.11 | S64: 5925.6 | T64: =SUM(U64:AJ64)-AG64-AC64-Y64-U64 -> 63860.75 | U64: =SUM(V64:X64) -> 20938.8 | V64: 7584.37 | W64: 7305.39 | X64: 6049.04 | Y64: =SUM(Z64:AB64) -> 14837.06 | Z64: 5369.94 | AA64: 5071.19 | AB64: 4395.93 | AC64: =SUM(AD64:AF64) -> 14054.66 | AD64: 4732.17 | AE64: 4359.07 | AF64: 4963.42 | AG64: =SUM(AH64:AJ64) -> 14030.23 | AH64: 4406.43 | AI64: 4812 | AJ64: 4811.8 | AL64: 4886.04 | AM64: 55439.16
B65: Personnel Expenses | C65: =SUM(C66:C86) -> 1100836.3 | D65: =SUM(D66:D86) -> 0 | E65: =SUM(E66:E86) -> 0 | F65: =SUM(F66:F86) -> 0 | G65: =SUM(G66:G86) -> 0 | H65: =SUM(H66:H86) -> 0 | I65: =SUM(I66:I86) -> 0 | J65: =SUM(J66:J86) -> 0 | ... AJ65: =SUM(AJ66:AJ86) -> 438738.8 | AL65: =SUM(AL66:AL86) -> 570580.97 | AM65: =SUM(AM66:AM86) -> 3919359.8
B66: Employee Insurance | C66: =SUM(D66:S66)-P66-L66-H66-D66 -> 60134.46 | D66: =SUM(E66:G66) -> 0 | H66: =SUM(I66:K66) -> 0 | L66: =SUM(M66:O66) -> 0 | P66: =SUM(Q66:S66) -> 60134.46 | R66: 30392.98 | S66: 29741.48 | T66: =SUM(U66:AJ66)-AG66-AC66-Y66-U66 -> 253638.95 | U66: =SUM(V66:X66) -> 89016.13 | V66: 31733.53 | W66: 29305.2 | X66: 27977.4 | Y66: =SUM(Z66:AB66) -> 78013.47 | Z66: 28052.4 | AA66: 26999.25 | AB66: 22961.82 | AC66: =SUM(AD66:AF66) -> 23288.78 | AD66: 21986.19 | AE66: 21437.72 | AF66: -20135.13 | AG66: =SUM(AH66:AJ66) -> 63320.57 | AH66: 22374.34 | AI66: 20878.79 | AJ66: 20067.44 | AL66: 19139.83 | AM66: 155647.64
B67: Leave Air Fare Expense | C67: =SUM(D67:S67)-P67-L67-H67-D67 -> 0 | D67: =SUM(E67:G67) -> 0 | H67: =SUM(I67:K67) -> 0 | L67: =SUM(M67:O67) -> 0 | P67: =SUM(Q67:S67) -> 0 | R67: 0 | S67: 0 | T67: =SUM(U67:AJ67)-AG67-AC67-Y67-U67 -> 48824.67 | U67: =SUM(V67:X67) -> 24704.12 | V67: 8704.12 | W67: 16000 | X67: 0 | Y67: =SUM(Z67:AB67) -> 14636.87 | Z67: 0 | AA67: 7805 | AB67: 6831.87 | AC67: =SUM(AD67:AF67) -> 9483.68 | AD67: 7540 | AE67: 0 | AF67: 1943.68 | AG67: =SUM(AH67:AJ67) -> 0 | AH67: 0 | AI67: 0 | AJ67: 0
B68: Leave Pay Expense | C68: =SUM(D68:S68)-P68-L68-H68-D68 -> 3937 | D68: =SUM(E68:G68) -> 0 | H68: =SUM(I68:K68) -> 0 | L68: =SUM(M68:O68) -> 0 | P68: =SUM(Q68:S68) -> 3937 | R68: 3937 | S68: 0 | T68: =SUM(U68:AJ68)-AG68-AC68-Y68-U68 -> 269403.87 | U68: =SUM(V68:X68) -> 262912.5 | V68: 262912.5 | W68: 0 | X68: 0 | Y68: =SUM(Z68:AB68) -> 0 | Z68: 0 | AA68: 0 | AB68: 0 | AC68: =SUM(AD68:AF68) -> 0 | AD68: 0 | AE68: 0 | AF68: 0 | AG68: =SUM(AH68:AJ68) -> 6491.37 | AH68: 3171.39 | AI68: 1749.98 | AJ68: 1570 | AL68: 47874.96 | AM68: 71427.81
B69: Employee Referral Allowance | C69: =SUM(D69:S69)-P69-L69-H69-D69 -> 0 | D69: =SUM(E69:G69) -> 0 | H69: =SUM(I69:K69) -> 0 | L69: =SUM(M69:O69) -> 0 | P69: =SUM(Q69:S69) -> 0 | R69: 0 | S69: 0 | T69: =SUM(U69:AJ69)-AG69-AC69-Y69-U69 -> 41187.5 | U69: =SUM(V69:X69) -> 17000 | V69: 0 | W69: 2500 | X69: 14500 | Y69: =SUM(Z69:AB69) -> 3500 | Z69: 0 | AA69: 3500 | AB69: 0 | AC69: =SUM(AD69:AF69) -> 17187.5 | AD69: 17187.5 | AE69: 0 | AF69: 0 | AG69: =SUM(AH69:AJ69) -> 3500 | AH69: 0 | AI69: 3500 | AJ69: 0 | AL69: 0 | AM69: 12377.78
B70: Maintenance Allowance | C70: =SUM(D70:S70)-P70-L70-H70-D70 -> 7000 | D70: =SUM(E70:G70) -> 0 | H70: =SUM(I70:K70) -> 0 | L70: =SUM(M70:O70) -> 0 | P70: =SUM(Q70:S70) -> 7000 | R70: 3500 | S70: 3500 | T70: =SUM(U70:AJ70)-AG70-AC70-Y70-U70 -> 40709.68 | U70: =SUM(V70:X70) -> 11209.68 | V70: 3500 | W70: 4000 | X70: 3709.68 | Y70: =SUM(Z70:AB70) -> 10500 | Z70: 3500 | AA70: 4000 | AB70: 3000 | AC70: =SUM(AD70:AF70) -> 12000 | AD70: 6000 | AE70: 3000 | AF70: 3000 | AG70: =SUM(AH70:AJ70) -> 7000 | AH70: 0 | AI70: 7000 | AJ70: 0 | AL70: 9000 | AM70: 50915.87
B71: Per Diem Allowance | C71: =SUM(D71:S71)-P71-L71-H71-D71 -> 0 | D71: =SUM(E71:G71) -> 0 | H71: =SUM(I71:K71) -> 0 | L71: =SUM(M71:O71) -> 0 | P71: =SUM(Q71:S71) -> 0 | R71: 0 | S71: 0 | T71: =SUM(U71:AJ71)-AG71-AC71-Y71-U71 -> 19780 | U71: =SUM(V71:X71) -> 5700 | V71: 300 | W71: 3000 | X71: 2400 | Y71: =SUM(Z71:AB71) -> 0 | Z71: 0 | AA71: 0 | AB71: 0 | AC71: =SUM(AD71:AF71) -> 600 | AD71: 0 | AE71: 0 | AF71: 600 | AG71: =SUM(AH71:AJ71) -> 13480 | AH71: 1800 | AI71: 7800 | AJ71: 3880
B72: Employee Benefit expense | C72: =SUM(D72:S72)-P72-L72-H72-D72 -> 83.4 | D72: =SUM(E72:G72) -> 0 | H72: =SUM(I72:K72) -> 0 | L72: =SUM(M72:O72) -> 0 | P72: =SUM(Q72:S72) -> 83.4 | R72: 0 | S72: 83.4 | T72: =SUM(U72:AJ72)-AG72-AC72-Y72-U72 -> 0 | U72: =SUM(V72:X72) -> 0 | V72: 0 | W72: 0
B73: Employee Related Govt Fees | C73: =SUM(D73:S73)-P73-L73-H73-D73 -> 17866.62 | D73: =SUM(E73:G73) -> 0 | H73: =SUM(I73:K73) -> 0 | L73: =SUM(M73:O73) -> 0 | P73: =SUM(Q73:S73) -> 17866.62 | R73: 7583.31 | S73: 10283.31 | T73: =SUM(U73:AJ73)-AG73-AC73-Y73-U73 -> 75886.76 | U73: =SUM(V73:X73) -> 11384.76 | V73: 4999.98 | W73: 2881.03 | X73: 3503.75 | Y73: =SUM(Z73:AB73) -> 38512 | Z73: 13075 | AA73: 19937 | AB73: 5500 | AC73: =SUM(AD73:AF73) -> 560 | AD73: 500 | AE73: 0 | AF73: 60 | AG73: =SUM(AH73:AJ73) -> 25430 | AH73: 3700 | AI73: 0 | AJ73: 21730 | AL73: 22339.49 | AM73: 161134.51
B74: Telecome Allowance | C74: =SUM(D74:S74)-P74-L74-H74-D74 -> 2400 | D74: =SUM(E74:G74) -> 0 | H74: =SUM(I74:K74) -> 0 | L74: =SUM(M74:O74) -> 0 | P74: =SUM(Q74:S74) -> 2400 | R74: 1200 | S74: 1200 | T74: =SUM(U74:AJ74)-AG74-AC74-Y74-U74 -> 15200 | U74: =SUM(V74:X74) -> 3600 | V74: 1200 | W74: 1200 | X74: 1200 | Y74: =SUM(Z74:AB74) -> 3600 | Z74: 1200 | AA74: 1200 | AB74: 1200 | AC74: =SUM(AD74:AF74) -> 4800 | AD74: 2400 | AE74: 1200 | AF74: 1200 | AG74: =SUM(AH74:AJ74) -> 3200 | AH74: 0 | AI74: 3200 | AJ74: 0 | AL74: 3400 | AM74: 15800.58
B75: US Employer Taxes | C75: =SUM(D75:S75)-P75-L75-H75-D75 -> 0 | D75: =SUM(E75:G75) -> 0 | H75: =SUM(I75:K75) -> 0 | L75: =SUM(M75:O75) -> 0 | P75: =SUM(Q75:S75) -> 0 | R75: 0 | S75: 0 | T75: =SUM(U75:AJ75)-AG75-AC75-Y75-U75 -> 0 | U75: =SUM(V75:X75) -> 0 | V75: 0 | W75: 0 | X75: 0 | Y75: =SUM(Z75:AB75) -> 0 | Z75: 0 | AA75: 0 | AB75: 0 | AC75: =SUM(AD75:AF75) -> 0 | AD75: 0 | AE75: 0 | AF75: 0 | AH75: 0 | AI75: 0 | AJ75: 0 | AL75: 0
B76: GOSI | C76: =SUM(D76:S76)-P76-L76-H76-D76 -> 31567.97 | D76: =SUM(E76:G76) -> 0 | H76: =SUM(I76:K76) -> 0 | L76: =SUM(M76:O76) -> 0 | P76: =SUM(Q76:S76) -> 31567.97 | R76: 15169.53 | S76: 16398.44 | T76: =SUM(U76:AJ76)-AG76-AC76-Y76-U76 -> 195802.25 | U76: =SUM(V76:X76) -> 59758.75 | V76: 14867.04 | W76: 22809.76 | X76: 22081.95 | Y76: =SUM(Z76:AB76) -> 53577.75 | Z76: 20219.27 | AA76: 20132.82 | AB76: 13225.66 | AC76: =SUM(AD76:AF76) -> 33786.5 | AD76: 12414.99 | AE76: 11182.63 | AF76: 10188.88 | AG76: =SUM(AH76:AJ76) -> 48679.25 | AH76: 13037.78 | AI76: 18534.91 | AJ76: 17106.56 | AL76: 17220.56 | AM76: 167751.58
B77: HUMAN RESOUACES DEVELOPMENT FUND | C77: =SUM(D77:S77)-P77-L77-H77-D77 -> -6000 | D77: =SUM(E77:G77) -> 0 | H77: =SUM(I77:K77) -> 0 | L77: =SUM(M77:O77) -> 0 | P77: =SUM(Q77:S77) -> -6000 | R77: 0 | S77: -6000 | T77: =SUM(U77:AJ77)-AG77-AC77-Y77-U77 -> -81000 | U77: =SUM(V77:X77) -> -18000 | V77: -6000 | W77: 0 | X77: -12000 | Y77: =SUM(Z77:AB77) -> -18000 | Z77: 0 | AA77: -6000 | AB77: -12000 | AC77: =SUM(AD77:AF77) -> -18000 | AD77: 0 | AE77: -18000 | AF77: 0 | AG77: =SUM(AH77:AJ77) -> -27000 | AH77: -18000 | AI77: 0 | AJ77: -9000 | AL77: -15000 | AM77: -81000
B78: Recruitments & Visas | C78: =SUM(D78:S78)-P78-L78-H78-D78 -> 172.5 | D78: =SUM(E78:G78) -> 0 | H78: =SUM(I78:K78) -> 0 | L78: =SUM(M78:O78) -> 0 | P78: =SUM(Q78:S78) -> 172.5 | R78: 0 | S78: 172.5 | T78: =SUM(U78:AJ78)-AG78-AC78-Y78-U78 -> 145000.97 | U78: =SUM(V78:X78) -> 1782.24 | V78: 357.68 | W78: 992.56 | X78: 432 | Y78: =SUM(Z78:AB78) -> 36365.61 | Z78: 708.33 | AA78: 0 | AB78: 35657.28 | AC78: =SUM(AD78:AF78) -> 96372.54 | AD78: 60451.06 | AE78: 33921.48 | AF78: 2000 | AG78: =SUM(AH78:AJ78) -> 10480.58 | AH78: 0 | AI78: 0 | AJ78: 10480.58 | AL78: 0 | AM78: 53546.33
B79: Bonus | C79: =SUM(D79:S79)-P79-L79-H79-D79 -> 0 | D79: =SUM(E79:G79) -> 0 | H79: =SUM(I79:K79) -> 0 | L79: =SUM(M79:O79) -> 0 | P79: =SUM(Q79:S79) -> 0 | R79: 0 | S79: 0 | T79: =SUM(U79:AJ79)-AG79-AC79-Y79-U79 -> 164672.67 | U79: =SUM(V79:X79) -> 102600 | V79: 500 | W79: 0 | X79: 102100 | Y79: =SUM(Z79:AB79) -> 0 | Z79: 0 | AA79: 0 | AB79: 0 | AC79: =SUM(AD79:AF79) -> 14197.67 | AD79: 10000 | AE79: 4197.67 | AF79: 0 | AG79: =SUM(AH79:AJ79) -> 47875 | AH79: 13500 | AI79: 12000 | AJ79: 22375 | AL79: 2739 | AM79: 42731.37
B80: Quarterly Bonus | C80: =SUM(D80:S80)-P80-L80-H80-D80 -> -8014 | D80: =SUM(E80:G80) -> 0 | H80: =SUM(I80:K80) -> 0 | L80: =SUM(M80:O80) -> 0 | P80: =SUM(Q80:S80) -> -8014 | R80: -8014 | S80: 0 | T80: =SUM(U80:AJ80)-AG80-AC80-Y80-U80 -> 178810 | U80: =SUM(V80:X80) -> 84600 | V80: 75450 | W80: 0 | X80: 9150 | Y80: =SUM(Z80:AB80) -> 94210 | Z80: 60810 | AA80: 0 | AB80: 33400 | AC80: =SUM(AD80:AF80) -> 0
B81: Salaries - Basic | C81: =SUM(D81:S81)-P81-L81-H81-D81 -> 737960.28 | D81: =SUM(E81:G81) -> 0 | H81: =SUM(I81:K81) -> 0 | L81: =SUM(M81:O81) -> 0 | P81: =SUM(Q81:S81) -> 737960.28 | R81: 352497.87 | S81: 385462.41 | T81: =SUM(U81:AJ81)-AG81-AC81-Y81-U81 -> 3794104 | U81: =SUM(V81:X81) -> 1067104.6 | V81: 310110.92 | W81: 380882.45 | X81: 376111.26 | Y81: =SUM(Z81:AB81) -> 1155309.4 | Z81: 419704.37 | AA81: 374266.99 | AB81: 361338.05 | AC81: =SUM(AD81:AF81) -> 826244.98 | AD81: 328604.03 | AE81: 266398.27 | AF81: 231242.68 | AG81: =SUM(AH81:AJ81) -> 745444.95 | AH81: 248601.64 | AI81: 230193.71 | AJ81: 266649.6 | AL81: 274704.86 | AM81: 2392437.9
B82: Salaries - Housing | C82: =SUM(D82:S82)-P82-L82-H82-D82 -> 173902.32 | D82: =SUM(E82:G82) -> 0 | H82: =SUM(I82:K82) -> 0 | L82: =SUM(M82:O82) -> 0 | P82: =SUM(Q82:S82) -> 173902.32 | R82: 88117.47 | S82: 85784.85 | T82: =SUM(U82:AJ82)-AG82-AC82-Y82-U82 -> 818286.04 | U82: =SUM(V82:X82) -> 266137.17 | V82: 76991.1 | W82: 94305.7 | X82: 94840.37 | Y82: =SUM(Z82:AB82) -> 218600.13 | Z82: 74520.57 | AA82: 74520.57 | AB82: 69558.99 | AC82: =SUM(AD82:AF82) -> 168254.97 | AD82: 63768.57 | AE82: 53374.07 | AF82: 51112.33 | AG82: =SUM(AH82:AJ82) -> 165293.77 | AH82: 54676.09 | AI82: 50710.09 | AJ82: 59907.59 | AL82: 58989.69 | AM82: 495183.73
B83: Salaries - Others | C83: =SUM(D83:S83)-P83-L83-H83-D83 -> 4301.04 | D83: =SUM(E83:G83) -> 0 | H83: =SUM(I83:K83) -> 0 | L83: =SUM(M83:O83) -> 0 | P83: =SUM(Q83:S83) -> 4301.04 | R83: 2843 | S83: 1458.04 | T83: =SUM(U83:AJ83)-AG83-AC83-Y83-U83 -> 217771.63 | U83: =SUM(V83:X83) -> 100394 | V83: 57935.5 | W83: 39035.5 | X83: 3423 | Y83: =SUM(Z83:AB83) -> 44744.3 | Z83: 3010.5 | AA83: 1633.8 | AB83: 40100 | AC83: =SUM(AD83:AF83) -> 36000 | AD83: 36000 | AE83: 0 | AF83: 0 | AG83: =SUM(AH83:AJ83) -> 36633.33 | AH83: 36633.33 | AI83: 0 | AJ83: 0 | AL83: 0 | AM83: 51169.78
B84: Salaries - Transportation | C84: =SUM(D84:S84)-P84-L84-H84-D84 -> 69609.81 | D84: =SUM(E84:G84) -> 0 | H84: =SUM(I84:K84) -> 0 | L84: =SUM(M84:O84) -> 0 | P84: =SUM(Q84:S84) -> 69609.81 | R84: 35270.87 | S84: 34338.94 | T84: =SUM(U84:AJ84)-AG84-AC84-Y84-U84 -> 334100.35 | U84: =SUM(V84:X84) -> 106520.34 | V84: 30815.38 | W84: 37745.93 | X84: 37959.03 | Y84: =SUM(Z84:AB84) -> 91694.9 | Z84: 31227.67 | AA84: 31227.67 | AB84: 29239.56 | AC84: =SUM(AD84:AF84) -> 68742.42 | AD84: 26923.29 | AE84: 21363.12 | AF84: 20456.01 | AG84: =SUM(AH84:AJ84) -> 67142.69 | AH84: 22878.58 | AI84: 20292.08 | AJ84: 23972.03 | AL84: 23601.29 | AM84: 207649.09
B85: End Of Service Benefits | C85: =SUM(D85:S85)-P85-L85-H85-D85 -> 0 | D85: =SUM(E85:G85) -> 0 | H85: =SUM(I85:K85) -> 0 | L85: =SUM(M85:O85) -> 0 | P85: =SUM(Q85:S85) -> 0 | R85: 0 | S85: 0 | T85: =SUM(U85:AJ85)-AG85-AC85-Y85-U85 -> 56241.04 | U85: =SUM(V85:X85) -> 52741.04 | V85: 52741.04 | W85: 0 | X85: 0 | Y85: =SUM(Z85:AB85) -> 0 | Z85: 0 | AA85: 0 | AB85: 0 | AC85: =SUM(AD85:AF85) -> 0 | AD85: 0 | AE85: 0 | AF85: 0 | AG85: =SUM(AH85:AJ85) -> 3500 | AH85: 3500 | AI85: 0 | AJ85: 0 | AL85: 106571.29 | AM85: 120889.78
B86: Staff Education/Growth Allowance | C86: =SUM(D86:S86)-P86-L86-H86-D86 -> 5914.92 | D86: =SUM(E86:G86) -> 0 | H86: =SUM(I86:K86) -> 0 | L86: =SUM(M86:O86) -> 0 | P86: =SUM(Q86:S86) -> 5914.92 | R86: 355.28 | S86: 5559.64 | T86: =SUM(U86:AJ86)-AG86-AC86-Y86-U86 -> 18372.95 | U86: =SUM(V86:X86) -> 9675.28 | V86: 4758.53 | W86: 4558.35 | X86: 358.4 | Y86: =SUM(Z86:AB86) -> 5207.41 | Z86: 3816.94 | AA86: 1390.47 | AB86: 0 | AC86: =SUM(AD86:AF86) -> 3490.26 | AD86: 3490.26 | AE86: 0 | AF86: 0 | AG86: =SUM(AH86:AJ86) -> 0 | AH86: 0 | AI86: 0 | AJ86: 0 | AL86: 0 | AM86: 1696.05
B87: Operating expenses | C87: =+C65+C60+C56+C39+C19 -> 1631888.1 | D87: =+D65+D60+D56+D39+D19 -> 0 | E87: =+E65+E60+E56+E39+E19 -> 0 | F87: =+F65+F60+F56+F39+F19 -> 0 | G87: =+G65+G60+G56+G39+G19 -> 0 | H87: =SUM(I87:K87) -> 0 | I87: =+I65+I60+I56+I39+I19 -> 0 | J87: =+J65+J60+J56+J39+J19 -> 0 | K87: =+K65+K60+K56+K39+K19 -> 0 | L87: =SUM(M87:O87) -> 0 | M87: =+M65+M60+M56+M39+M19 -> 0 | N87: =+N65+N60+N56+N39+N19 -> 0 | O87: =+O65+O60+O56+O39+O19 -> 0 | P87: =+P65+P60+P56+P39+P19 -> 1631888.1 | Q87: =+Q65+Q60+Q56+Q39+Q19 -> 0 | R87: =+R65+R60+R56+R39+R19 -> 721171.9 | S87: =+S65+S60+S56+S39+S19 -> 910716.24 | T87: =+T65+T60+T56+T39+T19 -> 11303500 | ... X87: =+X65+X60+X56+X39+X19 -> 1440279.9 | Y87: =SUM(Z87:AB87) -> 2656477.6 | Z87: =+Z65+Z60+Z56+Z39+Z19 -> 965610.6 | AA87: =+AA65+AA60+AA56+AA39+AA19 -> 745851.39 | AB87: =+AB65+AB60+AB56+AB39+AB19 -> 945015.65 | AC87: =SUM(AD87:AF87) -> 1976729.6 | AD87: =+AD65+AD60+AD56+AD39+AD19 -> 815454.98 | AE87: =+AE65+AE60+AE56+AE39+AE19 -> 593002.38 | AF87: =+AF65+AF60+AF56+AF39+AF19 -> 568272.28 | AG87: =+AG65+AG60+AG56+AG39+AG19 -> 1729014.8 | AH87: =+AH65+AH60+AH56+AH39+AH19 -> 551159.6 | AI87: =+AI65+AI60+AI56+AI39+AI19 -> 563589.35 | AJ87: =+AJ65+AJ60+AJ56+AJ39+AJ19 -> 614265.86 | AL87: =+AL65+AL60+AL56+AL39+AL19 -> 1092217.9 | AM87: =+AM65+AM60+AM56+AM39+AM19 -> 5870217.1
B90: Net operating profit / (loss) | C90: =SUM(C14+C16+C15)-C87 -> 1939346.9 | D90: =SUM(D14+D16+D15)-D87 -> 0 | E90: =SUM(E14+E16+E15)-E87 -> 0 | F90: =SUM(F14+F16+F15)-F87 -> 0 | G90: =SUM(G14+G16+G15)-G87 -> 0 | H90: =SUM(H14+H16+H15)-H87 -> 0 | I90: =SUM(I14+I16+I15)-I87 -> 0 | J90: =SUM(J14+J16+J15)-J87 -> 0 | ... AJ90: =SUM(AJ14+AJ16+AJ15)-AJ87 -> 295326.68 | AL90: =SUM(AL14+AL16)-AL87 -> -51077.73 | AM90: =SUM(AM14+AM16)-AM87 -> 1809565.5
AM92: 0
B93: Exchange Gain or Loss | C93: =SUM(D93:S93)-P93-L93-H93-D93 -> -8588.92 | D93: =SUM(E93:G93) -> 0 | H93: =SUM(I93:K93) -> 0 | L93: =SUM(M93:O93) -> 0 | P93: =SUM(Q93:S93) -> -8588.92 | R93: -7530.97 | S93: -1057.95 | T93: =SUM(U93:AJ93)-AG93-AC93-Y93-U93 -> -34788.11 | U93: =SUM(V93:X93) -> -24111.56 | V93: -4519.2 | W93: -6631.73 | X93: -12960.63 | Y93: =SUM(Z93:AB93) -> -6437.42 | Z93: -0.01 | AA93: -6437.41 | AB93: 0 | AC93: =SUM(AD93:AF93) -> -2857.02 | AD93: -465.87 | AE93: -2342.32 | AF93: -48.83 | AG93: =SUM(AH93:AJ93) -> -1382.11 | AH93: -749.93 | AI93: -602.3 | AJ93: -29.88 | AL93: -49465.83 | AM93: -51128.21
C94: =SUM(D94:S94)-P94-L94-H94-D94 -> 0 | T94: =SUM(U94:AJ94)-AG94-AC94-Y94-U94 -> 0 | AM94: 0
B95: Gain Or Loss on Disposal | C95: =SUM(D95:S95)-P95-L95-H95-D95 -> 0 | D95: =SUM(E95:G95) -> 0 | H95: =SUM(I95:K95) -> 0 | P95: =SUM(Q95:S95) -> 0 | S95: 0 | T95: =SUM(U95:AJ95)-AG95-AC95-Y95-U95 -> 758.04 | U95: =SUM(V95:X95) -> 0 | Y95: =SUM(Z95:AB95) -> 0 | AA95: 0 | AB95: 0 | AD95: 0 | AE95: 0 | AF95: 0 | AG95: =SUM(AH95:AJ95) -> 758.04 | AH95: 758.04 | AI95: 0 | AJ95: 0 | AL95: 6362.26 | AM95: 6362.26
C97: =SUM(D97:S97)-P97-L97-H97-D97 -> 0 | T97: =SUM(U97:AJ97)-AG97-AC97-Y97-U97 -> 0 | AM97: 0
B98: Investor's Profit sharing (Unrealized) | C98: =SUM(D98:S98)-P98-L98-H98-D98 -> 0 | D98: =SUM(E98:G98) -> 0 | H98: =SUM(I98:K98) -> 0 | L98: =SUM(M98:O98) -> 0 | P98: =SUM(Q98:S98) -> 0 | S98: 0 | T98: =SUM(U98:AJ98)-AG98-AC98-Y98-U98 -> 0 | U98: =SUM(V98:X98) -> 0 | W98: 0 | X98: 0 | Y98: =SUM(Z98:AB98) -> 0 | AC98: =SUM(AD98:AF98) -> 0 | AG98: =SUM(AH98:AJ98) -> 0 | AL98: 475000 | AM98: -706164.61
C99: =SUM(D99:S99)-P99-L99-H99-D99 -> 0 | T99: =SUM(U99:AJ99)-AG99-AC99-Y99-U99 -> 0 | AM99: 0
B100: Financing expense (Al-Raeda) | C100: =SUM(D100:S100)-P100-L100-H100-D100 -> -60566.67 | D100: =SUM(E100:G100) -> 0 | H100: =SUM(I100:K100) -> 0 | L100: =SUM(M100:O100) -> 0 | P100: =SUM(Q100:S100) -> -60566.67 | R100: -30283.34 | S100: -30283.33 | T100: =SUM(U100:AJ100)-AG100-AC100-Y100-U100 -> -363399.98 | U100: =SUM(V100:X100) -> -90849.99 | V100: -30283.33 | W100: -30283.33 | X100: -30283.33 | Y100: =SUM(Z100:AB100) -> -90849.99 | Z100: -30283.33 | AA100: -30283.33 | AB100: -30283.33 | AC100: =SUM(AD100:AF100) -> -90849.99 | AD100: -30283.33 | AE100: -30283.33 | AF100: -30283.33 | AG100: =SUM(AH100:AJ100) -> -90850.01 | AH100: -30283.37 | AI100: -30283.31 | AJ100: -30283.33 | AL100: -30283.33 | AM100: -365252.64
C101: =SUM(D101:S101)-P101-L101-H101-D101 -> 0 | T101: =SUM(U101:AJ101)-AG101-AC101-Y101-U101 -> 0 | AM101: 0
B102: Financing expense (Arbah) | C102: =SUM(D102:S102)-P102-L102-H102-D102 -> -724395.84 | D102: =SUM(E102:G102) -> 0 | H102: =SUM(I102:K102) -> 0 | L102: =SUM(M102:O102) -> 0 | P102: =SUM(Q102:S102) -> -724395.84 | R102: -353840.28 | S102: -370555.56 | T102: =SUM(U102:AJ102)-AG102-AC102-Y102-U102 -> -4324423.6 | U102: =SUM(V102:X102) -> -1148520.8 | V102: -387069.45 | W102: -387069.45 | X102: -374381.94 | Y102: =SUM(Z102:AB102) -> -1153152.8 | Z102: -391097.22 | AA102: -383041.67 | AB102: -379013.9 | AC102: =SUM(AD102:AF102) -> -1140263.9 | AD102: -391097.22 | AE102: -378409.72 | AF102: -370756.95 | AG102: =SUM(AH102:AJ102) -> -882486.1 | AH102: -387069.44 | AI102: -239250 | AJ102: -256166.66 | AL102: -255965.28 | AM102: -497027.78
C103: =SUM(D103:S103)-P103-L103-H103-D103 -> 0 | T103: =SUM(U103:AJ103)-AG103-AC103-Y103-U103 -> 0 | AM103: 0
B104: Financing expense (STV) | C104: =SUM(D104:S104)-P104-L104-H104-D104 -> 0 | D104: =SUM(E104:G104) -> 0 | H104: =SUM(I104:K104) -> 0 | L104: =SUM(M104:O104) -> 0 | T104: =SUM(U104:AJ104)-AG104-AC104-Y104-U104 -> 0 | U104: =SUM(V104:X104) -> 0 | Y104: =SUM(Z104:AB104) -> 0 | AC104: =SUM(AD104:AF104) -> 0 | AE104: 0 | AF104: 0 | AI104: 0 | AJ104: 0 | AL104: 0 | AM104: 0
AM105: 0
B106: Financing Expense (Anas Ibrahim Al Hozaimi) | C106: =SUM(D106:S106)-P106-L106-H106-D106 -> 0 | D106: =SUM(E106:G106) -> 0 | H106: =SUM(I106:K106) -> 0 | L106: =SUM(M106:O106) -> 0 | T106: =SUM(U106:AJ106)-AG106-AC106-Y106-U106 -> 0 | U106: =SUM(V106:X106) -> 0 | Y106: =SUM(Z106:AB106) -> 0 | AC106: =SUM(AD106:AF106) -> 0 | AE106: 0 | AF106: 0 | AI106: 0 | AJ106: 0
B108: Financing Expense (Salimuddin Siraj) | C108: =SUM(D108:S108)-P108-L108-H108-D108 -> 0 | D108: =SUM(E108:G108) -> 0 | H108: =SUM(I108:K108) -> 0 | L108: =SUM(M108:O108) -> 0 | T108: =SUM(U108:AJ108)-AG108-AC108-Y108-U108 -> 0 | U108: =SUM(V108:X108) -> 0 | Y108: =SUM(Z108:AB108) -> 0 | AC108: =SUM(AD108:AF108) -> 0 | AE108: 0 | AF108: 0 | AI108: 0 | AJ108: 0
B110: Financing Expense (Amal Abdulmohsen)
B112: Financing Expense (SIDF) | C112: =SUM(D112:S112)-P112-L112-H112-D112 -> -470356.51 | D112: =SUM(E112:G112) -> 0 | H112: =SUM(I112:K112) -> 0 | L112: =SUM(M112:O112) -> 0 | P112: =SUM(Q112:S112) -> -470356.51 | R112: -292518.53 | S112: -177837.98
B114: Financing Processing Fee Expense | C114: =SUM(D114:S114)-P114-L114-H114-D114 -> 0 | D114: =SUM(E114:G114) -> 0 | H114: =SUM(I114:K114) -> 0 | L114: =SUM(M114:O114) -> 0 | P114: =SUM(Q114:S114) -> 0 | S114: 0 | T114: =SUM(U114:AJ114)-AG114-AC114-Y114-U114 -> -52500 | U114: =SUM(V114:X114) -> 0 | W114: 0 | Y114: =SUM(Z114:AB114) -> 0 | AB114: 0 | AC114: =SUM(AD114:AF114) -> 0 | AD114: 0 | AE114: 0 | AF114: 0 | AG114: =SUM(AH114:AJ114) -> -52500 | AH114: 0 | AI114: -52500 | AJ114: 0 | AL114: 0 | AM114: -102500
...

Sheet BS Feb KSA
D4: -1 | P4: -1
B6: STATEMENT OF FINANCIAL POSITION (KSA SAR) | D6: 46387 | E6: 46356 | F6: 46326 | G6: 46295 | H6: 46265 | I6: 46234 | J6: 46203 | K6: 46173 | L6: 46142 | M6: 46112 | N6: 46081 | O6: 46053 | P6: 46022 | Q6: 45991 | R6: 45961 | S6: 45930 | T6: 45900 | U6: 45869 | V6: 45838 | W6: 45808 | X6: 45777 | Y6: 45747 | Z6: 45716 | AA6: 45688 | AC6: 45291 | AD6: 45657
B7: AS OF 28 Feb 2026
B8: ASSETS
B10: Cash and Bank Balances | D10: =SUM(D11:D30) -> 0 | E10: =SUM(E11:E30) -> 0 | F10: =SUM(F11:F30) -> 0 | G10: =SUM(G11:G30) -> 0 | H10: =SUM(H11:H30) -> 0 | I10: =SUM(I11:I31) -> 0 | J10: =SUM(J11:J31) -> 0 | K10: =SUM(K11:K30) -> 0 | L10: =SUM(L11:L29) -> 0 | M10: =SUM(M11:M29) -> 0 | N10: =SUM(N11:N30) -> 21114591 | O10: =SUM(O11:O30) -> 10108437 | P10: =SUM(P11:P30) -> 5193846.4 | Q10: =SUM(Q11:Q30) -> 2433842.9 | R10: =SUM(R11:R30) -> 8732807.8 | S10: =SUM(S11:S30) -> 3751151.1 | T10: =SUM(T11:T30) -> 3703439.9 | U10: =SUM(U11:U31) -> 2071152.1 | V10: =SUM(V11:V31) -> 6618299.3 | W10: =SUM(W11:W30) -> 6035298.9 | X10: =SUM(X11:X29) -> 6828123.3 | Y10: =SUM(Y11:Y29) -> 4763461.8 | Z10: =SUM(Z11:Z29) -> 11306999 | AA10: =SUM(AA11:AA29) -> 5535732.6 | AC10: 3957363.2 | AD10: =SUM(AD11:AD29) -> 10448735
B11: ALINMA BILDNW FEE | C11: =B11 -> ALINMA BILDNW FEE | N11: 0 | O11: 0 | P11: 0 | Q11: 0 | R11: 0 | S11: 0 | T11: 0 | U11: 0 | V11: 0 | W11: 0 | X11: 0 | Y11: 0 | Z11: 0 | AA11: 0 | AC11: 0 | AD11: 0
B12: ALINMA BILDNW PROFIT | C12: =B12 -> ALINMA BILDNW PROFIT | N12: 0 | O12: 0 | P12: 0 | Q12: 0 | R12: 0 | S12: 0 | T12: 0 | U12: 0 | V12: 0 | W12: 0 | X12: 140074.92 | Y12: 140074.92 | Z12: 140074.92 | AA12: 140103.67 | AC12: 0 | AD12: 140103.67
B13: ALINMA CLIENT PROFIT | C13: =B13 -> ALINMA CLIENT PROFIT | N13: 0 | O13: 0 | P13: 0 | Q13: 0 | R13: 0 | S13: 0 | T13: 0 | U13: 0 | V13: 0 | W13: 0 | X13: 135818.27 | Y13: 135818.27 | Z13: 166814.23 | AA13: 166842.98 | AC13: 668024.87 | AD13: 166842.98
B14: ALINMA DINAR DEALs PROFIT | C14: =B14 -> ALINMA DINAR DEALs PROFIT | N14: 0 | O14: 0 | P14: 0 | Q14: 0 | R14: 0 | S14: 0 | T14: 0 | U14: 0 | V14: 0 | W14: 0 | X14: 91275.6 | Y14: 91275.6 | Z14: 91275.6 | AA14: 26086.96 | AC14: 0 | AD14: 30000
B15: ALINMA DINAR DEALs VAT | C15: =B15 -> ALINMA DINAR DEALs VAT | N15: 0 | O15: 0 | P15: 0 | Q15: 0 | R15: 0 | S15: 0 | T15: 0 | U15: 0 | V15: 0 | W15: 0 | X15: 0 | Y15: 0 | Z15: 0 | AA15: 0 | AC15: 43532.61 | AD15: 0
B16: ALINMA EQUITY | C16: =B16 -> ALINMA EQUITY | N16: 1597648.6 | O16: 843035.65 | P16: 477588.36 | Q16: =276114.21 -> 276114.21 | R16: =272657.47 -> 272657.47 | S16: 447636.35 | T16: 27033.82 | U16: 260341.61 | V16: 243984.07 | W16: 427314.42 | X16: 269658.08 | Y16: 792735.94 | Z16: 1482647.5 | AA16: 268408.67 | AC16: 767469.48 | AD16: 1315636.9
B17: ALINMA USD | C17: =B17 -> ALINMA USD | N17: 0 | O17: 0 | P17: 0 | Q17: 0 | R17: 0 | S17: 0 | T17: 0 | U17: 0 | V17: 0 | W17: 0 | X17: 0 | Y17: 0 | Z17: 0 | AA17: 0 | AC17: 0.44 | AD17: 0
B18: ALINMA VAT | C18: =B18 -> ALINMA VAT | N18: 2680.22 | O18: 1850.44 | P18: 1850.44 | Q18: 1850.44 | R18: 1495.53 | S18: 13439.92 | T18: 11985.57 | U18: 75189.77 | V18: 73991.63 | W18: 1.04 | X18: 216190.05 | Y18: 210463.42 | Z18: 200112.41 | AA18: 295015.01 | AC18: 90759.47 | AD18: 131821.9
B19: ALINMA-DEBT | C19: =B19 -> ALINMA-DEBT | N19: 9608915.4 | O19: 1845260.8 | P19: 324493.81 | Q19: 1328664.5 | R19: 6295570.3 | S19: 2340058.2 | T19: 3289226.9 | U19: 1660211.7 | V19: 6201976.1 | W19: 4513496.9 | X19: 5896394.3 | Y19: 3318463.4 | Z19: 9175560.6 | AA19: 4576535.8 | AC19: 2381669.3 | AD19: 8593232.1
B20: ANB-BILDNW TRADINGCOMPANY | C20: =B20 -> ANB-BILDNW TRADINGCOMPANY | N20: 706 | O20: 706 | P20: 706 | Q20: 706 | R20: 706 | S20: 706 | T20: 706 | U20: 706 | V20: 706 | W20: 706 | X20: 706 | Y20: 706 | Z20: 706 | AA20: 106 | AC20: 100.8 | AD20: 6
B21: Riyadh Bank | C21: =B21 -> Riyadh Bank | N21: 130.48 | O21: 130.48 | P21: 130.48 | Q21: 130.48 | R21: 130.48 | S21: 130.48 | T21: 130.48 | U21: 130.48 | V21: 130.48 | W21: 130.48 | X21: 130.48 | Y21: 130.48 | Z21: 130.48 | AA21: 130.48 | AC21: 6.31 | AD21: 30.48
B22: Saudi Awwal Bank (SAB)-5001 | C22: =B22 -> Saudi Awwal Bank (SAB)-5001 | N22: 9333530.6 | O22: 6837833.2 | P22: 161737.04 | Q22: 642122.4 | R22: 2001328.5 | S22: 749992.23 | T22: 100 | U22: 100 | V22: 100
B23: Saudi Awwal Bank (SAB)-5002 | C23: =B23 -> Saudi Awwal Bank (SAB)-5002 | N23: 449991.95 | O23: 449991.95 | P23: 2250000
B24: US Checking Account | C24: =B24 -> US Checking Account | N24: 0 | O24: 0 | P24: 0 | Q24: 0 | R24: 0 | S24: 0 | T24: 0 | U24: 0 | V24: 0 | W24: 0 | X24: 0 | Y24: 0 | Z24: 0 | AA24: 0 | AD24: 0
B25: anb - Tanmeya Debt Acct | C25: =B25 -> anb - Tanmeya Debt Acct | N25: 37094.8 | O25: 37094.8 | P25: 37094.8 | Q25: 37094.8 | R25: 37094.8 | S25: 37094.8 | T25: 37094.8 | U25: 37094.8 | V25: 37094.8 | W25: 37094.8 | X25: 37094.8 | Y25: 37094.8 | Z25: 37094.8 | AA25: 37094.8 | AD25: 37094.8
B26: Simplifi | C26: =B26 -> Simplifi | N26: 7822.62 | O26: 7822.62 | P26: 7822.62 | Q26: 7822.62 | R26: 7822.62 | S26: 7822.62 | T26: 7822.62 | U26: 7822.62 | V26: 7822.62 | W26: 7822.62 | X26: 7822.62 | Y26: 7822.62 | Z26: 7822.62 | AA26: 7822.62 | AD26: 7822.62
B27: SiFi Wallet | C27: =B27 -> SiFi Wallet | N27: -3233.66 | O27: 5088.47 | P27: 19073.71 | Q27: 22604.65 | R27: 13409.11 | S27: 22387.23 | T27: 15814.78 | U27: 20975.45 | V27: 41534 | W27: 37494.58 | X27: 31308.32 | Y27: 25000
B28: Sinking Fund Account | C28: =B28 -> Sinking Fund Account | N28: 104755.43 | O28: 104755.43 | P28: 104755.43 | Q28: 104755.43 | R28: 104755.43 | S28: 104755.43 | T28: 276809.23
B29: Petty Cash | C29: =B29 -> Petty Cash | N29: 10841.71 | O29: 11186.71 | P29: 17506.71 | Q29: 20969.21 | R29: 6863.71 | S29: 36154.71 | T29: 36715.69 | U29: 8579.6 | V29: 10959.6 | W29: 2491.77 | X29: 1649.94 | Y29: 3876.4 | Z29: 4759.4 | AA29: 17585.52 | AC29: 5800 | AD29: 26143.5
B30: Control/ Adjustment | C30: =B30 -> Control/ Adjustment | N30: -36293.05 | O30: -36319.83 | P30: 1791087 | Q30: -8991.84 | R30: -9026.21 | S30: -9026.88 | T30: 0 | U30: -0.01 | V30: 0 | W30: 1008746.3
B32: Trade Receivables (net) | D32: =SUM(D33:D34) -> 0 | E32: =SUM(E33:E34) -> 0 | F32: =SUM(F33:F34) -> 0 | G32: =SUM(G33:G34) -> 0 | H32: =SUM(H33:H34) -> 0 | I32: =SUM(I33:I34) -> 0 | J32: =SUM(J33:J34) -> 0 | K32: =SUM(K33:K34) -> 0 | ... AA32: =SUM(AA33:AA34) -> 41571833 | AC32: 25749560 | AD32: =SUM(AD33:AD34) -> 39178410
B33: Trade Receivables - Gross | C33: Accounts Receivable | N33: 80843930 | O33: 79176075 | P33: 74207264 | Q33: 67634653 | R33: 60700920 | S33: 58161987 | T33: 60295260 | U33: 63272134 | V33: 53991265 | W33: 55060572 | X33: 54945077 | Y33: 56093249 | Z33: 48931754 | AA33: 42002842 | AC33: 25749560 | AD33: 39584419
B34: Closing Provision for doubtful Accounts | C34: Provision for Doubtful Debts | N34: -1152044.2 | O34: -1152044.2 | P34: -1152044.2 | Q34: -678587.63 | R34: -678587.63 | S34: -678587.63 | T34: -1366836 | U34: -1341836 | V34: -556009 | W34: -531009 | X34: =506009*(-1) -> -506009 | Y34: =481009*(-1) -> -481009 | Z34: =456009*(-1) -> -456009 | AA34: =431009*(-1) -> -431009 | AC34: 0 | AD34: -406009
B36: Prepaid Expenses & Other recievables | D36: =SUM(D37:D52) -> 0 | E36: =SUM(E37:E52) -> 0 | F36: =SUM(F37:F52) -> 0 | G36: =SUM(G37:G52) -> 0 | H36: =SUM(H37:H52) -> 0 | I36: =SUM(I37:I52) -> 0 | J36: =SUM(J37:J52) -> 0 | K36: =SUM(K37:K52) -> 0 | L36: =SUM(L37:L52) -> 0 | M36: =SUM(M37:M53) -> 0 | N36: =SUM(N37:N52) -> 19015730 | O36: =SUM(O37:O52) -> 14043475 | P36: =SUM(P37:P52) -> 16759490 | Q36: =SUM(Q37:Q52) -> 13478509 | R36: =SUM(R37:R52) -> 12698551 | S36: =SUM(S37:S52) -> 12990816 | T36: =SUM(T37:T52) -> 9109504.1 | U36: =SUM(U37:U52) -> 8959889.8 | ... X36: =SUM(X37:X52) -> 3623673.8 | Y36: =SUM(Y37:Y53) -> 1466553.8 | Z36: =SUM(Z37:Z53) -> 1750361.7 | AA36: =SUM(AA37:AA53) -> 3197061.1 | AC36: 288133.91 | AD36: =SUM(AD37:AD53) -> 1263663.6
B37: Prepaid Vendors | C37: Prepaid vendors Bildnw Inc. | N37: 15925680 | O37: 12539611 | P37: 12629040 | Q37: 11912369 | R37: 11075859 | S37: 11332316 | T37: 7411466.9 | U37: 7284763.8 | V37: 6372603.1 | W37: 3515144.3 | X37: 2040088.9 | Y37: 0 | Z37: 0 | AA37: 0 | AC37: -8.05 | AD37: 0
B38: Prepaid Accommodation Rent Expense | C38: =B38 -> Prepaid Accommodation Rent Expense | N38: 10416.67 | O38: 0 | P38: 0 | Q38: 0 | R38: 0 | S38: 0 | T38: 0 | U38: 10666.69 | V38: 12800.02 | W38: 2133.35 | X38: 4266.68 | Y38: 6400.01 | Z38: 8533.34 | AA38: 10666.67 | AD38: 0
B39: Prepaid Financing Expense | C39: =B39 -> Prepaid Financing Expense | N39: 18888.91 | O39: 20000.02 | P39: 21111.13 | Q39: 22222.24 | R39: 23333.35 | S39: 24444.46 | T39: 25555.57 | U39: 26666.68 | V39: 27777.79 | W39: 28888.9 | X39: 30000.01 | Y39: 31111.12 | Z39: 32222.23 | AA39: 33333.34 | AD39: 34444.45
B40: Prepaid Govt. Legal Expense | C40: =B40 -> Prepaid Govt. Legal Expense | N40: 9110.02 | O40: 16878.35 | P40: 24646.68 | Q40: 4915.01 | R40: 7683.34 | S40: 10451.67 | T40: 10000 | U40: 12500 | V40: 0 | W40: 5416.65 | X40: 10833.32 | Y40: 16249.99 | Z40: 21666.66 | AA40: 27083.33 | AD40: 32500
B41: Prepaid IT Subscriptions Expense | C41: =B41 -> Prepaid IT Subscriptions Expense | N41: 64783.94 | O41: 41447.61 | P41: 48628.78 | Q41: 55809.95 | R41: 68815.01 | S41: 81820.07 | T41: 58825.13 | U41: 54061.19 | V41: 63623 | W41: 44747.31 | X41: 44921.62 | Y41: 49960.93 | Z41: 56792.32 | AA41: 63623.71 | AD41: 70455.1
B42: Prepaid Office Rent Expense | C42: =B42 -> Prepaid Office Rent Expense | N42: 24684.44 | O42: 0 | P42: 0 | Q42: 0 | R42: 24097.51 | S42: 48195.01 | T42: 72292.51 | U42: 96390.01 | V42: 5062.51 | W42: 6075.01 | X42: 30172.51 | Y42: 54270.01 | Z42: 78367.51 | AA42: 102465.01 | AD42: 126562.51
B43: Prepaid Other Expense | C43: =B43 -> Prepaid Other Expense | N43: 24637.46 | O43: 53727.44 | P43: 77440.92 | Q43: 105418.32 | R43: 133395.72 | S43: 161373.12 | T43: 182258.52 | U43: 181205.77 | V43: 194719.59 | W43: 213412.41 | X43: 186011.13 | Y43: 8171.65 | Z43: 23200.23 | AA43: 43267.67 | AC43: 71234.03 | AD43: 75416.45
B44: Prepaid Employment Expense (Iqama) | C44: =B44 -> Prepaid Employment Expense (Iqama) | N44: 45708.43 | O44: 53291.74 | P44: 41475.05 | Q44: 36125.03 | R44: 22666.68 | S44: 7791.67
B45: Fund Raising Expense receivable | C45: =B45 -> Fund Raising Expense receivable | N45: 4837 | O45: 4837 | P45: 4837 | Q45: 4837 | R45: 4837 | S45: 4837 | T45: 4837 | U45: 4837 | V45: 4837 | W45: 0 | X45: 0 | Y45: 0 | Z45: 215625 | AA45: 0
B46: Employee Receivable | C46: Employee Advance | N46: 210516.54 | O46: 149408.21 | P46: 125999.88 | Q46: 128774.9 | R46: 139325.6 | S46: 127799.47 | T46: 154230.58 | U46: 128380.2 | V46: 97432.82 | W46: 74575.87 | X46: 95688.5 | Y46: 116972.13 | Z46: 133805.47 | AA46: 134197.37 | AC46: 57592.47 | AD46: 150690.88
B47: Security deposits | C47: =B47 -> Security deposits | N47: 11446 | O47: 11446 | P47: 11446 | Q47: 11446 | R47: 11446 | S47: 11446 | T47: 11446 | U47: 2000 | V47: 2000 | W47: 2000 | X47: 2000 | Y47: 2000 | Z47: 2000 | AA47: 2000 | AC47: 1500 | AD47: 2000
B48: Advance to Other Vendors | C48: =B48 -> Advance to Other Vendors | N48: 29076.96 | O48: 29076.96 | P48: 39246.96 | Q48: 61746.96 | R48: 52246.96 | S48: 45496.96 | T48: 43746.96 | U48: 34668.4 | V48: 27996.96 | W48: 27996.96 | X48: 27996.96 | Y48: 29723.81 | Z48: 26454.81 | AA48: 9354.81
B49: Other Receivables | C49: =B49 -> Other Receivables | N49: 0 | O49: 0 | P49: 0 | Q49: 11094.99 | R49: 11094.99 | S49: 11094.99 | T49: 11094.99 | U49: 0 | V49: 0 | W49: 0 | X49: 0 | Y49: 0 | Z49: 0 | AA49: 0 | AC49: 112999.2 | AD49: 0
B50: Input VAT | C50: =B50 -> Input VAT | N50: 1512193.7 | O50: 0 | P50: 2611867.6 | Q50: 0 | R50: 0 | S50: 0 | T50: 0 | U50: 0 | V50: 0 | W50: 0 | X50: 27944.17 | Y50: 27944.17 | Z50: 27944.17 | AA50: 27944.17 | AC50: 44816.26 | AD50: 28469.18
B51: Profit Reserve Account (Deposit) | C51: =B51 -> Profit Reserve Account (Deposit) | N51: 1123750 | O51: 1123750 | P51: 1123750 | Q51: 1123750 | R51: 1123750 | S51: 1123750 | T51: 1123750 | U51: 1123750 | V51: 1123750 | W51: 1123750 | X51: 1123750 | Y51: 1123750 | Z51: 1123750 | AA51: 743125 | AD51: 743125
B52: Short-term Investments | C52: =B52 -> Short-term Investments | N52: 0 | O52: 0 | P52: 0 | R52: 0 | S52: 0 | T52: 0 | U52: 0 | V52: 0 | W52: 0 | X52: 0 | Y52: 0 | Z52: 0 | AA52: 2000000
B54: TOTAL CURRENT ASSETS | D54: =+D36+D10+D32 -> 0 | E54: =+E36+E10+E32 -> 0 | F54: =+F36+F10+F32 -> 0 | G54: =+G36+G10+G32 -> 0 | H54: =+H36+H10+H32 -> 0 | I54: =+I36+I10+I32 -> 0 | J54: =+J36+J10+J32 -> 0 | K54: =+K36+K10+K32 -> 0 | ... AA54: =+AA36+AA10+AA32 -> 50304627 | AC54: 29995057 | AD54: =+AD36+AD10+AD32 -> 50890809
B57: Fixed Assets (net) | D57: =SUM(D58:D70) -> 0 | E57: =SUM(E58:E70) -> 0 | F57: =SUM(F58:F70) -> 0 | G57: =SUM(G58:G70) -> 0 | H57: =SUM(H58:H70) -> 0 | I57: =SUM(I58:I70) -> 0 | J57: =SUM(J58:J70) -> 0 | K57: =SUM(K58:K70) -> 0 | ... AA57: =SUM(AA58:AA70) -> 257134.46 | AC57: 129248.72 | AD57: =SUM(AD58:AD70) -> 208363.25
B58: Accumulated Depreciation - Furniture & Fixture | C58: =B58 -> Accumulated Depreciation - Furniture & Fixture | N58: -46474.29 | O58: -44669.33 | P58: -42864.37 | Q58: -41059.41 | R58: -39254.45 | S58: -37449.49 | T58: -35923.69 | U58: -34320.6 | V58: -32783.91 | W58: -31247.22 | X58: -29710.53 | Y58: -28173.84 | Z58: -26637.15 | AA58: -25239.35 | AC58: -8619.79 | AD58: -23841.55
B59: Accumulated Depreciation - Motor Vehicle | C59: =B59 -> Accumulated Depreciation - Motor Vehicle | N59: -15273.13 | O59: -14469.51 | P59: -13665.89 | Q59: -12862.27 | R59: -12058.65 | S59: -11255.03 | T59: -10451.41 | U59: -9647.79 | V59: -8844.17 | W59: -8040.55 | X59: -7236.93 | Y59: -6433.31 | Z59: -5629.69 | AA59: -4826.07 | AC59: -11379.68 | AD59: -4022.45
B60: Accumulated Depreciation - Office Equipment's | C60: =B60 -> Accumulated Depreciation - Office Equipment's | N60: -157375.64 | O60: -151809.53 | P60: -154171.27 | Q60: -146586.9 | R60: -139281.51 | S60: -133232.47 | T60: -127862.53 | U60: -122791.34 | V60: -118395.41 | W60: -113663.24 | X60: -109304.17 | Y60: -104340.75 | Z60: -100692.36 | AA60: -95880.36 | AC60: -35629.4 | AD60: -91068.56
B61: Accumulated Depreciation-Building Improvement | C61: =B61 -> Accumulated Depreciation-Building Improvement | N61: -29730.4 | O61: -26014.1 | P61: -22297.8 | Q61: -18581.5 | R61: -14865.2 | S61: -11148.9 | T61: -7432.6 | U61: -3716.3
B62: Fixed Asset not yet in use | C62: =B62 -> Fixed Asset not yet in use | N62: 2068.06 | O62: 2068.06 | P62: 2068.06 | Q62: 2068.06 | R62: 2068.06 | S62: 2068.06 | T62: 2068.06 | U62: 2068.06 | V62: 2068.06 | W62: 2068.06 | X62: 2068.06 | Y62: 2068.06 | Z62: 2068.06 | AA62: 2068.06 | AD62: 0
B63: Furniture & Fixture | C63: =B63 -> Furniture & Fixture | N63: 66911.1 | O63: 66911.1 | P63: 66911.1 | Q63: 66911.1 | R63: 66911.1 | S63: 56861.1 | T63: 56861.1 | U63: 55320.87 | V63: 55320.87 | W63: 55320.87 | X63: 55320.87 | Y63: 55320.87 | Z63: 50320.87 | AA63: 50320.87 | AC63: 44482.61 | AD63: 47320.87
B64: Motor Vehicle | C64: =B64 -> Motor Vehicle | N64: 48217.39 | O64: 48217.39 | P64: 48217.39 | Q64: 48217.39 | R64: 48217.39 | S64: 48217.39 | T64: 48217.39 | U64: 48217.39 | V64: 48217.39 | W64: 48217.39 | X64: 48217.39 | Y64: 48217.39 | Z64: 48217.39 | AA64: 48217.39 | AC64: 52521.74 | AD64: 48217.39
B65: Building Improvement | C65: =B65 -> Building Improvement | N65: 178382.44 | O65: 178382.44 | P65: 178382.44 | Q65: 178382.44 | R65: 178382.44 | S65: 178382.44 | T65: 178382.44 | U65: 178382.44
B66: Intangible Assets | C66: =B66 -> Intangible Assets | N66: 1000 | O66: 1000 | P66: 1000 | Q66: 1000 | R66: 1000 | S66: 1000 | T66: 1000 | U66: 1000 | V66: 1000 | W66: 1000
B67: Office Equipment | C67: =B67 -> Office Equipment | N67: 271539.53 | O67: 264791.53 | P67: 264791.53 | Q67: 256966.31 | R67: 226813.98 | S67: 206561.73 | T67: 197351.73 | U67: 185440.43 | V67: 184313.04 | W67: 173563.17 | X67: 173563.17 | Y67: 154959.81 | Z67: 141910.11 | AA67: 141910.11 | AC67: 87873.24 | AD67: 140389.23
B68: Product Development | C68: =B68 -> Product Development | N68: 25000 | O68: 25000 | P68: 25000 | Q68: 25000 | R68: 20000 | S68: 15000 | T68: 10000 | U68: 5000
B69: Capital Work in Progress (Tangible) | C69: =B69 -> Capital Work in Progress (Tangible) | N69: 0 | O69: 0 | P69: 0 | R69: 0 | S69: 0 | T69: 0 | U69: 0 | V69: 176022.44 | W69: 170200.74 | X69: 170200.74 | Y69: 162177.39 | Z69: =161968.7+208.69 -> 162177.39 | AA69: 140563.81 | AD69: 91368.32
B70: Capital Work in Progress (Intangible) | C70: =B70 -> Capital Work in Progress (Intangible) | N70: 0 | O70: 0 | P70: 0 | R70: 0 | S70: 0 | T70: 0 | U70: 0 | V70: 0 | W70: 0 | X70: 0 | Y70: 0 | Z70: 0 | AA70: 0
B71: Intercompany Receivable | D71: =SUM(D72:D79) -> 0 | E71: =SUM(E72:E79) -> 0 | F71: =SUM(F72:F79) -> 0 | G71: =SUM(G72:G79) -> 0 | H71: =SUM(H72:H79) -> 0 | I71: =SUM(I72:I79) -> 0 | J71: =SUM(J72:J79) -> 0 | K71: =SUM(K72:K75) -> 0 | L71: =SUM(L72:L75) -> 0 | M71: =SUM(M72:M79) -> 0 | N71: =SUM(N72:N79) -> 1839510 | O71: =SUM(O72:O79) -> 1803251.9 | P71: =SUM(P72:P79) -> 1691856.1 | Q71: =SUM(Q72:Q79) -> 1575621.1 | R71: =SUM(R72:R79) -> 1530424.1 | S71: =SUM(S72:S79) -> 1412657.6 | T71: =SUM(T72:T79) -> 1399979.4 | ... V71: =SUM(V72:V79) -> 319145.32 | W71: =SUM(W72:W75) -> 302093.63 | X71: =SUM(X72:X75) -> 294043.63 | Y71: =SUM(Y72:Y79) -> 280008.57 | Z71: =SUM(Z72:Z75) -> 280008.57 | AA71: =SUM(AA72:AA75) -> 280008.57 | AC71: 200320 | AD71: =SUM(AD72:AD75) -> 275541.35
B72: Buildnow Inc. (US) | C72: =B72 -> Buildnow Inc. (US) | N72: 1756700.7 | O72: 1720442.7 | P72: 1615122.1 | Q72: 1502512.1 | R72: 1459297.6 | S72: 1342934.6 | T72: 1332281.9 | U72: 646252.94 | V72: 293647.89 | W72: 279850.36 | X72: 279850.36 | Y72: 269850 | Z72: 269850 | AA72: 269850 | AC72: 200320 | AD72: 269850
B73: Buildnow Tech BD | C73: =B73 -> Buildnow Tech BD | N73: 41.33 | O73: 41.33 | P73: 41.33 | Q73: 41.33 | R73: 41.33 | S73: 41.33 | T73: 41.33 | U73: 41.33 | V73: 41.33 | W73: 41.33 | X73: 41.33 | Y73: 41.33 | Z73: 41.33 | AA73: 41.33 | AD73: 41.33
B74: Buildnow Trading Co (KSA) | C74: =B74 -> Buildnow Trading Co (KSA) | N74: 0 | O74: 0 | P74: 0 | Q74: 0 | R74: 0 | S74: 0 | T74: 0 | U74: 0 | V74: 0 | W74: 0 | X74: 0 | Y74: 0 | Z74: 0 | AA74: 0 | AD74: 0
B75: MISA KSA | C75: =B75 -> MISA KSA | N75: 30842.42 | O75: 30842.42 | P75: 30842.42 | Q75: 29017.42 | R75: 29017.42 | S75: 25201.94 | T75: 25201.94 | U75: 25201.94 | V75: 25201.94 | W75: 22201.94 | X75: 14151.94 | Y75: 10117.24 | Z75: 10117.24 | AA75: 10117.24 | AD75: 5650.02
B76: RHQ Company | C76: =B76 -> RHQ Company | N76: 7671.35 | O76: 7671.35 | P76: 1596.1 | Q76: 1596.1 | R76: -386.42 | S76: 2025.58
B77: BNPL-CMA | C77: =B77 -> BNPL-CMA | N77: 44000 | O77: 44000 | P77: 44000 | Q77: 42200 | R77: 42200 | S77: 42200 | T77: 42200 | U77: 40000
B78: Buildnow UK | C78: =B78 -> Buildnow UK | N78: 254.16 | O78: 254.16 | P78: 254.16 | Q78: 254.16 | R78: 254.16 | S78: 254.16 | T78: 254.16 | U78: 254.16 | V78: 254.16 | W78: 0 | X78: 0
B80: Investment in Subsidiaries | D80: =SUM(D81) -> 0 | E80: =SUM(E81) -> 0 | F80: =SUM(F81) -> 0 | G80: =SUM(G81) -> 0 | H80: =SUM(H81) -> 0 | I80: =SUM(I81) -> 0 | J80: =SUM(J81) -> 0 | K80: =SUM(K81) -> 0 | ... AA80: =SUM(AA81) -> 0 | AD80: =SUM(AD81) -> 0
B81: Buildnow BD Technology Subsidiary | C81: =B81 -> Buildnow BD Technology Subsidiary | F81: 0 | G81: 0 | H81: 0 | I81: 0 | J81: 0 | K81: 0 | L81: 0 | M81: 0 | N81: 0 | O81: 0 | R81: 0 | S81: 0 | T81: 0 | U81: 0 | V81: 0 | W81: 0 | X81: 0 | Y81: 0 | Z81: 0 | AA81: 0
B84: TOTAL NON CURRENT ASSETS | D84: =+D71+D57+D80 -> 0 | E84: =+E71+E57+E80 -> 0 | F84: =+F71+F57+F80 -> 0 | G84: =+G71+G57+G80 -> 0 | H84: =+H71+H57+H80 -> 0 | I84: =+I71+I57+I80 -> 0 | J84: =+J71+J57+J80 -> 0 | K84: =+K71+K57+K80 -> 0 | ... AA84: =+AA71+AA57+AA80 -> 537143.03 | AC84: 329568.72 | AD84: =+AD71+AD57+AD80 -> 483904.6
B87: TOTAL ASSETS | D87: =+D84+D54 -> 0 | E87: =+E84+E54 -> 0 | F87: =+F84+F54 -> 0 | G87: =+G84+G54 -> 0 | H87: =+H84+H54 -> 0 | I87: =+I84+I54 -> 0 | J87: =+J84+J54 -> 0 | K87: =+K84+K54 -> 0 | ... AA87: =+AA84+AA54 -> 50841770 | AC87: 30324626 | AD87: =+AD84+AD54 -> 51374713 | AG87: =AE87-AF87 -> 0
B90: LIABILITIES & OWNER'S EQUITY
B92: Other Payables and Accruals | D92: =SUM(D93:D114) -> 0 | E92: =SUM(E93:E114) -> 0 | F92: =SUM(F93:F114) -> 0 | G92: =SUM(G93:G114) -> 0 | H92: =SUM(H93:H114) -> 0 | I92: =SUM(I93:I114) -> 0 | J92: =SUM(J93:J114) -> 0 | K92: =SUM(K93:K114) -> 0 | ... AA92: =SUM(AA93:AA114) -> 1130334.3 | AC92: 1472393.1 | AD92: =SUM(AD93:AD113) -> 1665946.3
B93: Zakat Provision | C93: Provision for Zakat | N93: 5902.9 | O93: 5902.9 | P93: 5902.9 | Q93: 5902.9 | R93: 5902.9 | S93: 5902.9 | T93: 5902.9 | U93: 5902.9 | V93: 5902.9 | W93: 5902.9 | X93: =Y93 -> 45000 | Y93: 45000 | Z93: 45000 | AA93: 45000 | AC93: 75000 | AD93: 0
B94: Misc. Payables | C94: =B94 -> Misc. Payables | N94: 0 | O94: 0 | P94: 0 | Q94: 0 | R94: 0 | S94: 0 | T94: 0 | U94: 0 | V94: 0 | W94: 158987.5 | X94: 158987.5 | Y94: 158987.5 | Z94: 158987.5 | AA94: 158987.5 | AC94: 158987.5 | AD94: 158987.5
B95: Consultancy Fee Payable | C95: =B95 -> Consultancy Fee Payable | N95: 0 | O95: 0 | P95: 0 | Q95: 0 | R95: 0 | S95: 0 | T95: 0 | U95: 0 | V95: 0
B96: Other Payables | C96: =B96 -> Other Payables | N96: 127255.97 | O96: 262755.28 | P96: =214241.23+35000 -> 249241.23 | Q96: 193897.54 | R96: 183785.76 | S96: 183574.57 | T96: 100165.03 | U96: 128246.38 | V96: 166750.08 | W96: 152279.58 | X96: 244959.08 | Y96: 186045.58 | Z96: 186226.96 | AA96: 182694.27 | AD96: 139840
B97: Unearned Revenue | C97: =B97 -> Unearned Revenue | N97: 13725.11 | O97: 13724.88 | P97: 13723.45 | Q97: 13720.72 | R97: 13717.4 | S97: 12329.04 | T97: 262324.38 | U97: 12324.64 | V97: 12270.48 | W97: 10547.36 | X97: 10546.47 | Y97: 10544.82 | Z97: 10543.5 | AA97: -100.96 | AC97: 0.35 | AD97: 1373.79
B98: Employee Payable | C98: =B98 -> Employee Payable | N98: 0 | O98: 0 | P98: 0 | Q98: 0 | R98: 0 | S98: 0 | T98: 0 | U98: 0 | V98: 0 | W98: 0 | X98: 0 | Y98: 0 | Z98: 0 | AA98: 0 | AC98: 616.48 | AD98: 0
B99: Employee Allowance Payable | C99: =B99 -> Employee Allowance Payable | N99: 4700 | O99: 4700 | P99: 4000 | Q99: 0 | R99: 5409.68 | S99: 4700 | T99: 4700 | U99: 4200 | V99: 4200 | W99: 0 | X99: 0 | Y99: 0 | Z99: 4900 | AA99: 0
B100: Accounts Payable | C100: =B100 -> Accounts Payable | N100: 1019882.8 | O100: 1077281.2 | P100: 57047.14 | Q100: 259886.38 | R100: 57026.5 | S100: 82345.77 | T100: 709595.53 | U100: 94951.09 | V100: 185549.69 | W100: 282007.45 | X100: 246996.89 | Y100: 565016.33 | Z100: 566378.49 | AA100: 337658.79 | AC100: 0 | AD100: 877017.06
B101: Accrued Expenses | C101: =B101 -> Accrued Expenses | N101: 0 | O101: 0 | AD101: 25866.83
B102: VAT Payable (GAZT) | C102: GCC VAT Payable | N102: 1.78 | O102: 149172 | P102: 1.45 | Q102: 566220.41 | R102: 314646.46 | S102: 521945.53 | T102: 143546.61 | U102: 538204.98 | V102: 623802.37 | W102: 296852.7 | X102: 422673.48 | Y102: 572259.44 | Z102: 506512.24 | AA102: 158790.34 | AC102: 317117.71 | AD102: 129870.78
B103: Accrued Investor Profit | C103: =B103 -> Accrued Investor Profit | N103: 0 | O103: 0 | P103: 0 | Q103: 0 | R103: 0 | S103: 0 | T103: 0 | U103: 0 | V103: 0 | W103: 9954 | X103: 66292.27 | Y103: 66292.27 | Z103: 66292.27 | AA103: 66292.27 | AC103: 310223.26 | AD103: 119793.9
B104: Accrued Investor Profit (Unrealized) | C104: =B104 -> Accrued Investor Profit (Unrealized) | N104: 0 | O104: 0 | P104: 0 | Q104: 0 | R104: 0 | S104: 0 | T104: 0 | U104: 0 | V104: 0 | W104: 0 | X104: 0 | Y104: 0 | Z104: 0 | AA104: 0
B105: Leave Air Fare Payable | C105: =B105 -> Leave Air Fare Payable | N105: 0 | O105: 0 | P105: 7350
B106: Leave Pay Payable | C106: Provision for Leave Pay | N106: 264025.04 | O106: 264025.04 | P106: 264025.04 | Q106: 5857.26 | R106: 10798.26 | S106: 16746.96 | T106: 16746.96 | U106: 28646.96 | V106: 41530.96 | W106: 44774.96 | X106: 44774.96 | Y106: 44774.96 | Z106: 47874.96 | AA106: 47874.96 | AD106: 47874.96
B107: Salary Control Account | C107: Salaries & Wages Payables | N107: 449984.14 | O107: 9300.17 | P107: 50000.17 | Q107: 20000.17 | R107: 0.18 | S107: 5000.17 | T107: 0.18 | U107: 37833.51 | V107: 0.17 | W107: 15000.17 | X107: 19318.34 | Y107: =17970.88-17970.71 -> 0.17 | Z107: 0.17 | AA107: 0.15 | AC107: 2237.5 | AD107: 31871.18
B108: Accrued COGS | C108: =B108 -> Accrued COGS | N108: 14784290 | O108: 10439672 | P108: 11582144 | Q108: 11451308 | R108: 10231118 | S108: 9971471.7 | T108: 6609166.6 | U108: 7097296.8 | V108: 5564391.5 | W108: 2516415.7 | X108: 1977692.6
B109: Output VAT | C109: =B109 -> Output VAT | N109: 2463674.9 | O109: 0 | P109: 3039744.2 | Q109: 0 | R109: 0 | S109: 0 | T109: 0 | U109: 0 | V109: 0 | W109: 0 | X109: 73342.56 | Y109: 73342.56 | Z109: 73342.45 | AA109: 73342.41 | AC109: 65677.87 | AD109: 73342.41
B110: GOSI Payable | C110: =B110 -> GOSI Payable | N110: 22974.49 | O110: 23486.34 | P110: 21085.6 | Q110: 27674.24 | R110: 29148.31 | S110: 28972.67 | T110: 28886.22 | U110: 21632.43 | V110: 20301.81 | W110: 19069.45 | X110: 18075.7 | Y110: 20924.5 | Z110: 26421.63 | AA110: 28845.08 | AC110: 6851.52 | AD110: 29169.43
B111: Deferred Revenue | C111: =B111 -> Deferred Revenue | N111: 11 | O111: 11 | P111: 11 | Q111: 11 | R111: 11 | S111: 11 | T111: 11 | U111: 11 | V111: 11 | W111: 11 | X111: 11 | Y111: 11 | Z111: 11 | AA111: 11
B112: Dividend Payable (Investor) | N112: 0 | O112: 0 | P112: 0 | R112: 0 | S112: 0 | T112: 0 | U112: 0 | V112: 0 | W112: 0 | X112: 0 | Y112: 0 | Z112: 30938.46 | AA112: 30938.46 | AD112: 30938.46
B113: Debt Settlement Payable | N113: 0 | O113: 0 | P113: 0 | Q113: 0 | R113: 0 | S113: 0 | T113: 0 | U113: 0 | V113: 0 | W113: 0 | X113: 0 | Y113: 0 | AA113: 0 | AD113: 0
B115: Short term Financing | D115: =SUM(D116:D124) -> 0 | E115: =SUM(E116:E124) -> 0 | F115: =SUM(F116:F124) -> 0 | G115: =SUM(G116:G124) -> 0 | H115: =SUM(H116:H124) -> 0 | I115: =SUM(I116:I124) -> 0 | J115: =SUM(J116:J124) -> 0 | K115: =SUM(K116:K124) -> 0 | ... AA115: =SUM(AA116:AA124) -> 22530283 | AC115: 2239362.4 | AD115: =SUM(AD116:AD124) -> 22530283
B116: Interest payable (Al-Raeda) | O116: 0 | P116: 0 | Q116: 0 | R116: 0 | S116: 0 | T116: 30283.33 | U116: 30283.33 | V116: 0 | W116: 30283.33 | X116: 30283.33 | Y116: 30283.33 | Z116: 30283.29 | AA116: 30283.31 | AC116: 33956.18 | AD116: 30283.31
B117: Short-term Financing (Al Raedah) | C117: Debt Financing (Al Raedah 2) | N117: 2000000 | O117: 2000000 | P117: 2000000 | Q117: 2000000 | R117: 2000000 | S117: 2000000 | T117: 2000000 | U117: 2000000 | V117: 2000000 | W117: 2000000 | X117: =Y117 -> 2000000 | Y117: =Z117 -> 2000000 | Z117: =AA117 -> 2000000 | AA117: 2000000 | AC117: 2205406.3 | AD117: 2000000
B118: Arbah Murabaha Facility | C118: =B118 -> Arbah Murabaha Facility | N118: 31000000 | O118: 31000000 | P118: 31000000 | Q118: 31000000 | R118: 31000000 | S118: 31000000 | T118: 31000000 | U118: 31000000 | V118: 31000000 | W118: 31000000 | X118: 31000000 | Y118: 31000000 | Z118: 31000000 | AA118: 20500000 | AD118: 20500000
B119: SIDF Loan Facility | C119: =B119 -> SIDF Loan Facility | N119: 30000000 | O119: 20000000 | P119: 10000000
...

Sheet IS Feb USA
B7: INCOME STATEMENT (US SAR) | C7: YTD | D7: Q4 | E7: MTD | F7: MTD | G7: MTD | H7: Q3 | I7: MTD | J7: MTD | K7: MTD | L7: Q2 | M7: MTD | N7: MTD | O7: MTD | P7: Q1 | Q7: MTD | R7: MTD | S7: MTD | T7: YTD | U7: Q4 | V7: MTD | W7: MTD | X7: MTD | Y7: Q3 | Z7: MTD | AA7: MTD | AB7: MTD | AC7: Q2 | AD7: MTD | AE7: MTD | AF7: MTD | AG7: Q1 | AH7: MTD | AI7: MTD | AJ7: MTD | AL7: MTD | AM7: YTD
B8: FOR THE PERIOD 28 Feb 2026 | C8: 46387 | D8: 2026 | E8: 46387 | F8: 46356 | G8: 46326 | H8: 2026 | I8: 46295 | J8: 46265 | K8: 46234 | L8: 2026 | M8: 46203 | N8: 46173 | O8: 46142 | P8: 2026 | Q8: 46112 | R8: 46081 | S8: 46053 | T8: 46022 | U8: 2025 | V8: 46022 | W8: 45991 | X8: 45961 | Y8: 2025 | Z8: 45930 | AA8: 45900 | AB8: 45869 | AC8: 2025 | AD8: 45838 | AE8: 45808 | AF8: 45777 | AG8: 2025 | AH8: 45747 | AI8: 45716 | AJ8: 45688 | AL8: 45657 | AM8: 45657
B10: Sales | C10: =SUM(D10:S10)-P10-L10-H10-D10 -> 0 | D10: =SUM(E10:G10) -> 0 | H10: =SUM(I10:K10) -> 0 | I10: 0 | J10: 0 | K10: 0 | L10: =SUM(M10:O10) -> 0 | M10: 0 | N10: 0 | O10: 0 | P10: =SUM(Q10:S10) -> 0 | Q10: 0 | R10: 0 | S10: 0 | T10: =SUM(U10:AJ10)-AG10-AC10-Y10-U10 -> 0 | U10: =SUM(V10:X10) -> 0 | Y10: =SUM(Z10:AB10) -> 0 | Z10: 0 | AA10: 0 | AB10: 0 | AC10: =SUM(AD10:AF10) -> 0 | AD10: 0 | AE10: 0 | AF10: 0 | AG10: =SUM(AH10:AJ10) -> 0 | AH10: 0 | AI10: 0 | AJ10: 0 | AM10: 0
B11: Sales Discount | H11: =SUM(I11:K11) -> 0 | K11: 0 | L11: =SUM(M11:O11) -> 0 | M11: 0 | O11: 0 | S11: 0 | Y11: =SUM(Z11:AB11) -> 0 | AB11: 0 | AC11: =SUM(AD11:AF11) -> 0 | AD11: 0 | AF11: 0
B12: Cost of Goods Sold | C12: =SUM(D12:S12)-P12-L12-H12-D12 -> 0 | D12: =SUM(E12:G12) -> 0 | H12: =SUM(I12:K12) -> 0 | I12: 0 | J12: 0 | K12: 0 | L12: =SUM(M12:O12) -> 0 | M12: 0 | N12: 0 | O12: 0 | P12: =SUM(Q12:S12) -> 0 | Q12: 0 | R12: 0 | S12: 0 | T12: =SUM(U12:AJ12)-AG12-AC12-Y12-U12 -> 0 | U12: =SUM(V12:X12) -> 0 | Y12: =SUM(Z12:AB12) -> 0 | Z12: 0 | AA12: 0 | AB12: 0 | AC12: =SUM(AD12:AF12) -> 0 | AD12: 0 | AE12: 0 | AF12: 0 | AG12: =SUM(AH12:AJ12) -> 0 | AH12: 0 | AI12: 0 | AJ12: 0 | AM12: 0
B13: Purchase Discounts | C13: =SUM(D13:S13)-P13-L13-H13-D13 -> 0 | D13: =SUM(E13:G13) -> 0 | H13: =SUM(I13:K13) -> 0 | I13: 0 | J13: 0 | K13: 0 | L13: =SUM(M13:O13) -> 0 | M13: 0 | N13: 0 | O13: 0 | P13: =SUM(Q13:S13) -> 0 | Q13: 0 | R13: 0 | S13: 0 | T13: =SUM(U13:AJ13)-AG13-AC13-Y13-U13 -> 0 | U13: =SUM(V13:X13) -> 0 | Y13: =SUM(Z13:AB13) -> 0 | Z13: 0 | AA13: 0 | AB13: 0 | AC13: =SUM(AD13:AF13) -> 0 | AD13: 0 | AE13: 0 | AF13: 0 | AG13: =SUM(AH13:AJ13) -> 0 | AH13: 0 | AI13: 0 | AJ13: 0 | AM13: 0
B14: Gross Profit / (Loss) | C14: =+C10-C12 -> 0 | D14: =+D10-D12 -> 0 | E14: =+E10-E12 -> 0 | F14: =+F10-F12 -> 0 | G14: =+G10-G12 -> 0 | H14: =+H10-H12 -> 0 | I14: =+I10-I12 -> 0 | J14: =+J10-J12 -> 0 | K14: 0 | L14: =+L10-L12 -> 0 | M14: =+M10-M12 -> 0 | N14: =+N10-N12 -> 0 | O14: =+O10-O12 -> 0 | P14: =+P10-P12 -> 0 | Q14: =+Q10-Q12 -> 0 | R14: =+R10-R12 -> 0 | S14: =+S10-S12 -> 0 | ... AA14: =+AA10-AA12 -> 0 | AB14: 0 | AC14: =+AC10-AC12 -> 0 | AD14: =+AD10-AD12 -> 0 | AE14: =+AE10-AE12 -> 0 | AF14: =+AF10-AF12 -> 0 | AG14: =+AG10-AG12 -> 0 | AH14: =+AH10-AH12 -> 0 | AI14: =+AI10-AI12 -> 0 | AJ14: =+AJ10-AJ12 -> 0 | AL14: =+AL10-AL12 -> 0 | AM14: 0
B15: Other Income | C15: =+D15+H15+L15+P15 -> 0 | D15: =SUM(E15:G15) -> 0 | H15: =SUM(I15:K15) -> 0 | L15: =SUM(M15:O15) -> 0 | O15: 0 | P15: =SUM(Q15:S15) -> 0 | Q15: 0 | S15: 0 | T15: =+U15+Y15+AC15+AG15 -> 230.96 | U15: =SUM(V15:X15) -> 0 | Y15: =SUM(Z15:AB15) -> 124.13 | Z15: 37.5 | AB15: 86.63 | AC15: =SUM(AD15:AF15) -> 98.26 | AD15: 49.13 | AE15: 49.13 | AF15: 0 | AG15: =SUM(AH15:AJ15) -> 8.57 | AH15: 0 | AI15: 8.57
B16: Consultation Income | C16: =+D16+H16+L16+P16 -> 0 | D16: =SUM(E16:G16) -> 0 | H16: =SUM(I16:K16) -> 0 | I16: 0 | J16: 0 | K16: 0 | L16: =SUM(M16:O16) -> 0 | N16: 0 | O16: 0 | P16: =SUM(Q16:S16) -> 0 | Q16: 0 | R16: 0 | S16: 0 | T16: =+U16+Y16+AC16+AG16 -> 0 | U16: =SUM(V16:X16) -> 0 | Y16: =SUM(Z16:AB16) -> 0 | Z16: 0 | AA16: 0 | AB16: 0 | AC16: =SUM(AD16:AF16) -> 0 | AE16: 0 | AF16: 0 | AG16: =SUM(AH16:AJ16) -> 0 | AH16: 0 | AI16: 0 | AJ16: 0 | AM16: 0
B17: Gross Income | C17: =+D17+H17+L17+P17 -> 0 | D17: =SUM(E17:G17) -> 0 | E17: =+E16+E14 -> 0 | F17: =+F16+F14 -> 0 | G17: =+G16+G14 -> 0 | H17: =SUM(I17:K17) -> 0 | I17: =+I16+I14 -> 0 | J17: =+J16+J14 -> 0 | K17: =+K16+K14 -> 0 | L17: =SUM(M17:O17) -> 0 | M17: =+M16+M14 -> 0 | N17: =+N16+N14 -> 0 | O17: =+O16+O14 -> 0 | P17: =SUM(Q17:S17) -> 0 | Q17: =+Q16+Q14 -> 0 | R17: =+R16+R14 -> 0 | S17: =+S16+S14 -> 0 | T17: =+U17+Y17+AC17+AG17 -> 0 | U17: =SUM(V17:X17) -> 0 | V17: =+V16+V14 -> 0 | W17: =+W16+W14 -> 0 | X17: =+X16+X14 -> 0 | Y17: =SUM(Z17:AB17) -> 0 | Z17: =+Z16+Z14 -> 0 | AA17: =+AA16+AA14 -> 0 | AB17: =+AB16+AB14 -> 0 | AC17: =SUM(AD17:AF17) -> 0 | AD17: =+AD16+AD14 -> 0 | AE17: =+AE16+AE14 -> 0 | AF17: =+AF16+AF14 -> 0 | AG17: =SUM(AH17:AJ17) -> 0 | AH17: =+AH16+AH14 -> 0 | AI17: =+AI16+AI14 -> 0 | AJ17: =+AJ16+AJ14 -> 0 | AL17: =+AL16+AL14 -> 0 | AM17: 0
B19: General and Administrative Expenses | C19: =SUM(C20:C36) -> 110952.55 | D19: =SUM(D20:D36) -> 0 | E19: =SUM(E20:E38) -> 0 | F19: =SUM(F20:F38) -> 0 | G19: =SUM(G20:G38) -> 0 | H19: =SUM(H20:H36) -> 0 | I19: =SUM(I20:I36) -> 0 | J19: =SUM(J20:J36) -> 0 | K19: =SUM(K20:K36) -> 0 | L19: =SUM(L20:L36) -> 0 | M19: =SUM(M20:M36) -> 0 | N19: =SUM(N20:N36) -> 0 | O19: =SUM(O20:O36) -> 0 | ... U19: =SUM(U20:U36) -> 175978.66 | V19: =SUM(V20:V38) -> 66302.95 | W19: =SUM(W20:W38) -> 54700.53 | X19: =SUM(X20:X38) -> 54975.19 | Y19: =SUM(Y20:Y36) -> 137466.07 | Z19: =SUM(Z20:Z36) -> 53626.05 | AA19: =SUM(AA20:AA36) -> 41895.4 | AB19: =SUM(AB20:AB36) -> 41944.62 | AC19: =SUM(AC20:AC36) -> 132170.5 | AD19: =SUM(AD20:AD36) -> 38505.31 | AE19: =SUM(AE20:AE36) -> 47225.39 | AF19: =SUM(AF20:AF36) -> 46439.8 | ... AJ19: =SUM(AJ20:AJ36) -> 37396.01 | AL19: =SUM(AL20:AL36) -> 33034.48 | AM19: =SUM(AM20:AM36) -> 317021.54
B20: Bad Debt | C20: =SUM(D20:S20)-P20-L20-H20-D20 -> 0 | D20: =SUM(E20:G20) -> 0 | H20: =SUM(I20:K20) -> 0 | L20: =SUM(M20:O20) -> 0 | P20: =SUM(Q20:S20) -> 0 | T20: =SUM(U20:AJ20)-AG20-AC20-Y20-U20 -> 0 | U20: =SUM(V20:X20) -> 0 | Y20: =SUM(Z20:AB20) -> 0 | AB20: 0 | AC20: =SUM(AD20:AF20) -> 0 | AF20: 0 | AG20: =SUM(AH20:AJ20) -> 0 | AH20: 0 | AI20: 0 | AJ20: 0 | AL20: 0 | AM20: 0
B21: Bank Fees and Charges | C21: =SUM(D21:S21)-P21-L21-H21-D21 -> 4023.15 | D21: =SUM(E21:G21) -> 0 | H21: =SUM(I21:K21) -> 0 | L21: =SUM(M21:O21) -> 0 | P21: =SUM(Q21:S21) -> 4023.15 | R21: 1640.47 | S21: 2382.68 | T21: =SUM(U21:AJ21)-AG21-AC21-Y21-U21 -> 23806.49 | U21: =SUM(V21:X21) -> 6354.89 | V21: 2799.75 | W21: 1044.61 | X21: 2510.53 | Y21: =SUM(Z21:AB21) -> 5516.69 | Z21: 1401.42 | AA21: 1613.27 | AB21: 2502 | AC21: =SUM(AD21:AF21) -> 5864.87 | AD21: 1620.12 | AE21: 1984.52 | AF21: 2260.23 | AG21: =SUM(AH21:AJ21) -> 6070.04 | AH21: 2424.47 | AI21: 1909.9 | AJ21: 1735.67 | AL21: 2027.25 | AM21: 17230.24
B22: Office Supplies | C22: =SUM(D22:S22)-P22-L22-H22-D22 -> 0 | D22: =SUM(E22:G22) -> 0 | H22: =SUM(I22:K22) -> 0 | L22: =SUM(M22:O22) -> 0 | P22: =SUM(Q22:S22) -> 0 | S22: 0 | T22: =SUM(U22:AJ22)-AG22-AC22-Y22-U22 -> 1046.52 | U22: =SUM(V22:X22) -> 71.06 | V22: 0 | W22: 71.06 | X22: 0 | Y22: =SUM(Z22:AB22) -> 0 | AB22: 0 | AC22: =SUM(AD22:AF22) -> 0 | AE22: 0 | AF22: 0 | AG22: =SUM(AH22:AJ22) -> 975.46 | AH22: 0 | AI22: 975.46 | AJ22: 0 | AL22: 0 | AM22: 28437.69
B23: Office Utilities - Electricity/Water/Janitorial | C23: =SUM(D23:S23)-P23-L23-H23-D23 -> 0 | D23: =SUM(E23:G23) -> 0 | H23: =SUM(I23:K23) -> 0 | L23: =SUM(M23:O23) -> 0 | P23: =SUM(Q23:S23) -> 0 | T23: =SUM(U23:AJ23)-AG23-AC23-Y23-U23 -> 0 | U23: =SUM(V23:X23) -> 0 | V23: 0 | X23: 0 | Y23: =SUM(Z23:AB23) -> 0 | AB23: 0 | AC23: =SUM(AD23:AF23) -> 0 | AE23: 0 | AF23: 0 | AG23: =SUM(AH23:AJ23) -> 0 | AH23: 0 | AI23: 0 | AJ23: 0 | AL23: 0 | AM23: 0
B24: Office Expenses | C24: =SUM(D24:S24)-P24-L24-H24-D24 -> 0 | D24: =SUM(E24:G24) -> 0 | H24: =SUM(I24:K24) -> 0 | L24: =SUM(M24:O24) -> 0 | P24: =SUM(Q24:S24) -> 0 | S24: 0 | T24: =SUM(U24:AJ24)-AG24-AC24-Y24-U24 -> 667.5 | U24: =SUM(V24:X24) -> 0 | V24: 0 | X24: 0 | Y24: =SUM(Z24:AB24) -> 0 | Z24: 0 | AB24: 0 | AC24: =SUM(AD24:AF24) -> 667.5 | AD24: 0 | AE24: 0 | AF24: 667.5 | AG24: =SUM(AH24:AJ24) -> 0 | AH24: 0 | AI24: 0 | AJ24: 0 | AL24: 0 | AM24: 2963.41
B25: Office Repair & Maintenance Expense | L25: =SUM(M25:O25) -> 0 | P25: =SUM(Q25:S25) -> 0 | V25: 0 | X25: 0
B26: Travel Expense | C26: =SUM(D26:S26)-P26-L26-H26-D26 -> 2487.72 | D26: =SUM(E26:G26) -> 0 | H26: =SUM(I26:K26) -> 0 | L26: =SUM(M26:O26) -> 0 | P26: =SUM(Q26:S26) -> 2487.72 | R26: 687.72 | S26: 1800 | T26: =SUM(U26:AJ26)-AG26-AC26-Y26-U26 -> 13275.92 | U26: =SUM(V26:X26) -> 10260.88 | V26: 6471.88 | W26: 1684.86 | X26: 2104.14 | Y26: =SUM(Z26:AB26) -> 3015.04 | Z26: 178.05 | AA26: 2836.99 | AB26: 0 | AC26: =SUM(AD26:AF26) -> 0 | AE26: 0 | AF26: 0 | AG26: =SUM(AH26:AJ26) -> 0 | AH26: 0 | AI26: 0 | AJ26: 0 | AL26: 0 | AM26: 8231.25
B27: Printing and Stationery | C27: =SUM(D27:S27)-P27-L27-H27-D27 -> 0 | D27: =SUM(E27:G27) -> 0 | H27: =SUM(I27:K27) -> 0 | L27: =SUM(M27:O27) -> 0 | P27: =SUM(Q27:S27) -> 0 | S27: 0 | T27: =SUM(U27:AJ27)-AG27-AC27-Y27-U27 -> 223.48 | U27: =SUM(V27:X27) -> 0 | V27: 0 | X27: 0 | Y27: =SUM(Z27:AB27) -> 0 | AB27: 0 | AC27: =SUM(AD27:AF27) -> 0 | AD27: 0 | AE27: 0 | AF27: 0 | AG27: =SUM(AH27:AJ27) -> 223.48 | AH27: 0 | AI27: 0 | AJ27: 223.48 | AL27: 0 | AM27: 0
B28: Rent Expense (G&A) | C28: =SUM(D28:S28)-P28-L28-H28-D28 -> 0 | D28: =SUM(E28:G28) -> 0 | H28: =SUM(I28:K28) -> 0 | L28: =SUM(M28:O28) -> 0 | P28: =SUM(Q28:S28) -> 0 | T28: =SUM(U28:AJ28)-AG28-AC28-Y28-U28 -> 0 | U28: =SUM(V28:X28) -> 0 | V28: 0 | X28: 0 | Y28: =SUM(Z28:AB28) -> 0 | AB28: 0 | AC28: =SUM(AD28:AF28) -> 0 | AD28: 0 | AE28: 0 | AF28: 0 | AG28: =SUM(AH28:AJ28) -> 0 | AH28: 0 | AI28: 0 | AJ28: 0 | AL28: 0 | AM28: 0
B29: Meals and Entertainment | C29: =SUM(D29:S29)-P29-L29-H29-D29 -> 1014.94 | D29: =SUM(E29:G29) -> 0 | H29: =SUM(I29:K29) -> 0 | L29: =SUM(M29:O29) -> 0 | P29: =SUM(Q29:S29) -> 1014.94 | R29: 1014.94 | S29: 0 | T29: =SUM(U29:AJ29)-AG29-AC29-Y29-U29 -> 6281.59 | U29: =SUM(V29:X29) -> 2641.82 | V29: =1486.69+150 -> 1636.69 | W29: 0 | X29: 1005.13 | Y29: =SUM(Z29:AB29) -> 986.55 | Z29: 0 | AA29: 574.05 | AB29: 412.5 | AC29: =SUM(AD29:AF29) -> 1677.26 | AD29: 0 | AE29: 1677.26 | AF29: 0 | AG29: =SUM(AH29:AJ29) -> 975.96 | AH29: 0 | AI29: 975.96 | AJ29: 0 | AL29: 0 | AM29: 7229.12
B30: Audit & Consultancy expense | C30: =SUM(D30:S30)-P30-L30-H30-D30 -> 0 | D30: =SUM(E30:G30) -> 0 | H30: =SUM(I30:K30) -> 0 | L30: =SUM(M30:O30) -> 0 | P30: =SUM(Q30:S30) -> 0 | T30: =SUM(U30:AJ30)-AG30-AC30-Y30-U30 -> 0 | U30: =SUM(V30:X30) -> 0 | V30: 0 | X30: 0 | Y30: =SUM(Z30:AB30) -> 0 | AB30: 0 | AC30: =SUM(AD30:AF30) -> 0 | AD30: 0 | AE30: 0 | AF30: 0 | AG30: =SUM(AH30:AJ30) -> 0 | AH30: 0 | AI30: 0 | AJ30: 0 | AL30: 0 | AM30: 0
B31: Communication Exp - Mobile & Internet | C31: =SUM(D31:S31)-P31-L31-H31-D31 -> 0 | D31: =SUM(E31:G31) -> 0 | H31: =SUM(I31:K31) -> 0 | L31: =SUM(M31:O31) -> 0 | P31: =SUM(Q31:S31) -> 0 | S31: 0 | T31: =SUM(U31:AJ31)-AG31-AC31-Y31-U31 -> 1983.34 | U31: =SUM(V31:X31) -> 0 | V31: 0 | X31: 0 | Y31: =SUM(Z31:AB31) -> 1348.39 | AB31: 1348.39 | AC31: =SUM(AD31:AF31) -> 346.34 | AD31: 0 | AE31: 0 | AF31: 346.34 | AG31: =SUM(AH31:AJ31) -> 288.61 | AH31: 0 | AI31: 173.24 | AJ31: 115.37 | AL31: 0 | AM31: 852.62
B32: Subscriptions & Memberships | C32: =SUM(D32:S32)-P32-L32-H32-D32 -> 103426.74 | D32: =SUM(E32:G32) -> 0 | H32: =SUM(I32:K32) -> 0 | L32: =SUM(M32:O32) -> 0 | P32: =SUM(Q32:S32) -> 103426.74 | R32: 49890.22 | S32: 53536.52 | T32: =SUM(U32:AJ32)-AG32-AC32-Y32-U32 -> 525463.26 | U32: =SUM(V32:X32) -> 156650.01 | V32: 55394.62 | W32: 51900 | X32: 49355.39 | Y32: =SUM(Z32:AB32) -> 126599.4 | Z32: 52046.58 | AA32: 36871.09 | AB32: 37681.73 | AC32: =SUM(AD32:AF32) -> 123614.53 | AD32: 36885.19 | AE32: 43563.61 | AF32: 43165.73 | AG32: =SUM(AH32:AJ32) -> 118599.32 | AH32: 50222.06 | AI32: 37076.83 | AJ32: 31300.43 | AL32: 29315.68 | AM32: 244247.23
B33: Events & Activity Expense | C33: =SUM(D33:S33)-P33-L33-H33-D33 -> 0 | D33: =SUM(E33:G33) -> 0 | H33: =SUM(I33:K33) -> 0 | L33: =SUM(M33:O33) -> 0 | P33: =SUM(Q33:S33) -> 0 | T33: =SUM(U33:AJ33)-AG33-AC33-Y33-U33 -> 0 | U33: =SUM(V33:X33) -> 0 | V33: 0 | X33: 0 | Y33: =SUM(Z33:AB33) -> 0
B34: Team Building Activities | C34: =SUM(D34:S34)-P34-L34-H34-D34 -> 0 | D34: =SUM(E34:G34) -> 0 | L34: =SUM(M34:O34) -> 0 | P34: =SUM(Q34:S34) -> 0 | T34: =SUM(U34:AJ34)-AG34-AC34-Y34-U34 -> 0 | U34: =SUM(V34:X34) -> 0 | V34: 0 | X34: 0
B35: Penny Difference | C35: =SUM(D35:S35)-P35-L35-H35-D35 -> 0 | H35: =SUM(I35:K35) -> 0 | L35: =SUM(M35:O35) -> 0 | P35: =SUM(Q35:S35) -> 0 | S35: 0 | T35: =SUM(U35:AJ35)-AG35-AC35-Y35-U35 -> 0.01 | V35: 0.01 | X35: 0 | Y35: =SUM(Z35:AB35) -> 0 | AB35: 0 | AD35: 0 | AE35: 0 | AF35: 0 | AG35: =SUM(AH35:AJ35) -> 0 | AH35: 0 | AI35: 0 | AJ35: 0 | AL35: 0 | AM35: 0
B36: Low Value Assets | C36: =SUM(D36:S36)-P36-L36-H36-D36 -> 0 | D36: =SUM(E36:G36) -> 0 | H36: =SUM(I36:K36) -> 0 | L36: =SUM(M36:O36) -> 0 | P36: =SUM(Q36:S36) -> 0 | S36: 0 | T36: =SUM(U36:AJ36)-AG36-AC36-Y36-U36 -> 4021.06 | U36: =SUM(V36:X36) -> 0 | V36: 0 | X36: 0 | Y36: =SUM(Z36:AB36) -> 0 | AB36: 0 | AC36: =SUM(AD36:AF36) -> 0 | AD36: 0 | AE36: 0 | AF36: 0 | AG36: =SUM(AH36:AJ36) -> 4021.06 | AH36: 0 | AI36: 0 | AJ36: 4021.06 | AL36: 1691.55 | AM36: 7829.98
B37: Charity | C37: =SUM(D37:S37)-P37-L37-H37-D37 -> 0 | D37: =SUM(E37:G37) -> 0 | H37: =SUM(I37:K37) -> 0 | L37: =SUM(M37:O37) -> 0 | P37: =SUM(Q37:S37) -> 0 | T37: =SUM(U37:AJ37)-AG37-AC37-Y37-U37 -> 0 | U37: =SUM(V37:X37) -> 0 | V37: 0 | X37: 0 | Y37: =SUM(Z37:AB37) -> 0 | AB37: 0 | AD37: 0 | AE37: 0 | AF37: 0 | AG37: =SUM(AH37:AJ37) -> 0 | AH37: 0 | AI37: 0 | AJ37: 0 | AM37: 0
B38: Witholding Tax | C38: =SUM(D38:S38)-P38-L38-H38-D38 -> 0 | D38: =SUM(E38:G38) -> 0 | H38: =SUM(I38:K38) -> 0 | L38: =SUM(M38:O38) -> 0 | P38: =SUM(Q38:S38) -> 0 | T38: =SUM(U38:AJ38)-AG38-AC38-Y38-U38 -> 0 | U38: =SUM(V38:X38) -> 0 | V38: 0 | X38: 0 | Y38: =SUM(Z38:AB38) -> 0 | AB38: 0 | AD38: 0 | AE38: 0 | AF38: 0 | AG38: =SUM(AH38:AJ38) -> 0 | AH38: 0 | AI38: 0 | AJ38: 0 | AM38: 0
B39: Selling Expenses | C39: =SUM(C40:C55) -> 82983.06 | D39: =SUM(E39:G39) -> 0 | E39: =SUM(E40:E55) -> 0 | F39: =SUM(F40:F55) -> 0 | G39: =SUM(G40:G55) -> 0 | H39: =SUM(I39:K39) -> 0 | I39: =SUM(I40:I55) -> 0 | J39: =SUM(J40:J55) -> 0 | K39: =SUM(K40:K55) -> 0 | L39: =SUM(M39:O39) -> 0 | M39: =SUM(M40:M55) -> 0 | N39: =SUM(N40:N55) -> 0 | O39: =SUM(O40:O55) -> 0 | P39: =SUM(Q39:S39) -> 82983.06 | Q39: =SUM(Q40:Q55) -> 0 | R39: =SUM(R40:R55) -> 45138.65 | S39: =SUM(S40:S55) -> 37844.41 | T39: =SUM(T40:T55) -> 669599.75 | U39: =SUM(V39:X39) -> 162969.64 | V39: =SUM(V40:V55) -> 52018.05 | W39: =SUM(W40:W55) -> 41585.01 | X39: =SUM(X40:X55) -> 69366.58 | Y39: =SUM(Z39:AB39) -> 177755.03 | Z39: =SUM(Z40:Z55) -> 55789.35 | AA39: =SUM(AA40:AA55) -> 56565.6 | AB39: =SUM(AB40:AB55) -> 65400.08 | AC39: =SUM(AD39:AF39) -> 155760.79 | AD39: =SUM(AD40:AD55) -> 68407.3 | AE39: =SUM(AE40:AE55) -> 59361.17 | AF39: =SUM(AF40:AF55) -> 27992.32 | AG39: =SUM(AH39:AJ39) -> 173114.29 | AH39: =SUM(AH40:AH55) -> 41542.73 | AI39: =SUM(AI40:AI55) -> 95489.88 | AJ39: =SUM(AJ40:AJ55) -> 36081.68 | AL39: =SUM(AL40:AL55) -> 29936.94 | AM39: =SUM(AM40:AM55) -> 179659.18
B40: Business travel expenses | C40: =SUM(D40:S40)-P40-L40-H40-D40 -> 0 | D40: =SUM(E40:G40) -> 0 | H40: =SUM(I40:K40) -> 0 | L40: =SUM(M40:O40) -> 0 | P40: =SUM(Q40:S40) -> 0 | S40: 0 | T40: =SUM(U40:AJ40)-AG40-AC40-Y40-U40 -> 83690.52 | U40: =SUM(V40:X40) -> 6761.32 | V40: 811.01 | W40: 2549.51 | X40: 3400.8 | Y40: =SUM(Z40:AB40) -> 12885.49 | Z40: 0 | AA40: 995.44 | AB40: 11890.05 | AC40: =SUM(AD40:AF40) -> 15967.62 | AD40: 7793.14 | AE40: 6787.8 | AF40: 1386.68 | AG40: =SUM(AH40:AJ40) -> 48076.09 | AH40: 7086.76 | AI40: 36880.6 | AJ40: 4108.73 | AL40: 37.58 | AM40: 14193.81
B41: Business Accommodation Expense | C41: =SUM(D41:S41)-P41-L41-H41-D41 -> 0 | D41: =SUM(E41:G41) -> 0 | H41: =SUM(I41:K41) -> 0 | L41: =SUM(M41:O41) -> 0 | P41: =SUM(Q41:S41) -> 0 | S41: 0 | T41: =SUM(U41:AJ41)-AG41-AC41-Y41-U41 -> 6445.12 | U41: =SUM(V41:X41) -> 3421.77 | V41: 0 | W41: 0 | X41: 3421.77 | Y41: =SUM(Z41:AB41) -> 0 | AC41: =SUM(AD41:AF41) -> 1020.9 | AF41: 1020.9 | AG41: =SUM(AH41:AJ41) -> 2002.45 | AH41: 1401.17 | AJ41: 601.28
B42: Collection Commission | C42: =SUM(D42:S42)-P42-L42-H42-D42 -> 0 | D42: =SUM(E42:G42) -> 0 | H42: =SUM(I42:K42) -> 0 | L42: =SUM(M42:O42) -> 0 | P42: =SUM(Q42:S42) -> 0 | T42: =SUM(U42:AJ42)-AG42-AC42-Y42-U42 -> 0 | U42: =SUM(V42:X42) -> 0 | V42: 0 | Y42: =SUM(Z42:AB42) -> 0 | AB42: 0 | AC42: =SUM(AD42:AF42) -> 0 | AD42: 0 | AE42: 0 | AF42: 0 | AG42: =SUM(AH42:AJ42) -> 0 | AH42: 0 | AI42: 0 | AJ42: 0 | AL42: 0 | AM42: 0
B43: Dinar commission | C43: =SUM(D43:S43)-P43-L43-H43-D43 -> 0 | D43: =SUM(E43:G43) -> 0 | H43: =SUM(I43:K43) -> 0 | L43: =SUM(M43:O43) -> 0 | P43: =SUM(Q43:S43) -> 0 | T43: =SUM(U43:AJ43)-AG43-AC43-Y43-U43 -> 0 | U43: =SUM(V43:X43) -> 0 | V43: 0 | Y43: =SUM(Z43:AB43) -> 0 | AB43: 0 | AC43: =SUM(AD43:AF43) -> 0 | AD43: 0 | AE43: 0 | AF43: 0 | AG43: =SUM(AH43:AJ43) -> 0 | AH43: 0 | AI43: 0 | AJ43: 0 | AL43: 0 | AM43: 0
B44: New customer commission | C44: =SUM(D44:S44)-P44-L44-H44-D44 -> 0 | D44: =SUM(E44:G44) -> 0 | H44: =SUM(I44:K44) -> 0 | L44: =SUM(M44:O44) -> 0 | P44: =SUM(Q44:S44) -> 0 | T44: =SUM(U44:AJ44)-AG44-AC44-Y44-U44 -> 0 | U44: =SUM(V44:X44) -> 0 | V44: 0 | Y44: =SUM(Z44:AB44) -> 0 | AB44: 0 | AC44: =SUM(AD44:AF44) -> 0 | AD44: 0 | AE44: 0 | AF44: 0 | AG44: =SUM(AH44:AJ44) -> 0 | AH44: 0 | AI44: 0 | AJ44: 0 | AL44: 0 | AM44: 0
B45: New Approved client Commission (SDA) | C45: =SUM(D45:S45)-P45-L45-H45-D45 -> 0 | H45: =SUM(I45:K45) -> 0 | T45: =SUM(U45:AJ45)-AG45-AC45-Y45-U45 -> 0 | V45: 0 | Y45: =SUM(Z45:AB45) -> 0 | AB45: 0 | AD45: 0 | AE45: 0 | AF45: 0 | AH45: 0 | AI45: 0 | AJ45: 0
B46: Sales Commission-Employee | C46: =SUM(D46:S46)-P46-L46-H46-D46 -> 0 | H46: =SUM(I46:K46) -> 0 | T46: =SUM(U46:AJ46)-AG46-AC46-Y46-U46 -> 0 | V46: 0 | Y46: =SUM(Z46:AB46) -> 0 | AB46: 0 | AD46: 0 | AE46: 0 | AF46: 0 | AH46: 0 | AI46: 0 | AJ46: 0
B47: Cash Purchase - Backend Margin | C47: =SUM(D47:S47)-P47-L47-H47-D47 -> 0 | H47: =SUM(I47:K47) -> 0 | L47: =SUM(M47:O47) -> 0 | T47: =SUM(U47:AJ47)-AG47-AC47-Y47-U47 -> 0 | V47: 0 | Y47: =SUM(Z47:AB47) -> 0 | AB47: 0 | AC47: =SUM(AD47:AF47) -> 0 | AD47: 0 | AE47: 0 | AF47: 0 | AH47: 0 | AI47: 0 | AJ47: 0 | AL47: 0
B48: Cash Sale Commission | C48: =SUM(D48:S48)-P48-L48-H48-D48 -> 0 | H48: =SUM(I48:K48) -> 0 | L48: =SUM(M48:O48) -> 0 | T48: =SUM(U48:AJ48)-AG48-AC48-Y48-U48 -> 0 | V48: 0 | Y48: =SUM(Z48:AB48) -> 0 | AB48: 0 | AC48: =SUM(AD48:AF48) -> 0 | AD48: 0 | AE48: 0 | AF48: 0 | AH48: 0 | AI48: 0 | AJ48: 0 | AL48: 0
B49: Bonus Commission | C49: =SUM(D49:S49)-P49-L49-H49-D49 -> 0 | H49: =SUM(I49:K49) -> 0 | T49: =SUM(U49:AJ49)-AG49-AC49-Y49-U49 -> 0 | V49: 0 | Y49: =SUM(Z49:AB49) -> 0 | AB49: 0
B50: Third Party Referral Incentive | C50: =SUM(D50:S50)-P50-L50-H50-D50 -> 0 | H50: =SUM(I50:K50) -> 0 | T50: =SUM(U50:AJ50)-AG50-AC50-Y50-U50 -> 0 | V50: 0 | Y50: =SUM(Z50:AB50) -> 0 | AB50: 0
B51: Deal-related expenses | C51: =SUM(D51:S51)-P51-L51-H51-D51 -> 0 | D51: =SUM(E51:G51) -> 0 | T51: =SUM(U51:AJ51)-AG51-AC51-Y51-U51 -> 0 | U51: =SUM(V51:X51) -> 0 | V51: 0
B52: Credit Assessment Expense | C52: =SUM(D52:S52)-P52-L52-H52-D52 -> 0 | T52: =SUM(U52:AJ52)-AG52-AC52-Y52-U52 -> 0
B53: Fuel/Mileage Expenses | C53: =SUM(D53:S53)-P53-L53-H53-D53 -> 0 | D53: =SUM(E53:G53) -> 0 | H53: =SUM(I53:K53) -> 0 | L53: =SUM(M53:O53) -> 0 | P53: =SUM(Q53:S53) -> 0 | T53: =SUM(U53:AJ53)-AG53-AC53-Y53-U53 -> 0 | U53: =SUM(V53:X53) -> 0 | V53: 0 | Y53: =SUM(Z53:AB53) -> 0 | AB53: 0 | AC53: =SUM(AD53:AF53) -> 0 | AD53: 0 | AE53: 0 | AF53: 0 | AG53: =SUM(AH53:AJ53) -> 0 | AH53: 0 | AI53: 0 | AJ53: 0 | AL53: 0 | AM53: 0
B54: Marketing, Promotion & Advertising | C54: =SUM(D54:S54)-P54-L54-H54-D54 -> 82983.06 | D54: =SUM(E54:G54) -> 0 | H54: =SUM(I54:K54) -> 0 | L54: =SUM(M54:O54) -> 0 | P54: =SUM(Q54:S54) -> 82983.06 | R54: 45138.65 | S54: 37844.41 | T54: =SUM(U54:AJ54)-AG54-AC54-Y54-U54 -> 579464.11 | U54: =SUM(V54:X54) -> 152786.55 | V54: 51207.04 | W54: 39035.5 | X54: 62544.01 | Y54: =SUM(Z54:AB54) -> 164869.54 | Z54: 55789.35 | AA54: 55570.16 | AB54: 53510.03 | AC54: =SUM(AD54:AF54) -> 138772.27 | AD54: 60614.16 | AE54: 52573.37 | AF54: 25584.74 | AG54: =SUM(AH54:AJ54) -> 123035.75 | AH54: 33054.8 | AI54: 58609.28 | AJ54: 31371.67 | AL54: 29899.36 | AM54: 165465.37
B55: Trade Credit Insurance | C55: =SUM(D55:S55)-P55-L55-H55-D55 -> 0 | D55: =SUM(E55:G55) -> 0 | H55: =SUM(I55:K55) -> 0 | K55: 0 | L55: =SUM(M55:O55) -> 0 | N55: 0 | O55: 0 | P55: =SUM(Q55:S55) -> 0 | T55: =SUM(U55:AJ55)-AG55-AC55-Y55-U55 -> 0 | U55: =SUM(V55:X55) -> 0 | V55: 0 | Y55: =SUM(Z55:AB55) -> 0 | AB55: 0 | AC55: =SUM(AD55:AF55) -> 0 | AE55: 0 | AF55: 0 | AG55: =SUM(AH55:AJ55) -> 0 | AH55: 0 | AI55: 0 | AJ55: 0 | AL55: 0 | AM55: 0
B56: Legal & Consultation Expenses | C56: =SUM(C57:C59) -> 166579.88 | D56: =SUM(E56:G56) -> 0 | E56: =SUM(E57:E59) -> 0 | F56: =SUM(F57:F59) -> 0 | G56: =SUM(G57:G59) -> 0 | H56: =SUM(I56:K56) -> 0 | I56: =SUM(I57:I59) -> 0 | J56: =SUM(J57:J59) -> 0 | K56: =SUM(K57:K59) -> 0 | L56: =SUM(M56:O56) -> 0 | M56: =SUM(M57:M59) -> 0 | N56: =SUM(N57:N59) -> 0 | O56: =SUM(O57:O59) -> 0 | P56: =SUM(Q56:S56) -> 166579.88 | Q56: =SUM(Q57:Q59) -> 0 | R56: =SUM(R57:R59) -> 80677.52 | S56: =SUM(S57:S59) -> 85902.36 | T56: =SUM(T57:T59) -> 1563755.7 | U56: =SUM(V56:X56) -> 448539 | V56: =SUM(V57:V59) -> 128679.12 | W56: =SUM(W57:W59) -> 128520.88 | X56: =SUM(X57:X59) -> 191339 | Y56: =SUM(Z56:AB56) -> 420453.06 | Z56: =SUM(Z57:Z59) -> 157985.82 | AA56: =SUM(AA57:AA59) -> 119195.64 | AB56: =SUM(AB57:AB59) -> 143271.6 | AC56: =SUM(AD56:AF56) -> 488266.15 | AD56: =SUM(AD57:AD59) -> 211433.14 | AE56: =SUM(AE57:AE59) -> 130831.25 | AF56: =SUM(AF57:AF59) -> 146001.76 | AG56: =SUM(AH56:AJ56) -> 206497.47 | AH56: =SUM(AH57:AH59) -> 73447.24 | AI56: =SUM(AI57:AI59) -> 71688.22 | AJ56: =SUM(AJ57:AJ59) -> 61362.01 | AL56: =SUM(AL57:AL59) -> 79135.86 | AM56: =SUM(AM57:AM59) -> 504511.88
B57: Consultant Expense | C57: =SUM(D57:S57)-P57-L57-H57-D57 -> 157467.73 | D57: =SUM(E57:G57) -> 0 | H57: =SUM(I57:K57) -> 0 | L57: =SUM(M57:O57) -> 0 | P57: =SUM(Q57:S57) -> 157467.73 | R57: 75832.13 | S57: 81635.6 | T57: =SUM(U57:AJ57)-AG57-AC57-Y57-U57 -> 1411571 | U57: =SUM(V57:X57) -> 353084.13 | V57: 121860.83 | W57: 121702.59 | X57: 109520.71 | Y57: =SUM(Z57:AB57) -> 396573.48 | Z57: 148998.87 | AA57: 112386.58 | AB57: 135188.03 | AC57: =SUM(AD57:AF57) -> 474904.62 | AD57: 207175.65 | AE57: 126573.76 | AF57: 141155.21 | AG57: =SUM(AH57:AJ57) -> 187008.74 | AH57: 69203.37 | AI57: 58649.16 | AJ57: 59156.21 | AL57: 74891.99 | AM57: 441363.3
B58: Government & Compliance Expense | C58: =SUM(D58:S58)-P58-L58-H58-D58 -> 0 | D58: =SUM(E58:G58) -> 0 | E58: 0 | G58: 0 | H58: =SUM(I58:K58) -> 0 | K58: 0 | L58: =SUM(M58:O58) -> 0 | M58: 0 | N58: 0 | O58: 0 | P58: =SUM(Q58:S58) -> 0 | Q58: 0 | R58: 0 | T58: =SUM(U58:AJ58)-AG58-AC58-Y58-U58 -> 0 | U58: =SUM(V58:X58) -> 0 | V58: 0 | X58: 0 | Y58: =SUM(Z58:AB58) -> 0 | AB58: 0 | AC58: =SUM(AD58:AF58) -> 0 | AD58: 0 | AE58: 0 | AF58: 0 | AG58: =SUM(AH58:AJ58) -> 0 | AH58: 0 | AI58: 0 | AJ58: 0 | AL58: 0 | AM58: 0
B59: Legal | C59: =SUM(D59:S59)-P59-L59-H59-D59 -> 9112.15 | D59: =SUM(E59:G59) -> 0 | H59: =SUM(I59:K59) -> 0 | L59: =SUM(M59:O59) -> 0 | P59: =SUM(Q59:S59) -> 9112.15 | R59: 4845.39 | S59: 4266.76 | T59: =SUM(U59:AJ59)-AG59-AC59-Y59-U59 -> 152184.71 | U59: =SUM(V59:X59) -> 95454.87 | V59: 6818.29 | W59: 6818.29 | X59: 81818.29 | Y59: =SUM(Z59:AB59) -> 23879.58 | Z59: 8986.95 | AA59: 6809.06 | AB59: 8083.57 | AC59: =SUM(AD59:AF59) -> 13361.53 | AD59: 4257.49 | AE59: 4257.49 | AF59: 4846.55 | AG59: =SUM(AH59:AJ59) -> 19488.73 | AH59: 4243.87 | AI59: 13039.06 | AJ59: 2205.8 | AL59: 4243.87 | AM59: 63148.58
B60: Depreciation Expenses | C60: =SUM(C61:C64) -> 1856.12 | D60: =SUM(E60:G60) -> 0 | E60: =SUM(E61:E64) -> 0 | F60: =SUM(F61:F64) -> 0 | G60: =SUM(G61:G64) -> 0 | H60: =SUM(I60:K60) -> 0 | I60: =SUM(I61:I64) -> 0 | J60: =SUM(J61:J64) -> 0 | K60: =SUM(K61:K64) -> 0 | L60: =SUM(M60:O60) -> 0 | M60: =SUM(M61:M64) -> 0 | N60: =SUM(N61:N64) -> 0 | O60: =SUM(O61:O64) -> 0 | P60: =SUM(Q60:S60) -> 1856.12 | Q60: =SUM(Q61:Q64) -> 0 | R60: =SUM(R61:R64) -> 928.06 | S60: =SUM(S61:S64) -> 928.06 | T60: =SUM(T61:T64) -> 8975.34 | U60: =SUM(V60:X60) -> 2393.58 | V60: =SUM(V61:V64) -> 797.86 | W60: =SUM(W61:W64) -> 797.86 | X60: =SUM(X61:X64) -> 797.86 | Y60: =SUM(Z60:AB60) -> 2393.58 | Z60: =SUM(Z61:Z64) -> 797.86 | AA60: =SUM(AA61:AA64) -> 797.86 | AB60: =SUM(AB61:AB64) -> 797.86 | AC60: =SUM(AD60:AF60) -> 2393.58 | AD60: =SUM(AD61:AD64) -> 797.86 | AE60: =SUM(AE61:AE64) -> 797.86 | AF60: =SUM(AF61:AF64) -> 797.86 | AG60: =SUM(AH60:AJ60) -> 1794.6 | AH60: =SUM(AH61:AH64) -> 598.2 | AI60: =SUM(AI61:AI64) -> 598.2 | AJ60: =SUM(AJ61:AJ64) -> 598.2 | AL60: =SUM(AL61:AL64) -> 598.2 | AM60: =SUM(AM61:AM64) -> 3589.2
B61: Depreciation - Furniture & Fixture | C61: =SUM(D61:S61)-P61-L61-H61-D61 -> 0 | D61: =SUM(E61:G61) -> 0 | E61: 0 | H61: =SUM(I61:K61) -> 0 | K61: 0 | L61: =SUM(M61:O61) -> 0 | M61: 0 | N61: 0 | O61: 0 | P61: =SUM(Q61:S61) -> 0 | Q61: 0 | R61: 0 | T61: =SUM(U61:AJ61)-AG61-AC61-Y61-U61 -> 0 | U61: =SUM(V61:X61) -> 0 | V61: 0 | Y61: =SUM(Z61:AB61) -> 0 | AB61: 0 | AC61: =SUM(AD61:AF61) -> 0 | AD61: 0 | AE61: 0 | AF61: 0 | AG61: =SUM(AH61:AJ61) -> 0 | AH61: 0 | AI61: 0 | AJ61: 0 | AL61: 0 | AM61: 0
B62: Depreciation - Motor Vehicle | C62: =SUM(D62:S62)-P62-L62-H62-D62 -> 0 | D62: =SUM(E62:G62) -> 0 | E62: 0 | H62: =SUM(I62:K62) -> 0 | K62: 0 | L62: =SUM(M62:O62) -> 0 | M62: 0 | N62: 0 | O62: 0 | P62: =SUM(Q62:S62) -> 0 | Q62: 0 | R62: 0 | T62: =SUM(U62:AJ62)-AG62-AC62-Y62-U62 -> 0 | U62: =SUM(V62:X62) -> 0 | V62: 0 | Y62: =SUM(Z62:AB62) -> 0 | AB62: 0 | AC62: =SUM(AD62:AF62) -> 0 | AD62: 0 | AE62: 0 | AF62: 0 | AG62: =SUM(AH62:AJ62) -> 0 | AH62: 0 | AI62: 0 | AJ62: 0 | AL62: 0 | AM62: 0
B63: Depreciation-Building Improvement | C63: =SUM(D63:S63)-P63-L63-H63-D63 -> 0 | D63: =SUM(E63:G63) -> 0 | E63: 0 | H63: =SUM(I63:K63) -> 0 | K63: 0 | T63: =SUM(U63:AJ63)-AG63-AC63-Y63-U63 -> 0 | U63: =SUM(V63:X63) -> 0 | V63: 0 | Y63: =SUM(Z63:AB63) -> 0 | AB63: 0
B64: Depreciation - Office Equipment's | C64: =SUM(D64:S64)-P64-L64-H64-D64 -> 1856.12 | D64: =SUM(E64:G64) -> 0 | H64: =SUM(I64:K64) -> 0 | L64: =SUM(M64:O64) -> 0 | P64: =SUM(Q64:S64) -> 1856.12 | R64: 928.06 | S64: 928.06 | T64: =SUM(U64:AJ64)-AG64-AC64-Y64-U64 -> 8975.34 | U64: =SUM(V64:X64) -> 2393.58 | V64: 797.86 | W64: 797.86 | X64: 797.86 | Y64: =SUM(Z64:AB64) -> 2393.58 | Z64: 797.86 | AA64: 797.86 | AB64: 797.86 | AC64: =SUM(AD64:AF64) -> 2393.58 | AD64: 797.86 | AE64: 797.86 | AF64: 797.86 | AG64: =SUM(AH64:AJ64) -> 1794.6 | AH64: 598.2 | AI64: 598.2 | AJ64: 598.2 | AL64: 598.2 | AM64: 3589.2
B65: Personnel Expenses | C65: =SUM(C66:C86) -> 656327.98 | D65: =SUM(D66:D86) -> 0 | E65: =SUM(E66:E86) -> 0 | F65: =SUM(F66:F86) -> 0 | G65: =SUM(G66:G86) -> 0 | H65: =SUM(H66:H86) -> 0 | I65: =SUM(I66:I86) -> 0 | J65: =SUM(J66:J86) -> 0 | ... AJ65: =SUM(AJ66:AJ86) -> 196300.63 | AL65: =SUM(AL66:AL86) -> 145009.16 | AM65: =SUM(AM66:AM86) -> 1863026.3
B66: Employee Insurance | C66: =SUM(D66:S66)-P66-L66-H66-D66 -> 10308 | D66: =SUM(E66:G66) -> 0 | H66: =SUM(I66:K66) -> 0 | L66: =SUM(M66:O66) -> 0 | P66: =SUM(Q66:S66) -> 10308 | S66: 10308 | T66: =SUM(U66:AJ66)-AG66-AC66-Y66-U66 -> 2790 | U66: =SUM(V66:X66) -> 2790 | V66: 2790 | Y66: =SUM(Z66:AB66) -> 0 | AB66: 0 | AC66: =SUM(AD66:AF66) -> 0 | AD66: 0 | AE66: 0 | AF66: 0 | AG66: =SUM(AH66:AJ66) -> 0 | AH66: 0 | AI66: 0 | AJ66: 0 | AL66: 0 | AM66: 0
B67: Leave Air Fare Expense | C67: =SUM(D67:S67)-P67-L67-H67-D67 -> 0 | H67: =SUM(I67:K67) -> 0 | T67: =SUM(U67:AJ67)-AG67-AC67-Y67-U67 -> 0 | V67: 0 | Y67: =SUM(Z67:AB67) -> 0 | AB67: 0 | AD67: 0 | AE67: 0 | AF67: 0
B68: Leave Pay Expense | C68: =SUM(D68:S68)-P68-L68-H68-D68 -> 1599.15 | D68: =SUM(E68:G68) -> 0 | H68: =SUM(I68:K68) -> 0 | R68: 1599.15 | S68: 0 | T68: =SUM(U68:AJ68)-AG68-AC68-Y68-U68 -> 31001.67 | U68: =SUM(V68:X68) -> 31001.67 | V68: 0 | W68: 31001.67 | Y68: =SUM(Z68:AB68) -> 0 | AB68: 0 | AD68: 0 | AE68: 0 | AF68: 0 | AH68: 0 | AI68: 0 | AJ68: 0 | AL68: 0
B69: Employee Referral Allowance | C69: =SUM(D69:S69)-P69-L69-H69-D69 -> 0 | D69: =SUM(E69:G69) -> 0 | H69: =SUM(I69:K69) -> 0 | L69: =SUM(M69:O69) -> 0 | P69: =SUM(Q69:S69) -> 0 | S69: 0 | T69: =SUM(U69:AJ69)-AG69-AC69-Y69-U69 -> 0 | U69: =SUM(V69:X69) -> 0 | V69: 0 | Y69: =SUM(Z69:AB69) -> 0 | AB69: 0 | AC69: =SUM(AD69:AF69) -> 0 | AD69: 0 | AE69: 0 | AF69: 0 | AG69: =SUM(AH69:AJ69) -> 0 | AH69: 0 | AI69: 0 | AJ69: 0 | AL69: 0 | AM69: 682.08
B70: Maintenance Allowance | C70: =SUM(D70:S70)-P70-L70-H70-D70 -> 0 | D70: =SUM(E70:G70) -> 0 | H70: =SUM(I70:K70) -> 0 | L70: =SUM(M70:O70) -> 0 | P70: =SUM(Q70:S70) -> 0 | T70: =SUM(U70:AJ70)-AG70-AC70-Y70-U70 -> 0 | U70: =SUM(V70:X70) -> 0 | V70: 0 | Y70: =SUM(Z70:AB70) -> 0 | AB70: 0 | AC70: =SUM(AD70:AF70) -> 0 | AD70: 0 | AE70: 0 | AF70: 0 | AG70: =SUM(AH70:AJ70) -> 0 | AH70: 0 | AI70: 0 | AJ70: 0 | AL70: 0 | AM70: 0
B71: Per Diem Allowance | C71: =SUM(D71:S71)-P71-L71-H71-D71 -> 0 | D71: =SUM(E71:G71) -> 0 | H71: =SUM(I71:K71) -> 0 | S71: 0 | T71: =SUM(U71:AJ71)-AG71-AC71-Y71-U71 -> 1800 | U71: =SUM(V71:X71) -> 1800 | V71: 0 | W71: 0 | X71: 1800 | Y71: =SUM(Z71:AB71) -> 0 | AB71: 0 | AD71: 0 | AE71: 0 | AF71: 0 | AH71: 0 | AI71: 0 | AJ71: 0
B72: Employee Benefit expense | C72: =SUM(D72:S72)-P72-L72-H72-D72 -> 0 | D72: =SUM(E72:G72) -> 0 | H72: =SUM(I72:K72) -> 0 | S72: 0 | T72: =SUM(U72:AJ72)-AG72-AC72-Y72-U72 -> 4845.75 | U72: =SUM(V72:X72) -> 4845.75 | V72: 0 | W72: 0 | X72: 4845.75 | Y72: =SUM(Z72:AB72) -> 0
B73: Employee Related Govt Fees | C73: =SUM(D73:S73)-P73-L73-H73-D73 -> 0 | D73: =SUM(E73:G73) -> 0 | H73: =SUM(I73:K73) -> 0 | L73: =SUM(M73:O73) -> 0 | S73: 0 | T73: =SUM(U73:AJ73)-AG73-AC73-Y73-U73 -> 549.56 | U73: =SUM(V73:X73) -> 549.56 | V73: 153.75 | W73: 0 | X73: 395.81 | Y73: =SUM(Z73:AB73) -> 0 | Z73: 0 | AB73: 0 | AC73: =SUM(AD73:AF73) -> 0 | AD73: 0 | AE73: 0 | AF73: 0 | AH73: 0 | AI73: 0 | AJ73: 0 | AL73: 0 | AM73: 7500.1
B74: Telecome Allowance | C74: =SUM(D74:S74)-P74-L74-H74-D74 -> 0 | D74: =SUM(E74:G74) -> 0 | H74: =SUM(I74:K74) -> 0 | L74: =SUM(M74:O74) -> 0 | P74: =SUM(Q74:S74) -> 0 | S74: 0 | T74: =SUM(U74:AJ74)-AG74-AC74-Y74-U74 -> 0 | U74: =SUM(V74:X74) -> 0 | V74: 0 | Y74: =SUM(Z74:AB74) -> 0 | AB74: 0 | AC74: =SUM(AD74:AF74) -> 0 | AD74: 0 | AE74: 0 | AF74: 0 | AG74: =SUM(AH74:AJ74) -> 0 | AH74: 0 | AI74: 0 | AJ74: 0 | AL74: 0 | AM74: 647.88
B75: US Employer Taxes | C75: =SUM(D75:S75)-P75-L75-H75-D75 -> 7222.32 | D75: =SUM(E75:G75) -> 0 | H75: =SUM(I75:K75) -> 0 | L75: =SUM(M75:O75) -> 0 | P75: =SUM(Q75:S75) -> 7222.32 | R75: 4362.79 | S75: 2859.53 | T75: =SUM(U75:AJ75)-AG75-AC75-Y75-U75 -> 33265.01 | U75: =SUM(V75:X75) -> 7914.57 | V75: 2467.2 | W75: 2523.04 | X75: 2924.33 | Y75: =SUM(Z75:AB75) -> 7377.01 | Z75: 3322.62 | AA75: 1319.59 | AB75: 2734.8 | AC75: =SUM(AD75:AF75) -> 5066.47 | AD75: 0 | AE75: 1135.31 | AF75: 3931.16 | AG75: =SUM(AH75:AJ75) -> 12906.96 | AH75: 4054.24 | AI75: 4561.27 | AJ75: 4291.45 | AL75: 3054.31 | AM75: 35255.31
B76: GOSI | C76: =SUM(D76:S76)-P76-L76-H76-D76 -> 0 | D76: =SUM(E76:G76) -> 0 | H76: =SUM(I76:K76) -> 0 | L76: =SUM(M76:O76) -> 0 | P76: =SUM(Q76:S76) -> 0 | T76: =SUM(U76:AJ76)-AG76-AC76-Y76-U76 -> 0 | U76: =SUM(V76:X76) -> 0 | V76: 0 | Y76: =SUM(Z76:AB76) -> 0 | AB76: 0 | AC76: =SUM(AD76:AF76) -> 0 | AD76: 0 | AE76: 0 | AF76: 0 | AG76: =SUM(AH76:AJ76) -> 0 | AH76: 0 | AI76: 0 | AJ76: 0 | AL76: 0 | AM76: 0
B77: HUMAN RESOUACES DEVELOPMENT FUND | C77: =SUM(D77:S77)-P77-L77-H77-D77 -> 0 | D77: =SUM(E77:G77) -> 0 | H77: =SUM(I77:K77) -> 0 | L77: =SUM(M77:O77) -> 0 | P77: =SUM(Q77:S77) -> 0 | T77: =SUM(U77:AJ77)-AG77-AC77-Y77-U77 -> 0 | U77: =SUM(V77:X77) -> 0 | V77: 0 | Y77: =SUM(Z77:AB77) -> 0 | AB77: 0 | AC77: =SUM(AD77:AF77) -> 0 | AD77: 0 | AE77: 0 | AF77: 0 | AG77: =SUM(AH77:AJ77) -> 0 | AH77: 0 | AI77: 0 | AJ77: 0 | AL77: 0 | AM77: 0
B78: Recruitments & Visas | C78: =SUM(D78:S78)-P78-L78-H78-D78 -> 8650.24 | D78: =SUM(E78:G78) -> 0 | H78: =SUM(I78:K78) -> 0 | L78: =SUM(M78:O78) -> 0 | P78: =SUM(Q78:S78) -> 8650.24 | R78: 840 | S78: 7810.24 | T78: =SUM(U78:AJ78)-AG78-AC78-Y78-U78 -> 201373.91 | U78: =SUM(V78:X78) -> 72731.22 | V78: 10371.64 | W78: 8613.27 | X78: 53746.31 | Y78: =SUM(Z78:AB78) -> 86572.6 | Z78: 5408.34 | AA78: 65191.05 | AB78: 15973.21 | AC78: =SUM(AD78:AF78) -> 39017.39 | AD78: 14121.64 | AE78: 24181.73 | AF78: 714.02 | AG78: =SUM(AH78:AJ78) -> 3052.7 | AH78: 3052.7 | AI78: 0 | AJ78: 0 | AL78: 0 | AM78: 1681.29
B79: Bonus | C79: =SUM(D79:S79)-P79-L79-H79-D79 -> 0 | D79: =SUM(E79:G79) -> 0 | H79: =SUM(I79:K79) -> 0 | L79: =SUM(M79:O79) -> 0 | P79: =SUM(Q79:S79) -> 0 | S79: 0 | T79: =SUM(U79:AJ79)-AG79-AC79-Y79-U79 -> 227596.38 | U79: =SUM(V79:X79) -> 110000.02 | V79: 0 | W79: 0 | X79: 110000.02 | Y79: =SUM(Z79:AB79) -> 49999.99 | Z79: 0 | AA79: 49999.99 | AB79: 0 | AC79: =SUM(AD79:AF79) -> 39675 | AD79: 0 | AE79: 39675 | AF79: 0 | AG79: =SUM(AH79:AJ79) -> 27921.37 | AH79: 11887.31 | AI79: 0 | AJ79: 16034.06 | AL79: 0 | AM79: 55786.27
B80: Quarterly Bonus | C80: =SUM(D80:S80)-P80-L80-H80-D80 -> 22786.88 | H80: =SUM(I80:K80) -> 0 | R80: 22786.88 | S80: 0 | T80: =SUM(U80:AJ80)-AG80-AC80-Y80-U80 -> 85246.14 | V80: 20673.38 | W80: 0 | X80: 12000 | Y80: =SUM(Z80:AB80) -> 52572.76 | Z80: 20673.38 | AB80: 31899.38
B81: Salaries - Basic | C81: =SUM(D81:S81)-P81-L81-H81-D81 -> 597676.87 | D81: =SUM(E81:G81) -> 0 | H81: =SUM(I81:K81) -> 0 | L81: =SUM(M81:O81) -> 0 | P81: =SUM(Q81:S81) -> 597676.87 | R81: 309790.67 | S81: 287886.2 | T81: =SUM(U81:AJ81)-AG81-AC81-Y81-U81 -> 2101354.6 | U81: =SUM(V81:X81) -> 634333.47 | V81: 246330.22 | W81: 191073.27 | X81: 196929.98 | Y81: =SUM(Z81:AB81) -> 407831.09 | Z81: 138477.33 | AA81: 136755 | AB81: 132598.76 | AC81: =SUM(AD81:AF81) -> 513121.98 | AD81: 125293.76 | AE81: 194485.26 | AF81: 193342.96 | AG81: =SUM(AH81:AJ81) -> 546068.11 | AH81: 193402.09 | AI81: 179697.3 | AJ81: 172968.72 | AL81: 140124.7 | AM81: 1748663
B82: Salaries - Housing | C82: =SUM(D82:S82)-P82-L82-H82-D82 -> 0 | D82: =SUM(E82:G82) -> 0 | H82: =SUM(I82:K82) -> 0 | L82: =SUM(M82:O82) -> 0 | P82: =SUM(Q82:S82) -> 0 | T82: =SUM(U82:AJ82)-AG82-AC82-Y82-U82 -> 0 | U82: =SUM(V82:X82) -> 0 | V82: 0 | Y82: =SUM(Z82:AB82) -> 0 | AB82: 0 | AC82: =SUM(AD82:AF82) -> 0 | AD82: 0 | AE82: 0 | AF82: 0 | AG82: =SUM(AH82:AJ82) -> 0 | AH82: 0 | AI82: 0 | AJ82: 0 | AL82: 0 | AM82: 0
B83: Salaries - Others | C83: =SUM(D83:S83)-P83-L83-H83-D83 -> 6452.85 | D83: =SUM(E83:G83) -> 0 | H83: =SUM(I83:K83) -> 0 | L83: =SUM(M83:O83) -> 0 | P83: =SUM(Q83:S83) -> 6452.85 | R83: 0 | S83: 6452.85 | T83: =SUM(U83:AJ83)-AG83-AC83-Y83-U83 -> 0 | U83: =SUM(V83:X83) -> 0 | V83: 0 | Y83: =SUM(Z83:AB83) -> 0 | AB83: 0 | AC83: =SUM(AD83:AF83) -> 0 | AD83: 0 | AE83: 0 | AF83: 0 | AG83: =SUM(AH83:AJ83) -> 0 | AH83: 0 | AI83: 0 | AJ83: 0 | AL83: 0 | AM83: 1589.07
B84: Salaries - Transportation | C84: =SUM(D84:S84)-P84-L84-H84-D84 -> 0 | D84: =SUM(E84:G84) -> 0 | H84: =SUM(I84:K84) -> 0 | L84: =SUM(M84:O84) -> 0 | P84: =SUM(Q84:S84) -> 0 | T84: =SUM(U84:AJ84)-AG84-AC84-Y84-U84 -> 0 | U84: =SUM(V84:X84) -> 0 | V84: 0 | Y84: =SUM(Z84:AB84) -> 0 | AB84: 0 | AC84: =SUM(AD84:AF84) -> 0 | AD84: 0 | AE84: 0 | AF84: 0 | AG84: =SUM(AH84:AJ84) -> 0 | AH84: 0 | AI84: 0 | AJ84: 0 | AL84: 0 | AM84: 0
B85: End Of Service Benefits | C85: =SUM(D85:S85)-P85-L85-H85-D85 -> 0 | D85: =SUM(E85:G85) -> 0 | H85: =SUM(I85:K85) -> 0 | L85: =SUM(M85:O85) -> 0 | P85: =SUM(Q85:S85) -> 0 | S85: 0 | T85: =SUM(U85:AJ85)-AG85-AC85-Y85-U85 -> 16506.4 | U85: =SUM(V85:X85) -> 0 | V85: 0 | X85: 0 | Y85: =SUM(Z85:AB85) -> 13500 | AB85: 13500 | AC85: =SUM(AD85:AF85) -> 0 | AD85: 0 | AE85: 0 | AF85: 0 | AG85: =SUM(AH85:AJ85) -> 3006.4 | AH85: 0 | AI85: 0 | AJ85: 3006.4 | AL85: 1830.15 | AM85: 9346.15
B86: Staff Education/Growth Allowance | C86: =SUM(D86:S86)-P86-L86-H86-D86 -> 1631.67 | D86: =SUM(E86:G86) -> 0 | H86: =SUM(I86:K86) -> 0 | L86: =SUM(M86:O86) -> 0 | R86: 0 | S86: 1631.67 | T86: =SUM(U86:AJ86)-AG86-AC86-Y86-U86 -> 0 | U86: =SUM(V86:X86) -> 0 | Y86: =SUM(Z86:AB86) -> 0 | AC86: =SUM(AD86:AF86) -> 0 | AD86: 0 | AE86: 0 | AF86: 0 | AI86: 0 | AJ86: 0 | AL86: 0 | AM86: 1875.2
B87: Operating expenses | C87: =+C65+C60+C56+C39+C19 -> 1018699.6 | D87: =SUM(E87:G87) -> 0 | E87: =+E65+E60+E56+E39+E19 -> 0 | F87: =+F65+F60+F56+F39+F19 -> 0 | G87: =+G65+G60+G56+G39+G19 -> 0 | H87: =SUM(I87:K87) -> 0 | I87: =+I65+I60+I56+I39+I19 -> 0 | J87: =+J65+J60+J56+J39+J19 -> 0 | K87: =+K65+K60+K56+K39+K19 -> 0 | L87: =SUM(M87:O87) -> 0 | M87: =+M65+M60+M56+M39+M19 -> 0 | N87: =+N65+N60+N56+N39+N19 -> 0 | O87: =+O65+O60+O56+O39+O19 -> 0 | P87: =SUM(Q87:S87) -> 1018699.6 | Q87: =+Q65+Q60+Q56+Q39+Q19 -> 0 | R87: =+R65+R60+R56+R39+R19 -> 519357.07 | S87: =+S65+S60+S56+S39+S19 -> 499342.52 | T87: =+T65+T60+T56+T39+T19 -> 5525429.4 | U87: =SUM(V87:X87) -> 1688520.5 | V87: =+V65+V60+V56+V39+V19 -> 530584.17 | W87: =+W65+W60+W56+W39+W19 -> 458815.53 | X87: =+X65+X60+X56+X39+X19 -> 699120.83 | Y87: =SUM(Z87:AB87) -> 1355921.2 | Z87: =+Z65+Z60+Z56+Z39+Z19 -> 436080.75 | AA87: =+AA65+AA60+AA56+AA39+AA19 -> 471720.13 | AB87: =+AB65+AB60+AB56+AB39+AB19 -> 448120.31 | AC87: =SUM(AD87:AF87) -> 1375471.9 | AD87: =+AD65+AD60+AD56+AD39+AD19 -> 458559.01 | AE87: =+AE65+AE60+AE56+AE39+AE19 -> 497692.97 | AF87: =+AF65+AF60+AF56+AF39+AF19 -> 419219.88 | AG87: =SUM(AH87:AJ87) -> 1105515.8 | AH87: =+AH65+AH60+AH56+AH39+AH19 -> 380631.04 | AI87: =+AI65+AI60+AI56+AI39+AI19 -> 393146.26 | AJ87: =+AJ65+AJ60+AJ56+AJ39+AJ19 -> 331738.53 | AL87: =+AL65+AL60+AL56+AL39+AL19 -> 287714.64 | AM87: =+AM65+AM60+AM56+AM39+AM19 -> 2867808.1
B90: Net operating profit / (loss) | C90: =SUM(C14+C16+C15)-C87 -> -1018699.6 | D90: =SUM(E90:G90) -> 0 | E90: =SUM(E14+E16+E15)-E87 -> 0 | F90: =SUM(F14+F16+F15)-F87 -> 0 | G90: =SUM(G14+G16+G15)-G87 -> 0 | H90: =SUM(I90:K90) -> 0 | I90: =SUM(I14+I16+I15)-I87 -> 0 | J90: =SUM(J14+J16+J15)-J87 -> 0 | K90: =SUM(K14+K16+K15)-K87 -> 0 | L90: =SUM(M90:O90) -> 0 | M90: =SUM(M14+M16+M15)-M87 -> 0 | N90: =SUM(N14+N16+N15)-N87 -> 0 | O90: =SUM(O14+O16+O15)-O87 -> 0 | P90: =SUM(Q90:S90) -> -1018699.6 | Q90: =SUM(Q14+Q16+Q15)-Q87 -> 0 | R90: =SUM(R14+R16+R15)-R87 -> -519357.07 | S90: =SUM(S14+S16+S15)-S87 -> -499342.52 | T90: =SUM(T14+T16+T15)-T87 -> -5525198.4 | U90: =SUM(V90:X90) -> -1688520.5 | V90: =SUM(V14+V16+V15)-V87 -> -530584.17 | W90: =SUM(W14+W16+W15)-W87 -> -458815.53 | X90: =SUM(X14+X16+X15)-X87 -> -699120.83 | Y90: =SUM(Z90:AB90) -> -1355797.1 | Z90: =SUM(Z14+Z16+Z15)-Z87 -> -436043.25 | AA90: =SUM(AA14+AA16+AA15)-AA87 -> -471720.13 | AB90: =SUM(AB14+AB16+AB15)-AB87 -> -448033.68 | AC90: =SUM(AD90:AF90) -> -1375373.6 | AD90: =SUM(AD14+AD16+AD15)-AD87 -> -458509.88 | AE90: =SUM(AE14+AE16+AE15)-AE87 -> -497643.84 | AF90: =SUM(AF14+AF16+AF15)-AF87 -> -419219.88 | AG90: =SUM(AH90:AJ90) -> -1105507.3 | AH90: =SUM(AH14+AH16+AH15)-AH87 -> -380631.04 | AI90: =SUM(AI14+AI16+AI15)-AI87 -> -393137.69 | AJ90: =SUM(AJ14+AJ16+AJ15)-AJ87 -> -331738.53 | AL90: =SUM(AL14+AL16)-AL87 -> -287714.64 | AM90: -2867808.1
B93: Exchange Gain or Loss | C93: =SUM(D93:S93)-P93-L93-H93-D93 -> -4.31 | D93: =SUM(E93:G93) -> 0 | H93: =SUM(I93:K93) -> 0 | L93: =SUM(M93:O93) -> 0 | P93: =SUM(Q93:S93) -> -4.31 | R93: 1.55 | S93: -5.86 | T93: =SUM(U93:AJ93)-AG93-AC93-Y93-U93 -> -2514.09 | U93: =SUM(V93:X93) -> 0.08 | V93: -0.02 | W93: 0.05 | X93: 0.05 | Y93: =SUM(Z93:AB93) -> -2664.95 | Z93: 0.03 | AA93: -1937.58 | AB93: -727.4 | AC93: =SUM(AD93:AF93) -> 150.89 | AD93: 0.02 | AE93: 152.02 | AF93: -1.15 | AG93: =SUM(AH93:AJ93) -> -0.11 | AH93: -0.04 | AI93: -0.03 | AJ93: -0.04 | AL93: 147.97 | AM93: -1090.21
C94: =SUM(D94:S94)-P94-L94-H94-D94 -> 0 | T94: =SUM(U94:AJ94)-AG94-AC94-Y94-U94 -> 0 | AM94: 0
B95: Gain Or Loss on Disposal | C95: =SUM(D95:S95)-P95-L95-H95-D95 -> 0 | D95: =SUM(E95:G95) -> 0 | R95: 0 | S95: 0 | T95: =SUM(U95:AJ95)-AG95-AC95-Y95-U95 -> 0 | U95: =SUM(V95:X95) -> 0 | AI95: 0 | AJ95: 0 | AM95: 0
C97: =SUM(D97:S97)-P97-L97-H97-D97 -> 0 | S97: 0 | T97: =SUM(U97:AJ97)-AG97-AC97-Y97-U97 -> 0 | AJ97: 0 | AM97: 0
B98: Investor's Profit sharing (Unrealized) | C98: =SUM(D98:S98)-P98-L98-H98-D98 -> 0 | D98: =SUM(E98:G98) -> 0 | H98: =SUM(I98:K98) -> 0 | J98: 0 | K98: 0 | L98: =SUM(M98:O98) -> 0 | M98: 0 | N98: 0 | O98: 0 | P98: =SUM(Q98:S98) -> 0 | R98: 0 | S98: 0 | T98: =SUM(U98:AJ98)-AG98-AC98-Y98-U98 -> 0 | U98: =SUM(V98:X98) -> 0 | Y98: =SUM(Z98:AB98) -> 0 | AA98: 0 | AB98: 0 | AC98: =SUM(AD98:AF98) -> 0 | AD98: 0 | AE98: 0 | AF98: 0 | AG98: =SUM(AH98:AJ98) -> 0 | AI98: 0 | AJ98: 0 | AM98: 0
C99: =SUM(D99:S99)-P99-L99-H99-D99 -> 0 | T99: =SUM(U99:AJ99)-AG99-AC99-Y99-U99 -> 0 | AM99: 0
B100: Short term financing expense (Al-Raeda) | C100: =SUM(D100:S100)-P100-L100-H100-D100 -> 0 | D100: =SUM(E100:G100) -> 0 | H100: =SUM(I100:K100) -> 0 | L100: =SUM(M100:O100) -> 0 | M100: 0 | N100: 0 | O100: 0 | P100: =SUM(Q100:S100) -> 0 | Q100: 0 | R100: 0 | S100: 0 | T100: =SUM(U100:AJ100)-AG100-AC100-Y100-U100 -> 0 | U100: =SUM(V100:X100) -> 0 | Y100: =SUM(Z100:AB100) -> 0 | AC100: =SUM(AD100:AF100) -> 0 | AD100: 0 | AE100: 0 | AF100: 0 | AG100: =SUM(AH100:AJ100) -> 0 | AH100: 0 | AI100: 0 | AJ100: 0 | AM100: 0
C101: =SUM(D101:S101)-P101-L101-H101-D101 -> 0 | T101: =SUM(U101:AJ101)-AG101-AC101-Y101-U101 -> 0 | AM101: 0
B102: Financing expense (Arbah) | C102: =SUM(D102:S102)-P102-L102-H102-D102 -> 0 | D102: =SUM(E102:G102) -> 0 | H102: =SUM(I102:K102) -> 0 | P102: =SUM(Q102:S102) -> 0 | R102: 0 | S102: 0 | T102: =SUM(U102:AJ102)-AG102-AC102-Y102-U102 -> 0 | U102: =SUM(V102:X102) -> 0 | Y102: =SUM(Z102:AB102) -> 0 | AG102: =SUM(AH102:AJ102) -> 0 | AI102: 0 | AJ102: 0 | AM102: 0
C103: =SUM(D103:S103)-P103-L103-H103-D103 -> 0 | T103: =SUM(U103:AJ103)-AG103-AC103-Y103-U103 -> 0 | AM103: 0
B104: Financing expense (STV) | C104: =SUM(D104:S104)-P104-L104-H104-D104 -> -78018.76 | D104: =SUM(E104:G104) -> 0 | H104: =SUM(I104:K104) -> 0 | L104: =SUM(M104:O104) -> 0 | P104: =SUM(Q104:S104) -> -78018.76 | R104: -39009.38 | S104: -39009.38 | T104: =SUM(U104:AJ104)-AG104-AC104-Y104-U104 -> -295867.16 | U104: =SUM(V104:X104) -> -94903.14 | V104: -39009.38 | W104: -27946.88 | X104: -27946.88 | Y104: =SUM(Z104:AB104) -> -83840.64 | Z104: -27946.88 | AA104: -27946.88 | AB104: -27946.88 | AC104: =SUM(AD104:AF104) -> -63571.88 | AD104: -27946.88 | AE104: -17812.5 | AF104: -17812.5 | AG104: =SUM(AH104:AJ104) -> -53551.5 | AH104: -17850.5 | AI104: -17850.5 | AJ104: -17850.5 | AL104: -17850.5 | AM104: -69147.2
C105: =SUM(D105:S105)-P105-L105-H105-D105 -> 0 | T105: =SUM(U105:AJ105)-AG105-AC105-Y105-U105 -> 0 | AM105: 0
B106: Financing Expense (Anas Ibrahim Al Hozaimi) | C106: =SUM(D106:S106)-P106-L106-H106-D106 -> -76125.01 | D106: =SUM(E106:G106) -> 0 | H106: =SUM(I106:K106) -> 0 | L106: =SUM(M106:O106) -> 0 | O106: 0 | P106: =SUM(Q106:S106) -> -76125.01 | R106: -41854.17 | S106: -34270.84 | T106: =SUM(U106:AJ106)-AG106-AC106-Y106-U106 -> -253416.66 | U106: =SUM(V106:X106) -> -102812.5 | V106: -34270.83 | W106: -34270.83 | X106: -34270.84 | Y106: =SUM(Z106:AB106) -> -95895.84 | Z106: -34270.83 | AA106: -34270.83 | AB106: -27354.18 | AC106: =SUM(AD106:AF106) -> -54708.32 | AD106: -33354.16 | AE106: -21354.16 | AF106: 0 | AI106: 0 | AJ106: 0
B108: Financing Expense (Salimuddin Siraj) | C108: =SUM(D108:S108)-P108-L108-H108-D108 -> -24166.68 | D108: =SUM(E108:G108) -> 0 | H108: =SUM(I108:K108) -> 0 | L108: =SUM(M108:O108) -> 0 | O108: 0 | P108: =SUM(Q108:S108) -> -24166.68 | R108: -12083.36 | S108: -12083.32 | T108: =SUM(U108:AJ108)-AG108-AC108-Y108-U108 -> -84583.32 | U108: =SUM(V108:X108) -> -36249.98 | V108: -12083.32 | W108: -12083.32 | X108: -12083.34 | Y108: =SUM(Z108:AB108) -> -36250.01 | Z108: -12083.34 | AA108: -12083.34 | AB108: -12083.33 | AC108: =SUM(AD108:AF108) -> -12083.33 | AD108: -12083.33 | AE108: 0 | AF108: 0 | AI108: 0 | AJ108: 0
B110: Financing Expense (Amal Abdulmohsen) | C110: =SUM(D110:S110)-P110-L110-H110-D110 -> 0 | D110: =SUM(E110:G110) -> 0 | H110: =SUM(I110:K110) -> 0 | P110: =SUM(Q110:S110) -> 0 | S110: 0 | T110: =SUM(U110:AJ110)-AG110-AC110-Y110-U110 -> -181250 | U110: =SUM(V110:X110) -> -108750 | V110: -36250 | W110: -36250 | X110: -36250 | Y110: =SUM(Z110:AB110) -> -72500 | Z110: -36250 | AA110: -36250
B112: Financing Expense (SIDF) | C112: =SUM(D112:S112)-P112-L112-H112-D112 -> 0 | D112: =SUM(E112:G112) -> 0 | H112: =SUM(I112:K112) -> 0 | P112: =SUM(Q112:S112) -> 0 | T112: =SUM(U112:AJ112)-AG112-AC112-Y112-U112 -> -119666.66 | U112: =SUM(V112:X112) -> -119666.66 | V112: -119666.66 | Y112: =SUM(Z112:AB112) -> 0
B114: Financing Processing Fee Expense | C114: =SUM(D114:S114)-P114-L114-H114-D114 -> 0 | D114: =SUM(E114:G114) -> 0 | H114: =SUM(I114:K114) -> 0 | L114: =SUM(M114:O114) -> 0 | P114: =SUM(Q114:S114) -> 0 | R114: 0 | S114: 0 | T114: =SUM(U114:AJ114)-AG114-AC114-Y114-U114 -> -9998.84 | U114: =SUM(V114:X114) -> 0 | Y114: =SUM(Z114:AB114) -> 0 | AC114: =SUM(AD114:AF114) -> -9998.84 | AE114: 0 | AF114: -9998.84 | AI114: 0 | AJ114: 0 | AM114: 0
C115: =SUM(D115:S115)-P115-L115-H115-D115 -> 0 | T115: =SUM(U115:AJ115)-AG115-AC115-Y115-U115 -> 0 | AM115: 0
B116: Fundraising Expense | C116: =SUM(D116:S116)-P116-L116-H116-D116 -> -2499.98 | D116: =SUM(E116:G116) -> 0 | H116: =SUM(I116:K116) -> 0 | L116: =SUM(M116:O116) -> 0 | P116: =SUM(Q116:S116) -> -2499.98 | R116: -1249.99 | S116: -1249.99 | T116: =SUM(U116:AJ116)-AG116-AC116-Y116-U116 -> -15007.86 | U116: =SUM(V116:X116) -> -3749.97 | V116: -1249.99 | W116: -1249.99 | X116: -1249.99 | Y116: =SUM(Z116:AB116) -> -3749.97 | Z116: -1249.99 | AA116: -1249.99 | AB116: -1249.99 | AC116: =SUM(AD116:AF116) -> -3749.97 | AD116: -1249.99 | AE116: -1249.99 | AF116: -1249.99 | AG116: =SUM(AH116:AJ116) -> -3757.95 | AH116: -1252.65 | AI116: -1252.65 | AJ116: -1252.65 | AL116: -1252.65 | AM116: -3757.95
C117: =SUM(D117:S117)-P117-L117-H117-D117 -> 0 | T117: =SUM(U117:AJ117)-AG117-AC117-Y117-U117 -> 0 | AM117: 0
...

Sheet BS Feb USA
B6: STATEMENT OF FINANCIAL POSITION (US SAR) | D6: 46387 | E6: 46356 | F6: 46326 | G6: 46295 | H6: 46265 | I6: 46234 | J6: 46203 | K6: 46173 | L6: 46142 | M6: 46112 | N6: 46081 | O6: 46053 | P6: 46022 | Q6: 45991 | R6: 45961 | S6: 45930 | T6: 45900 | U6: 45869 | V6: 45838 | W6: 45808 | X6: 45777 | Y6: 45747 | Z6: 45716 | AA6: 45688 | AC6: 45657
B7: As of 28 Feb 2026
B8: ASSETS
B10: Cash and Bank Balances | D10: =SUM(D11:D29) -> 0 | E10: =SUM(E11:E29) -> 0 | F10: =SUM(F11:F29) -> 0 | G10: =SUM(G11:G29) -> 0 | H10: =SUM(H11:H29) -> 0 | I10: =SUM(I11:I29) -> 0 | J10: =SUM(J11:J29) -> 0 | K10: =SUM(K11:K29) -> 0 | ... AA10: =SUM(AA11:AA29) -> 1685710.6 | AC10: =SUM(AC11:AC29) -> 2008252.4
B11: ALINMA BILDNW FEE | C11: =B11 -> ALINMA BILDNW FEE | I11: 0 | J11: 0 | K11: 0 | L11: 0 | M11: 0 | N11: 0 | O11: 0 | U11: 0 | V11: 0 | W11: 0 | X11: 0 | Y11: 0 | Z11: 0 | AA11: 0
B12: ALINMA BILDNW PROFIT | C12: =B12 -> ALINMA BILDNW PROFIT | I12: 0 | J12: 0 | K12: 0 | L12: 0 | M12: 0 | N12: 0 | O12: 0 | U12: 0 | V12: 0 | W12: 0 | X12: 0 | Y12: 0 | Z12: 0 | AA12: 0
B13: ALINMA CLIENT PROFIT | C13: =B13 -> ALINMA CLIENT PROFIT | I13: 0 | J13: 0 | K13: 0 | L13: 0 | M13: 0 | N13: 0 | O13: 0 | U13: 0 | V13: 0 | W13: 0 | X13: 0 | Y13: 0 | Z13: 0 | AA13: 0
B14: ALINMA DINAR DEALs PROFIT | C14: =B14 -> ALINMA DINAR DEALs PROFIT | I14: 0 | J14: 0 | K14: 0 | L14: 0 | M14: 0 | N14: 0 | O14: 0 | U14: 0 | V14: 0 | W14: 0 | X14: 0 | Y14: 0 | Z14: 0 | AA14: 0
B15: ALINMA DINAR DEALs VAT | C15: =B15 -> ALINMA DINAR DEALs VAT | O15: 0 | U15: 0 | V15: 0 | W15: 0 | X15: 0 | Y15: 0 | Z15: 0 | AA15: 0
B16: ALINMA EQUITY | C16: =B16 -> ALINMA EQUITY | O16: 0 | U16: 0 | V16: 0 | W16: 0 | X16: 0 | Y16: 0 | Z16: 0 | AA16: 0
B17: ALINMA USD | C17: =B17 -> ALINMA USD | O17: 0 | U17: 0 | V17: 0 | W17: 0 | X17: 0 | Y17: 0 | Z17: 0 | AA17: 0
B18: ALINMA VAT | C18: =B18 -> ALINMA VAT | O18: 0 | U18: 0 | V18: 0 | W18: 0 | X18: 0 | Y18: 0 | Z18: 0 | AA18: 0
B19: ALINMA-DEBT | C19: =B19 -> ALINMA-DEBT | O19: 0 | U19: 0 | V19: 0 | W19: 0 | X19: 0 | Y19: 0 | Z19: 0 | AA19: 0
B20: ANB-BILDNW TRADINGCOMPANY | C20: =B20 -> ANB-BILDNW TRADINGCOMPANY | O20: 0 | U20: 0 | V20: 0 | W20: 0 | X20: 0 | Y20: 0 | Z20: 0 | AA20: 0
B21: Riyad Bank | C21: =B21 -> Riyad Bank | O21: 0 | U21: 0 | V21: 0 | W21: 0 | X21: 0 | Y21: 0 | Z21: 0 | AA21: 0
B22: Saudi Awwal Bank (SAB)-5001 | C22: =B22 -> Saudi Awwal Bank (SAB)-5001 | O22: 0
B23: Saudi Awwal Bank (SAB)-5002 | C23: =B23 -> Saudi Awwal Bank (SAB)-5002 | O23: 0
B24: US Checking Account | C24: =B24 -> US Checking Account | N24: 3615947.2 | O24: 3972174.1 | P24: 4665832.4 | Q24: 7232496.4 | R24: 8332218.7 | S24: 1698141.5 | T24: 157288.17 | U24: 71680.74 | V24: 374733.33 | W24: 207571.61 | X24: 387020.37 | Y24: 825153.17 | Z24: 1283941.1 | AA24: 1685710.6 | AC24: 2008252.4
B25: ANB Tanmeya Debt A/C | C25: =B25 -> ANB Tanmeya Debt A/C | O25: 0 | U25: 0 | Z25: 0 | AA25: 0
B26: Simplifi | C26: =B26 -> Simplifi | O26: 0 | U26: 0 | Z26: 0 | AA26: 0
B27: SiFi Wallet | C27: =B27 -> SiFi Wallet | O27: 0 | U27: 0
B28: Sinking Fund | C28: =B28 -> Sinking Fund | O28: 0
B29: Petty Cash | C29: =B29 -> Petty Cash | O29: 0 | U29: 0 | Z29: 0 | AA29: 0 | AC29: 0
C30: =B30 -> 0
B32: Trade Receivables (net) | D32: =SUM(D33:D34) -> 0 | E32: =SUM(E33:E34) -> 0 | F32: =SUM(F33:F34) -> 0 | G32: =SUM(G33:G34) -> 0 | I32: =SUM(I33:I34) -> 0 | J32: =SUM(J33:J34) -> 0 | K32: =SUM(K33:K34) -> 0 | L32: =SUM(L33:L34) -> 0 | M32: =SUM(M33:M34) -> 0 | N32: =SUM(N33:N34) -> 0 | O32: =SUM(O33:O34) -> 0 | P32: =SUM(P33:P34) -> 0 | ... S32: =SUM(S33:S34) -> 0 | U32: =SUM(U33:U34) -> 0 | V32: =SUM(V33:V34) -> 0 | W32: =SUM(W33:W34) -> 0 | X32: =SUM(X33:X34) -> 0 | Y32: =SUM(Y33:Y34) -> 0 | Z32: =SUM(Z33:Z34) -> 0 | AA32: =SUM(AA33:AA34) -> 0 | AC32: =SUM(AC33:AC34) -> 0
B33: Trade Receivables - Gross | C33: Accounts Receivable | K33: 0 | L33: 0 | M33: 0 | N33: 0 | O33: 0 | W33: 0 | X33: 0 | Y33: 0 | Z33: 0 | AA33: 0
B34: Closing Provision for doubtful Accounts | C34: Provision for Doubtful Debts | D34: 0 | E34: 0 | F34: 0 | G34: 0 | I34: 0 | J34: 0 | K34: 0 | L34: 0 | M34: 0 | N34: 0 | O34: 0 | P34: 0 | Q34: 0 | R34: 0 | S34: 0 | U34: 0 | V34: 0 | W34: 0 | X34: 0 | Y34: 0 | Z34: 0 | AA34: 0 | AC34: 0
B36: Prepaid Expenses & Other recievables | D36: =SUM(D37:D50) -> 0 | E36: =SUM(E37:E50) -> 0 | F36: =SUM(F37:F50) -> 0 | G36: =SUM(G37:G50) -> 0 | H36: =SUM(H37:H50) -> 0 | I36: =SUM(I37:I50) -> 0 | J36: =SUM(J37:J50) -> 0 | K36: =SUM(K37:K50) -> 0 | L36: =SUM(L37:L50) -> 0 | M36: =SUM(M37:M53) -> 0 | N36: =SUM(N37:N50) -> 190985.2 | O36: =SUM(O37:O50) -> 203100.53 | P36: =SUM(P37:P50) -> 180412.78 | Q36: =SUM(Q37:Q50) -> 189850.03 | R36: =SUM(R37:R50) -> 212214.73 | S36: =SUM(S37:S50) -> 180274.82 | T36: =SUM(T37:T50) -> 203896.86 | U36: =SUM(U37:U50) -> 199268.9 | ... X36: =SUM(X37:X50) -> 167543.76 | Y36: =SUM(Y37:Y53) -> 164594.37 | Z36: =SUM(Z37:Z53) -> 164694.03 | AA36: =SUM(AA37:AA52) -> 161368.51 | AC36: =SUM(AC37:AC52) -> 131186.62
B37: Prepaid Vendors | C37: Prepaid vendors Bildnw Inc. | O37: 0 | Z37: 0 | AA37: 0
B38: Prepaid Accommodation Rent Expense | C38: =B38 -> Prepaid Accommodation Rent Expense | O38: 0 | Z38: 0 | AA38: 0
B39: Prepaid Financing Expense | C39: =B39 -> Prepaid Financing Expense | N39: 53894.21 | O39: 55144.2 | P39: 56394.19 | Q39: 57644.18 | R39: 58894.17 | S39: 60144.16 | T39: 61394.15 | U39: 62644.14 | V39: 63894.13 | W39: 65144.12 | X39: 66394.11 | Y39: 67644.1 | Z39: 68896.75 | AA39: 70149.4 | AC39: 71402.05
B40: Prepaid Govt. Legal Expense | C40: =B40 -> Prepaid Govt. Legal Expense | O40: 0 | Z40: 0 | AA40: 0
B41: Prepaid IT Subscriptions Expense | C41: =B41 -> Prepaid IT Subscriptions Expense | N41: 20811.83 | O41: 27410.41 | P41: 12330.91 | Q41: 13699.88 | R41: 496.31 | S41: 650.92 | T41: 4640.55 | U41: 8630.18 | V41: 3244.81 | W41: 7234.44 | X41: 11224.07 | Y41: 15213.7 | Z41: 9816.84 | AA41: 11955.6 | AC41: 15798.79
B42: Prepaid Office Rent Expense | C42: =B42 -> Prepaid Office Rent Expense | O42: 0 | Z42: 0 | AA42: 0
B43: Prepaid Other Expense | C43: =B43 -> Prepaid Other Expense | N43: 10869.72 | O43: 15136.48 | P43: 6278.24 | Q43: 13096.53 | R43: 19914.82 | S43: 14257.8 | T43: 21066.86 | U43: 27875.92 | V43: 34684.98 | W43: 10508.09 | X43: 14765.58 | Y43: 6576.57 | Z43: 10820.44 | AA43: 4103.51 | AC43: 6155.23
B44: Prepaid Employment Expense (Iqama) | C44: =B44 -> Prepaid Employment Expense (Iqama) | O44: 0
B45: Fund Raising Expense receivable | C45: =B45 -> Fund Raising Expense receivable | N45: 75160 | O45: 75160 | P45: 75160 | Q45: 75160 | R45: 75160 | S45: 75160 | T45: 75160 | U45: 75160 | V45: 75160 | W45: 75160 | X45: 75160 | Y45: 75160 | Z45: 75160 | AA45: 75160 | AC45: 37580
B46: Employee Receivable | C46: Employee Advance | N46: 30249.44 | O46: 30249.44 | P46: 30249.44 | Q46: 30249.44 | R46: 57749.43 | S46: 30061.94 | T46: 41635.3 | U46: 24208.66 | V46: 9375 | Y46: 0 | Z46: 0 | AA46: 0 | AC46: 250.55
B47: Security deposits | C47: =B47 -> Security deposits | O47: 0 | Z47: 0 | AA47: 0
B48: Advance to Other Vendors | C48: =B48 -> Advance to Other Vendors | O48: 0 | S48: 0 | T48: 0 | U48: 750 | Z48: 0
B49: Other Receivable | C49: =B49 -> Other Receivable | O49: 0 | Z49: 0 | AA49: 0
B50: Input VAT | C50: =B50 -> Input VAT | O50: 0 | Z50: 0 | AA50: 0
B51: Profit Reserve Account (Depsoit) | C51: =B51 -> Profit Reserve Account (Depsoit) | O51: 0 | Z51: 0 | AA51: 0
B52: Short-term Investments | C52: =B52 -> Short-term Investments | N52: 0 | O52: 0 | Z52: 0 | AA52: 0
B54: TOTAL CURRENT ASSETS | D54: =+D36+D10+D32 -> 0 | E54: =+E36+E10+E32 -> 0 | F54: =+F36+F10+F32 -> 0 | G54: =+G36+G10+G32 -> 0 | H54: =+H36+H10+H32 -> 0 | I54: =+I36+I10+I32 -> 0 | J54: =+J36+J10+J32 -> 0 | K54: =+K36+K10+K32 -> 0 | ... AA54: =+AA36+AA10+AA32 -> 1847079.1 | AC54: =+AC36+AC10+AC32 -> 2139439.1
B57: Fixed Assets (net) | D57: =SUM(D58:D70) -> 0 | E57: =SUM(E58:E70) -> 0 | F57: =SUM(F58:F70) -> 0 | G57: =SUM(G58:G70) -> 0 | H57: =SUM(H58:H70) -> 0 | I57: =SUM(I58:I70) -> 0 | J57: =SUM(J58:J70) -> 0 | K57: =SUM(K58:K70) -> 0 | ... AA57: =SUM(AA58:AA70) -> 10169.63 | AC57: =SUM(AC58:AC70) -> 10767.83
B58: Accumulated Depreciation - Furniture & Fixture | C58: =B58 -> Accumulated Depreciation - Furniture & Fixture | O58: 0 | Z58: 0 | AA58: 0
B59: Accumulated Depreciation - Motor Vehicle | C59: =B59 -> Accumulated Depreciation - Motor Vehicle | O59: 0 | Z59: 0 | AA59: 0
B60: Accumulated Depreciation - Office Equipment's | C60: =B60 -> Accumulated Depreciation - Office Equipment's | N60: -15071.55 | O60: -14143.5 | P60: -12564.45 | Q60: -11766.6 | R60: -10968.75 | S60: -10170.9 | T60: -9373.05 | U60: -8575.2 | V60: -7777.35 | W60: -6979.5 | X60: -6181.65 | Y60: -5383.8 | Z60: -4785.6 | AA60: -4187.4 | AC60: -3589.2
B61: Accumulated Depreciation-Building Improvement | C61: =B61 -> Accumulated Depreciation-Building Improvement | O61: 0
B62: Fixed Assets not in use | C62: =B62 -> Fixed Assets not in use | O62: 0 | Z62: 0 | AA62: 0
B63: Furniture & Fixture | C63: =B63 -> Furniture & Fixture | O63: 0 | Z63: 0 | AA63: 0
B64: Motor Vehicle | C64: =B64 -> Motor Vehicle | O64: 0 | Z64: 0 | AA64: 0
B65: Building Improvement | C65: =B65 -> Building Improvement | O65: 0
B66: Intangible Assets | C66: =B66 -> Intangible Assets | O66: 0
B67: Office Equipment | C67: =B67 -> Office Equipment | N67: 23877.05 | O67: 23877.05 | P67: 23877.05 | Q67: 23877.05 | R67: 23877.05 | S67: 23877.05 | T67: 23877.05 | U67: 19189.55 | V67: 19189.55 | W67: 19189.55 | X67: 19189.55 | Y67: 14357.03 | Z67: 14357.03 | AA67: 14357.03 | AC67: 14357.03
B68: Product Development | C68: =B68 -> Product Development | N68: 103345 | O68: 103345 | P68: 103345 | Q68: 103345 | R68: 103345 | S68: 103345 | T68: 103345 | U68: 103345 | V68: 103345 | W68: 103345 | X68: 103345 | Y68: 58249 | Z68: 58249 | AA68: 0
B69: Capital Work in Progress (Tangible) | C69: =B69 -> Capital Work in Progress (Tangible) | O69: 0 | T69: 0 | Z69: 0
B70: Capital Work in Progress (Intangible) | C70: =B70 -> Capital Work in Progress (Intangible) | O70: 0 | T70: 0 | U70: 0 | V70: 0
B71: Intercompany | D71: =SUM(D72:D78) -> 0 | E71: =SUM(E72:E78) -> 0 | F71: =SUM(F72:F78) -> 0 | G71: =SUM(G72:G78) -> 0 | H71: =SUM(H72:H78) -> 0 | I71: =SUM(I72:I78) -> 0 | J71: =SUM(J72:J78) -> 0 | K71: =SUM(K72:K78) -> 0 | L71: =SUM(L72:L78) -> 0 | M71: =SUM(M72:M79) -> 0 | N71: =SUM(N72:N78) -> 36708724 | O71: =SUM(O72:O78) -> 36708724 | P71: =SUM(P72:P78) -> 36427474 | Q71: =SUM(Q72:Q78) -> 37545948 | R71: =SUM(R72:R78) -> 37545948 | S71: =SUM(S72:S78) -> 29858448 | T71: =SUM(T72:T78) -> 29854793 | U71: =SUM(U72:U78) -> 29854793 | ... X71: =SUM(X72:X78) -> 25916113 | Y71: =SUM(Y72:Y79) -> 24466113 | Z71: =SUM(Z72:Z75) -> 24466079 | AA71: =SUM(AA72:AA75) -> 24466079 | AC71: =SUM(AC72:AC75) -> 24466079
B72: Buildnow Inc. (US) | C72: =B72 -> Buildnow Inc. (US) | O72: 0 | Z72: 0 | AA72: 0
B73: Buildnow Tech BD | C73: =B73 -> Buildnow Tech BD | N73: 2686.97 | O73: 2686.97 | P73: 2686.97 | Q73: 2686.97 | R73: 2686.97 | S73: 2686.97 | T73: 2686.97 | U73: 2686.97 | V73: 2686.97 | W73: 2686.97 | X73: 2686.97 | Y73: 2686.97 | Z73: 2686.97 | AA73: 2686.97 | AC73: 2686.97
B74: Buildnow Trading Co (KSA) | C74: =B74 -> Buildnow Trading Co (KSA) | N74: 36227073 | O74: 36227073 | P74: 36227073 | Q74: 37352073 | R74: 37352073 | S74: 29852073 | T74: 29852073 | U74: 29852073 | V74: 26852073 | W74: 27415735 | X74: 25913392 | Y74: 24463392 | Z74: 24463392 | AA74: 24463392 | AC74: 24463392
B75: MISA KSA | C75: =B75 -> MISA KSA | O75: 0 | T75: 0 | Z75: 0 | AA75: 0
B76: RHQ Company | C76: =B76 -> RHQ Company | N76: 468750 | O76: 468750 | P76: 187500 | Q76: 187500 | R76: 187500
B77: BNPL-CMA | C77: =B77 -> BNPL-CMA | N77: 10180.51 | O77: 10180.51 | P77: 10180.51 | Q77: 3654.23 | R77: 3654.23 | S77: 3654.23 | T77: 0
B78: Buildnow UK | C78: =B78 -> Buildnow UK | N78: 33.75 | O78: 33.75 | P78: 33.75 | Q78: 33.75 | R78: 33.75 | S78: 33.75 | T78: 33.75 | U78: 33.75 | V78: 33.75 | W78: 33.75 | X78: 33.75 | Y78: 33.75
B80: Investment in Subsidiaries | D80: =SUM(D81:D82) -> 0 | E80: =SUM(E81:E82) -> 0 | F80: =SUM(F81:F82) -> 0 | G80: =SUM(G81:G82) -> 0 | H80: =SUM(H81:H82) -> 0 | I80: =SUM(I81:I82) -> 0 | J80: =SUM(J81:J82) -> 0 | K80: =SUM(K81:K82) -> 0 | ... AA80: =SUM(AA81:AA82) -> 3720.42 | AC80: =SUM(AC81:AC82) -> 3720.42
B81: Buildnow BD Technology Subsidiary | C81: =B81 -> Buildnow BD Technology Subsidiary | N81: 3720.42 | O81: 3720.42 | P81: 3720.42 | Q81: 3720.42 | R81: 3720.42 | S81: 3720.42 | T81: 3720.42 | U81: 3720.42 | V81: 3720.42 | W81: 3720.42 | X81: 3720.42 | Y81: 3720.42 | Z81: 3720.42 | AA81: 3720.42 | AC81: 3720.42
B84: TOTAL NON CURRENT ASSETS | D84: =+D71+D57+D80 -> 0 | E84: =+E71+E57+E80 -> 0 | F84: =+F71+F57+F80 -> 0 | G84: =+G71+G57+G80 -> 0 | H84: =+H71+H57+H80 -> 0 | I84: =+I71+I57+I80 -> 0 | J84: =+J71+J57+J80 -> 0 | K84: =+K71+K57+K80 -> 0 | ... AA84: =+AA71+AA57+AA80 -> 24479970 | AC84: =+AC71+AC57+AC80 -> 24480568
B87: TOTAL ASSETS | D87: =+D84+D54 -> 0 | E87: =+E84+E54 -> 0 | F87: =+F84+F54 -> 0 | G87: =+G84+G54 -> 0 | H87: =+H84+H54 -> 0 | I87: =+I84+I54 -> 0 | J87: =+J84+J54 -> 0 | K87: =+K84+K54 -> 0 | ... AA87: =+AA84+AA54 -> 26327049 | AC87: =+AC84+AC54 -> 26620007
B90: LIABILITIES & OWNER'S EQUITY
B92: Other Payables and Accruals | D92: =SUM(D93:D113) -> 0 | E92: =SUM(E93:E114) -> 0 | F92: =SUM(F93:F114) -> 0 | G92: =SUM(G93:G110) -> 0 | H92: =SUM(H93:H110) -> 0 | I92: =SUM(I93:I110) -> 0 | J92: =SUM(J93:J110) -> 0 | K92: =SUM(K93:K110) -> 0 | L92: =SUM(L93:L110) -> 0 | M92: =SUM(M93:M112) -> 0 | N92: =SUM(N93:N113) -> 477955.03 | O92: =SUM(O93:O113) -> 287619.96 | P92: =SUM(P93:P113) -> 139881.3 | Q92: =SUM(Q93:Q114) -> 232020.66 | R92: =SUM(R93:R114) -> 311357.76 | S92: =SUM(S93:S110) -> 235871.44 | T92: =SUM(T93:T110) -> 136196.29 | U92: =SUM(U93:U110) -> 152745.67 | V92: =SUM(V93:V110) -> 236270.73 | W92: =SUM(W93:W110) -> 131347.44 | X92: =SUM(X93:X110) -> 139694.68 | Y92: =SUM(Y93:Y112) -> 87465.06 | Z92: =SUM(Z93:Z112) -> 147182.89 | AA92: =SUM(AA93:AA110) -> 75735.22 | AC92: =SUM(AC93:AC113) -> 17851.76
B93: Zakat Provision | C93: Provision for Zakat | O93: 0 | Z93: 0 | AA93: 0
B94: Misc. Payables | C94: =B94 -> Misc. Payables | O94: 0 | Z94: 0 | AA94: 0
B95: Consultancy Fee Payable | C95: =B95 -> Consultancy Fee Payable | N95: 124965.1 | O95: 99228.03 | P95: 72389.99 | Q95: 105974.99 | R95: 45674.99 | S95: 60021.38 | T95: 34696.13 | U95: 48387.75 | V95: 65402.03 | W95: 40975.01
B96: Other Payables | C96: =B96 -> Other Payables | N96: 2005.13 | O96: 20673.38 | P96: 22694.18 | Q96: 0 | R96: 49684.5 | S96: 20673.38 | T96: 0 | U96: 0 | V96: 17386.19 | W96: 8498.69 | X96: 24172.94 | Y96: -3351.31 | Z96: 0 | AA96: 0
B97: Unearned Revenue | C97: =B97 -> Unearned Revenue | O97: 0 | Z97: 0 | AA97: 0
B98: Employee Payable | C98: =B98 -> Employee Payable | O98: 0 | Z98: 0 | AA98: 0
B99: Employee Allowance Payable | C99: =B99 -> Employee Allowance Payable | O99: 0 | Z99: 0
B100: Accounts Payable | C100: =B100 -> Accounts Payable | O100: 0 | Z100: 0 | AA100: 0
B101: Accrued Expenses | C101: =B101 -> Accrued Expenses | O101: 0 | Z101: 0 | AA101: 0
B102: VAT Payable (GAZT) | C102: GCC VAT Payable | O102: 0 | Z102: 0 | AA102: 0
B103: Accrued Investor Profit (STV) | C103: Profit Payable (STV) | N103: 117028.14 | O103: 78018.76 | P103: 39009.38 | Q103: 0 | R103: 139734.4 | S103: 111787.52 | T103: 83840.64 | U103: 55893.76 | V103: 27946.88 | W103: 0 | X103: 89214.5 | Y103: 71402 | Z103: 53551.5 | AA103: 35701 | AC103: 17850.5
B104: Accrued Investor Profit (Unrealized) | C104: =B104 -> Accrued Investor Profit (Unrealized) | O104: 0 | Z104: 0 | AA104: 0
B105: Leave Air Fare Payable | C105: =B105 -> Leave Air Fare Payable | O105: 0
B106: Leave Pay Payable | C106: Provision for Leave Pay | O106: 0 | Z106: 0 | AA106: 0
B107: Salary Control Account | C107: Salaries & Wages Payables | N107: 233956.66 | O107: 89699.79 | P107: 5787.75 | Q107: 126045.67 | R107: 76263.87 | S107: 43389.16 | T107: 17659.52 | U107: 48464.16 | V107: 125535.63 | W107: 81873.74 | X107: 26307.24 | Y107: 19414.37 | Z107: 93631.39 | AA107: 40034.22 | AC107: 1.26
B108: Accrued COGS | C108: =B108 -> Accrued COGS | O108: 0
B109: Output VAT | C109: =B109 -> Output VAT | O109: 0 | Z109: 0 | AA109: 0
B110: GOSI Payable | C110: =B110 -> GOSI Payable | O110: 0 | Z110: 0 | AA110: 0
B111: Deferred Revenue | C111: =B111 -> Deferred Revenue | O111: 0
B112: Dividend Payable (Investor) | O112: 0 | Z112: 0 | AA112: 0
B113: Debt Settlement Payable | O113: 0 | Z113: 0 | AA113: 0
B115: Short term Financing | D115: =SUM(D116:D124) -> 0 | E115: =SUM(E116:E125) -> 0 | F115: =SUM(F116:F125) -> 0 | G115: =SUM(G116:G125) -> 0 | H115: =SUM(H116:H125) -> 0 | I115: =SUM(I116:I124) -> 0 | J115: =SUM(J116:J124) -> 0 | K115: =SUM(K116:K124) -> 0 | L115: =SUM(L116:L124) -> 0 | M115: =SUM(M116:M124) -> 0 | N115: =SUM(N116:N124) -> 41854.17 | O115: =SUM(O116:O124) -> 24166.64 | P115: =SUM(P116:P124) -> 200291.64 | Q115: =SUM(Q116:Q125) -> 143020.83 | R115: =SUM(R116:R125) -> 96666.68 | S115: =SUM(S116:S125) -> 116875 | T115: =SUM(T116:T125) -> 34270.83 | U115: =SUM(U116:U124) -> 24166.66 | V115: =SUM(V116:V124) -> 66791.65 | W115: =SUM(W116:W124) -> 21354.16 | X115: =SUM(X116:X124) -> 0 | Y115: =SUM(Y116:Y124) -> 0 | Z115: =SUM(Z116:Z124) -> 0 | AA115: =SUM(AA116:AA124) -> 0 | AC115: =SUM(AC116:AC124) -> 0
B116: Interest payable (Al-Raeda) | O116: 0 | V116: 0 | W116: 0 | X116: 0 | Y116: 0 | Z116: 0 | AA116: 0
B117: Short-term Financing (Al Raedah) | C117: Debt Financing (Al Raedah 2) | O117: 0 | V117: 0 | W117: 0 | X117: 0 | Y117: 0 | Z117: 0 | AA117: 0
B118: Arbah Murabaha Facility | C118: =B118 -> Arbah Murabaha Facility | O118: 0
B119: SIDF Loan Facility | C119: =B119 -> SIDF Loan Facility | O119: 0
B120: Profit payable (Amal Abdulmohsen) | O120: 0 | P120: 0 | Q120: 108750 | R120: 72500 | S120: 36250
...

Sheet IS Jan Consolidated (YTD)
B7: INCOME STATEMENT (US SAR) | C7: YTD-Actual | D7: Q4 - A | E7: MTD | F7: MTD | G7: MTD | H7: Q3 - A | I7: MTD | J7: MTD | K7: MTD | L7: Q2 - A | M7: MTD | N7: MTD | O7: MTD | P7: Q1 A | Q7: MTD | R7: MTD | S7: MTD | T7: YTD-Variance | U7: YTD-Projected | V7: YTD-Actual | W7: MTD Variance | X7: MTD-Projected | Y7: Q4 - A | Z7: MTD | AA7: MTD | AB7: MTD | AC7: Q3 - A | AD7: MTD | AE7: MTD | AF7: MTD | AG7: Q2 - A | AH7: MTD | AI7: MTD | AJ7: MTD | AK7: Q1 A | AL7: MTD | AM7: MTD | AN7: MTD | AP7: MTD | AQ7: YTD
B8: FOR THE PERIOD 28 Feb 2026 | C8: 2026 | D8: 2025 | E8: 46022 | F8: 45991 | G8: 45961 | H8: 2025 | I8: 45930 | J8: 45900 | K8: 45869 | L8: 2025 | M8: 45838 | N8: 45808 | O8: 45777 | P8: 2026 | Q8: 45747 | R8: 46081 | S8: 46053 | T8: 2025 | U8: 2025 | V8: 2025 | Y8: 2025 | Z8: 46022 | AA8: 45991 | AB8: 45961 | AC8: 2025 | AD8: 45930 | AE8: 45900 | AF8: 45869 | AG8: 2025 | AH8: 45838 | AI8: 45808 | AJ8: 45777 | AK8: 2025 | AL8: 45747 | AM8: 45716 | AN8: 45688 | AP8: 45657 | AQ8: 2024
B10: Sales | C10: =H10+L10+D10+P10 -> 32825790 | D10: =SUM(E10:G10) -> 0 | E10: ='IS Feb KSA'!E10+'IS Feb USA'!E10 -> 0 | F10: ='IS Feb KSA'!F10+'IS Feb USA'!F10 -> 0 | G10: ='IS Feb KSA'!G10+'IS Feb USA'!G10 -> 0 | H10: =I10+J10+K10 -> 0 | I10: ='IS Feb KSA'!I10+'IS Feb USA'!I10 -> 0 | J10: ='IS Feb KSA'!J10+'IS Feb USA'!J10 -> 0 | K10: ='IS Feb KSA'!K10+'IS Feb USA'!K10 -> 0 | L10: =SUM(M10:O10) -> 0 | M10: ='IS Feb KSA'!M10+'IS Feb USA'!M10 -> 0 | N10: ='IS Feb KSA'!N10+'IS Feb USA'!N10 -> 0 | O10: ='IS Feb KSA'!O10+'IS Feb USA'!O10 -> 0 | P10: =SUM(Q10:S10) -> 32825790 | Q10: ='IS Feb KSA'!Q10+'IS Feb USA'!Q10 -> 0 | R10: ='IS Feb KSA'!R10+'IS Feb USA'!R10 -> 16439013 | S10: ='IS Feb KSA'!S10+'IS Feb USA'!S10 -> 16386777 | T10: =U10-V10 -> 19703031 | U10: 1.7752874e+08 | V10: =AC10+AG10+Y10+AK10 -> 1.578257e+08 | W10: =X10-AB10 -> 13138257 | X10: 28367446 | Y10: =SUM(Z10:AB10) -> 54905864 | Z10: ='IS Feb KSA'!V10+'IS Feb USA'!V10 -> 20791023 | AA10: ='IS Feb KSA'!W10+'IS Feb USA'!W10 -> 18885652 | AB10: ='IS Feb KSA'!X10+'IS Feb USA'!X10 -> 15229189 | AC10: =AD10+AE10+AF10 -> 37535436 | AD10: ='IS Feb KSA'!Z10+'IS Feb USA'!Z10 -> 9966234.8 | AE10: ='IS Feb KSA'!AA10+'IS Feb USA'!AA10 -> 7379008.3 | AF10: ='IS Feb KSA'!AB10+'IS Feb USA'!AB10 -> 20190193 | AG10: =SUM(AH10:AJ10) -> 32972335 | AH10: ='IS Feb KSA'!AD10+'IS Feb USA'!AD10 -> 11726376 | AI10: ='IS Feb KSA'!AE10+'IS Feb USA'!AE10 -> 11371331 | AJ10: ='IS Feb KSA'!AF10+'IS Feb USA'!AF10 -> 9874628.2 | AK10: =SUM(AL10:AN10) -> 32412070 | AL10: ='IS Feb KSA'!AH10+'IS Feb USA'!AH10 -> 13667110 | AM10: ='IS Feb KSA'!AI10+'IS Feb USA'!AI10 -> 10659013 | AN10: ='IS Feb KSA'!AJ10+'IS Feb USA'!AJ10 -> 8085946.4 | AP10: 10080211 | AQ10: 76420880
B11: Sales Discount | C11: =H11+L11+D11+P11 -> 14516.1 | E11: ='IS Feb KSA'!E11+'IS Feb USA'!E11 -> 0 | F11: ='IS Feb KSA'!F11+'IS Feb USA'!F11 -> 0 | G11: ='IS Feb KSA'!G11+'IS Feb USA'!G11 -> 0 | I11: ='IS Feb KSA'!I11+'IS Feb USA'!I11 -> 0 | K11: ='IS Feb KSA'!G11+'IS Feb USA'!G11 -> 0 | L11: =SUM(M11:O11) -> 0 | M11: ='IS Feb KSA'!M11+'IS Feb USA'!M11 -> 0 | N11: ='IS Feb KSA'!N11+'IS Feb USA'!N11 -> 0 | O11: ='IS Feb KSA'!O11+'IS Feb USA'!O11 -> 0 | P11: =SUM(Q11:S11) -> 14516.1 | Q11: ='IS Feb KSA'!Q11+'IS Feb USA'!Q11 -> 0 | R11: ='IS Feb KSA'!R11+'IS Feb USA'!R11 -> 14516.1 | S11: ='IS Feb KSA'!S11+'IS Feb USA'!S11 -> 0 | T11: =U11-V11 -> -82363.38 | U11: 0 | V11: =AC11+AG11+Y11+AK11 -> 82363.38 | W11: =X11-AB11 -> 0 | AF11: ='IS Feb KSA'!AB11+'IS Feb USA'!AB11 -> 0 | AG11: =SUM(AH11:AJ11) -> 82363.38 | AH11: ='IS Feb KSA'!AD11+'IS Feb USA'!AD11 -> -7558.83 | AI11: ='IS Feb KSA'!AE11+'IS Feb USA'!AE11 -> 78283.38 | AJ11: ='IS Feb KSA'!AF11+'IS Feb USA'!AF11 -> 11638.83
B12: Cost of Goods Sold | C12: =H12+L12+D12+P12 -> 29328846 | D12: =SUM(E12:G12) -> 0 | E12: ='IS Feb KSA'!E12+'IS Feb USA'!E12 -> 0 | F12: ='IS Feb KSA'!F12+'IS Feb USA'!F12 -> 0 | G12: ='IS Feb KSA'!G12+'IS Feb USA'!G12 -> 0 | H12: =I12+J12+K12 -> 0 | I12: ='IS Feb KSA'!I12+'IS Feb USA'!I12 -> 0 | J12: ='IS Feb KSA'!F12+'IS Feb USA'!F12 -> 0 | K12: ='IS Feb KSA'!G12+'IS Feb USA'!G12 -> 0 | L12: =SUM(M12:O12) -> 0 | M12: ='IS Feb KSA'!M12+'IS Feb USA'!M12 -> 0 | N12: ='IS Feb KSA'!N12+'IS Feb USA'!N12 -> 0 | O12: ='IS Feb KSA'!O12+'IS Feb USA'!O12 -> 0 | P12: =SUM(Q12:S12) -> 29328846 | Q12: ='IS Feb KSA'!Q12+'IS Feb USA'!Q12 -> 0 | R12: ='IS Feb KSA'!R12+'IS Feb USA'!R12 -> 14552433 | S12: ='IS Feb KSA'!S12+'IS Feb USA'!S12 -> 14776413 | T12: =U12-V12 -> 20071850 | U12: 1.6098437e+08 | V12: =AC12+AG12+Y12+AK12 -> 1.4091252e+08 | W12: =X12-AB12 -> 12210182 | X12: 25723810 | Y12: =SUM(Z12:AB12) -> 48616545 | Z12: ='IS Feb KSA'!V12+'IS Feb USA'!V12 -> 18140835 | AA12: ='IS Feb KSA'!W12+'IS Feb USA'!W12 -> 16962082 | AB12: ='IS Feb KSA'!X12+'IS Feb USA'!X12 -> 13513628 | AC12: =AD12+AE12+AF12 -> 33436502 | AD12: ='IS Feb KSA'!Z12+'IS Feb USA'!Z12 -> 8979707.7 | AE12: ='IS Feb KSA'!AA12+'IS Feb USA'!AA12 -> 6625405.5 | AF12: ='IS Feb KSA'!AB12+'IS Feb USA'!AB12 -> 17831388 | AG12: =SUM(AH12:AJ12) -> 29582790 | AH12: ='IS Feb KSA'!AD12+'IS Feb USA'!AD12 -> 10608445 | AI12: ='IS Feb KSA'!AE12+'IS Feb USA'!AE12 -> 10128323 | AJ12: ='IS Feb KSA'!AF12+'IS Feb USA'!AF12 -> 8846021.3 | AK12: =SUM(AL12:AN12) -> 29276685 | AL12: ='IS Feb KSA'!AH12+'IS Feb USA'!AH12 -> 12403281 | AM12: ='IS Feb KSA'!AI12+'IS Feb USA'!AI12 -> 9631833 | AN12: ='IS Feb KSA'!AJ12+'IS Feb USA'!AJ12 -> 7241571.2 | AP12: 9065157.9 | AQ12: 69127802
B13: Purchase Discounts | C13: =H13+L13+D13+P13 -> -88806.57 | D13: =SUM(E13:G13) -> 0 | E13: ='IS Feb KSA'!E13+'IS Feb USA'!E13 -> 0 | F13: ='IS Feb KSA'!F13+'IS Feb USA'!F13 -> 0 | G13: ='IS Feb KSA'!G13+'IS Feb USA'!G13 -> 0 | H13: =I13+J13+K13 -> 0 | I13: ='IS Feb KSA'!I13+'IS Feb USA'!I13 -> 0 | J13: ='IS Feb KSA'!F13+'IS Feb USA'!F13 -> 0 | K13: ='IS Feb KSA'!G13+'IS Feb USA'!G13 -> 0 | L13: =SUM(M13:O13) -> 0 | M13: ='IS Feb KSA'!M13+'IS Feb USA'!M13 -> 0 | N13: ='IS Feb KSA'!N13+'IS Feb USA'!N13 -> 0 | O13: ='IS Feb KSA'!O13+'IS Feb USA'!O13 -> 0 | P13: =SUM(Q13:S13) -> -88806.57 | Q13: ='IS Feb KSA'!Q13+'IS Feb USA'!Q13 -> 0 | R13: ='IS Feb KSA'!R13+'IS Feb USA'!R13 -> -12857.77 | S13: ='IS Feb KSA'!S13+'IS Feb USA'!S13 -> -75948.8 | T13: =U13-V13 -> 222027.19 | U13: 0 | V13: =AC13+AG13+Y13+AK13 -> -222027.19 | W13: =X13-AB13 -> 1550.94 | X13: 0 | Y13: =SUM(Z13:AB13) -> -148153.36 | Z13: ='IS Feb KSA'!V13+'IS Feb USA'!V13 -> -131612.06 | AA13: ='IS Feb KSA'!W13+'IS Feb USA'!W13 -> -14990.36 | AB13: ='IS Feb KSA'!X13+'IS Feb USA'!X13 -> -1550.94 | AC13: =AD13+AE13+AF13 -> 0 | AD13: ='IS Feb KSA'!Z13+'IS Feb USA'!Z13 -> 0 | AE13: ='IS Feb KSA'!AA13+'IS Feb USA'!AA13 -> 0 | AF13: ='IS Feb KSA'!AB13+'IS Feb USA'!AB13 -> 0 | AG13: =SUM(AH13:AJ13) -> -62005.67 | AH13: ='IS Feb KSA'!AD13+'IS Feb USA'!AD13 -> 0 | AI13: ='IS Feb KSA'!AE13+'IS Feb USA'!AE13 -> -62005.67 | AJ13: ='IS Feb KSA'!AF13+'IS Feb USA'!AF13 -> 0 | AK13: =SUM(AL13:AN13) -> -11868.16 | AL13: ='IS Feb KSA'!AH13+'IS Feb USA'!AH13 -> -7728.16 | AM13: ='IS Feb KSA'!AI13+'IS Feb USA'!AI13 -> -4140 | AN13: ='IS Feb KSA'!AJ13+'IS Feb USA'!AJ13 -> 0 | AP13: 0 | AQ13: -93226.45
B14: Gross Profit / (Loss) | C14: =+C10-C11-(C12+C13) -> 3571235 | D14: =+D10-D11-(D12+D13) -> 0 | E14: =+E10-E11-(E12+E13) -> 0 | F14: =+F10-F11-(F12+F13) -> 0 | G14: =+G10-G11-(G12+G13) -> 0 | H14: =+H10-H11-(H12+H13) -> 0 | I14: =+I10-I11-(I12+I13) -> 0 | J14: =+J10-J11-(J12+J13) -> 0 | ... S14: =+S10-S11-(S12+S13) -> 1686313.6 | T14: =U14-V14 -> -508482.84 | U14: =U10-U12+U13 -> 16544364 | V14: =AC14+AG14+Y14+AK14 -> 17052847 | W14: =X14-AB14 -> 926523.83 | X14: =+X10-(X12+X13)-X11 -> 2643635.9 | Y14: =SUM(Z14:AB14) -> 6437472.5 | Z14: ='IS Feb KSA'!V14+'IS Feb USA'!V14 -> 2781799.7 | AA14: ='IS Feb KSA'!W14+'IS Feb USA'!W14 -> 1938560.6 | AB14: ='IS Feb KSA'!X14+'IS Feb USA'!X14 -> 1717112.1 | AC14: =AD14+AE14+AF14 -> 4098934.8 | AD14: ='IS Feb KSA'!Z14+'IS Feb USA'!Z14 -> 986527.13 | AE14: ='IS Feb KSA'!AA14+'IS Feb USA'!AA14 -> 753602.78 | AF14: =+AF10-(AF12+AF13)-AF11 -> 2358804.9 | AG14: =+AG10-(AG12+AG13)-AG11 -> 3369187.1 | AH14: =+AH10-(AH12+AH13)-AH11 -> 1125489.3 | AI14: =+AI10-(AI12+AI13)-AI11 -> 1226729.8 | AJ14: =+AJ10-(AJ12+AJ13)-AJ11 -> 1016968 | AK14: =+AK10-(AK12+AK13) -> 3147252.4 | AL14: =+AL10-(AL12+AL13) -> 1271557.3 | AM14: =+AM10-(AM12+AM13) -> 1031319.9 | AN14: =+AN10-(AN12+AN13) -> 844375.15 | AP14: 1015053.3 | AQ14: 7386304.4
B15: Other Income | C15: =H15+L15+D15+P15 -> 0 | D15: =SUM(E15:G15) -> 0 | E15: ='IS Feb KSA'!E15+'IS Feb USA'!E15 -> 0 | F15: ='IS Feb KSA'!F15+'IS Feb USA'!F15 -> 0 | G15: ='IS Feb KSA'!G15+'IS Feb USA'!G15 -> 0 | H15: =I15+J15+K15 -> 0 | I15: ='IS Feb KSA'!I15+'IS Feb USA'!I15 -> 0 | J15: ='IS Feb KSA'!F15+'IS Feb USA'!F15 -> 0 | K15: ='IS Feb KSA'!G15+'IS Feb USA'!G15 -> 0 | L15: =SUM(M15:O15) -> 0 | M15: ='IS Feb KSA'!M15+'IS Feb USA'!M15 -> 0 | N15: ='IS Feb KSA'!N15+'IS Feb USA'!N15 -> 0 | O15: ='IS Feb KSA'!O15+'IS Feb USA'!O15 -> 0 | P15: =SUM(Q15:S15) -> 0 | Q15: ='IS Feb KSA'!Q15+'IS Feb USA'!Q15 -> 0 | R15: ='IS Feb KSA'!R15+'IS Feb USA'!R15 -> 0 | S15: ='IS Feb KSA'!S15+'IS Feb USA'!S15 -> 0 | T15: =U15-V15 -> -18230.96 | U15: 0 | V15: =AC15+AG15+Y15+AK15 -> 18230.96 | W15: =X15-AB15 -> 0 | Y15: =SUM(Z15:AB15) -> 0 | Z15: ='IS Feb KSA'!V15+'IS Feb USA'!V15 -> 0 | AA15: ='IS Feb KSA'!W15+'IS Feb USA'!W15 -> 0 | AB15: ='IS Feb KSA'!X15+'IS Feb USA'!X15 -> 0 | AC15: =AD15+AE15+AF15 -> 124.13 | AD15: ='IS Feb KSA'!Z15+'IS Feb USA'!Z15 -> 37.5 | AE15: ='IS Feb KSA'!AA15+'IS Feb USA'!AA15 -> 0 | AF15: ='IS Feb KSA'!AB15+'IS Feb USA'!AB15 -> 86.63 | AG15: =SUM(AH15:AJ15) -> 98.26 | AH15: ='IS Feb KSA'!AD15+'IS Feb USA'!AD15 -> 49.13 | AI15: ='IS Feb KSA'!AE15+'IS Feb USA'!AE15 -> 49.13 | AJ15: ='IS Feb KSA'!AF15+'IS Feb USA'!AF15 -> 0 | AK15: =SUM(AL15:AN15) -> 18008.57 | AL15: ='IS Feb KSA'!AH15+'IS Feb USA'!AH15 -> 12000 | AM15: ='IS Feb KSA'!AI15+'IS Feb USA'!AI15 -> 6008.57 | AN15: ='IS Feb KSA'!AJ15+'IS Feb USA'!AJ15 -> 0
B16: Consultation Income | C16: =H16+L16+D16+P16 -> 0 | D16: =SUM(E16:G16) -> 0 | E16: ='IS Feb KSA'!E16+'IS Feb USA'!E16 -> 0 | F16: ='IS Feb KSA'!F16+'IS Feb USA'!F16 -> 0 | G16: ='IS Feb KSA'!G16+'IS Feb USA'!G16 -> 0 | H16: =I16+J16+K16 -> 0 | I16: ='IS Feb KSA'!I16+'IS Feb USA'!I16 -> 0 | J16: ='IS Feb KSA'!F16+'IS Feb USA'!F16 -> 0 | K16: ='IS Feb KSA'!G16+'IS Feb USA'!G16 -> 0 | L16: =SUM(M16:O16) -> 0 | M16: ='IS Feb KSA'!M16+'IS Feb USA'!M16 -> 0 | N16: ='IS Feb KSA'!N16+'IS Feb USA'!N16 -> 0 | O16: ='IS Feb KSA'!O16+'IS Feb USA'!O16 -> 0 | P16: =SUM(Q16:S16) -> 0 | Q16: ='IS Feb KSA'!Q16+'IS Feb USA'!Q16 -> 0 | R16: ='IS Feb KSA'!R16+'IS Feb USA'!R16 -> 0 | S16: ='IS Feb KSA'!S16+'IS Feb USA'!S16 -> 0 | T16: =U16-V16 -> 482608.7 | U16: 547826.09 | V16: =AC16+AG16+Y16+AK16 -> 65217.39 | W16: =X16-AB16 -> 65217.391 | X16: 65217.391 | Y16: =SUM(Z16:AB16) -> 0 | Z16: ='IS Feb KSA'!V16+'IS Feb USA'!V16 -> 0 | AA16: ='IS Feb KSA'!W16+'IS Feb USA'!W16 -> 0 | AB16: ='IS Feb KSA'!X16+'IS Feb USA'!X16 -> 0 | AC16: =AD16+AE16+AF16 -> 0 | AD16: ='IS Feb KSA'!Z16+'IS Feb USA'!Z16 -> 0 | AE16: ='IS Feb KSA'!AA16+'IS Feb USA'!AA16 -> 0 | AF16: ='IS Feb KSA'!AB16+'IS Feb USA'!AB16 -> 0 | AG16: =SUM(AH16:AJ16) -> 0 | AH16: ='IS Feb KSA'!AD16+'IS Feb USA'!AD16 -> 0 | AI16: ='IS Feb KSA'!AE16+'IS Feb USA'!AE16 -> 0 | AJ16: ='IS Feb KSA'!AF16+'IS Feb USA'!AF16 -> 0 | AK16: =SUM(AL16:AN16) -> 65217.39 | AL16: ='IS Feb KSA'!AH16+'IS Feb USA'!AH16 -> 0 | AM16: ='IS Feb KSA'!AI16+'IS Feb USA'!AI16 -> 0 | AN16: ='IS Feb KSA'!AJ16+'IS Feb USA'!AJ16 -> 65217.39 | AP16: 26086.96 | AQ16: 293478.27
B17: Gross Income | C17: =+C16+C14+C15 -> 3571235 | D17: =+D16+D14+D15 -> 0 | E17: =+E16+E14+E15 -> 0 | F17: =+F16+F14+F15 -> 0 | G17: =+G16+G14+G15 -> 0 | H17: =+H16+H14+H15 -> 0 | I17: =+I16+I14+I15 -> 0 | J17: =+J16+J14+J15 -> 0 | ... S17: =+S16+S14+S15 -> 1686313.6 | T17: =U17-V17 -> -44105.105 | U17: =+U16+U14+U15 -> 17092190 | V17: =+V16+V14+V15 -> 17136295 | W17: =X17-AB17 -> 991741.22 | X17: =+X16+X14+X15 -> 2708853.3 | Y17: =+Y16+Y14+Y15 -> 6437472.5 | Z17: =+Z16+Z14+Z15 -> 2781799.7 | AA17: =+AA16+AA14+AA15 -> 1938560.6 | AB17: =+AB16+AB14+AB15 -> 1717112.1 | AC17: =+AC16+AC14+AC15 -> 4099058.9 | AD17: =+AD16+AD14+AD15 -> 986564.63 | AE17: =+AE16+AE14+AE15 -> 753602.78 | ... AN17: =+AN16+AN14+AN15 -> 909592.54 | AP17: =+AP16+AP14 -> 1041140.2 | AQ17: =+AQ16+AQ14 -> 7679782.6
T18: =U18-V18 -> 0 | W18: =X18-AB18 -> 0
B19: General and Administrative Expenses | C19: =SUM(C20:C38) -> 441641.97 | D19: =SUM(D20:D38) -> 0 | E19: =SUM(E20:E38) -> 0 | F19: =SUM(F20:F38) -> 0 | G19: =SUM(G20:G38) -> 0 | H19: =SUM(H20:H38) -> 0 | I19: =SUM(I20:I38) -> 0 | J19: =SUM(J20:J38) -> 0 | ... S19: =SUM(S20:S38) -> 293220.93 | T19: =U19-V19 -> -2852813.3 | U19: =SUM(U20:U38) -> 1044980.8 | V19: =SUM(V20:V38) -> 3897794.1 | W19: =X19-AB19 -> -546185.93 | X19: =SUM(X20:X38) -> 150156.31 | Y19: =SUM(Y20:Y38) -> 2475478.3 | Z19: =SUM(Z20:Z38) -> 778680.62 | AA19: =SUM(AA20:AA38) -> 1000455.5 | AB19: =SUM(AB20:AB38) -> 696342.24 | AC19: =SUM(AC20:AC38) -> 553018.77 | AD19: =SUM(AD20:AD38) -> 212030.82 | AE19: =SUM(AE20:AE38) -> 148023.47 | ... AN19: =SUM(AN20:AN38) -> 125881.16 | AP19: =SUM(AP20:AP38) -> 326464.28 | AQ19: =SUM(AQ20:AQ38) -> 1182570.3
B20: Bad Debt | C20: =H20+L20+D20+P20 -> 114105.01 | D20: =SUM(E20:G20) -> 0 | E20: ='IS Feb KSA'!E20+'IS Feb USA'!E20 -> 0 | F20: ='IS Feb KSA'!F20+'IS Feb USA'!F20 -> 0 | G20: ='IS Feb KSA'!G20+'IS Feb USA'!G20 -> 0 | H20: =I20+J20+K20 -> 0 | I20: ='IS Feb KSA'!I20+'IS Feb USA'!I20 -> 0 | J20: ='IS Feb KSA'!F20+'IS Feb USA'!F20 -> 0 | K20: ='IS Feb KSA'!G20+'IS Feb USA'!G20 -> 0 | L20: =SUM(M20:O20) -> 0 | M20: ='IS Feb KSA'!M20+'IS Feb USA'!M20 -> 0 | N20: ='IS Feb KSA'!N20+'IS Feb USA'!N20 -> 0 | O20: ='IS Feb KSA'!O20+'IS Feb USA'!O20 -> 0 | P20: =SUM(Q20:S20) -> 114105.01 | Q20: ='IS Feb KSA'!Q20+'IS Feb USA'!Q20 -> 0 | R20: ='IS Feb KSA'!R20+'IS Feb USA'!R20 -> 0 | S20: ='IS Feb KSA'!S20+'IS Feb USA'!S20 -> 114105.01 | T20: =U20-V20 -> -2044438.5 | U20: 0 | V20: =AC20+AG20+Y20+AK20 -> 2044438.5 | W20: =X20-AB20 -> -437283.39 | Y20: =SUM(Z20:AB20) -> 1820446.2 | Z20: ='IS Feb KSA'!V20+'IS Feb USA'!V20 -> 526062.9 | AA20: ='IS Feb KSA'!W20+'IS Feb USA'!W20 -> 857099.96 | AB20: ='IS Feb KSA'!X20+'IS Feb USA'!X20 -> 437283.39 | AC20: =AD20+AE20+AF20 -> 75000 | AD20: ='IS Feb KSA'!Z20+'IS Feb USA'!Z20 -> 25000 | AE20: ='IS Feb KSA'!AA20+'IS Feb USA'!AA20 -> 25000 | AF20: ='IS Feb KSA'!AB20+'IS Feb USA'!AB20 -> 25000 | AG20: =SUM(AH20:AJ20) -> 73991.16 | AH20: ='IS Feb KSA'!AD20+'IS Feb USA'!AD20 -> 25000 | AI20: ='IS Feb KSA'!AE20+'IS Feb USA'!AE20 -> 23991.16 | AJ20: ='IS Feb KSA'!AF20+'IS Feb USA'!AF20 -> 25000 | AK20: =SUM(AL20:AN20) -> 75001.1 | AL20: ='IS Feb KSA'!AH20+'IS Feb USA'!AH20 -> 25000.8 | AM20: ='IS Feb KSA'!AI20+'IS Feb USA'!AI20 -> 25000.3 | AN20: ='IS Feb KSA'!AJ20+'IS Feb USA'!AJ20 -> 25000 | AP20: 203009.5 | AQ20: 203016.64
B21: Bank Fees and Charges | C21: =H21+L21+D21+P21 -> 4977.77 | D21: =SUM(E21:G21) -> 0 | E21: ='IS Feb KSA'!E21+'IS Feb USA'!E21 -> 0 | F21: ='IS Feb KSA'!F21+'IS Feb USA'!F21 -> 0 | G21: ='IS Feb KSA'!G21+'IS Feb USA'!G21 -> 0 | H21: =I21+J21+K21 -> 0 | I21: ='IS Feb KSA'!I21+'IS Feb USA'!I21 -> 0 | J21: ='IS Feb KSA'!F21+'IS Feb USA'!F21 -> 0 | K21: ='IS Feb KSA'!G21+'IS Feb USA'!G21 -> 0 | L21: =SUM(M21:O21) -> 0 | M21: ='IS Feb KSA'!M21+'IS Feb USA'!M21 -> 0 | N21: ='IS Feb KSA'!N21+'IS Feb USA'!N21 -> 0 | O21: ='IS Feb KSA'!O21+'IS Feb USA'!O21 -> 0 | P21: =SUM(Q21:S21) -> 4977.77 | Q21: ='IS Feb KSA'!Q21+'IS Feb USA'!Q21 -> 0 | R21: ='IS Feb KSA'!R21+'IS Feb USA'!R21 -> 1793.1 | S21: ='IS Feb KSA'!S21+'IS Feb USA'!S21 -> 3184.67 | T21: =U21-V21 -> 7148.6792 | U21: 41123.759 | V21: =AC21+AG21+Y21+AK21 -> 33975.08 | W21: =X21-AB21 -> 3202.9532 | X21: 6517.4932 | Y21: =SUM(Z21:AB21) -> 8840.93 | Z21: ='IS Feb KSA'!V21+'IS Feb USA'!V21 -> 3684.69 | AA21: ='IS Feb KSA'!W21+'IS Feb USA'!W21 -> 1841.7 | AB21: ='IS Feb KSA'!X21+'IS Feb USA'!X21 -> 3314.54 | AC21: =AD21+AE21+AF21 -> 7403.73 | AD21: ='IS Feb KSA'!Z21+'IS Feb USA'!Z21 -> 1946.76 | AE21: ='IS Feb KSA'!AA21+'IS Feb USA'!AA21 -> 2143.75 | AF21: ='IS Feb KSA'!AB21+'IS Feb USA'!AB21 -> 3313.22 | AG21: =SUM(AH21:AJ21) -> 9150.7 | AH21: ='IS Feb KSA'!AD21+'IS Feb USA'!AD21 -> 2292.29 | AI21: ='IS Feb KSA'!AE21+'IS Feb USA'!AE21 -> 2672.61 | AJ21: ='IS Feb KSA'!AF21+'IS Feb USA'!AF21 -> 4185.8 | AK21: =SUM(AL21:AN21) -> 8579.72 | AL21: ='IS Feb KSA'!AH21+'IS Feb USA'!AH21 -> 3473.91 | AM21: ='IS Feb KSA'!AI21+'IS Feb USA'!AI21 -> 2762.55 | AN21: ='IS Feb KSA'!AJ21+'IS Feb USA'!AJ21 -> 2343.26 | AP21: 2381.41 | AQ21: 24338.49
B22: Office Supplies | C22: =H22+L22+D22+P22 -> 11778.03 | D22: =SUM(E22:G22) -> 0 | E22: ='IS Feb KSA'!E22+'IS Feb USA'!E22 -> 0 | F22: ='IS Feb KSA'!F22+'IS Feb USA'!F22 -> 0 | G22: ='IS Feb KSA'!G22+'IS Feb USA'!G22 -> 0 | H22: =I22+J22+K22 -> 0 | I22: ='IS Feb KSA'!I22+'IS Feb USA'!I22 -> 0 | J22: ='IS Feb KSA'!F22+'IS Feb USA'!F22 -> 0 | K22: ='IS Feb KSA'!G22+'IS Feb USA'!G22 -> 0 | L22: =SUM(M22:O22) -> 0 | M22: ='IS Feb KSA'!M22+'IS Feb USA'!M22 -> 0 | N22: ='IS Feb KSA'!N22+'IS Feb USA'!N22 -> 0 | O22: ='IS Feb KSA'!O22+'IS Feb USA'!O22 -> 0 | P22: =SUM(Q22:S22) -> 11778.03 | Q22: ='IS Feb KSA'!Q22+'IS Feb USA'!Q22 -> 0 | R22: ='IS Feb KSA'!R22+'IS Feb USA'!R22 -> 5544.51 | S22: ='IS Feb KSA'!S22+'IS Feb USA'!S22 -> 6233.52 | T22: =U22-V22 -> -27107.026 | U22: 49394.204 | V22: =AC22+AG22+Y22+AK22 -> 76501.23 | W22: =X22-AB22 -> 245.05346 | X22: 7828.2335 | Y22: =SUM(Z22:AB22) -> 18831.59 | Z22: ='IS Feb KSA'!V22+'IS Feb USA'!V22 -> 4745.27 | AA22: ='IS Feb KSA'!W22+'IS Feb USA'!W22 -> 6503.14 | AB22: ='IS Feb KSA'!X22+'IS Feb USA'!X22 -> 7583.18 | AC22: =AD22+AE22+AF22 -> 26652.27 | AD22: ='IS Feb KSA'!Z22+'IS Feb USA'!Z22 -> 9026.58 | AE22: ='IS Feb KSA'!AA22+'IS Feb USA'!AA22 -> 10858.29 | AF22: ='IS Feb KSA'!AB22+'IS Feb USA'!AB22 -> 6767.4 | AG22: =SUM(AH22:AJ22) -> 17661.99 | AH22: ='IS Feb KSA'!AD22+'IS Feb USA'!AD22 -> 5457.01 | AI22: ='IS Feb KSA'!AE22+'IS Feb USA'!AE22 -> 9625.38 | AJ22: ='IS Feb KSA'!AF22+'IS Feb USA'!AF22 -> 2579.6 | AK22: =SUM(AL22:AN22) -> 13355.38 | AL22: ='IS Feb KSA'!AH22+'IS Feb USA'!AH22 -> 2845.92 | AM22: ='IS Feb KSA'!AI22+'IS Feb USA'!AI22 -> 6669.62 | AN22: ='IS Feb KSA'!AJ22+'IS Feb USA'!AJ22 -> 3839.84 | AP22: 819.32 | AQ22: 54128.03
B23: Office Utilities - Electricity/Water/Janitorial | C23: =H23+L23+D23+P23 -> 0 | D23: =SUM(E23:G23) -> 0 | E23: ='IS Feb KSA'!E23+'IS Feb USA'!E23 -> 0 | F23: ='IS Feb KSA'!F23+'IS Feb USA'!F23 -> 0 | G23: ='IS Feb KSA'!G23+'IS Feb USA'!G23 -> 0 | H23: =I23+J23+K23 -> 0 | I23: ='IS Feb KSA'!I23+'IS Feb USA'!I23 -> 0 | J23: ='IS Feb KSA'!F23+'IS Feb USA'!F23 -> 0 | K23: ='IS Feb KSA'!G23+'IS Feb USA'!G23 -> 0 | L23: =SUM(M23:O23) -> 0 | M23: ='IS Feb KSA'!M23+'IS Feb USA'!M23 -> 0 | N23: ='IS Feb KSA'!N23+'IS Feb USA'!N23 -> 0 | O23: ='IS Feb KSA'!O23+'IS Feb USA'!O23 -> 0 | P23: =SUM(Q23:S23) -> 0 | Q23: ='IS Feb KSA'!Q23+'IS Feb USA'!Q23 -> 0 | R23: ='IS Feb KSA'!R23+'IS Feb USA'!R23 -> 0 | S23: ='IS Feb KSA'!S23+'IS Feb USA'!S23 -> 0 | T23: =U23-V23 -> 23874.649 | U23: 27415.839 | V23: =AC23+AG23+Y23+AK23 -> 3541.19 | W23: =X23-AB23 -> 4344.9954 | X23: 4344.9954 | Y23: =SUM(Z23:AB23) -> 0 | Z23: ='IS Feb KSA'!V23+'IS Feb USA'!V23 -> 0 | AA23: ='IS Feb KSA'!W23+'IS Feb USA'!W23 -> 0 | AB23: ='IS Feb KSA'!X23+'IS Feb USA'!X23 -> 0 | AC23: =AD23+AE23+AF23 -> 1649.27 | AD23: ='IS Feb KSA'!Z23+'IS Feb USA'!Z23 -> 165.22 | AE23: ='IS Feb KSA'!AA23+'IS Feb USA'!AA23 -> 949.15 | AF23: ='IS Feb KSA'!AB23+'IS Feb USA'!AB23 -> 534.9 | AG23: =SUM(AH23:AJ23) -> 1459.95 | AH23: ='IS Feb KSA'!AD23+'IS Feb USA'!AD23 -> 985.5 | AI23: ='IS Feb KSA'!AE23+'IS Feb USA'!AE23 -> 474.45 | AJ23: ='IS Feb KSA'!AF23+'IS Feb USA'!AF23 -> 0 | AK23: =SUM(AL23:AN23) -> 431.97 | AL23: ='IS Feb KSA'!AH23+'IS Feb USA'!AH23 -> 0 | AM23: ='IS Feb KSA'!AI23+'IS Feb USA'!AI23 -> 99.3 | AN23: ='IS Feb KSA'!AJ23+'IS Feb USA'!AJ23 -> 332.67 | AP23: 4705.55 | AQ23: 24609.21
B24: Office Expenses | C24: =H24+L24+D24+P24 -> 24907.84 | D24: =SUM(E24:G24) -> 0 | E24: ='IS Feb KSA'!E24+'IS Feb USA'!E24 -> 0 | F24: ='IS Feb KSA'!F24+'IS Feb USA'!F24 -> 0 | G24: ='IS Feb KSA'!G24+'IS Feb USA'!G24 -> 0 | H24: =I24+J24+K24 -> 0 | I24: ='IS Feb KSA'!I24+'IS Feb USA'!I24 -> 0 | J24: ='IS Feb KSA'!F24+'IS Feb USA'!F24 -> 0 | K24: ='IS Feb KSA'!G24+'IS Feb USA'!G24 -> 0 | L24: =SUM(M24:O24) -> 0 | M24: ='IS Feb KSA'!M24+'IS Feb USA'!M24 -> 0 | N24: ='IS Feb KSA'!N24+'IS Feb USA'!N24 -> 0 | O24: ='IS Feb KSA'!O24+'IS Feb USA'!O24 -> 0 | P24: =SUM(Q24:S24) -> 24907.84 | Q24: ='IS Feb KSA'!Q24+'IS Feb USA'!Q24 -> 0 | R24: ='IS Feb KSA'!R24+'IS Feb USA'!R24 -> 7342.16 | S24: ='IS Feb KSA'!S24+'IS Feb USA'!S24 -> 17565.68 | T24: =U24-V24 -> -33951.01 | U24: 13707.92 | V24: =AC24+AG24+Y24+AK24 -> 47658.93 | W24: =X24-AB24 -> -7890.2023 | X24: 2172.4977 | Y24: =SUM(Z24:AB24) -> 23520.55 | Z24: ='IS Feb KSA'!V24+'IS Feb USA'!V24 -> 3827.91 | AA24: ='IS Feb KSA'!W24+'IS Feb USA'!W24 -> 9629.94 | AB24: ='IS Feb KSA'!X24+'IS Feb USA'!X24 -> 10062.7 | AC24: =AD24+AE24+AF24 -> 12223.31 | AD24: ='IS Feb KSA'!Z24+'IS Feb USA'!Z24 -> 641.74 | AE24: ='IS Feb KSA'!AA24+'IS Feb USA'!AA24 -> 2711.91 | AF24: ='IS Feb KSA'!AB24+'IS Feb USA'!AB24 -> 8869.66 | AG24: =SUM(AH24:AJ24) -> 11781.16 | AH24: ='IS Feb KSA'!AD24+'IS Feb USA'!AD24 -> 3687.1 | AI24: ='IS Feb KSA'!AE24+'IS Feb USA'!AE24 -> 3555.84 | AJ24: ='IS Feb KSA'!AF24+'IS Feb USA'!AF24 -> 4538.22 | AK24: =SUM(AL24:AN24) -> 133.91 | AL24: ='IS Feb KSA'!AH24+'IS Feb USA'!AH24 -> 0 | AM24: ='IS Feb KSA'!AI24+'IS Feb USA'!AI24 -> 133.91 | AN24: ='IS Feb KSA'!AJ24+'IS Feb USA'!AJ24 -> 0 | AP24: 0 | AQ24: 3444.41
B25: Office Repair & Maintenance Expense | C25: =H25+L25+D25+P25 -> 2985 | D25: =SUM(E25:G25) -> 0 | E25: ='IS Feb KSA'!E25+'IS Feb USA'!E25 -> 0 | F25: ='IS Feb KSA'!F25+'IS Feb USA'!F25 -> 0 | G25: ='IS Feb KSA'!G25+'IS Feb USA'!G25 -> 0 | H25: =I25+J25+K25 -> 0 | I25: ='IS Feb KSA'!I25+'IS Feb USA'!I25 -> 0 | J25: ='IS Feb KSA'!F25+'IS Feb USA'!F25 -> 0 | K25: ='IS Feb KSA'!G25+'IS Feb USA'!G25 -> 0 | L25: =SUM(M25:O25) -> 0 | M25: ='IS Feb KSA'!M25+'IS Feb USA'!M25 -> 0 | N25: ='IS Feb KSA'!N25+'IS Feb USA'!N25 -> 0 | O25: ='IS Feb KSA'!O25+'IS Feb USA'!O25 -> 0 | P25: =SUM(Q25:S25) -> 2985 | Q25: ='IS Feb KSA'!Q25+'IS Feb USA'!Q25 -> 0 | R25: ='IS Feb KSA'!R25+'IS Feb USA'!R25 -> 1560 | S25: ='IS Feb KSA'!S25+'IS Feb USA'!S25 -> 1425 | T25: =U25-V25 -> -16428.24 | U25: 0 | V25: =AC25+AG25+Y25+AK25 -> 16428.24 | W25: =X25-AB25 -> -3806.67 | Y25: =SUM(Z25:AB25) -> 8126.67 | Z25: ='IS Feb KSA'!V25+'IS Feb USA'!V25 -> 3560 | AA25: ='IS Feb KSA'!W25+'IS Feb USA'!W25 -> 760 | AB25: ='IS Feb KSA'!X25+'IS Feb USA'!X25 -> 3806.67 | AC25: =AD25+AE25+AF25 -> 8301.57 | AD25: ='IS Feb KSA'!Z25+'IS Feb USA'!Z25 -> 4237.61 | AE25: ='IS Feb KSA'!AA25+'IS Feb USA'!AA25 -> 4063.96 | AF25: ='IS Feb KSA'!AB25+'IS Feb USA'!AB25 -> 0 | AG25: =SUM(AH25:AJ25) -> 0
B26: Travel Expense | C26: =H26+L26+D26+P26 -> 6444.86 | D26: =SUM(E26:G26) -> 0 | E26: ='IS Feb KSA'!E26+'IS Feb USA'!E26 -> 0 | F26: ='IS Feb KSA'!F26+'IS Feb USA'!F26 -> 0 | G26: ='IS Feb KSA'!G26+'IS Feb USA'!G26 -> 0 | H26: =I26+J26+K26 -> 0 | I26: ='IS Feb KSA'!I26+'IS Feb USA'!I26 -> 0 | J26: ='IS Feb KSA'!F26+'IS Feb USA'!F26 -> 0 | K26: ='IS Feb KSA'!G26+'IS Feb USA'!G26 -> 0 | L26: =SUM(M26:O26) -> 0 | M26: ='IS Feb KSA'!M26+'IS Feb USA'!M26 -> 0 | N26: ='IS Feb KSA'!N26+'IS Feb USA'!N26 -> 0 | O26: ='IS Feb KSA'!O26+'IS Feb USA'!O26 -> 0 | P26: =SUM(Q26:S26) -> 6444.86 | Q26: ='IS Feb KSA'!Q26+'IS Feb USA'!Q26 -> 0 | R26: ='IS Feb KSA'!R26+'IS Feb USA'!R26 -> 1695.53 | S26: ='IS Feb KSA'!S26+'IS Feb USA'!S26 -> 4749.33 | T26: =U26-V26 -> 19161.371 | U26: 49500.821 | V26: =AC26+AG26+Y26+AK26 -> 30339.45 | W26: =X26-AB26 -> 4517.5707 | X26: 7845.1307 | Y26: =SUM(Z26:AB26) -> 14720.21 | Z26: ='IS Feb KSA'!V26+'IS Feb USA'!V26 -> 8415.66 | AA26: ='IS Feb KSA'!W26+'IS Feb USA'!W26 -> 2976.99 | AB26: ='IS Feb KSA'!X26+'IS Feb USA'!X26 -> 3327.56 | AC26: =AD26+AE26+AF26 -> 3873.02 | AD26: ='IS Feb KSA'!Z26+'IS Feb USA'!Z26 -> 990.8 | AE26: ='IS Feb KSA'!AA26+'IS Feb USA'!AA26 -> 2836.99 | AF26: ='IS Feb KSA'!AB26+'IS Feb USA'!AB26 -> 45.23 | AG26: =SUM(AH26:AJ26) -> 3180.56 | AH26: ='IS Feb KSA'!AD26+'IS Feb USA'!AD26 -> 343.75 | AI26: ='IS Feb KSA'!AE26+'IS Feb USA'!AE26 -> 457.09 | AJ26: ='IS Feb KSA'!AF26+'IS Feb USA'!AF26 -> 2379.72 | AK26: =SUM(AL26:AN26) -> 8565.66 | AL26: ='IS Feb KSA'!AH26+'IS Feb USA'!AH26 -> 5067 | AM26: ='IS Feb KSA'!AI26+'IS Feb USA'!AI26 -> 3498.66 | AN26: ='IS Feb KSA'!AJ26+'IS Feb USA'!AJ26 -> 0 | AP26: 3750 | AQ26: 38163.24
B27: Printing and Stationery | C27: =H27+L27+D27+P27 -> 702.7 | D27: =SUM(E27:G27) -> 0 | E27: ='IS Feb KSA'!E27+'IS Feb USA'!E27 -> 0 | F27: ='IS Feb KSA'!F27+'IS Feb USA'!F27 -> 0 | G27: ='IS Feb KSA'!G27+'IS Feb USA'!G27 -> 0 | H27: =I27+J27+K27 -> 0 | I27: ='IS Feb KSA'!I27+'IS Feb USA'!I27 -> 0 | J27: ='IS Feb KSA'!F27+'IS Feb USA'!F27 -> 0 | K27: ='IS Feb KSA'!G27+'IS Feb USA'!G27 -> 0 | L27: =SUM(M27:O27) -> 0 | M27: ='IS Feb KSA'!M27+'IS Feb USA'!M27 -> 0 | N27: ='IS Feb KSA'!N27+'IS Feb USA'!N27 -> 0 | O27: ='IS Feb KSA'!O27+'IS Feb USA'!O27 -> 0 | P27: =SUM(Q27:S27) -> 702.7 | Q27: ='IS Feb KSA'!Q27+'IS Feb USA'!Q27 -> 0 | R27: ='IS Feb KSA'!R27+'IS Feb USA'!R27 -> 359.54 | S27: ='IS Feb KSA'!S27+'IS Feb USA'!S27 -> 343.16 | T27: =U27-V27 -> 721.53315 | U27: 9138.6132 | V27: =AC27+AG27+Y27+AK27 -> 8417.08 | W27: =X27-AB27 -> 68.331815 | X27: 1448.3318 | Y27: =SUM(Z27:AB27) -> 2051 | Z27: ='IS Feb KSA'!V27+'IS Feb USA'!V27 -> 0 | AA27: ='IS Feb KSA'!W27+'IS Feb USA'!W27 -> 671 | AB27: ='IS Feb KSA'!X27+'IS Feb USA'!X27 -> 1380 | AC27: =AD27+AE27+AF27 -> 4360.61 | AD27: ='IS Feb KSA'!Z27+'IS Feb USA'!Z27 -> 46 | AE27: ='IS Feb KSA'!AA27+'IS Feb USA'!AA27 -> 3717.22 | AF27: ='IS Feb KSA'!AB27+'IS Feb USA'!AB27 -> 597.39 | AG27: =SUM(AH27:AJ27) -> 1671.99 | AH27: ='IS Feb KSA'!AD27+'IS Feb USA'!AD27 -> 1219.99 | AI27: ='IS Feb KSA'!AE27+'IS Feb USA'!AE27 -> 452 | AJ27: ='IS Feb KSA'!AF27+'IS Feb USA'!AF27 -> 0 | AK27: =SUM(AL27:AN27) -> 333.48 | AL27: ='IS Feb KSA'!AH27+'IS Feb USA'!AH27 -> 0 | AM27: ='IS Feb KSA'!AI27+'IS Feb USA'!AI27 -> 0 | AN27: ='IS Feb KSA'!AJ27+'IS Feb USA'!AJ27 -> 333.48 | AP27: 241 | AQ27: 4591.36
B28: Rent Expense (G&A) | C28: =H28+L28+D28+P28 -> 33396.49 | D28: =SUM(E28:G28) -> 0 | E28: ='IS Feb KSA'!E28+'IS Feb USA'!E28 -> 0 | F28: ='IS Feb KSA'!F28+'IS Feb USA'!F28 -> 0 | G28: ='IS Feb KSA'!G28+'IS Feb USA'!G28 -> 0 | H28: =I28+J28+K28 -> 0 | I28: ='IS Feb KSA'!I28+'IS Feb USA'!I28 -> 0 | J28: ='IS Feb KSA'!F28+'IS Feb USA'!F28 -> 0 | K28: ='IS Feb KSA'!G28+'IS Feb USA'!G28 -> 0 | L28: =SUM(M28:O28) -> 0 | M28: ='IS Feb KSA'!M28+'IS Feb USA'!M28 -> 0 | N28: ='IS Feb KSA'!N28+'IS Feb USA'!N28 -> 0 | O28: ='IS Feb KSA'!O28+'IS Feb USA'!O28 -> 0 | P28: =SUM(Q28:S28) -> 33396.49 | Q28: ='IS Feb KSA'!Q28+'IS Feb USA'!Q28 -> 0 | R28: ='IS Feb KSA'!R28+'IS Feb USA'!R28 -> 10311.48 | S28: ='IS Feb KSA'!S28+'IS Feb USA'!S28 -> 23085.01 | T28: =U28-V28 -> -77405.913 | U28: 226166.67 | V28: =AC28+AG28+Y28+AK28 -> 303572.58 | W28: =X28-AB28 -> -1480.8333 | X28: 22616.667 | Y28: =SUM(Z28:AB28) -> 71280.02 | Z28: ='IS Feb KSA'!V28+'IS Feb USA'!V28 -> 23085.01 | AA28: ='IS Feb KSA'!W28+'IS Feb USA'!W28 -> 24097.51 | AB28: ='IS Feb KSA'!X28+'IS Feb USA'!X28 -> 24097.5 | AC28: =AD28+AE28+AF28 -> 74907.58 | AD28: ='IS Feb KSA'!Z28+'IS Feb USA'!Z28 -> 24097.5 | AE28: ='IS Feb KSA'!AA28+'IS Feb USA'!AA28 -> 24579.25 | AF28: ='IS Feb KSA'!AB28+'IS Feb USA'!AB28 -> 26230.83 | AG28: =SUM(AH28:AJ28) -> 78692.49 | AH28: ='IS Feb KSA'!AD28+'IS Feb USA'!AD28 -> 26230.83 | AI28: ='IS Feb KSA'!AE28+'IS Feb USA'!AE28 -> 26230.83 | AJ28: ='IS Feb KSA'!AF28+'IS Feb USA'!AF28 -> 26230.83 | AK28: =SUM(AL28:AN28) -> 78692.49 | AL28: ='IS Feb KSA'!AH28+'IS Feb USA'!AH28 -> 26230.83 | AM28: ='IS Feb KSA'!AI28+'IS Feb USA'!AI28 -> 26230.83 | AN28: ='IS Feb KSA'!AJ28+'IS Feb USA'!AJ28 -> 26230.83 | AP28: 32096.09 | AQ28: 127377.94
B29: Meals and Entertainment | C29: =H29+L29+D29+P29 -> 9034.79 | D29: =SUM(E29:G29) -> 0 | E29: ='IS Feb KSA'!E29+'IS Feb USA'!E29 -> 0 | F29: ='IS Feb KSA'!F29+'IS Feb USA'!F29 -> 0 | G29: ='IS Feb KSA'!G29+'IS Feb USA'!G29 -> 0 | H29: =I29+J29+K29 -> 0 | I29: ='IS Feb KSA'!I29+'IS Feb USA'!I29 -> 0 | J29: ='IS Feb KSA'!F29+'IS Feb USA'!F29 -> 0 | K29: ='IS Feb KSA'!G29+'IS Feb USA'!G29 -> 0 | L29: =SUM(M29:O29) -> 0 | M29: ='IS Feb KSA'!M29+'IS Feb USA'!M29 -> 0 | N29: ='IS Feb KSA'!N29+'IS Feb USA'!N29 -> 0 | O29: ='IS Feb KSA'!O29+'IS Feb USA'!O29 -> 0 | P29: =SUM(Q29:S29) -> 9034.79 | Q29: ='IS Feb KSA'!Q29+'IS Feb USA'!Q29 -> 0 | R29: ='IS Feb KSA'!R29+'IS Feb USA'!R29 -> 5141.97 | S29: ='IS Feb KSA'!S29+'IS Feb USA'!S29 -> 3892.82 | T29: =U29-V29 -> -42545.784 | U29: 48693.066 | V29: =AC29+AG29+Y29+AK29 -> 91238.85 | W29: =X29-AB29 -> 1171.1191 | X29: 7241.6591 | Y29: =SUM(Z29:AB29) -> 17450.39 | Z29: ='IS Feb KSA'!V29+'IS Feb USA'!V29 -> 6851.97 | AA29: ='IS Feb KSA'!W29+'IS Feb USA'!W29 -> 4527.88 | AB29: ='IS Feb KSA'!X29+'IS Feb USA'!X29 -> 6070.54 | AC29: =AD29+AE29+AF29 -> 22097.15 | AD29: ='IS Feb KSA'!Z29+'IS Feb USA'!Z29 -> 10439.41 | AE29: ='IS Feb KSA'!AA29+'IS Feb USA'!AA29 -> 6622.29 | AF29: ='IS Feb KSA'!AB29+'IS Feb USA'!AB29 -> 5035.45 | AG29: =SUM(AH29:AJ29) -> 20454 | AH29: ='IS Feb KSA'!AD29+'IS Feb USA'!AD29 -> 5737.6 | AI29: ='IS Feb KSA'!AE29+'IS Feb USA'!AE29 -> 7458.74 | AJ29: ='IS Feb KSA'!AF29+'IS Feb USA'!AF29 -> 7257.66 | AK29: =SUM(AL29:AN29) -> 31237.31 | AL29: ='IS Feb KSA'!AH29+'IS Feb USA'!AH29 -> 14668.43 | AM29: ='IS Feb KSA'!AI29+'IS Feb USA'!AI29 -> 6580.38 | AN29: ='IS Feb KSA'!AJ29+'IS Feb USA'!AJ29 -> 9988.5 | AP29: 3897.75 | AQ29: 91973.44
B30: Audit & Consultancy expense | C30: =H30+L30+D30+P30 -> 0 | D30: =SUM(E30:G30) -> 0 | E30: ='IS Feb KSA'!E30+'IS Feb USA'!E30 -> 0 | F30: ='IS Feb KSA'!F30+'IS Feb USA'!F30 -> 0 | G30: ='IS Feb KSA'!G30+'IS Feb USA'!G30 -> 0 | H30: =I30+J30+K30 -> 0 | I30: ='IS Feb KSA'!I30+'IS Feb USA'!I30 -> 0 | J30: ='IS Feb KSA'!F30+'IS Feb USA'!F30 -> 0 | K30: ='IS Feb KSA'!G30+'IS Feb USA'!G30 -> 0 | L30: =SUM(M30:O30) -> 0 | M30: ='IS Feb KSA'!M30+'IS Feb USA'!M30 -> 0 | N30: ='IS Feb KSA'!N30+'IS Feb USA'!N30 -> 0 | O30: ='IS Feb KSA'!O30+'IS Feb USA'!O30 -> 0 | P30: =SUM(Q30:S30) -> 0 | Q30: ='IS Feb KSA'!Q30+'IS Feb USA'!Q30 -> 0 | R30: ='IS Feb KSA'!R30+'IS Feb USA'!R30 -> 0 | S30: ='IS Feb KSA'!S30+'IS Feb USA'!S30 -> 0 | T30: =U30-V30 -> 3077.5548 | U30: 38077.555 | V30: =AC30+AG30+Y30+AK30 -> 35000 | W30: =X30-AB30 -> 6034.7159 | X30: 6034.7159 | Y30: =SUM(Z30:AB30) -> 35000 | Z30: ='IS Feb KSA'!V30+'IS Feb USA'!V30 -> 35000 | AA30: ='IS Feb KSA'!W30+'IS Feb USA'!W30 -> 0 | AB30: ='IS Feb KSA'!X30+'IS Feb USA'!X30 -> 0 | AC30: =AD30+AE30+AF30 -> 0 | AD30: ='IS Feb KSA'!Z30+'IS Feb USA'!Z30 -> 0 | AE30: ='IS Feb KSA'!AA30+'IS Feb USA'!AA30 -> 0 | AF30: ='IS Feb KSA'!AB30+'IS Feb USA'!AB30 -> 0 | AG30: =SUM(AH30:AJ30) -> 0 | AH30: ='IS Feb KSA'!AD30+'IS Feb USA'!AD30 -> 0 | AI30: ='IS Feb KSA'!AE30+'IS Feb USA'!AE30 -> 0 | AJ30: ='IS Feb KSA'!AF30+'IS Feb USA'!AF30 -> 0 | AK30: =SUM(AL30:AN30) -> 0 | AL30: ='IS Feb KSA'!AH30+'IS Feb USA'!AH30 -> 0 | AM30: ='IS Feb KSA'!AI30+'IS Feb USA'!AI30 -> 0 | AN30: ='IS Feb KSA'!AJ30+'IS Feb USA'!AJ30 -> 0 | AP30: 17500 | AQ30: 42500
B31: Communication Exp - Mobile & Internet | C31: =H31+L31+D31+P31 -> 18883.31 | D31: =SUM(E31:G31) -> 0 | E31: ='IS Feb KSA'!E31+'IS Feb USA'!E31 -> 0 | F31: ='IS Feb KSA'!F31+'IS Feb USA'!F31 -> 0 | G31: ='IS Feb KSA'!G31+'IS Feb USA'!G31 -> 0 | H31: =I31+J31+K31 -> 0 | I31: ='IS Feb KSA'!I31+'IS Feb USA'!I31 -> 0 | J31: ='IS Feb KSA'!F31+'IS Feb USA'!F31 -> 0 | K31: ='IS Feb KSA'!G31+'IS Feb USA'!G31 -> 0 | L31: =SUM(M31:O31) -> 0 | M31: ='IS Feb KSA'!M31+'IS Feb USA'!M31 -> 0 | N31: ='IS Feb KSA'!N31+'IS Feb USA'!N31 -> 0 | O31: ='IS Feb KSA'!O31+'IS Feb USA'!O31 -> 0 | P31: =SUM(Q31:S31) -> 18883.31 | Q31: ='IS Feb KSA'!Q31+'IS Feb USA'!Q31 -> 0 | R31: ='IS Feb KSA'!R31+'IS Feb USA'!R31 -> 6771.94 | S31: ='IS Feb KSA'!S31+'IS Feb USA'!S31 -> 12111.37 | T31: =U31-V31 -> -38311.161 | U31: 27415.839 | V31: =AC31+AG31+Y31+AK31 -> 65727 | W31: =X31-AB31 -> -8997.9046 | X31: 4344.9954 | Y31: =SUM(Z31:AB31) -> 29094.34 | Z31: ='IS Feb KSA'!V31+'IS Feb USA'!V31 -> 8861 | AA31: ='IS Feb KSA'!W31+'IS Feb USA'!W31 -> 6890.44 | AB31: ='IS Feb KSA'!X31+'IS Feb USA'!X31 -> 13342.9 | AC31: =AD31+AE31+AF31 -> 19057.91 | AD31: ='IS Feb KSA'!Z31+'IS Feb USA'!Z31 -> 9880.72 | AE31: ='IS Feb KSA'!AA31+'IS Feb USA'!AA31 -> 4099.12 | AF31: ='IS Feb KSA'!AB31+'IS Feb USA'!AB31 -> 5078.07 | AG31: =SUM(AH31:AJ31) -> 9207.75 | AH31: ='IS Feb KSA'!AD31+'IS Feb USA'!AD31 -> 3298.5 | AI31: ='IS Feb KSA'!AE31+'IS Feb USA'!AE31 -> 2802.08 | AJ31: ='IS Feb KSA'!AF31+'IS Feb USA'!AF31 -> 3107.17 | AK31: =SUM(AL31:AN31) -> 8367 | AL31: ='IS Feb KSA'!AH31+'IS Feb USA'!AH31 -> 5361.89 | AM31: ='IS Feb KSA'!AI31+'IS Feb USA'!AI31 -> 173.24 | AN31: ='IS Feb KSA'!AJ31+'IS Feb USA'!AJ31 -> 2831.87 | AP31: 2142.64 | AQ31: 25607.52
B32: Subscriptions & Memberships | C32: =H32+L32+D32+P32 -> 196004.01 | D32: =SUM(E32:G32) -> 0 | E32: ='IS Feb KSA'!E32+'IS Feb USA'!E32 -> 0 | F32: ='IS Feb KSA'!F32+'IS Feb USA'!F32 -> 0 | G32: ='IS Feb KSA'!G32+'IS Feb USA'!G32 -> 0 | H32: =I32+J32+K32 -> 0 | I32: ='IS Feb KSA'!I32+'IS Feb USA'!I32 -> 0 | J32: ='IS Feb KSA'!F32+'IS Feb USA'!F32 -> 0 | K32: ='IS Feb KSA'!G32+'IS Feb USA'!G32 -> 0 | L32: =SUM(M32:O32) -> 0 | M32: ='IS Feb KSA'!M32+'IS Feb USA'!M32 -> 0 | N32: ='IS Feb KSA'!N32+'IS Feb USA'!N32 -> 0 | O32: ='IS Feb KSA'!O32+'IS Feb USA'!O32 -> 0 | P32: =SUM(Q32:S32) -> 196004.01 | Q32: ='IS Feb KSA'!Q32+'IS Feb USA'!Q32 -> 0 | R32: ='IS Feb KSA'!R32+'IS Feb USA'!R32 -> 101893.31 | S32: ='IS Feb KSA'!S32+'IS Feb USA'!S32 -> 94110.7 | T32: =U32-V32 -> -548044.73 | U32: 456930.66 | V32: =AC32+AG32+Y32+AK32 -> 1004975.4 | W32: =X32-AB32 -> -65856.969 | X32: 72416.591 | Y32: =SUM(Z32:AB32) -> 345831.09 | Z32: ='IS Feb KSA'!V32+'IS Feb USA'!V32 -> 128688.36 | AA32: ='IS Feb KSA'!W32+'IS Feb USA'!W32 -> 78869.17 | AB32: ='IS Feb KSA'!X32+'IS Feb USA'!X32 -> 138273.56 | AC32: =AD32+AE32+AF32 -> 277793.6 | AD32: ='IS Feb KSA'!Z32+'IS Feb USA'!Z32 -> 115331.18 | AE32: ='IS Feb KSA'!AA32+'IS Feb USA'!AA32 -> 56876.15 | AF32: ='IS Feb KSA'!AB32+'IS Feb USA'!AB32 -> 105586.27 | AG32: =SUM(AH32:AJ32) -> 203714.73 | AH32: ='IS Feb KSA'!AD32+'IS Feb USA'!AD32 -> 75539.11 | AI32: ='IS Feb KSA'!AE32+'IS Feb USA'!AE32 -> 68015.58 | AJ32: ='IS Feb KSA'!AF32+'IS Feb USA'!AF32 -> 60160.04 | AK32: =SUM(AL32:AN32) -> 177635.97 | AL32: ='IS Feb KSA'!AH32+'IS Feb USA'!AH32 -> 61103.45 | AM32: ='IS Feb KSA'!AI32+'IS Feb USA'!AI32 -> 72800.7 | AN32: ='IS Feb KSA'!AJ32+'IS Feb USA'!AJ32 -> 43731.82 | AP32: 51500.23 | AQ32: 472140.14
B33: Events & Activity Expense | C33: =H33+L33+D33+P33 -> 13566.86 | D33: =SUM(E33:G33) -> 0 | E33: ='IS Feb KSA'!E33+'IS Feb USA'!E33 -> 0 | F33: ='IS Feb KSA'!F33+'IS Feb USA'!F33 -> 0 | G33: ='IS Feb KSA'!G33+'IS Feb USA'!G33 -> 0 | I33: ='IS Feb KSA'!I33+'IS Feb USA'!I33 -> 0 | J33: ='IS Feb KSA'!F33+'IS Feb USA'!F33 -> 0 | K33: ='IS Feb KSA'!G33+'IS Feb USA'!G33 -> 0 | L33: =SUM(M33:O33) -> 0 | M33: ='IS Feb KSA'!M33+'IS Feb USA'!M33 -> 0 | N33: ='IS Feb KSA'!N33+'IS Feb USA'!N33 -> 0 | O33: ='IS Feb KSA'!O33+'IS Feb USA'!O33 -> 0 | P33: =SUM(Q33:S33) -> 13566.86 | Q33: ='IS Feb KSA'!Q33+'IS Feb USA'!Q33 -> 0 | R33: ='IS Feb KSA'!R33+'IS Feb USA'!R33 -> 4007.5 | S33: ='IS Feb KSA'!S33+'IS Feb USA'!S33 -> 9559.36 | U33: 0 | V33: =AC33+AG33+Y33+AK33 -> 43313.02 | W33: =X33-AB33 -> -18842.92 | Y33: =SUM(Z33:AB33) -> 43313.02 | Z33: ='IS Feb KSA'!V33+'IS Feb USA'!V33 -> 22232.75 | AA33: ='IS Feb KSA'!W33+'IS Feb USA'!W33 -> 2237.35 | AB33: ='IS Feb KSA'!X33+'IS Feb USA'!X33 -> 18842.92
B34: Team Building Activities | C34: =H34+L34+D34+P34 -> 0 | D34: =SUM(E34:G34) -> 0 | E34: ='IS Feb KSA'!E34+'IS Feb USA'!E34 -> 0 | F34: ='IS Feb KSA'!F34+'IS Feb USA'!F34 -> 0 | G34: ='IS Feb KSA'!G34+'IS Feb USA'!G34 -> 0 | I34: ='IS Feb KSA'!I34+'IS Feb USA'!I34 -> 0 | J34: ='IS Feb KSA'!F34+'IS Feb USA'!F34 -> 0 | K34: ='IS Feb KSA'!G34+'IS Feb USA'!G34 -> 0 | L34: =SUM(M34:O34) -> 0 | M34: ='IS Feb KSA'!M34+'IS Feb USA'!M34 -> 0 | N34: ='IS Feb KSA'!N34+'IS Feb USA'!N34 -> 0 | O34: ='IS Feb KSA'!O34+'IS Feb USA'!O34 -> 0 | P34: =SUM(Q34:S34) -> 0 | Q34: ='IS Feb KSA'!Q34+'IS Feb USA'!Q34 -> 0 | R34: ='IS Feb KSA'!R34+'IS Feb USA'!R34 -> 0 | S34: ='IS Feb KSA'!S34+'IS Feb USA'!S34 -> 0 | U34: 0 | V34: =AC34+AG34+Y34+AK34 -> 1200 | W34: =X34-AB34 -> -1200 | Y34: =SUM(Z34:AB34) -> 1200 | Z34: ='IS Feb KSA'!V34+'IS Feb USA'!V34 -> 0 | AA34: ='IS Feb KSA'!W34+'IS Feb USA'!W34 -> 0 | AB34: ='IS Feb KSA'!X34+'IS Feb USA'!X34 -> 1200
B35: Penny Difference | C35: =H35+L35+D35+P35 -> 6.3 | D35: =SUM(E35:G35) -> 0 | E35: ='IS Feb KSA'!E35+'IS Feb USA'!E35 -> 0 | F35: ='IS Feb KSA'!F35+'IS Feb USA'!F35 -> 0 | G35: ='IS Feb KSA'!G35+'IS Feb USA'!G35 -> 0 | H35: =I35+J35+K35 -> 0 | I35: ='IS Feb KSA'!I35+'IS Feb USA'!I35 -> 0 | J35: ='IS Feb KSA'!F35+'IS Feb USA'!F35 -> 0 | K35: ='IS Feb KSA'!G35+'IS Feb USA'!G35 -> 0 | L35: =SUM(M35:O35) -> 0 | M35: ='IS Feb KSA'!M35+'IS Feb USA'!M35 -> 0 | N35: ='IS Feb KSA'!N35+'IS Feb USA'!N35 -> 0 | O35: ='IS Feb KSA'!O35+'IS Feb USA'!O35 -> 0 | P35: =SUM(Q35:S35) -> 6.3 | Q35: ='IS Feb KSA'!Q35+'IS Feb USA'!Q35 -> 0 | R35: ='IS Feb KSA'!R35+'IS Feb USA'!R35 -> 0 | S35: ='IS Feb KSA'!S35+'IS Feb USA'!S35 -> 6.3 | T35: =U35-V35 -> 9130.4432 | U35: 9138.6132 | V35: =AC35+AG35+Y35+AK35 -> 8.17 | W35: =X35-AB35 -> 1447.6818 | X35: 1448.3318 | Y35: =SUM(Z35:AB35) -> 0.66 | Z35: ='IS Feb KSA'!V35+'IS Feb USA'!V35 -> 0.01 | AA35: ='IS Feb KSA'!W35+'IS Feb USA'!W35 -> 0 | AB35: ='IS Feb KSA'!X35+'IS Feb USA'!X35 -> 0.65 | AC35: =AD35+AE35+AF35 -> 3.51 | AD35: ='IS Feb KSA'!Z35+'IS Feb USA'!Z35 -> 0.77 | AE35: ='IS Feb KSA'!AA35+'IS Feb USA'!AA35 -> 2.77 | AF35: ='IS Feb KSA'!AB35+'IS Feb USA'!AB35 -> -0.03 | AG35: =SUM(AH35:AJ35) -> 4 | AH35: ='IS Feb KSA'!AD35+'IS Feb USA'!AD35 -> 2.94 | AI35: ='IS Feb KSA'!AE35+'IS Feb USA'!AE35 -> 0.01 | AJ35: ='IS Feb KSA'!AF35+'IS Feb USA'!AF35 -> 1.05 | AK35: =SUM(AL35:AN35) -> 0 | AL35: ='IS Feb KSA'!AH35+'IS Feb USA'!AH35 -> 0 | AM35: ='IS Feb KSA'!AI35+'IS Feb USA'!AI35 -> 0 | AN35: ='IS Feb KSA'!AJ35+'IS Feb USA'!AJ35 -> 0 | AP35: 0.24 | AQ35: -103.77
B36: Low Value Assets | C36: =H36+L36+D36+P36 -> 849 | D36: =SUM(E36:G36) -> 0 | E36: ='IS Feb KSA'!E36+'IS Feb USA'!E36 -> 0 | F36: ='IS Feb KSA'!F36+'IS Feb USA'!F36 -> 0 | G36: ='IS Feb KSA'!G36+'IS Feb USA'!G36 -> 0 | H36: =I36+J36+K36 -> 0 | I36: ='IS Feb KSA'!I36+'IS Feb USA'!I36 -> 0 | J36: ='IS Feb KSA'!F36+'IS Feb USA'!F36 -> 0 | K36: ='IS Feb KSA'!G36+'IS Feb USA'!G36 -> 0 | L36: =SUM(M36:O36) -> 0 | M36: ='IS Feb KSA'!M36+'IS Feb USA'!M36 -> 0 | N36: ='IS Feb KSA'!N36+'IS Feb USA'!N36 -> 0 | O36: ='IS Feb KSA'!O36+'IS Feb USA'!O36 -> 0 | P36: =SUM(Q36:S36) -> 849 | Q36: ='IS Feb KSA'!Q36+'IS Feb USA'!Q36 -> 0 | R36: ='IS Feb KSA'!R36+'IS Feb USA'!R36 -> 0 | S36: ='IS Feb KSA'!S36+'IS Feb USA'!S36 -> 849 | T36: =U36-V36 -> -42182.164 | U36: 18277.226 | V36: =AC36+AG36+Y36+AK36 -> 60459.39 | W36: =X36-AB36 -> -15859.466 | X36: 2896.6636 | Y36: =SUM(Z36:AB36) -> 22771.62 | Z36: ='IS Feb KSA'!V36+'IS Feb USA'!V36 -> 1665.09 | AA36: ='IS Feb KSA'!W36+'IS Feb USA'!W36 -> 2350.4 | AB36: ='IS Feb KSA'!X36+'IS Feb USA'!X36 -> 18756.13 | AC36: =AD36+AE36+AF36 -> 13695.24 | AD36: ='IS Feb KSA'!Z36+'IS Feb USA'!Z36 -> 8226.53 | AE36: ='IS Feb KSA'!AA36+'IS Feb USA'!AA36 -> 1562.62 | AF36: ='IS Feb KSA'!AB36+'IS Feb USA'!AB36 -> 3906.09 | AG36: =SUM(AH36:AJ36) -> 5351.42 | AH36: ='IS Feb KSA'!AD36+'IS Feb USA'!AD36 -> 4772.18 | AI36: ='IS Feb KSA'!AE36+'IS Feb USA'!AE36 -> 157.5 | AJ36: ='IS Feb KSA'!AF36+'IS Feb USA'!AF36 -> 421.74 | AK36: =SUM(AL36:AN36) -> 18641.11 | AL36: ='IS Feb KSA'!AH36+'IS Feb USA'!AH36 -> 974.78 | AM36: ='IS Feb KSA'!AI36+'IS Feb USA'!AI36 -> 8417.44 | AN36: ='IS Feb KSA'!AJ36+'IS Feb USA'!AJ36 -> 9248.89 | AP36: 2420.55 | AQ36: 13174.86
B37: Charity | C37: =H37+L37+D37+P37 -> 4000 | D37: =SUM(E37:G37) -> 0 | E37: ='IS Feb KSA'!E37+'IS Feb USA'!E37 -> 0 | F37: ='IS Feb KSA'!F37+'IS Feb USA'!F37 -> 0 | G37: ='IS Feb KSA'!G37+'IS Feb USA'!G37 -> 0 | H37: =I37+J37+K37 -> 0 | I37: ='IS Feb KSA'!I37+'IS Feb USA'!I37 -> 0 | J37: ='IS Feb KSA'!F37+'IS Feb USA'!F37 -> 0 | K37: ='IS Feb KSA'!G37+'IS Feb USA'!G37 -> 0 | L37: =SUM(M37:O37) -> 0 | M37: ='IS Feb KSA'!M37+'IS Feb USA'!M37 -> 0 | N37: ='IS Feb KSA'!N37+'IS Feb USA'!N37 -> 0 | O37: ='IS Feb KSA'!O37+'IS Feb USA'!O37 -> 0 | P37: =SUM(Q37:S37) -> 4000 | Q37: ='IS Feb KSA'!Q37+'IS Feb USA'!Q37 -> 0 | R37: ='IS Feb KSA'!R37+'IS Feb USA'!R37 -> 2000 | S37: ='IS Feb KSA'!S37+'IS Feb USA'!S37 -> 2000 | T37: =U37-V37 -> -1000 | U37: 30000 | V37: =AC37+AG37+Y37+AK37 -> 31000 | W37: =X37-AB37 -> -6000 | X37: 3000 | Y37: =SUM(Z37:AB37) -> 13000 | Z37: ='IS Feb KSA'!V37+'IS Feb USA'!V37 -> 2000 | AA37: ='IS Feb KSA'!W37+'IS Feb USA'!W37 -> 2000 | AB37: ='IS Feb KSA'!X37+'IS Feb USA'!X37 -> 9000 | AC37: =AD37+AE37+AF37 -> 6000 | AD37: ='IS Feb KSA'!Z37+'IS Feb USA'!Z37 -> 2000 | AE37: ='IS Feb KSA'!AA37+'IS Feb USA'!AA37 -> 2000 | AF37: ='IS Feb KSA'!AB37+'IS Feb USA'!AB37 -> 2000 | AG37: =SUM(AH37:AJ37) -> 6000 | AH37: ='IS Feb KSA'!AD37+'IS Feb USA'!AD37 -> 2000 | AI37: ='IS Feb KSA'!AE37+'IS Feb USA'!AE37 -> 2000 | AJ37: ='IS Feb KSA'!AF37+'IS Feb USA'!AF37 -> 2000 | AK37: =SUM(AL37:AN37) -> 6000 | AL37: ='IS Feb KSA'!AH37+'IS Feb USA'!AH37 -> 2000 | AM37: ='IS Feb KSA'!AI37+'IS Feb USA'!AI37 -> 2000 | AN37: ='IS Feb KSA'!AJ37+'IS Feb USA'!AJ37 -> 2000 | AP37: 2000 | AQ37: 10000
B38: Witholding Tax | C38: =H38+L38+D38+P38 -> 0 | D38: =SUM(E38:G38) -> 0 | E38: ='IS Feb KSA'!E38+'IS Feb USA'!E38 -> 0 | F38: ='IS Feb KSA'!F38+'IS Feb USA'!F38 -> 0 | G38: ='IS Feb KSA'!G38+'IS Feb USA'!G38 -> 0 | I38: ='IS Feb KSA'!I38+'IS Feb USA'!I38 -> 0 | J38: ='IS Feb KSA'!F38+'IS Feb USA'!F38 -> 0 | K38: ='IS Feb KSA'!G38+'IS Feb USA'!G38 -> 0 | L38: =SUM(M38:O38) -> 0 | M38: ='IS Feb KSA'!M38+'IS Feb USA'!M38 -> 0 | N38: ='IS Feb KSA'!N38+'IS Feb USA'!N38 -> 0 | O38: ='IS Feb KSA'!O38+'IS Feb USA'!O38 -> 0 | Q38: ='IS Feb KSA'!Q38+'IS Feb USA'!Q38 -> 0 | R38: ='IS Feb KSA'!R38+'IS Feb USA'!R38 -> 0 | S38: ='IS Feb KSA'!S38+'IS Feb USA'!S38 -> 0 | T38: =U38-V38 -> 0 | U38: 0 | V38: =AC38+AG38+Y38+AK38 -> 0 | W38: =X38-AB38 -> 0 | X38: 0 | Y38: =SUM(Z38:AB38) -> 0 | Z38: ='IS Feb KSA'!V38+'IS Feb USA'!V38 -> 0 | AA38: ='IS Feb KSA'!W38+'IS Feb USA'!W38 -> 0 | AB38: ='IS Feb KSA'!X38+'IS Feb USA'!X38 -> 0 | AM38: ='IS Feb KSA'!AI38+'IS Feb USA'!AI38 -> 0 | AN38: ='IS Feb KSA'!AJ38+'IS Feb USA'!AJ38 -> 0 | AP38: 0 | AQ38: 47608.81
B39: Selling Expenses | C39: =SUM(C40:C55) -> 243251.08 | D39: =SUM(D40:D55) -> 0 | E39: =SUM(E40:E55) -> 0 | F39: =SUM(F40:F55) -> 0 | G39: =SUM(G40:G55) -> 0 | H39: =SUM(H40:H55) -> 0 | I39: =SUM(I40:I55) -> 0 | J39: =SUM(J40:J55) -> 0 | ... S39: =SUM(S40:S55) -> 124957.1 | T39: =U39-V39 -> 546074.46 | U39: =SUM(U40:U55) -> 2131463.9 | V39: =SUM(V40:V55) -> 1585389.5 | W39: =X39-AB39 -> 118554.61 | X39: =SUM(X40:X55) -> 266289.97 | Y39: =SUM(Y40:Y55) -> 450046.4 | Z39: =SUM(Z40:Z55) -> 155233.75 | AA39: =SUM(AA40:AA55) -> 147077.29 | AB39: =SUM(AB40:AB55) -> 147735.36 | AC39: =SUM(AC40:AC55) -> 469247.74 | AD39: =SUM(AD40:AD55) -> 170596.64 | AE39: =SUM(AE40:AE55) -> 99390.5 | ... AN39: =SUM(AN40:AN55) -> 92728.61 | AP39: =SUM(AP40:AP55) -> 88341.5 | AQ39: =SUM(AQ40:AQ55) -> 771628.36
B40: Business travel expenses | C40: =H40+L40+D40+P40 -> 17256.72 | D40: =SUM(E40:G40) -> 0 | E40: ='IS Feb KSA'!E40+'IS Feb USA'!E40 -> 0 | F40: ='IS Feb KSA'!F40+'IS Feb USA'!F40 -> 0 | G40: ='IS Feb KSA'!G40+'IS Feb USA'!G40 -> 0 | H40: =I40+J40+K40 -> 0 | I40: ='IS Feb KSA'!I40+'IS Feb USA'!I40 -> 0 | J40: ='IS Feb KSA'!F40+'IS Feb USA'!F40 -> 0 | K40: ='IS Feb KSA'!G40+'IS Feb USA'!G40 -> 0 | L40: =SUM(M40:O40) -> 0 | M40: ='IS Feb KSA'!M40+'IS Feb USA'!M40 -> 0 | N40: ='IS Feb KSA'!N40+'IS Feb USA'!N40 -> 0 | O40: ='IS Feb KSA'!O40+'IS Feb USA'!O40 -> 0 | P40: =SUM(Q40:S40) -> 17256.72 | Q40: ='IS Feb KSA'!Q40+'IS Feb USA'!Q40 -> 0 | R40: ='IS Feb KSA'!R40+'IS Feb USA'!R40 -> 6068.14 | S40: ='IS Feb KSA'!S40+'IS Feb USA'!S40 -> 11188.58 | T40: =U40-V40 -> -66011.47 | U40: 76155.11 | V40: =AC40+AG40+Y40+AK40 -> 142166.58 | W40: =X40-AB40 -> -2670.2082 | X40: 12069.432 | Y40: =SUM(Z40:AB40) -> 24716.93 | Z40: ='IS Feb KSA'!V40+'IS Feb USA'!V40 -> 18432.23 | AA40: ='IS Feb KSA'!W40+'IS Feb USA'!W40 -> -8454.94 | AB40: ='IS Feb KSA'!X40+'IS Feb USA'!X40 -> 14739.64 | AC40: =AD40+AE40+AF40 -> 24785.52 | AD40: ='IS Feb KSA'!Z40+'IS Feb USA'!Z40 -> 6977.04 | AE40: ='IS Feb KSA'!AA40+'IS Feb USA'!AA40 -> 2887 | AF40: ='IS Feb KSA'!AB40+'IS Feb USA'!AB40 -> 14921.48 | AG40: =SUM(AH40:AJ40) -> 28350.47 | AH40: ='IS Feb KSA'!AD40+'IS Feb USA'!AD40 -> 12154.14 | AI40: ='IS Feb KSA'!AE40+'IS Feb USA'!AE40 -> 11192.95 | AJ40: ='IS Feb KSA'!AF40+'IS Feb USA'!AF40 -> 5003.38 | AK40: =SUM(AL40:AN40) -> 64313.66 | AL40: ='IS Feb KSA'!AH40+'IS Feb USA'!AH40 -> 8038.76 | AM40: ='IS Feb KSA'!AI40+'IS Feb USA'!AI40 -> 41252.68 | AN40: ='IS Feb KSA'!AJ40+'IS Feb USA'!AJ40 -> 15022.22 | AP40: 18308.59 | AQ40: 110575.44
B41: Business Accommodation Expense | C41: =H41+L41+D41+P41 -> 17753.03 | D41: =SUM(E41:G41) -> 0 | E41: ='IS Feb KSA'!E41+'IS Feb USA'!E41 -> 0 | F41: ='IS Feb KSA'!F41+'IS Feb USA'!F41 -> 0 | G41: ='IS Feb KSA'!G41+'IS Feb USA'!G41 -> 0 | H41: =I41+J41+K41 -> 0 | I41: ='IS Feb KSA'!I41+'IS Feb USA'!I41 -> 0 | J41: ='IS Feb KSA'!F41+'IS Feb USA'!F41 -> 0 | K41: ='IS Feb KSA'!G41+'IS Feb USA'!G41 -> 0 | L41: =SUM(M41:O41) -> 0 | M41: ='IS Feb KSA'!M41+'IS Feb USA'!M41 -> 0 | N41: ='IS Feb KSA'!N41+'IS Feb USA'!N41 -> 0 | O41: ='IS Feb KSA'!O41+'IS Feb USA'!O41 -> 0 | P41: =SUM(Q41:S41) -> 17753.03 | Q41: ='IS Feb KSA'!Q41+'IS Feb USA'!Q41 -> 0 | R41: ='IS Feb KSA'!R41+'IS Feb USA'!R41 -> 16460.27 | S41: ='IS Feb KSA'!S41+'IS Feb USA'!S41 -> 1292.76 | T41: =U41-V41 -> -133961.27 | U41: 0 | V41: =AC41+AG41+Y41+AK41 -> 133961.27 | W41: =X41-AB41 -> -10016.7 | X41: 0 | Y41: =SUM(Z41:AB41) -> 44101.17 | Z41: ='IS Feb KSA'!V41+'IS Feb USA'!V41 -> 36312.33 | AA41: ='IS Feb KSA'!W41+'IS Feb USA'!W41 -> -2227.86 | AB41: ='IS Feb KSA'!X41+'IS Feb USA'!X41 -> 10016.7 | AC41: =AD41+AE41+AF41 -> 49747.17 | AD41: ='IS Feb KSA'!Z41+'IS Feb USA'!Z41 -> 28716.5 | AE41: ='IS Feb KSA'!AA41+'IS Feb USA'!AA41 -> 11602.53 | AF41: ='IS Feb KSA'!AB41+'IS Feb USA'!AB41 -> 9428.14 | AG41: =SUM(AH41:AJ41) -> 24529.09 | AH41: ='IS Feb KSA'!AD41+'IS Feb USA'!AD41 -> 13811.06 | AI41: ='IS Feb KSA'!AE41+'IS Feb USA'!AE41 -> 8712.51 | AJ41: ='IS Feb KSA'!AF41+'IS Feb USA'!AF41 -> 2005.52 | AK41: =SUM(AL41:AN41) -> 15583.84 | AL41: ='IS Feb KSA'!AH41+'IS Feb USA'!AH41 -> 1423.78 | AM41: ='IS Feb KSA'!AI41+'IS Feb USA'!AI41 -> 5592.49 | AN41: ='IS Feb KSA'!AJ41+'IS Feb USA'!AJ41 -> 8567.57 | AO41: ='IS Feb KSA'!AK41+'IS Feb USA'!AK41 -> 0 | AP41: ='IS Feb KSA'!AL41+'IS Feb USA'!AL41 -> 0
B42: Collection Commission | C42: =H42+L42+D42+P42 -> 0 | D42: =SUM(E42:G42) -> 0 | E42: ='IS Feb KSA'!E42+'IS Feb USA'!E42 -> 0 | F42: ='IS Feb KSA'!F42+'IS Feb USA'!F42 -> 0 | G42: ='IS Feb KSA'!G42+'IS Feb USA'!G42 -> 0 | H42: =I42+J42+K42 -> 0 | I42: ='IS Feb KSA'!I42+'IS Feb USA'!I42 -> 0 | J42: ='IS Feb KSA'!F42+'IS Feb USA'!F42 -> 0 | K42: ='IS Feb KSA'!G42+'IS Feb USA'!G42 -> 0 | L42: =SUM(M42:O42) -> 0 | M42: ='IS Feb KSA'!M42+'IS Feb USA'!M42 -> 0 | N42: ='IS Feb KSA'!N42+'IS Feb USA'!N42 -> 0 | O42: ='IS Feb KSA'!O42+'IS Feb USA'!O42 -> 0 | P42: =SUM(Q42:S42) -> 0 | Q42: ='IS Feb KSA'!Q42+'IS Feb USA'!Q42 -> 0 | R42: ='IS Feb KSA'!R42+'IS Feb USA'!R42 -> 0 | S42: ='IS Feb KSA'!S42+'IS Feb USA'!S42 -> 0 | T42: =U42-V42 -> 91386.132 | U42: 91386.132 | V42: =AC42+AG42+Y42+AK42 -> 0 | W42: =X42-AB42 -> 14483.318 | X42: 14483.318 | Y42: =SUM(Z42:AB42) -> 0 | Z42: ='IS Feb KSA'!V42+'IS Feb USA'!V42 -> 0 | AA42: ='IS Feb KSA'!W42+'IS Feb USA'!W42 -> 0 | AB42: ='IS Feb KSA'!X42+'IS Feb USA'!X42 -> 0 | AC42: =AD42+AE42+AF42 -> 0 | AD42: ='IS Feb KSA'!Z42+'IS Feb USA'!Z42 -> 0 | AE42: ='IS Feb KSA'!AA42+'IS Feb USA'!AA42 -> 0 | AF42: ='IS Feb KSA'!AB42+'IS Feb USA'!AB42 -> 0 | AG42: =SUM(AH42:AJ42) -> 0 | AH42: ='IS Feb KSA'!AD42+'IS Feb USA'!AD42 -> 0 | AI42: ='IS Feb KSA'!AE42+'IS Feb USA'!AE42 -> 0 | AJ42: ='IS Feb KSA'!AF42+'IS Feb USA'!AF42 -> 0 | AK42: =SUM(AL42:AN42) -> 0 | AL42: ='IS Feb KSA'!AH42+'IS Feb USA'!AH42 -> 0 | AM42: ='IS Feb KSA'!AI42+'IS Feb USA'!AI42 -> 0 | AN42: ='IS Feb KSA'!AJ42+'IS Feb USA'!AJ42 -> 0 | AP42: 4797.13 | AQ42: 61150.53
B43: Dinar commission | C43: =H43+L43+D43+P43 -> 0 | D43: =SUM(E43:G43) -> 0 | E43: ='IS Feb KSA'!E43+'IS Feb USA'!E43 -> 0 | F43: ='IS Feb KSA'!F43+'IS Feb USA'!F43 -> 0 | G43: ='IS Feb KSA'!G43+'IS Feb USA'!G43 -> 0 | H43: =I43+J43+K43 -> 0 | I43: ='IS Feb KSA'!I43+'IS Feb USA'!I43 -> 0 | J43: ='IS Feb KSA'!F43+'IS Feb USA'!F43 -> 0 | K43: ='IS Feb KSA'!G43+'IS Feb USA'!G43 -> 0 | L43: =SUM(M43:O43) -> 0 | M43: ='IS Feb KSA'!M43+'IS Feb USA'!M43 -> 0 | N43: ='IS Feb KSA'!N43+'IS Feb USA'!N43 -> 0 | O43: ='IS Feb KSA'!O43+'IS Feb USA'!O43 -> 0 | P43: =SUM(Q43:S43) -> 0 | Q43: ='IS Feb KSA'!Q43+'IS Feb USA'!Q43 -> 0 | R43: ='IS Feb KSA'!R43+'IS Feb USA'!R43 -> 0 | S43: ='IS Feb KSA'!S43+'IS Feb USA'!S43 -> 0 | T43: =U43-V43 -> 8378.2617 | U43: 10956.522 | V43: =AC43+AG43+Y43+AK43 -> 2578.26 | W43: =X43-AB43 -> 1304.3478 | X43: 1304.3478 | Y43: =SUM(Z43:AB43) -> 0 | Z43: ='IS Feb KSA'!V43+'IS Feb USA'!V43 -> 0 | AA43: ='IS Feb KSA'!W43+'IS Feb USA'!W43 -> 0 | AB43: ='IS Feb KSA'!X43+'IS Feb USA'!X43 -> 0 | AC43: =AD43+AE43+AF43 -> 0 | AD43: ='IS Feb KSA'!Z43+'IS Feb USA'!Z43 -> 0 | AE43: ='IS Feb KSA'!AA43+'IS Feb USA'!AA43 -> 0 | AF43: ='IS Feb KSA'!AB43+'IS Feb USA'!AB43 -> 0 | AG43: =SUM(AH43:AJ43) -> 1600 | AH43: ='IS Feb KSA'!AD43+'IS Feb USA'!AD43 -> 0 | AI43: ='IS Feb KSA'!AE43+'IS Feb USA'!AE43 -> 0 | AJ43: ='IS Feb KSA'!AF43+'IS Feb USA'!AF43 -> 1600 | AK43: =SUM(AL43:AN43) -> 978.26 | AL43: ='IS Feb KSA'!AH43+'IS Feb USA'!AH43 -> 0 | AM43: ='IS Feb KSA'!AI43+'IS Feb USA'!AI43 -> 978.26 | AN43: ='IS Feb KSA'!AJ43+'IS Feb USA'!AJ43 -> 0 | AP43: 0 | AQ43: 8543.48
B44: New customer commission | C44: =H44+L44+D44+P44 -> 13000 | D44: =SUM(E44:G44) -> 0 | E44: ='IS Feb KSA'!E44+'IS Feb USA'!E44 -> 0 | F44: ='IS Feb KSA'!F44+'IS Feb USA'!F44 -> 0 | G44: ='IS Feb KSA'!G44+'IS Feb USA'!G44 -> 0 | H44: =I44+J44+K44 -> 0 | I44: ='IS Feb KSA'!I44+'IS Feb USA'!I44 -> 0 | J44: ='IS Feb KSA'!F44+'IS Feb USA'!F44 -> 0 | K44: ='IS Feb KSA'!G44+'IS Feb USA'!G44 -> 0 | L44: =SUM(M44:O44) -> 0 | M44: ='IS Feb KSA'!M44+'IS Feb USA'!M44 -> 0 | N44: ='IS Feb KSA'!N44+'IS Feb USA'!N44 -> 0 | O44: ='IS Feb KSA'!O44+'IS Feb USA'!O44 -> 0 | P44: =SUM(Q44:S44) -> 13000 | Q44: ='IS Feb KSA'!Q44+'IS Feb USA'!Q44 -> 0 | R44: ='IS Feb KSA'!R44+'IS Feb USA'!R44 -> 5000 | S44: ='IS Feb KSA'!S44+'IS Feb USA'!S44 -> 8000 | T44: =U44-V44 -> -12767.336 | U44: 114232.66 | V44: =AC44+AG44+Y44+AK44 -> 127000 | W44: =X44-AB44 -> 8104.1477 | X44: 18104.148 | Y44: =SUM(Z44:AB44) -> 39000 | Z44: ='IS Feb KSA'!V44+'IS Feb USA'!V44 -> 7500 | AA44: ='IS Feb KSA'!W44+'IS Feb USA'!W44 -> 21500 | AB44: ='IS Feb KSA'!X44+'IS Feb USA'!X44 -> 10000 | AC44: =AD44+AE44+AF44 -> 35000 | AD44: ='IS Feb KSA'!Z44+'IS Feb USA'!Z44 -> 6000 | AE44: ='IS Feb KSA'!AA44+'IS Feb USA'!AA44 -> 7000 | AF44: ='IS Feb KSA'!AB44+'IS Feb USA'!AB44 -> 22000 | AG44: =SUM(AH44:AJ44) -> 34000 | AH44: ='IS Feb KSA'!AD44+'IS Feb USA'!AD44 -> 13000 | AI44: ='IS Feb KSA'!AE44+'IS Feb USA'!AE44 -> 6000 | AJ44: ='IS Feb KSA'!AF44+'IS Feb USA'!AF44 -> 15000 | AK44: =SUM(AL44:AN44) -> 19000 | AL44: ='IS Feb KSA'!AH44+'IS Feb USA'!AH44 -> 7000 | AM44: ='IS Feb KSA'!AI44+'IS Feb USA'!AI44 -> 7000 | AN44: ='IS Feb KSA'!AJ44+'IS Feb USA'!AJ44 -> 5000 | AP44: 5000 | AQ44: 44606.18
B45: New Approved client Commission (SDA) | C45: =H45+L45+D45+P45 -> 5500 | D45: =SUM(E45:G45) -> 0 | E45: ='IS Feb KSA'!E45+'IS Feb USA'!E45 -> 0 | F45: ='IS Feb KSA'!F45+'IS Feb USA'!F45 -> 0 | G45: ='IS Feb KSA'!G45+'IS Feb USA'!G45 -> 0 | H45: =I45+J45+K45 -> 0 | I45: ='IS Feb KSA'!I45+'IS Feb USA'!I45 -> 0 | J45: ='IS Feb KSA'!F45+'IS Feb USA'!F45 -> 0 | K45: ='IS Feb KSA'!G45+'IS Feb USA'!G45 -> 0 | L45: =SUM(M45:O45) -> 0 | M45: ='IS Feb KSA'!M45+'IS Feb USA'!M45 -> 0 | N45: ='IS Feb KSA'!N45+'IS Feb USA'!N45 -> 0 | O45: ='IS Feb KSA'!O45+'IS Feb USA'!O45 -> 0 | P45: =SUM(Q45:S45) -> 5500 | Q45: ='IS Feb KSA'!Q45+'IS Feb USA'!Q45 -> 0 | R45: ='IS Feb KSA'!R45+'IS Feb USA'!R45 -> 2500 | S45: ='IS Feb KSA'!S45+'IS Feb USA'!S45 -> 3000 | T45: =U45-V45 -> -55000 | U45: 0 | V45: =AC45+AG45+Y45+AK45 -> 55000 | W45: =X45-AB45 -> -7500 | X45: 0 | Y45: =SUM(Z45:AB45) -> 17200 | Z45: ='IS Feb KSA'!V45+'IS Feb USA'!V45 -> 3400 | AA45: ='IS Feb KSA'!W45+'IS Feb USA'!W45 -> 6300 | AB45: ='IS Feb KSA'!X45+'IS Feb USA'!X45 -> 7500 | AC45: =AD45+AE45+AF45 -> 14200 | AD45: ='IS Feb KSA'!Z45+'IS Feb USA'!Z45 -> 4900 | AE45: ='IS Feb KSA'!AA45+'IS Feb USA'!AA45 -> 3700 | AF45: ='IS Feb KSA'!AB45+'IS Feb USA'!AB45 -> 5600 | AG45: =SUM(AH45:AJ45) -> 10100 | AH45: ='IS Feb KSA'!AD45+'IS Feb USA'!AD45 -> 5400 | AI45: ='IS Feb KSA'!AE45+'IS Feb USA'!AE45 -> 1700 | AJ45: ='IS Feb KSA'!AF45+'IS Feb USA'!AF45 -> 3000 | AK45: =SUM(AL45:AN45) -> 13500 | AL45: ='IS Feb KSA'!AH45+'IS Feb USA'!AH45 -> 7000 | AM45: ='IS Feb KSA'!AI45+'IS Feb USA'!AI45 -> 5000 | AN45: ='IS Feb KSA'!AJ45+'IS Feb USA'!AJ45 -> 1500
B46: Sales Commission-Employee | C46: =H46+L46+D46+P46 -> 54400.79 | D46: =SUM(E46:G46) -> 0 | E46: ='IS Feb KSA'!E46+'IS Feb USA'!E46 -> 0 | F46: ='IS Feb KSA'!F46+'IS Feb USA'!F46 -> 0 | G46: ='IS Feb KSA'!G46+'IS Feb USA'!G46 -> 0 | H46: =I46+J46+K46 -> 0 | I46: ='IS Feb KSA'!I46+'IS Feb USA'!I46 -> 0 | J46: ='IS Feb KSA'!F46+'IS Feb USA'!F46 -> 0 | K46: ='IS Feb KSA'!G46+'IS Feb USA'!G46 -> 0 | L46: =SUM(M46:O46) -> 0 | M46: ='IS Feb KSA'!M46+'IS Feb USA'!M46 -> 0 | N46: ='IS Feb KSA'!N46+'IS Feb USA'!N46 -> 0 | O46: ='IS Feb KSA'!O46+'IS Feb USA'!O46 -> 0 | P46: =SUM(Q46:S46) -> 54400.79 | Q46: ='IS Feb KSA'!Q46+'IS Feb USA'!Q46 -> 0 | R46: ='IS Feb KSA'!R46+'IS Feb USA'!R46 -> 30932.16 | S46: ='IS Feb KSA'!S46+'IS Feb USA'!S46 -> 23468.63 | T46: =U46-V46 -> -323555.43 | U46: 0 | V46: =AC46+AG46+Y46+AK46 -> 323555.43 | W46: =X46-AB46 -> -27457.41 | X46: 0 | Y46: =SUM(Z46:AB46) -> 93218.17 | Z46: ='IS Feb KSA'!V46+'IS Feb USA'!V46 -> 29491.08 | AA46: ='IS Feb KSA'!W46+'IS Feb USA'!W46 -> 36269.68 | AB46: ='IS Feb KSA'!X46+'IS Feb USA'!X46 -> 27457.41 | AC46: =AD46+AE46+AF46 -> 102093.22 | AD46: ='IS Feb KSA'!Z46+'IS Feb USA'!Z46 -> 19446.8 | AE46: ='IS Feb KSA'!AA46+'IS Feb USA'!AA46 -> 14722.76 | AF46: ='IS Feb KSA'!AB46+'IS Feb USA'!AB46 -> 67923.66 | AG46: =SUM(AH46:AJ46) -> 71738.54 | AH46: ='IS Feb KSA'!AD46+'IS Feb USA'!AD46 -> 26518.85 | AI46: ='IS Feb KSA'!AE46+'IS Feb USA'!AE46 -> 19610.97 | AJ46: ='IS Feb KSA'!AF46+'IS Feb USA'!AF46 -> 25608.72 | AK46: =SUM(AL46:AN46) -> 56505.5 | AL46: ='IS Feb KSA'!AH46+'IS Feb USA'!AH46 -> 20701.1 | AM46: ='IS Feb KSA'!AI46+'IS Feb USA'!AI46 -> 19876.4 | AN46: ='IS Feb KSA'!AJ46+'IS Feb USA'!AJ46 -> 15928 | AP46: 107.5 | AQ46: 4457.77
B47: NPL Loss Expense | C47: =H47+L47+D47+P47 -> 0 | D47: =SUM(E47:G47) -> 0 | E47: ='IS Feb KSA'!E47+'IS Feb USA'!E47 -> 0 | F47: ='IS Feb KSA'!F47+'IS Feb USA'!F47 -> 0 | G47: ='IS Feb KSA'!G47+'IS Feb USA'!G47 -> 0 | H47: =I47+J47+K47 -> 0 | I47: ='IS Feb KSA'!I47+'IS Feb USA'!I47 -> 0 | J47: ='IS Feb KSA'!F47+'IS Feb USA'!F47 -> 0 | K47: ='IS Feb KSA'!G47+'IS Feb USA'!G47 -> 0 | L47: =SUM(M47:O47) -> 0 | M47: ='IS Feb KSA'!M47+'IS Feb USA'!M47 -> 0 | N47: ='IS Feb KSA'!N47+'IS Feb USA'!N47 -> 0 | O47: ='IS Feb KSA'!O47+'IS Feb USA'!O47 -> 0 | P47: =SUM(Q47:S47) -> 0 | Q47: ='IS Feb KSA'!Q47+'IS Feb USA'!Q47 -> 0 | R47: ='IS Feb KSA'!R47+'IS Feb USA'!R47 -> 0 | S47: ='IS Feb KSA'!S47+'IS Feb USA'!S47 -> 0 | T47: =U47-V47 -> 1160953 | U47: 1160953 | V47: =AC47+AG47+Y47+AK47 -> 0 | W47: =X47-AB47 -> 40494.195 | X47: 40494.195 | Y47: =SUM(Z47:AB47) -> 0 | Z47: ='IS Feb KSA'!V47+'IS Feb USA'!V47 -> 0 | AA47: ='IS Feb KSA'!W47+'IS Feb USA'!W47 -> 0 | AB47: ='IS Feb KSA'!X47+'IS Feb USA'!X47 -> 0 | AC47: =AD47+AE47+AF47 -> 0 | AD47: ='IS Feb KSA'!Z47+'IS Feb USA'!Z47 -> 0 | AE47: ='IS Feb KSA'!AA47+'IS Feb USA'!AA47 -> 0 | AF47: ='IS Feb KSA'!AB47+'IS Feb USA'!AB47 -> 0 | AG47: =SUM(AH47:AJ47) -> 0 | AH47: ='IS Feb KSA'!AD47+'IS Feb USA'!AD47 -> 0 | AI47: ='IS Feb KSA'!AE47+'IS Feb USA'!AE47 -> 0 | AJ47: ='IS Feb KSA'!AF47+'IS Feb USA'!AF47 -> 0 | AK47: =SUM(AL47:AN47) -> 0 | AL47: ='IS Feb KSA'!AH47+'IS Feb USA'!AH47 -> 0 | AM47: ='IS Feb KSA'!AI47+'IS Feb USA'!AI47 -> 0 | AN47: ='IS Feb KSA'!AJ47+'IS Feb USA'!AJ47 -> 0
