Workbook
Name \a: #REF!
Name \a: #REF!
Name \a: #REF!
Name \a: #REF!
Name \c: [1]FLASH!#REF!
Name \c: [1]FLASH!#REF!
Name \c: [1]FLASH!#REF!
Name \c: [1]FLASH!#REF!
Name \f: [1]FLASH!#REF!
Name \f: [1]FLASH!#REF!
Name \f: [1]FLASH!#REF!
Name \f: [1]FLASH!#REF!
Name \q: [1]FLASH!#REF!
Name \q: [1]FLASH!#REF!
Name \q: [1]FLASH!#REF!
Name \q: [1]FLASH!#REF!
Name \s: #REF!
Name \s: #REF!
Name \s: #REF!
Name \s: #REF!
Name \t: [1]FLASH!#REF!
Name \t: [1]FLASH!#REF!
Name \t: [1]FLASH!#REF!
Name \t: [1]FLASH!#REF!
Name \u: '[2]R & M - H L P'!#REF!
Name \u: '[2]R & M - H L P'!#REF!
Name \u: '[2]R & M - H L P'!#REF!
Name \u: '[2]R & M - H L P'!#REF!
Name \z: '[2]R & M - H L P'!#REF!
Name _1: #REF!
Name _1: #REF!
Name _1: #REF!
Name _1: #REF!
Name _2: #REF!
Name _2: #REF!
Name _2: #REF!
Name _2: #REF!
Name _3: #REF!
Name _3: #REF!
Name _3: #REF!
Name _3: #REF!
Name A: #REF!
Name A: #REF!
Name A: #REF!
Name A: #REF!
Name Audit_adj: [3]validation!$I$9
Name Audit_adj_LY: [3]validation_LY!$I$9
Name Axis: OFFSET(#REF!,0,0,MAX(#REF!),1)
Name Axis: OFFSET(#REF!,0,0,MAX(#REF!),1)
Name Axis: OFFSET(#REF!,0,0,MAX(#REF!),1)
Name Axis: OFFSET(#REF!,0,0,MAX(#REF!),1)
Name Axis1: OFFSET(#REF!,0,0,MAX(#REF!),1)
Name Axis1: OFFSET(#REF!,0,0,MAX(#REF!),1)
Name Axis1: OFFSET(#REF!,0,0,MAX(#REF!),1)
Name Axis1: OFFSET(#REF!,0,0,MAX(#REF!),1)
Name B: #REF!
Name B: #REF!
Name B: #REF!
Name B: #REF!
Name BUDGETM: '[4]Budget By Month'!$E$7:$R$83

Sheet IS Dec KSA
B7: INCOME STATEMENT (KSA SAR) | C7: YTD | D7: Q4 | E7: MTD | F7: MTD | G7: MTD | H7: Q3 | I7: MTD | J7: MTD | K7: MTD | L7: Q2 | M7: MTD | N7: MTD | O7: MTD | P7: Q1 | Q7: MTD | R7: MTD | S7: MTD
B8: FOR THE PERIOD 31st December 2024 | C8: 45657 | D8: 2024 | E8: 45657 | F8: 45626 | G8: 45596 | H8: 2024 | I8: 45565 | J8: 45535 | K8: 45504 | L8: 2024 | M8: 45473 | N8: 45443 | O8: 45412 | P8: 2024 | Q8: 45382 | R8: 45350 | S8: 45322
B10: Sales | C10: =SUM(D10:S10)-P10-L10-H10-D10 -> 76420880 | D10: =SUM(E10:G10) -> 21384440 | E10: 10080211 | F10: 7198821.6 | G10: 4105407 | H10: =SUM(I10:K10) -> 18352785 | I10: 4309452.5 | J10: 6772612 | K10: 7270720.4 | L10: =SUM(M10:O10) -> 19534533 | M10: 6957712.6 | N10: 7682337.2 | O10: 4894483.3 | P10: =SUM(Q10:S10) -> 17149122 | Q10: 9910492.9 | R10: 4805893.4 | S10: 2432735.6
B11: Cost of Goods Sold | C11: =SUM(D11:S11)-P11-L11-H11-D11 -> 69127802 | D11: =SUM(E11:G11) -> 19099399 | E11: 9065157.9 | F11: 6363435 | G11: 3670806.6 | H11: =SUM(I11:K11) -> 16705223 | I11: 3901380 | J11: 6268336 | K11: 6535506.8 | L11: =SUM(M11:O11) -> 17712883 | M11: 6212033.5 | N11: 6980089.4 | O11: 4520760 | P11: =SUM(Q11:S11) -> 15610297 | Q11: 9054208.4 | R11: 4407294 | S11: 2148794.4
B12: Purchase Discounts | C12: =SUM(D12:S12)-P12-L12-H12-D12 -> -93226.45 | D12: =SUM(E12:G12) -> -1236.25 | E12: 0 | G12: -1236.25 | H12: =SUM(I12:K12) -> -54172.81 | I12: -6670 | J12: -7915.43 | K12: -39587.38 | L12: =SUM(M12:O12) -> -18295.8 | N12: -5820.46 | O12: -12475.34 | P12: =SUM(Q12:S12) -> -19521.59 | Q12: -11033.03 | R12: -8488.56 | S12: 0
B13: Gross Profit / (Loss) | C13: =+C10-(C11+C12) -> 7386304.4 | D13: =+D10-(D11+D12) -> 2286276.6 | E13: =+E10-(E11+E12) -> 1015053.3 | F13: =+F10-(F11+F12) -> 835386.63 | G13: =+G10-(G11+G12) -> 435836.72 | H13: =+H10-(H11+H12) -> 1701735 | I13: =+I10-(I11+I12) -> 414742.55 | J13: =+J10-(J11+J12) -> 512191.45 | ... S13: =+S10-(S11+S12) -> 283941.25
B14: Consultation Income | C14: =+D14+H14+L14+P14 -> 293478.27 | D14: =SUM(E14:G14) -> 26086.96 | E14: 26086.96 | G14: 0 | H14: =SUM(I14:K14) -> 143478.26 | I14: 0 | J14: 0 | K14: 143478.26 | L14: =SUM(M14:O14) -> 0 | M14: 0 | N14: 0 | O14: 0 | P14: =SUM(Q14:S14) -> 123913.05 | Q14: 19565.22 | R14: 104347.83 | S14: 0
B15: Gross Income | C15: =+D15+H15+L15+P15 -> 7679782.6 | D15: =SUM(E15:G15) -> 2312363.6 | E15: =+E14+E13 -> 1041140.2 | F15: =+F14+F13 -> 835386.63 | G15: =+G14+G13 -> 435836.72 | H15: =SUM(I15:K15) -> 1845213.2 | I15: =+I14+I13 -> 414742.55 | J15: =+J14+J13 -> 512191.45 | K15: =+K14+K13 -> 918279.21 | L15: =SUM(M15:O15) -> 1839946.1 | M15: =+M14+M13 -> 745679.15 | N15: =+N14+N13 -> 708068.27 | O15: =+O14+O13 -> 386198.65 | P15: =SUM(Q15:S15) -> 1682259.8 | Q15: =+Q14+Q13 -> 886882.8 | R15: =+R14+R13 -> 511435.75 | S15: =+S14+S13 -> 283941.25
B17: General and Administrative Expenses | C17: =SUM(C18:C33) -> 865548.78 | D17: =SUM(D18:D33) -> 472997.6 | E17: =SUM(E18:E33) -> 293429.8 | F17: =SUM(F18:F33) -> 73778.62 | G17: =SUM(G18:G33) -> 105789.18 | H17: =SUM(H18:H33) -> 144942.12 | I17: =SUM(I18:I33) -> 65829.61 | J17: =SUM(J18:J33) -> 32644.12 | ... S17: =SUM(S18:S33) -> 46670.67
B18: Bad Debt | C18: =SUM(D18:S18)-P18-L18-H18-D18 -> 203016.64 | D18: =SUM(E18:G18) -> 203011.78 | E18: 203009.5 | F18: 0.37 | G18: 1.91 | H18: =SUM(I18:K18) -> 2.67 | I18: 0.5 | J18: 0.4 | K18: 1.77 | L18: =SUM(M18:O18) -> 0.63 | M18: 0 | N18: 0.63 | O18: 0 | P18: =SUM(Q18:S18) -> 1.56 | Q18: 0.51 | R18: 0.27 | S18: 0.78
B19: Bank Fees and Charges | C19: =SUM(D19:S19)-P19-L19-H19-D19 -> 7108.25 | D19: =SUM(E19:G19) -> 1210.76 | E19: 354.16 | F19: 434.86 | G19: 421.74 | H19: =SUM(I19:K19) -> 1167.17 | I19: 268.89 | J19: 319.69 | K19: 578.59 | L19: =SUM(M19:O19) -> 2248.14 | M19: 570.09 | N19: 954.67 | O19: 723.38 | P19: =SUM(Q19:S19) -> 2482.18 | Q19: 872.4 | R19: 1040.14 | S19: 569.64
B20: Office Supplies | C20: =SUM(D20:S20)-P20-L20-H20-D20 -> 25690.34 | D20: =SUM(E20:G20) -> 2690.87 | E20: 819.32 | F20: 669.05 | G20: 1202.5 | H20: =SUM(I20:K20) -> 8440 | I20: 4877.46 | J20: 3027.63 | K20: 534.91 | L20: =SUM(M20:O20) -> 8750.4 | M20: 682.6 | N20: 7993.77 | O20: 74.03 | P20: =SUM(Q20:S20) -> 5809.07 | Q20: 7.83 | R20: 3179.47 | S20: 2621.77
B21: Office Utilities - Electricity/Water/Janitorial | C21: =SUM(D21:S21)-P21-L21-H21-D21 -> 24609.21 | D21: =SUM(E21:G21) -> 13664.34 | E21: 4705.55 | F21: 1182.28 | G21: 7776.51 | H21: =SUM(I21:K21) -> 6139.69 | I21: 282 | J21: 4257.65 | K21: 1600.04 | L21: =SUM(M21:O21) -> 3342.28 | M21: 983.6 | N21: 1889.74 | O21: 468.94 | P21: =SUM(Q21:S21) -> 1462.9 | Q21: 824.4 | R21: 454 | S21: 184.5
B22: Office Expenses | C22: =SUM(D22:S22)-P22-L22-H22-D22 -> 481 | D22: =SUM(E22:G22) -> 1 | E22: 0 | F22: 0 | G22: 1 | H22: =SUM(I22:K22) -> 0 | I22: 0 | J22: 0 | K22: 0 | L22: =SUM(M22:O22) -> 0 | M22: 0 | N22: 0 | O22: 0 | P22: =SUM(Q22:S22) -> 480 | Q22: 0 | R22: 480 | S22: 0
B23: Travel Expense | C23: =SUM(D23:S23)-P23-L23-H23-D23 -> 29931.99 | D23: =SUM(E23:G23) -> 3750 | E23: 3750 | F23: 0 | G23: 0 | H23: =SUM(I23:K23) -> 18156.74 | I23: 2446.84 | J23: 0 | K23: 15709.9 | L23: =SUM(M23:O23) -> 8025.25 | M23: 0 | N23: 8025.25 | O23: 0 | P23: =SUM(Q23:S23) -> 0 | Q23: 0 | R23: 0 | S23: 0
B24: Printing and Stationery | C24: =SUM(D24:S24)-P24-L24-H24-D24 -> 4591.36 | D24: =SUM(E24:G24) -> 1056.29 | E24: 241 | F24: 675.29 | G24: 140 | H24: =SUM(I24:K24) -> 2690.93 | I24: 990.06 | J24: 0 | K24: 1700.87 | L24: =SUM(M24:O24) -> 69.57 | M24: 69.57 | N24: 0 | O24: 0 | P24: =SUM(Q24:S24) -> 774.57 | Q24: 0 | R24: 774.57 | S24: 0
B25: Rent Expense (G&A) | C25: =SUM(D25:S25)-P25-L25-H25-D25 -> 127377.94 | D25: =SUM(E25:G25) -> 48093.19 | E25: 32096.09 | F25: 7998.55 | G25: 7998.55 | H25: =SUM(I25:K25) -> 23995.64 | I25: 7998.55 | J25: 7998.55 | K25: 7998.54 | L25: =SUM(M25:O25) -> 23899.98 | M25: 7966.66 | N25: 7966.66 | O25: 7966.66 | P25: =SUM(Q25:S25) -> 31389.13 | Q25: 10162.66 | R25: 10162.66 | S25: 11063.81
B26: Meals and Entertainment | C26: =SUM(D26:S26)-P26-L26-H26-D26 -> 84744.32 | D26: =SUM(E26:G26) -> 48368.41 | E26: 3897.75 | F26: 25111.76 | G26: 19358.9 | H26: =SUM(I26:K26) -> 19542.3 | I26: 8268.64 | J26: 6052.74 | K26: 5220.92 | L26: =SUM(M26:O26) -> 8918.73 | M26: 3696.52 | N26: 3183.82 | O26: 2038.39 | P26: =SUM(Q26:S26) -> 7914.88 | Q26: 1173.66 | R26: 3478.57 | S26: 3262.65
B27: Audit & Consultancy expense | C27: =SUM(D27:S27)-P27-L27-H27-D27 -> 42500 | D27: =SUM(E27:G27) -> 17500 | E27: 17500 | F27: 0 | G27: 0 | H27: =SUM(I27:K27) -> 0 | I27: 0 | J27: 0 | K27: 0 | L27: =SUM(M27:O27) -> 12500 | M27: 12500 | N27: 0 | O27: 0 | P27: =SUM(Q27:S27) -> 12500 | Q27: 0 | R27: 0 | S27: 12500
B28: Communication Exp - Mobile & Internet | C28: =SUM(D28:S28)-P28-L28-H28-D28 -> 24754.9 | D28: =SUM(E28:G28) -> 8450.21 | E28: 2142.64 | F28: 2122.61 | G28: 4184.96 | H28: =SUM(I28:K28) -> 3845.24 | I28: 0 | J28: 1922.61 | K28: 1922.63 | L28: =SUM(M28:O28) -> 6691.58 | M28: 1929.83 | N28: 2812.12 | O28: 1949.63 | P28: =SUM(Q28:S28) -> 5767.87 | Q28: 1922.63 | R28: 1922.61 | S28: 1922.63
B29: Subscriptions & Memberships | C29: =SUM(D29:S29)-P29-L29-H29-D29 -> 227892.91 | D29: =SUM(E29:G29) -> 62247.3 | E29: 22184.55 | F29: 31415.34 | G29: 8647.41 | H29: =SUM(I29:K29) -> 60961.74 | I29: 40696.67 | J29: 9168.95 | K29: 11096.12 | L29: =SUM(M29:O29) -> 54654.93 | M29: 7414.94 | N29: 27481.49 | O29: 19758.5 | P29: =SUM(Q29:S29) -> 50028.94 | Q29: 19510.85 | R29: 15973.2 | S29: 14544.89
B30: Penny Difference | C30: =SUM(D30:S30)-P30-L30-H30-D30 -> -103.77 | D30: =SUM(E30:G30) -> -0.24 | E30: 0.24 | F30: 0.01 | G30: -0.49 | I30: 0 | J30: -104.1 | K30: -0.03 | L30: =SUM(M30:O30) -> 0.6 | M30: 0.12 | N30: 0.04 | O30: 0.44 | P30: =SUM(Q30:S30) -> 0 | Q30: 0 | R30: 0 | S30: 0
B31: Low Value Assets | C31: =SUM(D31:S31)-P31-L31-H31-D31 -> 5344.88 | D31: =SUM(E31:G31) -> 5344.88 | E31: 729 | F31: 4168.5 | G31: 447.38 | I31: 0 | J31: 0 | K31: 0 | M31: 0 | N31: 0 | O31: 0 | Q31: 0 | R31: 0 | S31: 0
B32: Charity | C32: =SUM(D32:S32)-P32-L32-H32-D32 -> 10000 | D32: =SUM(E32:G32) -> 10000 | E32: 2000 | F32: 0 | G32: 8000
B33: Witholding Tax | C33: =SUM(D33:S33)-P33-L33-H33-D33 -> 47608.81 | D33: =SUM(E33:G33) -> 47608.81 | E33: 0 | F33: 0 | G33: 47608.81
B34: Selling Expenses | C34: =SUM(C35:C43) -> 591969.18 | D34: =SUM(D35:D43) -> 189997.51 | E34: =SUM(E35:E43) -> 58404.56 | F34: =SUM(F35:F43) -> 67054.63 | G34: =SUM(G35:G43) -> 64538.32 | H34: =SUM(H35:H43) -> 155905.83 | I34: =SUM(I35:I43) -> 69145.88 | J34: =SUM(J35:J43) -> 42955.06 | ... S34: =SUM(S35:S43) -> 24674.48
B35: Business travel expenses | C35: =SUM(D35:S35)-P35-L35-H35-D35 -> 96381.63 | D35: =SUM(E35:G35) -> 61361.03 | E35: 18271.01 | F35: 18913.71 | G35: 24176.31 | H35: =SUM(I35:K35) -> 13512.9 | I35: 4564.64 | J35: 690 | K35: 8258.26 | L35: =SUM(M35:O35) -> 16278.5 | M35: 2500 | N35: 0 | O35: 13778.5 | P35: =SUM(Q35:S35) -> 5229.2 | Q35: 1340 | R35: 3889.2 | S35: 0
B36: Collection Commission | C36: =SUM(D36:S36)-P36-L36-H36-D36 -> 61150.53 | D36: =SUM(E36:G36) -> 8117.57 | E36: 4797.13 | F36: 0 | G36: 3320.44 | H36: =SUM(I36:K36) -> 17715.01 | I36: 3388.45 | J36: 11016.84 | K36: 3309.72 | L36: =SUM(M36:O36) -> 17647.36 | M36: 10814.05 | N36: 4426.28 | O36: 2407.03 | P36: =SUM(Q36:S36) -> 17670.59 | Q36: 6731.53 | R36: 1817.82 | S36: 9121.24
B37: Dinar commission | C37: =SUM(D37:S37)-P37-L37-H37-D37 -> 8543.48 | D37: =SUM(E37:G37) -> 0 | E37: 0 | F37: 0 | G37: 0 | H37: =SUM(I37:K37) -> 2869.57 | I37: 0 | J37: 1304.35 | K37: 1565.22 | L37: =SUM(M37:O37) -> 391.3 | M37: 0 | N37: 0 | O37: 391.3 | P37: =SUM(Q37:S37) -> 5282.61 | Q37: 2086.96 | R37: 0 | S37: 3195.65
B38: New customer commission | C38: =SUM(D38:S38)-P38-L38-H38-D38 -> 44606.18 | D38: =SUM(E38:G38) -> 13166.48 | E38: 5000 | F38: 8166.48 | G38: 0 | H38: =SUM(I38:K38) -> 9439.7 | I38: 1500 | J38: 5939.7 | K38: 2000 | L38: =SUM(M38:O38) -> 13000 | M38: 7000 | N38: 3000 | O38: 3000 | P38: =SUM(Q38:S38) -> 9000 | Q38: 2000 | R38: 1000 | S38: 6000
B39: Cash Purchase - Backend Margin | C39: =SUM(D39:S39)-P39-L39-H39-D39 -> 4457.77 | D39: =SUM(E39:G39) -> 687.5 | E39: 107.5 | F39: 0 | G39: 580 | H39: =SUM(I39:K39) -> 481.81 | I39: 481.81 | J39: 0 | K39: 0 | L39: =SUM(M39:O39) -> 3288.46 | M39: 506.13 | N39: 2782.33 | O39: 0 | P39: =SUM(Q39:S39) -> 0 | Q39: 0 | R39: 0 | S39: 0
B40: Cash Sale Commission | C40: =SUM(D40:S40)-P40-L40-H40-D40 -> 21797.18 | D40: =SUM(E40:G40) -> 240 | E40: 0 | F40: 120 | G40: 120 | H40: =SUM(I40:K40) -> 4162.38 | I40: 720 | J40: 3442.38 | K40: 0 | L40: =SUM(M40:O40) -> 17394.8 | M40: 6744.8 | N40: 10650 | O40: 0 | P40: =SUM(Q40:S40) -> 0 | Q40: 0 | R40: 0 | S40: 0
B41: Fuel/Mileage Expenses | C41: =SUM(D41:S41)-P41-L41-H41-D41 -> 42649.18 | D41: =SUM(E41:G41) -> 12753.84 | E41: 4340.78 | F41: 3114.39 | G41: 5298.67 | H41: =SUM(I41:K41) -> 10160.15 | I41: 4905.08 | J41: 1943.42 | K41: 3311.65 | L41: =SUM(M41:O41) -> 12392.19 | M41: 4093.31 | N41: 5875.86 | O41: 2423.02 | P41: =SUM(Q41:S41) -> 7343 | Q41: 4287.21 | R41: 1634.11 | S41: 1421.68
B42: Marketing & Advertising | C42: =SUM(D42:S42)-P42-L42-H42-D42 -> 93575.77 | D42: =SUM(E42:G42) -> 16006.67 | E42: 0 | F42: 10851.91 | G42: 5154.76 | H42: =SUM(I42:K42) -> 41735.47 | I42: 34993.8 | J42: 0 | K42: 6741.67 | L42: =SUM(M42:O42) -> 18316.57 | M42: 6055.73 | N42: 5907.61 | O42: 6353.23 | P42: =SUM(Q42:S42) -> 17517.06 | Q42: 6361.77 | R42: 6219.38 | S42: 4935.91
B43: Trade Credit Insurance | C43: =SUM(D43:S43)-P43-L43-H43-D43 -> 218807.46 | D43: =SUM(E43:G43) -> 77664.42 | E43: 25888.14 | F43: 25888.14 | G43: 25888.14 | H43: =SUM(I43:K43) -> 55828.84 | I43: 18592.1 | J43: 18618.37 | K43: 18618.37 | L43: =SUM(M43:O43) -> 50426.81 | M43: 16795.28 | N43: 16808.98 | O43: 16822.55 | P43: =SUM(Q43:S43) -> 34887.39 | Q43: 16822.55 | R43: 18064.84 | S43: 0
B44: Legal & Consultation Expenses | C44: =SUM(C45:C47) -> 408151.68 | D44: =SUM(D45:D47) -> 210401.22 | E44: =SUM(E45:E47) -> 161922.26 | F44: =SUM(F45:F47) -> 23924.35 | G44: =SUM(G45:G47) -> 24554.61 | H44: =SUM(H45:H47) -> 91831.38 | I44: =SUM(I45:I47) -> 28490.25 | J44: =SUM(J45:J47) -> 50369.3 | ... S44: =SUM(S45:S47) -> 19548.99
B45: Consultant Expense | C45: =SUM(D45:S45)-P45-L45-H45-D45 -> 74533.33 | D45: =SUM(E45:G45) -> 0 | E45: 0 | F45: 0 | G45: 0 | H45: =SUM(I45:K45) -> 13333.33 | I45: 3333.33 | J45: 0 | K45: 10000 | L45: =SUM(M45:O45) -> 30000 | M45: 10000 | N45: 10000 | O45: 10000 | P45: =SUM(Q45:S45) -> 31200 | Q45: 10000 | R45: 10000 | S45: 11200
B46: Government & Compliance Expense | C46: =SUM(D46:S46)-P46-L46-H46-D46 -> 29073.83 | D46: =SUM(E46:G46) -> 7668.36 | E46: 1332.26 | F46: 3174.35 | G46: 3161.75 | H46: =SUM(I46:K46) -> 9461.39 | I46: 1380.25 | J46: 5155.14 | K46: 2926 | L46: =SUM(M46:O46) -> 3638.5 | M46: 1201.75 | N46: 1656.75 | O46: 780 | P46: =SUM(Q46:S46) -> 8305.58 | Q46: 1253.5 | R46: 4165.59 | S46: 2886.49
B47: Legal | C47: =SUM(D47:S47)-P47-L47-H47-D47 -> 304544.52 | D47: =SUM(E47:G47) -> 202732.86 | E47: 160590 | F47: 20750 | G47: 21392.86 | H47: =SUM(I47:K47) -> 69036.66 | I47: 23776.67 | J47: 45214.16 | K47: 45.83 | M47: 5462.5 | N47: 5462.5 | O47: 5462.5 | P47: =SUM(Q47:S47) -> 16387.5 | Q47: 5462.5 | R47: 5462.5 | S47: 5462.5
B48: Depreciation Expenses | C48: =SUM(C49:C51) -> 85187.69 | D48: =SUM(D49:D51) -> 23197.02 | E48: =SUM(E49:E51) -> 7880.36 | F48: =SUM(F49:F51) -> 7291.25 | G48: =SUM(G49:G51) -> 8025.41 | H48: =SUM(H49:H51) -> 22696.56 | I48: =SUM(I49:I51) -> 7935.01 | J48: =SUM(J49:J51) -> 8024.9 | ... S48: =SUM(S49:S51) -> 6000.35
B49: Depreciation - Furniture & Fixture | C49: =SUM(D49:S49)-P49-L49-H49-D49 -> 15221.76 | D49: =SUM(E49:G49) -> 3943.41 | E49: 1314.47 | F49: 1314.47 | G49: 1314.47 | H49: =SUM(I49:K49) -> 3864.57 | I49: 1314.47 | J49: 1314.47 | K49: 1235.63 | L49: =SUM(M49:O49) -> 3706.89 | M49: 1235.63 | N49: 1235.63 | O49: 1235.63 | P49: =SUM(Q49:S49) -> 3706.89 | Q49: 1235.63 | R49: 1235.63 | S49: 1235.63
B50: Depreciation - Motor Vehicle | C50: =SUM(D50:S50)-P50-L50-H50-D50 -> 14526.77 | D50: =SUM(E50:G50) -> 5039.55 | E50: 1679.85 | F50: 1679.85 | G50: 1679.85 | H50: =SUM(I50:K50) -> 4235.06 | I50: 1679.85 | J50: 1679.85 | K50: 875.36 | L50: =SUM(M50:O50) -> 2626.08 | M50: 875.36 | N50: 875.36 | O50: 875.36 | P50: =SUM(Q50:S50) -> 2626.08 | Q50: 875.36 | R50: 875.36 | S50: 875.36
B51: Depreciation - Office Equipment's | C51: =SUM(D51:S51)-P51-L51-H51-D51 -> 55439.16 | D51: =SUM(E51:G51) -> 14214.06 | E51: 4886.04 | F51: 4296.93 | G51: 5031.09 | H51: =SUM(I51:K51) -> 14596.93 | I51: 4940.69 | J51: 5030.58 | K51: 4625.66 | M51: 4625.66 | N51: 4625.66 | O51: 4625.66 | P51: =SUM(Q51:S51) -> 12751.19 | Q51: 4625.66 | R51: 4236.17 | S51: 3889.36
B52: Personnel Expenses | C52: =SUM(C53:C69) -> 3919359.8 | D52: =SUM(D53:D69) -> 1374316.7 | E52: =SUM(E53:E69) -> 570580.97 | F52: =SUM(F53:F69) -> 404929.95 | G52: =SUM(G53:G69) -> 398805.74 | H52: =SUM(H53:H69) -> 1092875.5 | I52: =SUM(I53:I69) -> 385135.93 | J52: =SUM(J53:J69) -> 411730.57 | ... S52: =SUM(S53:S69) -> 155018.47
B53: Employee Insurance | C53: =SUM(D53:S53)-P53-L53-H53-D53 -> 155647.64 | D53: =SUM(E53:G53) -> 55475.28 | E53: 19139.83 | F53: 18825.08 | G53: 17510.37 | H53: =SUM(I53:K53) -> 49398.66 | I53: 17220.59 | J53: 16380.48 | K53: 15797.59 | L53: =SUM(M53:O53) -> 37231.82 | M53: 12374.81 | N53: 12614.48 | O53: 12242.53 | P53: =SUM(Q53:S53) -> 13541.88 | Q53: 5797.64 | R53: 4107.86 | S53: 3636.38
B54: Leave Pay Expense | C54: =SUM(D54:S54)-P54-L54-H54-D54 -> 71427.81 | D54: =SUM(E54:G54) -> 58357.68 | E54: 47874.96 | F54: 4523.71 | G54: 5959.01 | H54: =SUM(I54:K54) -> 11233.13 | I54: 2420 | J54: 4613.13 | K54: 4200 | L54: =SUM(M54:O54) -> 1837 | M54: 0 | N54: 1837 | O54: 0 | P54: =SUM(Q54:S54) -> 0 | Q54: 0 | R54: 0 | S54: 0
B55: Employee Referral Allowance | C55: =SUM(D55:S55)-P55-L55-H55-D55 -> 12377.78 | D55: =SUM(E55:G55) -> 3000 | E55: 0 | F55: 3000 | G55: 0 | H55: =SUM(I55:K55) -> 0 | I55: 0 | J55: 0 | K55: 0 | L55: =SUM(M55:O55) -> 4377.78 | M55: 0 | N55: 0 | O55: 4377.78 | P55: =SUM(Q55:S55) -> 5000 | Q55: 0 | R55: 5000 | S55: 0
B56: Maintenance Allowance | C56: =SUM(D56:S56)-P56-L56-H56-D56 -> 50915.87 | D56: =SUM(E56:G56) -> 16500 | E56: 9000 | F56: 3210.43 | G56: 4289.57 | H56: =SUM(I56:K56) -> 7891 | I56: 3000 | J56: 1391 | K56: 3500 | L56: =SUM(M56:O56) -> 14714 | M56: 4000 | N56: 7214 | O56: 3500 | P56: =SUM(Q56:S56) -> 11810.87 | Q56: 6810.87 | R56: 2500 | S56: 2500
B57: Employee Related Govt Fees | C57: =SUM(D57:S57)-P57-L57-H57-D57 -> 161134.51 | D57: =SUM(E57:G57) -> 29728.93 | E57: 22339.49 | F57: -1760.56 | G57: 9150 | H57: =SUM(I57:K57) -> 71666.75 | I57: 19950 | J57: 19250 | K57: 32466.75 | L57: =SUM(M57:O57) -> 42651.83 | M57: 17938 | N57: 18013 | O57: 6700.83 | P57: =SUM(Q57:S57) -> 17087 | Q57: 17087 | R57: 0 | S57: 0
B58: Telecome Allowance | C58: =SUM(D58:S58)-P58-L58-H58-D58 -> 15800.58 | D58: =SUM(E58:G58) -> 6600 | E58: 3400 | F58: 1400 | G58: 1800 | H58: =SUM(I58:K58) -> 2800 | I58: 1200 | J58: 0 | K58: 1600 | L58: =SUM(M58:O58) -> 3400 | M58: 1000 | N58: 1200 | O58: 1200 | P58: =SUM(Q58:S58) -> 3000.58 | Q58: 1400 | R58: 800.58 | S58: 800
B59: US Employer Taxes | D59: =SUM(E59:G59) -> 0 | E59: 0 | F59: 0 | G59: 0 | H59: =SUM(I59:K59) -> 0 | I59: 0 | J59: 0 | K59: 0 | M59: 0 | N59: 0 | O59: 0 | Q59: 0 | R59: 0 | S59: 0
B60: GOSI | C60: =SUM(D60:S60)-P60-L60-H60-D60 -> 167751.58 | D60: =SUM(E60:G60) -> 51066.62 | E60: 17220.56 | F60: 17776.14 | G60: 16069.92 | H60: =SUM(I60:K60) -> 47360.02 | I60: 15944.87 | J60: 15669.64 | K60: 15745.51 | L60: =SUM(M60:O60) -> 42946.21 | M60: 14900.91 | N60: 14377.1 | O60: 13668.2 | P60: =SUM(Q60:S60) -> 26378.73 | Q60: 13429.24 | R60: 8948.41 | S60: 4001.08
B61: HUMAN RESOUACES DEVELOPMENT FUND | C61: =SUM(D61:S61)-P61-L61-H61-D61 -> -81000 | D61: =SUM(E61:G61) -> -30000 | E61: -15000 | F61: 0 | G61: -15000 | H61: =SUM(I61:K61) -> -15000 | I61: -3000 | J61: -6000 | K61: -6000 | L61: =SUM(M61:O61) -> -12000 | M61: 0 | N61: -6000 | O61: -6000 | P61: =SUM(Q61:S61) -> -24000 | Q61: -6000 | R61: -6000 | S61: -12000
B62: Recruitments & Visas | C62: =SUM(D62:S62)-P62-L62-H62-D62 -> 53546.33 | D62: =SUM(E62:G62) -> 4172 | E62: 0 | F62: 0 | G62: 4172 | H62: =SUM(I62:K62) -> 44447.04 | I62: 950.37 | J62: 43496.67 | K62: 0 | L62: =SUM(M62:O62) -> 0 | M62: 0 | N62: 0 | O62: 0 | P62: =SUM(Q62:S62) -> 4927.29 | Q62: 0 | R62: 0 | S62: 4927.29
B63: Bonus | C63: =SUM(D63:S63)-P63-L63-H63-D63 -> 42731.37 | D63: =SUM(E63:G63) -> 5739 | E63: 2739 | F63: 0 | G63: 3000 | H63: =SUM(I63:K63) -> 11992.37 | I63: 1000 | J63: 10992.37 | K63: 0 | L63: =SUM(M63:O63) -> 0 | M63: 0 | N63: 0 | O63: 0 | P63: =SUM(Q63:S63) -> 25000 | Q63: 25000 | R63: 0 | S63: 0
B64: Salaries - Basic | C64: =SUM(D64:S64)-P64-L64-H64-D64 -> 2392437.9 | D64: =SUM(E64:G64) -> 803388.87 | E64: 274704.86 | F64: 259156.23 | G64: 269527.78 | H64: =SUM(I64:K64) -> 653135.13 | I64: 246828.76 | J64: 226362.21 | K64: 179944.16 | L64: =SUM(M64:O64) -> 536239.26 | M64: 183818.93 | N64: 179740.96 | O64: 172679.37 | P64: =SUM(Q64:S64) -> 399674.66 | Q64: 172970.96 | R64: 123078.7 | S64: 103625
B65: Salaries - Housing | C65: =SUM(D65:S65)-P65-L65-H65-D65 -> 495183.73 | D65: =SUM(E65:G65) -> 168553.53 | E65: 58989.69 | F65: 55452.72 | G65: 54111.12 | H65: =SUM(I65:K65) -> 144565.78 | I65: 55492.1 | J65: 50338.14 | K65: 38735.54 | L65: =SUM(M65:O65) -> 112634.6 | M65: 39705.23 | N65: 38594.22 | O65: 34335.15 | P65: =SUM(Q65:S65) -> 69429.82 | Q65: 34335.15 | R65: 24519.67 | S65: 10575
B66: Salaries - Others | C66: =SUM(D66:S66)-P66-L66-H66-D66 -> 51169.78 | D66: =SUM(E66:G66) -> 20359.09 | E66: 0 | F66: 17511.12 | G66: 2847.97 | H66: =SUM(I66:K66) -> 2685.89 | I66: 1200 | J66: 0 | K66: 1485.89 | L66: =SUM(M66:O66) -> -99.76 | M66: 0 | N66: 0 | O66: -99.76 | P66: =SUM(Q66:S66) -> 28224.56 | Q66: 3304.17 | R66: 0 | S66: 24920.39
B67: Salaries - Transportation | C67: =SUM(D67:S67)-P67-L67-H67-D67 -> 207649.09 | D67: =SUM(E67:G67) -> 67447.71 | E67: 23601.29 | F67: 22186.93 | G67: 21659.49 | H67: =SUM(I67:K67) -> 59573.7 | I67: 22929.24 | J67: 21149.05 | K67: 15495.41 | L67: =SUM(M67:O67) -> 45053.02 | M67: 15882.08 | N67: 15437.48 | O67: 13733.46 | P67: =SUM(Q67:S67) -> 35574.66 | Q67: 13733.46 | R67: 9807.87 | S67: 12033.33
B68: End Of Service Benefits | C68: =SUM(D68:S68)-P68-L68-H68-D68 -> 120889.78 | D68: =SUM(E68:G68) -> 113927.95 | E68: 106571.29 | F68: 3648.15 | G68: 3708.51 | I68: 0 | J68: 6961.83 | K68: 0 | M68: 0 | N68: 0 | O68: 0 | Q68: 0 | R68: 0 | S68: 0
B69: Staff Education/Growth Allowance | C69: =SUM(D69:S69)-P69-L69-H69-D69 -> 1696.05 | D69: =SUM(E69:G69) -> 0 | E69: 0 | F69: 0 | G69: 0 | H69: =SUM(I69:K69) -> 1126.05 | I69: 0 | J69: 1126.05 | K69: 0 | L69: =SUM(M69:O69) -> 570 | M69: 570 | N69: 0 | O69: 0 | P69: =SUM(Q69:S69) -> 0 | Q69: 0 | R69: 0 | S69: 0
B70: Operating expenses | C70: =+C52+C48+C44+C34+C17 -> 5870217.1 | D70: =SUM(E70:G70) -> 2270910 | E70: =+E52+E48+E44+E34+E17 -> 1092217.9 | F70: =+F52+F48+F44+F34+F17 -> 576978.8 | G70: =+G52+G48+G44+G34+G17 -> 601713.26 | H70: =SUM(I70:K70) -> 1515109.1 | I70: =+I52+I48+I44+I34+I17 -> 556536.68 | J70: =+J52+J48+J44+J34+J17 -> 545723.95 | K70: =+K52+K48+K44+K34+K17 -> 412848.48 | L70: =SUM(M70:O70) -> 1178029.8 | M70: =+M52+M48+M44+M34+M17 -> 403914.09 | N70: =+N52+N48+N44+N34+N17 -> 416643.39 | O70: =+O52+O48+O44+O34+O17 -> 357472.31 | P70: =SUM(Q70:S70) -> 906168.24 | Q70: =+Q52+Q48+Q44+Q34+Q17 -> 385426.1 | R70: =+R52+R48+R44+R34+R17 -> 268829.18 | S70: =+S52+S48+S44+S34+S17 -> 251912.96
B73: Net operating profit / (loss) | C73: =SUM(C13+C14)-C70 -> 1809565.5 | D73: =SUM(D13+D14)-D70 -> 41453.56 | E73: =SUM(E13+E14)-E70 -> -51077.73 | F73: =SUM(F13+F14)-F70 -> 258407.83 | G73: =SUM(G13+G14)-G70 -> -165876.54 | H73: =SUM(H13+H14)-H70 -> 330104.1 | I73: =SUM(I13+I14)-I70 -> -141794.13 | J73: =SUM(J13+J14)-J70 -> -33532.5 | ... S73: =SUM(S13+S14)-S70 -> 32028.29
C75: =SUM(D75:S75)-P75-L75-H75-D75 -> 0
B76: Exchange Gain or Loss | C76: =SUM(D76:S76)-P76-L76-H76-D76 -> -51128.21 | D76: =SUM(E76:G76) -> -49166.02 | E76: -49465.83 | F76: 0 | G76: 299.81 | H76: =SUM(I76:K76) -> -1737.44 | I76: 0 | J76: -1737.44 | K76: 0 | L76: =SUM(M76:O76) -> -224.75 | M76: 0 | N76: 0 | O76: -224.75 | P76: =SUM(Q76:S76) -> 0 | Q76: 0 | R76: 0 | S76: 0
C77: =SUM(D77:S77)-P77-L77-H77-D77 -> 0
B78: Gain Or Loss on Disposal | C78: =SUM(D78:S78)-P78-L78-H78-D78 -> 6362.26 | D78: =SUM(E78:G78) -> 6362.26 | E78: 6362.26
C80: =SUM(D80:S80)-P80-L80-H80-D80 -> 0
B81: Investor's Profit sharing (Unrealized) | C81: =SUM(D81:S81)-P81-L81-H81-D81 -> -706164.61 | D81: =SUM(E81:G81) -> 440000 | E81: 475000 | F81: -20000 | G81: -15000 | H81: =SUM(I81:K81) -> -369927.06 | I81: -90000 | J81: -108312.47 | K81: -171614.59 | L81: =SUM(M81:O81) -> -430787.54 | M81: -164188.26 | N81: -170587.62 | O81: -96011.66 | P81: =SUM(Q81:S81) -> -345450.01 | Q81: -184731.71 | R81: -92622.21 | S81: -68096.09
C82: =SUM(D82:S82)-P82-L82-H82-D82 -> 0
B83: Financing expense (Al-Raeda) | C83: =SUM(D83:S83)-P83-L83-H83-D83 -> -365252.64 | D83: =SUM(E83:G83) -> -90849.99 | E83: -30283.33 | F83: -30283.33 | G83: -30283.33 | H83: =SUM(I83:K83) -> -90849.99 | I83: -30283.33 | J83: -30283.33 | K83: -30283.33 | L83: =SUM(M83:O83) -> -90849.99 | M83: -30283.33 | N83: -30283.33 | O83: -30283.33 | P83: =SUM(Q83:S83) -> -92702.67 | Q83: -30283.33 | R83: -30283.33 | S83: -32136.01
C84: =SUM(D84:S84)-P84-L84-H84-D84 -> 0
B85: Financing expense (Arbah) | C85: =SUM(D85:S85)-P85-L85-H85-D85 -> -497027.78 | D85: =SUM(E85:G85) -> -497027.78 | E85: -255965.28 | F85: -118416.67 | G85: -122645.83
C86: =SUM(D86:S86)-P86-L86-H86-D86 -> 0
B87: Financing expense (STV) | C87: =SUM(D87:S87)-P87-L87-H87-D87 -> 0 | D87: =SUM(E87:G87) -> 0 | E87: 0
C88: =SUM(D88:S88)-P88-L88-H88-D88 -> 0
B89: Financing Processing Fee Expense | C89: =SUM(D89:S89)-P89-L89-H89-D89 -> -102500 | D89: =SUM(E89:G89) -> -102500 | E89: 0 | F89: -50000 | G89: -52500
C90: =SUM(D90:S90)-P90-L90-H90-D90 -> 0
B91: Fundraising Expense | C91: =SUM(D91:S91)-P91-L91-H91-D91 -> -5555.55 | D91: =SUM(E91:G91) -> -3333.33 | E91: -1111.11 | F91: -1111.11 | G91: -1111.11 | H91: =SUM(I91:K91) -> -2222.22 | I91: -1111.11 | J91: -1111.11 | K91: 0 | L91: =SUM(M91:O91) -> 0 | M91: 0 | N91: 0 | O91: 0 | P91: =SUM(Q91:S91) -> 0 | Q91: 0 | R91: 0 | S91: 0
C92: =SUM(D92:S92)-P92-L92-H92-D92 -> 0
B93: Non-operating Income/(Expenses) | C93: =SUM(D93:S93)-P93-L93-H93-D93 -> 0 | D93: =SUM(E93:G93) -> 0 | E93: 0 | F93: 0 | G93: 0 | H93: =SUM(I93:K93) -> 0 | I93: 0 | J93: 0 | K93: 0 | L93: =SUM(M93:O93) -> 0 | M93: 0 | N93: 0 | O93: 0 | P93: =SUM(Q93:S93) -> 0 | Q93: 0 | R93: 0 | S93: 0
C94: =SUM(D94:S94)-P94-L94-H94-D94 -> 0
B95: Zakat / Income Tax | C95: =SUM(D95:S95)-P95-L95-H95-D95 -> 5910.49 | D95: =SUM(E95:G95) -> 0 | E95: 0 | F95: 0 | G95: 0 | H95: 0 | I95: 0 | J95: 0 | K95: 0 | L95: =SUM(M95:O95) -> 5910.49 | M95: 0 | N95: 5910.49 | O95: 0 | P95: 0 | Q95: 0 | R95: 0 | S95: 0
B97: Net income / (loss) | C97: =+C73+C83+C93+C95+C81+C91+C76+C85+C89+C78 -> 94209.46 | D97: =+D73+D83+D93+D95+D81+D91+D76+D85+D89+D78 -> -255061.3 | E97: =+E73+E83+E93+E95+E81+E91+E76+E85+E89+E78 -> 93458.98 | F97: =+F73+F83+F93+F95+F81+F91+F76+F85+F89+F78 -> 38596.72 | G97: =+G73+G83+G93+G95+G81+G91+G76+G85+G89+G78 -> -387117 | H97: =+H73+H83+H93+H95+H81+H91+H76+H85+H89+H78 -> -134632.61 | I97: =+I73+I83+I93+I95+I81+I91+I76+I85+I89+I78 -> -263188.57 | J97: =+J73+J83+J93+J95+J81+J91+J76+J85+J89+J78 -> -174976.85 | ... S97: =+S73+S83+S93+S95+S81+S91+S76+S85+S89+S78 -> -68203.81

Sheet BS Dec KSA
B6: STATEMENT OF FINANCIAL POSITION (KSA SAR) | C6: 45657 | D6: 45626 | E6: 45596 | F6: 45565 | G6: 45535 | H6: 45504 | I6: 45473 | J6: 45443 | K6: 45412 | L6: 45382 | M6: 45350 | N6: 45322 | P6: 45291
B7: AS OF 31st December 2024
B8: ASSETS
B10: Cash and Bank Balances | C10: =SUM(C11:C25) -> 10448735 | D10: =SUM(D11:D25) -> 13623467 | E10: =SUM(E11:E25) -> 14580341 | F10: =SUM(F11:F25) -> 4079900.2 | G10: =SUM(G11:G25) -> 1768114.7 | H10: =SUM(H11:H25) -> 4979907 | I10: =SUM(I11:I25) -> 7931667.7 | J10: =SUM(J11:J25) -> 3213576.5 | ... N10: =SUM(N11:N25) -> 4556446.7 | P10: 3957363.2
B11: ALINMA BILDNW FEE | C11: 0 | D11: 0 | F11: 0 | G11: 0 | H11: 75.7 | I11: 75.7 | J11: 75.7 | K11: 75.7 | L11: 0 | M11: 37036.55 | N11: 26646.61 | P11: 0
B12: ALINMA BILDNW PROFIT | C12: 140103.67 | D12: 140103.67 | E12: 140103.67 | F12: 0 | G12: 0 | H12: 569757.95 | I12: 0 | J12: 0 | K12: 0 | L12: 0 | M12: 428055.73 | N12: 408472.76 | P12: 0
B13: ALINMA CLIENT PROFIT | C13: 166842.98 | D13: 166834.93 | E13: 166834.93 | F13: 339620.94 | G13: 339620.94 | H13: -8.05 | I13: 1708.15 | J13: 1708.15 | K13: 1708.15 | L13: 729157.71 | M13: 266776.95 | N13: 188464.65 | P13: 668024.87
B14: ALINMA DINAR DEALs PROFIT | C14: 30000 | D14: 0 | E14: 0 | F14: 0 | G14: 0 | H14: 165000 | I14: 0 | J14: 0 | K14: 0 | L14: 0 | M14: 15000 | N14: 0 | P14: 0
B15: ALINMA DINAR DEALs VAT | C15: 0 | D15: 0 | E15: 0 | F15: 0 | G15: 0 | H15: 0 | I15: 0 | J15: 0 | K15: 0 | L15: 2934.78 | M15: 0 | N15: 0 | P15: 43532.61
B16: ALINMA EQUITY | C16: 1315636.9 | D16: 2292020.2 | E16: 1849786.1 | F16: 88790.6 | G16: 1257082.2 | H16: 46543.89 | I16: 168320.11 | J16: 23714.23 | K16: 465178.53 | L16: 2339786.4 | M16: 3910746 | N16: 1030009.5 | P16: 767469.48
B17: ALINMA USD | C17: 0 | D17: 0 | E17: 0 | F17: 0 | G17: 0 | H17: 356567.64 | I17: 686567.64 | J17: 1186567.6 | K17: 1186567.6 | L17: 1232245.3 | M17: 0.44 | N17: 0.44 | P17: 0.44
B18: ALINMA VAT | C18: 131821.9 | D18: 100685.09 | E18: 88071.43 | F18: 67480.41 | G18: 29428.08 | H18: 29383.75 | I18: 29383.75 | J18: 39479.28 | K18: 39465.34 | L18: 54326.84 | M18: 34284.09 | N18: 19246.15 | P18: 90759.47
B19: ALINMA-DEBT | C19: 8593232.1 | D19: 10906870 | E19: 12317444 | F19: 3467930 | G19: 135882.26 | H19: 3806484.8 | I19: 7042461.1 | J19: 1958900.2 | K19: 606214.56 | L19: 991645.23 | M19: 3300295.3 | N19: 2883475.3 | P19: 2381669.3
B20: ANB-BILDNW TRADINGCOMPANY | C20: 6 | D20: 6 | E20: 6 | F20: 6 | G20: 6 | H20: 6 | I20: 6 | J20: 6 | K20: 6 | L20: 6 | M20: 6 | N20: 6 | P20: 100.8
B21: Riyadh Bank | C21: 30.48 | D21: 30.48 | E21: 30.48 | F21: 30.48 | G21: 30.48 | H21: 30.48 | I21: 30.48 | J21: 30.48 | K21: 30.48 | L21: 30.48 | M21: 30.48 | N21: 30.48 | P21: 6.31
B22: US Checking Account | C22: 0 | D22: 0 | E22: 0 | F22: 0 | G22: 0 | H22: 0 | I22: 0 | J22: 0 | K22: 0 | L22: 0 | M22: 0 | N22: 0
B23: anb - Tanmeya Debt Acct | C23: 37094.8 | D23: 94.8 | E23: 94.8 | F23: 94.8 | G23: 94.8 | H23: 94.8 | I23: 94.8 | J23: 94.8 | K23: 94.8 | L23: 94.8 | M23: 94.8 | N23: 94.8
B24: Simplifi | C24: 7822.62 | D24: 7822.62 | E24: 12970 | F24: 12970 | G24: 2970 | H24: 2970 | I24: 20 | J24: 0 | K24: 0 | L24: 0 | M24: 0 | N24: 0
B25: Petty Cash | C25: 26143.5 | D25: 8999.5 | E25: 4999.5 | F25: 102977 | G25: 3000 | H25: 3000 | I25: 3000 | J25: 3000 | K25: 3000 | L25: 3000 | M25: 3000 | N25: 0 | P25: 5800
B27: Trade Receivables (net) | C27: =SUM(C28:C29) -> 39178410 | D27: =SUM(D28:D29) -> 35535924 | E27: =SUM(E28:E29) -> 33632759 | F27: =SUM(F28:F29) -> 34548085 | G27: =SUM(G28:G29) -> 37084008 | H27: =SUM(H28:H29) -> 34268040 | I27: =SUM(I28:I29) -> 31927623 | J27: =SUM(J28:J29) -> 31054504 | ... N27: =SUM(N28:N29) -> 25019982 | P27: 25749560
B28: Trade Receivables - Gross | C28: 39584419 | D28: 35738924 | E28: 33835759 | F28: 34751085 | G28: 37287008 | H28: 34471040 | I28: 32130623 | J28: 31257504 | K28: 31952970 | L28: 29354142 | M28: 24957358 | N28: 25222982 | P28: 25749560
B29: Provision for doubtful Accounts | C29: -406009 | D29: -203000 | E29: -203000 | F29: -203000 | G29: -203000 | H29: -203000 | I29: -203000 | J29: -203000 | K29: -203000 | L29: -203000 | M29: -203000 | N29: -203000 | P29: 0
B31: Prepaid Expenses & Other recievables | C31: =SUM(C32:C44) -> 1263663.6 | D31: =SUM(D32:D44) -> 1239829.7 | E31: =SUM(E32:E44) -> 745420.18 | F31: =SUM(F32:F43) -> 366541.22 | G31: =SUM(G32:G43) -> 453953.95 | H31: =SUM(H32:H43) -> 352908.58 | I31: =SUM(I32:I43) -> 312499.7 | J31: =SUM(J32:J43) -> 353032.39 | K31: =SUM(K32:K43) -> 318973.06 | L31: =SUM(L32:L43) -> -1226013.6 | M31: =SUM(M32:M43) -> 283971.54 | N31: =SUM(N32:N43) -> 204303.4 | P31: 288133.91
B32: Prepaid Vendors | C32: 0 | D32: -8.05 | E32: -8.05 | F32: -18293.05 | G32: 17091.95 | H32: 17091.95 | I32: -8.05 | J32: -8.05 | K32: -8.05 | L32: -8.05 | M32: -8.05 | N32: -8.05 | P32: -8.05
B33: Prepaid Accommodation Rent Expense | C33: 0 | D33: -10666.63 | E33: -8533.3 | F33: -6399.97 | G33: -4266.64 | H33: -2133.31 | I33: 0.02 | J33: 2133.35 | K33: -8533.32 | L33: -6399.99 | M33: -2070.66 | N33: 2258.67
B34: Prepaid Financing Expense | C34: 34444.45 | D34: 35555.56 | E34: 36666.67 | F34: 37777.78 | G34: 38888.89 | H34: 0 | I34: 0 | J34: 0 | K34: 0 | L34: 0 | M34: 0 | N34: 0
B35: Prepaid Govt. Legal Expense | C35: 32500 | D35: 37916.67 | E35: 43333.34 | F35: 48750.01 | G35: 54166.68 | H35: 45.84 | I35: 91.67 | J35: 5554.17 | K35: 11016.67 | L35: 16479.17 | M35: 21941.67 | N35: 27404.17
B36: Prepaid IT Subscriptions Expense | C36: 70455.1 | D36: 7399.82 | E36: 8407.32 | F36: 11165.72 | G36: 13924.12 | H36: 7232.52 | I36: 9203.42 | J36: 11174.32 | K36: 10743.59 | L36: 12932.86 | M36: 15122.13 | N36: 17311.4
B37: Prepaid Office Rent Expense | C37: 126562.51 | D37: 156525.23 | E37: 11730.45 | F37: 17595.67 | G37: 23460.89 | H37: -5865.19 | I37: 0.02 | J37: 5833.35 | K37: 11666.68 | L37: 17500.01 | M37: 23333.34 | N37: 29166.67
B38: Prepaid Other Expense | C38: 75416.45 | D38: 108630.62 | E38: 90215.04 | F38: 121117.42 | G38: 146777.02 | H38: 173911.51 | I38: 110904.11 | J38: 123278.93 | K38: 122420.42 | L38: 2208.55 | M38: 99757.97 | N38: 9481.31 | P38: 71234.03
B39: Fund Raising Expense receivable
B40: Employee Receivable | C40: 150690.88 | D40: 130882.32 | E40: 127030.83 | F40: 99394.9 | G40: 108416.5 | H40: 107216.1 | I40: 138558.16 | J40: 152088.92 | K40: 119559.81 | L40: 92393.14 | M40: 76092.47 | N40: 70092.47 | P40: 57592.47
B41: Security deposits | C41: 2000 | D41: 2000 | E41: 2000 | F41: 2000 | G41: 2000 | H41: 1500 | I41: 1500 | J41: 1500 | K41: 1500 | L41: 1500 | M41: 1500 | N41: 1500 | P41: 1500
B42: Other Receivables | C42: 0 | D42: 0 | E42: 0 | F42: 0 | G42: 0 | H42: 500 | I42: 0 | J42: 0 | K42: 0 | L42: 0 | M42: 0 | N42: 0 | P42: 112999.2
B43: Input VAT | C43: 28469.18 | D43: 28469.18 | E43: 53952.88 | F43: 53432.74 | G43: 53494.54 | H43: 53409.16 | I43: 52250.35 | J43: 51477.4 | K43: 50607.26 | L43: -1362619.3 | M43: 48302.67 | N43: 47096.76 | P43: 44816.26
B44: Profit Reserve Account (Deposit) | C44: 743125 | D44: 743125 | E44: 380625 | F44: 0 | G44: 0 | I44: 0 | J44: 0 | K44: 0 | L44: 0 | M44: 0
B46: TOTAL CURRENT ASSETS | C46: =+C31+C10+C27 -> 50890809 | D46: =+D31+D10+D27 -> 50399221 | E46: =+E31+E10+E27 -> 48958521 | F46: =+F31+F10+F27 -> 38994527 | G46: =+G31+G10+G27 -> 39306076 | H46: =+H31+H10+H27 -> 39600856 | I46: =+I31+I10+I27 -> 40171790 | J46: =+J31+J10+J27 -> 34621113 | ... N46: =+N31+N10+N27 -> 29780732 | P46: 29995057
B49: Fixed Assets (net) | C49: =SUM(C50:C57) -> 208363.25 | D49: =SUM(D50:D57) -> 161601.55 | E49: =SUM(E50:E57) -> 145409.86 | F49: =SUM(F50:F57) -> 153435.27 | G49: =SUM(G50:G57) -> 159109.41 | H49: =SUM(H50:H57) -> 108959.76 | I49: =SUM(I50:I57) -> 113097.31 | J49: =SUM(J50:J57) -> 119833.96 | ... N49: =SUM(N50:N57) -> 128719.67 | P49: 129248.72
B50: Accumulated Depreciation - Furniture & Fixture | C50: -23841.55 | D50: -22527.08 | E50: -21212.61 | F50: -19898.14 | G50: -18583.67 | H50: -17269.2 | I50: -16033.57 | J50: -14797.94 | K50: -13562.31 | L50: -12326.68 | M50: -11091.05 | N50: -9855.42 | P50: -8619.79
B51: Accumulated Depreciation - Motor Vehicle | C51: -4022.45 | D51: -24226.6 | E51: -22546.75 | F51: -20866.9 | G51: -19187.05 | H51: -17507.2 | I51: -16631.84 | J51: -15756.48 | K51: -14881.12 | L51: -14005.76 | M51: -13130.4 | N51: -12255.04 | P51: -11379.68
B52: Accumulated Depreciation - Office Equipment's | C52: -91068.56 | D52: -86182.52 | E52: -81885.59 | F52: -76854.5 | G52: -71913.81 | H52: -66883.23 | I52: -62257.57 | J52: -57631.91 | K52: -53006.25 | L52: -48380.59 | M52: -43754.93 | N52: -39518.76 | P52: -35629.4
B53: Fixed Asset not yet in use | C53: 0 | D53: 0 | E53: 0 | F53: 0 | G53: 0 | H53: 0.1 | I53: 0 | J53: 0 | K53: 0 | L53: 0 | M53: 0 | N53: 0
B54: Furniture & Fixture | C54: 47320.87 | D54: 47320.87 | E54: 47320.87 | F54: 47320.87 | G54: 47320.87 | H54: 44482.61 | I54: 44482.61 | J54: 44482.61 | K54: 44482.61 | L54: 44482.61 | M54: 44482.61 | N54: 44482.61 | P54: 44482.61
B55: Motor Vehicle | C55: 48217.39 | D55: 100739.13 | E55: 100739.13 | F55: 100739.13 | G55: 100739.13 | H55: 52521.74 | I55: 52521.74 | J55: 52521.74 | K55: 52521.74 | L55: 52521.74 | M55: 52521.74 | N55: 52521.74 | P55: 52521.74
B56: Office Equipment | C56: 140389.23 | D56: 132960.54 | E56: 122994.81 | F56: 122994.81 | G56: 120733.94 | H56: 113614.94 | I56: 111015.94 | J56: 111015.94 | K56: 111015.94 | L56: 111015.94 | M56: 101668.02 | N56: 93344.54 | P56: 87873.24
B57: Capital Work in Progress | C57: 91368.32 | D57: 13517.21 | G57: 0 | K57: 0 | L57: 0 | M57: 0
B59: Intercompany Receivable | C59: =SUM(C60:C63) -> 275541.35 | D59: =SUM(D60:D63) -> 266041.35 | E59: =SUM(E60:E63) -> 258541.35 | F59: =SUM(F60:F63) -> 243541.35 | G59: =SUM(G60:G63) -> 240541.35 | H59: =SUM(H60:H63) -> 200511.35 | I59: =SUM(I60:I63) -> 200511.35 | J59: =SUM(J60:J63) -> 200511.35 | ... N59: =SUM(N60:N63) -> 200511.35 | P59: 200320
B60: Buildnow Inc. (US) | C60: 269850 | D60: 262350 | E60: 254850 | F60: 239850 | G60: 236850 | H60: 200320 | I60: 200320 | J60: 200320 | K60: 200320 | L60: 200320 | M60: 200320 | N60: 200320 | P60: 200320
B61: Buildnow Tech BD | C61: 41.33 | D61: 41.33 | E61: 41.33 | F61: 41.33 | G61: 41.33 | H61: 41.33 | I61: 41.33 | J61: 41.33 | K61: 41.33 | L61: 41.33 | M61: 41.33 | N61: 41.33
B62: Buildnow Trading Co (KSA) | C62: 0 | D62: 0 | E62: 0 | F62: 0 | G62: 0 | H62: 0 | I62: 0 | J62: 0 | K62: 0 | L62: 0 | M62: 0 | N62: 0
B63: MISA KSA | C63: 5650.02 | D63: 3650.02 | E63: 3650.02 | F63: 3650.02 | G63: 3650.02 | H63: 150.02 | I63: 150.02 | J63: 150.02 | K63: 150.02 | L63: 150.02 | M63: 150.02 | N63: 150.02
B65: Investment in Subsidiaries | C65: =SUM(C66) -> 0 | D65: =SUM(D66) -> 0 | E65: =SUM(E66) -> 0 | F65: =SUM(F66) -> 0 | G65: =SUM(G66) -> 0 | H65: =SUM(H66) -> 0 | I65: =SUM(I66) -> 0 | J65: =SUM(J66) -> 0 | ... N65: =SUM(N66) -> 0
B66: Buildnow BD Technology Subsidiary
B69: TOTAL NON CURRENT ASSETS | C69: =+C59+C49+C65 -> 483904.6 | D69: =+D59+D49+D65 -> 427642.9 | E69: =+E59+E49+E65 -> 403951.21 | F69: =+F59+F49+F65 -> 396976.62 | G69: =+G59+G49+G65 -> 399650.76 | H69: =+H59+H49+H65 -> 309471.11 | I69: =+I59+I49+I65 -> 313608.66 | J69: =+J59+J49+J65 -> 320345.31 | ... N69: =+N59+N49+N65 -> 329231.02 | P69: 329568.72
B72: TOTAL ASSETS | C72: =+C69+C46 -> 51374713 | D72: =+D69+D46 -> 50826864 | E72: =+E69+E46 -> 49362472 | F72: =+F69+F46 -> 39391503 | G72: =+G69+G46 -> 39705727 | H72: =+H69+H46 -> 39910327 | I72: =+I69+I46 -> 40485399 | J72: =+J69+J46 -> 34941459 | ... N72: =+N69+N46 -> 30109963 | P72: 30324626
B75: LIABILITIES & OWNER'S EQUITY
B77: Other Payables and Accruals | C77: =SUM(C78:C94) -> 1665946.3 | D77: =SUM(D78:D95) -> 1367592.9 | E77: =SUM(E78:E95) -> 9379298 | F77: =SUM(F78:F95) -> 1521212.4 | G77: =SUM(G78:G95) -> 1572247.7 | H77: =SUM(H78:H95) -> 1601870.6 | I77: =SUM(I78:I95) -> 2480475.4 | J77: =SUM(J78:J95) -> 1204328.5 | K77: =SUM(K78:K95) -> 1057700.7 | ... N77: =SUM(N78:N95) -> 959820.89 | P77: 1472393.1
B78: Zakat Provision | C78: 0 | F78: 0 | G78: 0 | H78: 0 | I78: 0 | J78: 0 | K78: 39481 | L78: 39481 | M78: 39481 | N78: 39481 | P78: 75000
B79: Misc. Payables | C79: 158987.5 | D79: 158987.5 | E79: 158987.5 | F79: 158987.5 | G79: 158987.5 | H79: 158987.5 | I79: 158987.5 | J79: 158987.5 | K79: 158987.5 | L79: 158987.5 | M79: 158987.5 | N79: 158987.5 | P79: 158987.5
B80: Other Payables | C80: 139840 | D80: -3255.65 | E80: 81853.05 | F80: 85108.7 | G80: 143804.35 | H80: 143804.35 | I80: 143804.35 | J80: 143804.35 | K80: 202500 | L80: 202500 | M80: 0 | N80: 0
B81: Unearned Revenue | C81: 1373.79 | D81: 1372.92 | E81: 1371.15 | F81: 1370.24 | G81: 0 | H81: 104.1 | I81: 103.24 | J81: 103.24 | K81: 103.24 | L81: 45780.52 | M81: 102.82 | N81: 102.82 | P81: 0.35
B82: Employee Payable | C82: 0 | D82: 716.48 | E82: 716.48 | F82: 716.48 | G82: 716.48 | H82: 716.48 | I82: 716.48 | J82: 716.48 | K82: 716.48 | L82: 716.48 | M82: 716.48 | N82: 716.48 | P82: 616.48
B83: Accounts Payable | C83: 877017.06 | D83: 393994.53 | E83: 109792.73 | F83: 63875.59 | G83: 188753.42 | H83: 207570.12 | I83: 1074112.6 | J83: 0.57 | K83: 0.57 | L83: 0.57 | M83: 46713.57 | N83: 46713.57 | P83: 0
B84: Accrued Expenses | C84: 25866.83 | D84: -1030.15 | E84: -27927.13 | F84: -54824.11 | G84: -81721.09 | H84: -108618.09 | I84: -135515.09 | J84: -162412.08 | K84: -189309.06 | L84: -216206.04 | M84: 26896.98 | N84: 0
B85: VAT Payable (GAZT) | C85: 129870.78 | D85: 87148.86 | E85: 137073.2 | F85: 40260.02 | G85: 36509.21 | H85: 223097.27 | I85: 108021.91 | J85: 88598.41 | K85: 33431.76 | L85: 247341.03 | M85: 56633.7 | N85: 34553.58 | P85: 317117.71
B86: Accrued Investor Profit | C86: 119793.9 | D86: 595802.74 | E86: 576811.58 | F86: 766015.92 | G86: 940141.87 | H86: 840108.03 | I86: 676772.07 | J86: 866837.73 | K86: 706338.11 | L86: 620400.88 | M86: 687558.97 | N86: 603768.9 | P86: 310223.26
B87: Accrued Investor Profit (Unrealized)
B88: Leave Pay Payable | C88: 47874.96 | D88: 0 | E88: 0 | F88: 0 | G88: 0 | H88: 0 | I88: 0 | J88: 0 | K88: 0 | L88: 0 | M88: 0 | N88: 0
B89: Salary Control Account | C89: 31871.18 | D89: -0.02 | E89: 9600 | F89: 104500 | G89: 86500.01 | H89: 37500.01 | I89: 10500.01 | J89: 10500.01 | K89: 10500.01 | L89: 0.01 | M89: 0 | N89: 0 | P89: 2237.5
B90: Consultancy Fee Payable | C90: 0 | D90: 0 | G90: 0 | H90: 0 | I90: 0 | J90: 0 | K90: 0 | L90: 0 | M90: 0 | N90: 0 | P90: 0
B91: Output VAT | C91: 73342.41 | D91: 73342.34 | E91: 73342.29 | F91: 72333.57 | G91: 72245.31 | H91: 72159.68 | I91: 71010.65 | J91: 70237.7 | K91: 69367.48 | L91: -1490723.6 | M91: 67062.87 | N91: 65857.67 | P91: 65677.87
B92: GOSI Payable | C92: 29169.43 | D92: 29574.85 | E92: 27004.01 | F92: 27047.43 | G92: 26310.63 | H92: 26441.13 | I92: 26086.92 | J92: 25232.09 | K92: 23861.15 | L92: 23622.19 | M92: 15259.39 | N92: 9639.37 | P92: 6851.52
B93: Dividend Payable (Investor) | C93: 30938.46 | D93: 30938.46 | E93: 30938.46 | F93: 255821.07 | G93: 0 | H93: 0 | I93: 345874.68 | J93: 1722.47 | K93: 1722.47 | L93: 241815.37 | M93: 0 | N93: 0
B94: Debt Settlement Payable | C94: 0 | D94: 0 | E94: 8199734.7 | F94: 0
B96: Short term Financing | C96: =SUM(C97:C99) -> 22530283 | D96: =SUM(D97:D99) -> 22530283 | E96: =SUM(E97:E99) -> 12530283 | F96: =SUM(F97:F98) -> 2030283.3 | G96: =SUM(G97:G98) -> 2030283.3 | H96: =SUM(H97:H98) -> 2030283.3 | I96: =SUM(I97:I98) -> 2030283.3 | J96: =SUM(J97:J98) -> 2030283.3 | K96: =SUM(K97:K98) -> 2030283.3 | L96: =SUM(L97:L98) -> 2030283.3 | M96: =SUM(M97:M98) -> 2030283.3 | N96: =+N98+N97 -> 2030283.3 | P96: 2239362.4
B97: Interest payable (Al-Raeda) | C97: 30283.31 | D97: 30283.31 | E97: 30283.31 | F97: 30283.31 | G97: 30283.31 | H97: 30283.31 | I97: 30283.31 | J97: 30283.31 | K97: 30283.31 | L97: 30283.31 | M97: 30283.31 | N97: 30283.31 | P97: 33956.18
B98: Short-term Financing (Al Raedah) | C98: 2000000 | D98: 2000000 | E98: 2000000 | F98: 2000000 | G98: 2000000 | H98: 2000000 | I98: 2000000 | J98: 2000000 | K98: 2000000 | L98: 2000000 | M98: 2000000 | N98: 2000000 | P98: 2205406.3
B99: Arbah Murabaha Facility | C99: 20500000 | D99: 20500000 | E99: 10500000
B102: TOTAL CURRENT LIABILITIES | C102: =+C96+C77 -> 24196230 | D102: =+D96+D77 -> 23897876 | E102: =+E96+E77 -> 21909581 | F102: =+F96+F77 -> 3551495.7 | G102: =+G96+G77 -> 3602531 | H102: =+H96+H77 -> 3632153.9 | I102: =+I96+I77 -> 4510758.7 | J102: =+J96+J77 -> 3234611.8 | ... N102: =+N96+N77 -> 2990104.2 | P102: 3711755.5
B105: Related parties Loan | C105: 24463392 | D105: 24413927 | E105: 24976427 | F105: 32976427 | G105: 32976427 | H105: 32976427 | I105: 32976427 | J105: 28855927 | K105: 28855927 | L105: 28855927 | M105: 28855927 | N105: 25860319 | P105: 25111418
B107: External Debt Investor | C107: 1186567.2 | D107: 1186567.2 | E107: 1186567.2 | F107: 1186567.2 | G107: 1186567.2 | H107: 1186567.2 | I107: 1186567.2 | J107: 1186567.2 | K107: 1186567.2 | L107: 1186567.2 | M107: 0 | N107: 0 | P107: 0
B109: End of Service Indemnity | C109: 139978.12 | D109: 33406.83 | E109: 33406.83 | F109: 33406.83 | G109: 33406.83 | H109: 33406.83 | I109: 33406.83 | J109: 33406.83 | K109: 33406.83 | L109: 33406.83 | M109: 33406.83 | N109: 33406.83 | P109: 33406.83
B111: TOTAL LONG-TERM LIABILITIES | C111: =+C109+C105+C107 -> 25789938 | D111: =+D109+D105+D107 -> 25633901 | E111: =+E109+E105+E107 -> 26196401 | F111: =+F109+F105+F107 -> 34196401 | G111: =+G109+G105+G107 -> 34196401 | H111: =+H109+H105+H107 -> 34196401 | I111: =+I109+I105+I107 -> 34196401 | J111: =+J109+J105+J107 -> 30075901 | ... N111: =+N109+N105+N107 -> 25893726 | P111: 25144824
K112: =+J112-J113 -> 0
B114: Equity Financing | C114: 0 | D114: 0 | E114: 0 | F114: 0 | G114: 0 | H114: 0 | I114: 0 | J114: 0 | K114: 0 | L114: 0 | M114: 0 | N114: 0
B116: Contribution from Owners | C116: 25000 | D116: 25000 | E116: 25000 | F116: 25000 | G116: 25000 | H116: 25000 | I116: 25000 | J116: 25000 | K116: 25000 | L116: 25000 | M116: 25000 | N116: 25000 | P116: 25000
B118: Statutory Reserve | C118: 7500 | D118: 7500 | E118: 7500 | F118: 7500 | G118: 7500 | H118: 7500 | I118: 7500 | J118: 7500 | K118: 7500 | L118: 7500 | M118: 7500 | N118: 7500 | P118: 7500
B120: Profit & Loss for the period | C120: 94209.46 | D120: 750.48 | E120: -37846.24 | F120: 349270.76 | G120: 612459.33 | H120: 787436.18 | I120: 483903.37 | J120: 336609.9 | K120: 240145.48 | L120: 337938.88 | M120: 51497.22 | N120: -68203.81 | P120: 1192072.3
B122: Retained Earnings/(Accumulated Losses) | C122: 1261836.2 | D122: 1261836.2 | E122: 1261836.2 | F122: 1261836.2 | G122: 1261836.2 | H122: 1261836.2 | I122: 1261836.2 | J122: 1261836.2 | K122: 1261836.2 | L122: 1261836.2 | M122: 1261836.2 | N122: 1261836.2 | P122: 243473.5
B124: TOTAL OWNER'S EQUITY | C124: =+C116+C118+C120+C122 -> 1388545.7 | D124: =+D116+D118+D120+D122 -> 1295086.7 | E124: =+E116+E118+E120+E122 -> 1256490 | F124: =+F116+F118+F120+F122 -> 1643607 | G124: =+G116+G118+G120+G122 -> 1906795.6 | H124: =+H116+H118+H120+H122 -> 2081772.4 | I124: =+I116+I118+I120+I122 -> 1778239.6 | J124: =+J116+J118+J120+J122 -> 1630946.1 | ... N124: =+N116+N118+N120+N122 -> 1226132.4 | P124: 1468045.8
B127: TOTAL LIABILITIES & EQUITY | C127: =+C124+C102+C111 -> 51374713 | D127: =+D124+D102+D111 -> 50826864 | E127: =+E124+E102+E111 -> 49362472 | F127: =+F124+F102+F111 -> 39391503 | G127: =+G124+G102+G111 -> 39705727 | H127: =+H124+H102+H111 -> 39910327 | I127: =+I124+I102+I111 -> 40485399 | J127: =+J124+J102+J111 -> 34941459 | ... N127: =+N124+N102+N111 -> 30109963 | P127: =+P124+P102+P111+P116 -> 30349626
D128: =+D127-D72 -> 0.0099999905 | E128: =+E127-E72 -> 0.0099999979 | F128: =+F127-F72 -> 0.0099999979 | G128: =+G127-G72 -> 0.0099999979

Sheet IS Dec USA
B7: INCOME STATEMENT (US SAR) | C7: YTD | D7: Q4 | E7: MTD | F7: MTD | G7: MTD | H7: Q3 | I7: MTD | J7: MTD | K7: MTD | L7: Q2 | M7: MTD | N7: MTD | O7: MTD | P7: Q1 | Q7: MTD | R7: MTD | S7: MTD
B8: FOR THE PERIOD 31st December 2024 | C8: 45657 | D8: 2024 | E8: 45657 | F8: 45626 | G8: 45596 | H8: 2024 | I8: 45565 | J8: 45535 | K8: 45504 | L8: 2024 | M8: 45473 | N8: 45443 | O8: 45412 | P8: 2024 | Q8: 45382 | R8: 45350 | S8: 45322
B10: Sales | C10: =SUM(D10:S10)-P10-L10-H10-D10 -> 0 | D10: =SUM(E10:G10) -> 0 | H10: =SUM(I10:K10) -> 0 | I10: 0 | J10: 0 | K10: 0 | L10: =SUM(M10:O10) -> 0 | N10: 0 | O10: 0 | P10: =SUM(Q10:S10) -> 0
B11: Cost of Goods Sold | C11: =SUM(D11:S11)-P11-L11-H11-D11 -> 0 | D11: =SUM(E11:G11) -> 0 | H11: =SUM(I11:K11) -> 0 | I11: 0 | J11: 0 | K11: 0 | L11: =SUM(M11:O11) -> 0 | N11: 0 | O11: 0 | P11: =SUM(Q11:S11) -> 0
B12: Purchase Discounts | C12: =SUM(D12:S12)-P12-L12-H12-D12 -> 0 | D12: =SUM(E12:G12) -> 0 | H12: =SUM(I12:K12) -> 0 | I12: 0 | J12: 0 | K12: 0 | L12: =SUM(M12:O12) -> 0 | N12: 0 | O12: 0 | P12: =SUM(Q12:S12) -> 0 | R12: 0 | S12: 0
B13: Gross Profit / (Loss) | C13: =+C10-C11 -> 0 | D13: =+D10-D11 -> 0 | E13: =+E10-E11 -> 0 | F13: =+F10-F11 -> 0 | G13: =+G10-G11 -> 0 | H13: =+H10-H11 -> 0 | I13: =+I10-I11 -> 0 | J13: =+J10-J11 -> 0 | ... S13: =+S10-S11 -> 0
B14: Consultation Income | C14: =+D14+H14+L14+P14 -> 0 | D14: =SUM(E14:G14) -> 0 | H14: =SUM(I14:K14) -> 0 | I14: 0 | J14: 0 | K14: 0 | L14: =SUM(M14:O14) -> 0 | N14: 0 | O14: 0 | P14: =SUM(Q14:S14) -> 0 | R14: 0 | S14: 0
B15: Gross Income | C15: =+D15+H15+L15+P15 -> 0 | D15: =SUM(E15:G15) -> 0 | E15: =+E14+E13 -> 0 | F15: =+F14+F13 -> 0 | G15: =+G14+G13 -> 0 | H15: =SUM(I15:K15) -> 0 | I15: =+I14+I13 -> 0 | J15: =+J14+J13 -> 0 | K15: =+K14+K13 -> 0 | L15: =SUM(M15:O15) -> 0 | M15: =+M14+M13 -> 0 | N15: =+N14+N13 -> 0 | O15: =+O14+O13 -> 0 | P15: =SUM(Q15:S15) -> 0 | Q15: =+Q14+Q13 -> 0 | R15: =+R14+R13 -> 0 | S15: =+S14+S13 -> 0
B17: General and Administrative Expenses | C17: =SUM(C18:C31) -> 317021.54 | D17: =SUM(D18:D31) -> 115113.19 | E17: =SUM(E18:E31) -> 33034.48 | F17: =SUM(F18:F31) -> 44311.49 | G17: =SUM(G18:G31) -> 37767.22 | H17: =SUM(H18:H31) -> 77767.64 | I17: =SUM(I18:I31) -> 34142.11 | J17: =SUM(J18:J31) -> 21961.48 | ... S17: =SUM(S18:S31) -> 17457.23
B18: Bad Debt | C18: =SUM(D18:S18)-P18-L18-H18-D18 -> 0 | D18: =SUM(E18:G18) -> 0 | E18: 0 | F18: 0 | H18: =SUM(I18:K18) -> 0 | I18: 0 | J18: 0 | K18: 0 | L18: =SUM(M18:O18) -> 0 | N18: 0 | O18: 0 | P18: =SUM(Q18:S18) -> 0 | R18: 0 | S18: 0
B19: Bank Fees and Charges | C19: =SUM(D19:S19)-P19-L19-H19-D19 -> 17230.24 | D19: =SUM(E19:G19) -> 4537.66 | E19: 2027.25 | F19: 434.05 | G19: 2076.36 | H19: =SUM(I19:K19) -> 4386.01 | I19: 647.84 | J19: 1416.04 | K19: 2322.13 | L19: =SUM(M19:O19) -> 5055.6 | M19: 874.61 | N19: 2342.25 | O19: 1838.74 | P19: =SUM(Q19:S19) -> 3250.97 | Q19: 770.09 | R19: 1035.89 | S19: 1444.99
B20: Office Supplies | C20: =SUM(D20:S20)-P20-L20-H20-D20 -> 28437.69 | D20: =SUM(E20:G20) -> 0 | E20: 0 | F20: 0 | H20: =SUM(I20:K20) -> 3082.46 | I20: 0 | J20: 3082.46 | K20: 0 | L20: =SUM(M20:O20) -> 15407.8 | N20: 0 | O20: 15407.8 | P20: =SUM(Q20:S20) -> 9947.43 | Q20: 2311.17 | R20: 3758 | S20: 3878.26
B21: Office Utilities - Electricity/Water/Janitorial | C21: =SUM(D21:S21)-P21-L21-H21-D21 -> 0 | D21: =SUM(E21:G21) -> 0 | E21: 0 | H21: =SUM(I21:K21) -> 0 | I21: 0 | J21: 0 | K21: 0 | L21: =SUM(M21:O21) -> 0 | M21: 0 | N21: 0 | O21: 0 | P21: =SUM(Q21:S21) -> 0 | R21: 0 | S21: 0
B22: Office Equipment Expensed under Sect 1.263(a)-1(f) | C22: =SUM(D22:S22)-P22-L22-H22-D22 -> 2963.41 | D22: =SUM(E22:G22) -> 0 | E22: 0 | H22: =SUM(I22:K22) -> 0 | I22: 0 | J22: 0 | K22: 0 | L22: =SUM(M22:O22) -> 0 | M22: 0 | N22: 0 | O22: 0 | P22: =SUM(Q22:S22) -> 2963.41 | R22: 2963.41 | S22: 0
B23: Travel Expense | C23: =SUM(D23:S23)-P23-L23-H23-D23 -> 8231.25 | D23: =SUM(E23:G23) -> 0 | E23: 0 | H23: =SUM(I23:K23) -> 0 | I23: 0 | J23: 0 | K23: 0 | L23: =SUM(M23:O23) -> 581.28 | M23: 308.16 | N23: 0 | O23: 273.12 | P23: =SUM(Q23:S23) -> 7649.97 | Q23: 814.47 | R23: 6835.5 | S23: 0
B24: Printing and Stationery | C24: =SUM(D24:S24)-P24-L24-H24-D24 -> 0 | D24: =SUM(E24:G24) -> 0 | E24: 0 | H24: =SUM(I24:K24) -> 0 | I24: 0 | J24: 0 | K24: 0 | L24: =SUM(M24:O24) -> 0 | N24: 0 | O24: 0 | P24: =SUM(Q24:S24) -> 0 | R24: 0 | S24: 0
B25: Rent Expense (G&A) | C25: =SUM(D25:S25)-P25-L25-H25-D25 -> 0 | D25: =SUM(E25:G25) -> 0 | E25: 0 | H25: =SUM(I25:K25) -> 0 | I25: 0 | J25: 0 | K25: 0 | L25: =SUM(M25:O25) -> 0 | N25: 0 | O25: 0 | P25: =SUM(Q25:S25) -> 0 | R25: 0 | S25: 0
B26: Meals and Entertainment | C26: =SUM(D26:S26)-P26-L26-H26-D26 -> 7229.12 | D26: =SUM(E26:G26) -> 0 | E26: 0 | H26: =SUM(I26:K26) -> 3196.93 | I26: 202.7 | J26: 245.74 | K26: 2748.49 | L26: =SUM(M26:O26) -> 0 | N26: 0 | O26: 0 | P26: =SUM(Q26:S26) -> 4032.19 | R26: 198.65 | S26: 3833.54
B27: Audit & Consultancy expense | C27: =SUM(D27:S27)-P27-L27-H27-D27 -> 0 | D27: =SUM(E27:G27) -> 0 | E27: 0 | H27: =SUM(I27:K27) -> 0 | I27: 0 | J27: 0 | K27: 0 | L27: =SUM(M27:O27) -> 0 | N27: 0 | O27: 0 | P27: =SUM(Q27:S27) -> 0 | R27: 0 | S27: 0
B28: Communication Exp - Mobile & Internet | C28: =SUM(D28:S28)-P28-L28-H28-D28 -> 852.62 | D28: =SUM(E28:G28) -> 0 | E28: 0 | H28: =SUM(I28:K28) -> 346.26 | I28: 288.54 | J28: 0 | K28: 57.72 | L28: =SUM(M28:O28) -> 412.78 | M28: 115.45 | N28: 115.48 | O28: 181.85 | P28: =SUM(Q28:S28) -> 93.58 | Q28: 93.58 | R28: 0 | S28: 0
B29: Subscriptions & Memberships | C29: =SUM(D29:S29)-P29-L29-H29-D29 -> 244247.23 | D29: =SUM(E29:G29) -> 108883.98 | E29: 29315.68 | F29: 43877.44 | G29: 35690.86 | H29: =SUM(I29:K29) -> 60617.55 | I29: 26864.6 | J29: 17217.24 | K29: 16535.71 | L29: =SUM(M29:O29) -> 44868.96 | M29: 19305.83 | N29: 11534.28 | O29: 14028.85 | P29: =SUM(Q29:S29) -> 29876.74 | Q29: 10848.96 | R29: 10727.34 | S29: 8300.44
B30: Penny Difference | C30: =SUM(D30:S30)-P30-L30-H30-D30 -> 0 | E30: 0 | I30: 0 | J30: 0 | K30: 0 | N30: 0 | O30: 0 | P30: =SUM(Q30:S30) -> 0 | Q30: 0 | R30: 0 | S30: 0
B31: Low Value Assets | C31: =SUM(D31:S31)-P31-L31-H31-D31 -> 7829.98 | D31: =SUM(E31:G31) -> 1691.55 | E31: 1691.55 | H31: =SUM(I31:K31) -> 6138.43 | I31: 6138.43 | J31: 0 | K31: 0 | L31: =SUM(M31:O31) -> 0 | M31: 0 | N31: 0 | O31: 0 | P31: =SUM(Q31:S31) -> 0 | Q31: 0 | R31: 0 | S31: 0
B32: Charity | C32: =SUM(D32:S32)-P32-L32-H32-D32 -> 0 | D32: =SUM(E32:G32) -> 0
B33: Witholding Tax | C33: =SUM(D33:S33)-P33-L33-H33-D33 -> 0 | D33: =SUM(E33:G33) -> 0
B34: Selling Expenses | C34: =SUM(C35:C43) -> 179659.18 | D34: =SUM(E34:G34) -> 73090.28 | E34: =SUM(E35:E43) -> 29936.94 | F34: =SUM(F35:F43) -> 32160.56 | G34: =SUM(G35:G43) -> 10992.78 | H34: =SUM(I34:K34) -> 62020.56 | I34: =SUM(I35:I43) -> 40990.65 | J34: =SUM(J35:J43) -> 9457.6 | K34: =SUM(K35:K43) -> 11572.31 | L34: =SUM(M34:O34) -> 24919.87 | M34: =SUM(M35:M43) -> 4320.01 | N34: =SUM(N35:N43) -> 13096.29 | O34: =SUM(O35:O43) -> 7503.57 | P34: =SUM(Q34:S34) -> 19628.47 | Q34: =SUM(Q35:Q43) -> 11296.27 | R34: =SUM(R35:R43) -> 3875.59 | S34: =SUM(S35:S43) -> 4456.61
B35: Business travel expenses | C35: =SUM(D35:S35)-P35-L35-H35-D35 -> 14193.81 | D35: =SUM(E35:G35) -> 37.58 | E35: 37.58 | H35: =SUM(I35:K35) -> 2342.43 | I35: 0 | J35: 0 | K35: 2342.43 | L35: =SUM(M35:O35) -> 5343.88 | M35: 0 | N35: 2912.45 | O35: 2431.43 | P35: =SUM(Q35:S35) -> 6469.92 | Q35: 6469.92 | R35: 0 | S35: 0
B36: Collection Commission | C36: =SUM(D36:S36)-P36-L36-H36-D36 -> 0 | D36: =SUM(E36:G36) -> 0 | E36: 0 | H36: =SUM(I36:K36) -> 0 | I36: 0 | J36: 0 | K36: 0 | L36: =SUM(M36:O36) -> 0 | N36: 0 | O36: 0 | P36: =SUM(Q36:S36) -> 0 | R36: 0 | S36: 0
B37: Dinar commission | C37: =SUM(D37:S37)-P37-L37-H37-D37 -> 0 | D37: =SUM(E37:G37) -> 0 | E37: 0 | H37: =SUM(I37:K37) -> 0 | I37: 0 | J37: 0 | K37: 0 | L37: =SUM(M37:O37) -> 0 | N37: 0 | O37: 0 | P37: =SUM(Q37:S37) -> 0 | R37: 0 | S37: 0
B38: New customer commission | C38: =SUM(D38:S38)-P38-L38-H38-D38 -> 0 | D38: =SUM(E38:G38) -> 0 | E38: 0 | H38: =SUM(I38:K38) -> 0 | I38: 0 | J38: 0 | K38: 0 | L38: =SUM(M38:O38) -> 0 | N38: 0 | O38: 0 | P38: =SUM(Q38:S38) -> 0 | R38: 0 | S38: 0
B39: Cash Purchase - Backend Margin | E39: 0 | I39: 0 | J39: 0 | K39: 0 | L39: =SUM(M39:O39) -> 0
B40: Cash Sale Commission | E40: 0 | I40: 0 | J40: 0 | K40: 0 | L40: =SUM(M40:O40) -> 0
B41: Fuel/Mileage Expenses | C41: =SUM(D41:S41)-P41-L41-H41-D41 -> 0 | D41: =SUM(E41:G41) -> 0 | E41: 0 | H41: =SUM(I41:K41) -> 0 | I41: 0 | J41: 0 | K41: 0 | L41: =SUM(M41:O41) -> 0 | N41: 0 | O41: 0 | P41: =SUM(Q41:S41) -> 0 | R41: 0 | S41: 0
B42: Marketing & Advertising | C42: =SUM(D42:S42)-P42-L42-H42-D42 -> 165465.37 | D42: =SUM(E42:G42) -> 73052.7 | E42: 29899.36 | F42: 32160.56 | G42: 10992.78 | H42: =SUM(I42:K42) -> 59678.13 | I42: 40990.65 | J42: 9457.6 | K42: 9229.88 | L42: =SUM(M42:O42) -> 19575.99 | M42: 4320.01 | N42: 10183.84 | O42: 5072.14 | P42: =SUM(Q42:S42) -> 13158.55 | Q42: 4826.35 | R42: 3875.59 | S42: 4456.61
B43: Trade Credit Insurance | C43: =SUM(D43:S43)-P43-L43-H43-D43 -> 0 | D43: =SUM(E43:G43) -> 0 | E43: 0 | H43: =SUM(I43:K43) -> 0 | I43: 0 | J43: 0 | K43: 0 | L43: =SUM(M43:O43) -> 0 | N43: 0 | O43: 0 | P43: =SUM(Q43:S43) -> 0 | R43: 0 | S43: 0
B44: Legal & Consultation Expenses | C44: =SUM(C45:C47) -> 504511.88 | D44: =SUM(E44:G44) -> 214570.64 | E44: =SUM(E45:E47) -> 79135.86 | F44: =SUM(F45:F47) -> 26923.49 | G44: =SUM(G45:G47) -> 108511.29 | H44: =SUM(I44:K44) -> 118231.98 | I44: =SUM(I45:I47) -> 27099.12 | J44: =SUM(J45:J47) -> 49594.14 | K44: =SUM(K45:K47) -> 41538.72 | L44: =SUM(M44:O44) -> 61290.31 | M44: =SUM(M45:M47) -> 17127.84 | N44: =SUM(N45:N47) -> 20851.49 | O44: =SUM(O45:O47) -> 23310.98 | P44: =SUM(Q44:S44) -> 110418.95 | Q44: =SUM(Q45:Q47) -> 13644.14 | R44: =SUM(R45:R47) -> 57587.66 | S44: =SUM(S45:S47) -> 39187.15
B45: Consultant Expense | C45: =SUM(D45:S45)-P45-L45-H45-D45 -> 441363.3 | D45: =SUM(E45:G45) -> 201530.87 | E45: 74891.99 | F45: 22525.54 | G45: 104113.34 | H45: =SUM(I45:K45) -> 105445.39 | I45: 22970.96 | J45: 45311.9 | K45: 37162.53 | L45: =SUM(M45:O45) -> 46365.61 | M45: 12845.6 | N45: 16569.25 | O45: 16950.76 | P45: =SUM(Q45:S45) -> 88021.43 | Q45: 11297.91 | R45: 39882.6 | S45: 36840.92
B46: Government & Compliance Expense | C46: =SUM(D46:S46)-P46-L46-H46-D46 -> 0 | D46: =SUM(E46:G46) -> 0 | E46: 0 | H46: =SUM(I46:K46) -> 0 | I46: 0 | J46: 0 | K46: 0 | L46: =SUM(M46:O46) -> 0 | M46: 0 | N46: 0 | O46: 0 | P46: =SUM(Q46:S46) -> 0 | R46: 0 | S46: 0
B47: Legal | C47: =SUM(D47:S47)-P47-L47-H47-D47 -> 63148.58 | D47: =SUM(E47:G47) -> 13039.77 | E47: 4243.87 | F47: 4397.95 | G47: 4397.95 | H47: =SUM(I47:K47) -> 12786.59 | I47: 4128.16 | J47: 4282.24 | K47: 4376.19 | L47: =SUM(M47:O47) -> 14924.7 | M47: 4282.24 | N47: 4282.24 | O47: 6360.22 | P47: =SUM(Q47:S47) -> 22397.52 | Q47: 2346.23 | R47: 17705.06 | S47: 2346.23
B48: Depreciation Expenses | C48: =SUM(C49:C51) -> 3589.2 | D48: =SUM(E48:G48) -> 1794.6 | E48: =SUM(E49:E51) -> 598.2 | F48: =SUM(F49:F51) -> 598.2 | G48: =SUM(G49:G51) -> 598.2 | H48: =SUM(I48:K48) -> 1794.6 | I48: =SUM(I49:I51) -> 598.2 | J48: =SUM(J49:J51) -> 598.2 | K48: =SUM(K49:K51) -> 598.2 | L48: =SUM(M48:O48) -> 0 | M48: =SUM(M49:M51) -> 0 | N48: =SUM(N49:N51) -> 0 | O48: =SUM(O49:O51) -> 0 | P48: =SUM(Q48:S48) -> 0 | Q48: =SUM(Q49:Q51) -> 0 | R48: =SUM(R49:R51) -> 0 | S48: =SUM(S49:S51) -> 0
B49: Depreciation - Furniture & Fixture | C49: =SUM(D49:S49)-P49-L49-H49-D49 -> 0 | D49: =SUM(E49:G49) -> 0 | E49: 0 | H49: =SUM(I49:K49) -> 0 | I49: 0 | J49: 0 | K49: 0 | L49: =SUM(M49:O49) -> 0 | N49: 0 | O49: 0 | P49: =SUM(Q49:S49) -> 0 | R49: 0 | S49: 0
B50: Depreciation - Motor Vehicle | C50: =SUM(D50:S50)-P50-L50-H50-D50 -> 0 | D50: =SUM(E50:G50) -> 0 | E50: 0 | H50: =SUM(I50:K50) -> 0 | I50: 0 | J50: 0 | K50: 0 | L50: =SUM(M50:O50) -> 0 | N50: 0 | O50: 0 | P50: =SUM(Q50:S50) -> 0 | R50: 0 | S50: 0
B51: Depreciation - Office Equipment's | C51: =SUM(D51:S51)-P51-L51-H51-D51 -> 3589.2 | D51: =SUM(E51:G51) -> 1794.6 | E51: 598.2 | F51: 598.2 | G51: 598.2 | H51: =SUM(I51:K51) -> 1794.6 | I51: 598.2 | J51: 598.2 | K51: 598.2 | L51: =SUM(M51:O51) -> 0 | N51: 0 | O51: 0 | P51: =SUM(Q51:S51) -> 0 | R51: 0 | S51: 0
B52: Personnel Expenses | C52: =SUM(C53:C69) -> 1863026.3 | D52: =SUM(D53:D69) -> 443337.68 | E52: =SUM(E53:E69) -> 145009.16 | F52: =SUM(F53:F69) -> 144210.47 | G52: =SUM(G53:G69) -> 154118.05 | H52: =SUM(H53:H69) -> 0 | I52: =SUM(I53:I69) -> 162868.81 | J52: =SUM(J53:J69) -> 178422.87 | ... S52: =SUM(S53:S69) -> 105383.12
B53: Employee Insurance | C53: =SUM(D53:S53)-P53-L53-H53-D53 -> 0 | D53: =SUM(E53:G53) -> 0 | E53: 0 | H53: =SUM(I53:K53) -> 0 | I53: 0 | J53: 0 | K53: 0 | L53: =SUM(M53:O53) -> 0 | N53: 0 | O53: 0 | P53: =SUM(Q53:S53) -> 0 | R53: 0 | S53: 0
B54: Leave Pay Expense | D54: =SUM(E54:G54) -> 0 | E54: 0 | I54: 0 | J54: 0 | K54: 0
B55: Employee Referral Allowance | C55: =SUM(D55:S55)-P55-L55-H55-D55 -> 682.08 | D55: =SUM(E55:G55) -> 0 | E55: 0 | H55: =SUM(I55:K55) -> 0 | I55: 0 | J55: 0 | K55: 0 | L55: =SUM(M55:O55) -> 682.08 | N55: 682.08 | O55: 0 | P55: =SUM(Q55:S55) -> 0 | R55: 0 | S55: 0
B56: Maintenance Allowance | C56: =SUM(D56:S56)-P56-L56-H56-D56 -> 0 | D56: =SUM(E56:G56) -> 0 | E56: 0 | I56: 0 | J56: 0 | K56: 0 | L56: =SUM(M56:O56) -> 0 | N56: 0 | O56: 0 | P56: =SUM(Q56:S56) -> 0 | R56: 0 | S56: 0
B57: Employee Related Govt Fees | C57: =SUM(D57:S57)-P57-L57-H57-D57 -> 7500.1 | D57: =SUM(E57:G57) -> 7500.1 | E57: 0 | F57: 7500.1 | I57: 0 | J57: 0 | K57: 0 | L57: =SUM(M57:O57) -> 0 | N57: 0 | O57: 0 | Q57: 0 | R57: 0 | S57: 0
B58: Telecome Allowance | C58: =SUM(D58:S58)-P58-L58-H58-D58 -> 647.88 | D58: =SUM(E58:G58) -> 187.9 | E58: 0 | F58: 93.95 | G58: 93.95 | I58: 93.95 | J58: 93.95 | K58: 93.95 | L58: =SUM(M58:O58) -> 178.13 | M58: 93.95 | N58: 84.18 | O58: 0 | P58: =SUM(Q58:S58) -> 0 | R58: 0 | S58: 0
B59: US Employer Taxes | C59: =SUM(D59:S59)-P59-L59-H59-D59 -> 35255.31 | D59: =SUM(E59:G59) -> 12383.44 | E59: 3054.31 | F59: 3445.67 | G59: 5883.46 | I59: 4584.32 | J59: 4830.81 | K59: 4713.37 | L59: =SUM(M59:O59) -> 8743.37 | M59: 4247.67 | N59: 4495.7 | O59: 0 | P59: =SUM(Q59:S59) -> 0 | R59: 0 | S59: 0
B60: GOSI | C60: =SUM(D60:S60)-P60-L60-H60-D60 -> 0 | D60: =SUM(E60:G60) -> 0 | E60: 0 | I60: 0 | J60: 0 | K60: 0 | L60: =SUM(M60:O60) -> 0 | N60: 0 | O60: 0 | P60: =SUM(Q60:S60) -> 0 | R60: 0 | S60: 0
B61: HUMAN RESOUACES DEVELOPMENT FUND | C61: =SUM(D61:S61)-P61-L61-H61-D61 -> 0 | D61: =SUM(E61:G61) -> 0 | E61: 0 | I61: 0 | J61: 0 | K61: 0 | L61: =SUM(M61:O61) -> 0 | N61: 0 | O61: 0 | P61: =SUM(Q61:S61) -> 0 | R61: 0 | S61: 0
B62: Recruitments & Visas | C62: =SUM(D62:S62)-P62-L62-H62-D62 -> 1681.29 | D62: =SUM(E62:G62) -> 1681.29 | E62: 0 | G62: 1681.29 | I62: 0 | J62: 0 | K62: 0 | L62: =SUM(M62:O62) -> 0 | N62: 0 | O62: 0 | P62: =SUM(Q62:S62) -> 0 | R62: 0 | S62: 0
B63: Bonus | C63: =SUM(D63:S63)-P63-L63-H63-D63 -> 55786.27 | D63: =SUM(E63:G63) -> 100.23 | E63: 0 | G63: 100.23 | I63: 0 | J63: 3758 | K63: 2630.6 | L63: =SUM(M63:O63) -> 26020.39 | M63: 82.68 | N63: 25937.71 | O63: 0 | P63: =SUM(Q63:S63) -> 23277.05 | Q63: 23277.05 | R63: 0 | S63: 0
B64: Salaries - Basic | C64: =SUM(D64:S64)-P64-L64-H64-D64 -> 1748663 | D64: =SUM(E64:G64) -> 417268.28 | E64: 140124.7 | F64: 133133.21 | G64: 144010.37 | I64: 153023.29 | J64: 169176.41 | K64: 175652.73 | L64: =SUM(M64:O64) -> 488331.08 | M64: 169968.86 | N64: 175513.15 | O64: 142849.07 | P64: =SUM(Q64:S64) -> 345211.21 | Q64: 131104.11 | R64: 108723.98 | S64: 105383.12
B65: Salaries - Housing | C65: =SUM(D65:S65)-P65-L65-H65-D65 -> 0 | D65: =SUM(E65:G65) -> 0 | E65: 0 | I65: 0 | J65: 0 | K65: 0 | L65: =SUM(M65:O65) -> 0 | N65: 0 | O65: 0 | P65: =SUM(Q65:S65) -> 0 | Q65: 0 | R65: 0 | S65: 0
B66: Salaries - Others | C66: =SUM(D66:S66)-P66-L66-H66-D66 -> 1589.07 | D66: =SUM(E66:G66) -> 0 | E66: 0 | I66: 0 | J66: 563.7 | K66: 0 | L66: =SUM(M66:O66) -> 0 | N66: 0 | O66: 0 | P66: =SUM(Q66:S66) -> 1025.37 | Q66: 622.51 | R66: 402.86 | S66: 0
B67: Salaries - Transportation | C67: =SUM(D67:S67)-P67-L67-H67-D67 -> 0 | D67: =SUM(E67:G67) -> 0 | E67: 0 | I67: 0 | J67: 0 | K67: 0 | L67: =SUM(M67:O67) -> 0 | N67: 0 | O67: 0 | P67: =SUM(Q67:S67) -> 0 | Q67: 0 | R67: 0 | S67: 0
B68: End Of Service Benefits | C68: =SUM(D68:S68)-P68-L68-H68-D68 -> 9346.15 | D68: =SUM(E68:G68) -> 4178.9 | E68: 1830.15 | G68: 2348.75 | I68: 5167.25 | J68: 0 | K68: 0 | L68: =SUM(M68:O68) -> 0 | N68: 0 | O68: 0 | P68: =SUM(Q68:S68) -> 0 | Q68: 0 | R68: 0 | S68: 0
B69: Staff Education/Growth Allowance | C69: =SUM(D69:S69)-P69-L69-H69-D69 -> 1875.2 | D69: =SUM(E69:G69) -> 37.54 | E69: 0 | F69: 37.54 | I69: 0 | J69: 0 | K69: -169.11 | L69: =SUM(M69:O69) -> 2006.77 | M69: 165.35 | N69: 0 | O69: 1841.42
B70: Operating expenses | C70: =+C52+C48+C44+C34+C17 -> 2867808.1 | D70: =SUM(E70:G70) -> 847906.39 | E70: =+E52+E48+E44+E34+E17 -> 287714.64 | F70: =+F52+F48+F44+F34+F17 -> 248204.21 | G70: =+G52+G48+G44+G34+G17 -> 311987.54 | H70: =SUM(I70:K70) -> 784028 | I70: =+I52+I48+I44+I34+I17 -> 265698.89 | J70: =+J52+J48+J44+J34+J17 -> 260034.29 | K70: =+K52+K48+K44+K34+K17 -> 258294.82 | L70: =SUM(M70:O70) -> 678498.42 | M70: =+M52+M48+M44+M34+M17 -> 216610.41 | N70: =+N52+N48+N44+N34+N17 -> 254652.61 | O70: =+O52+O48+O44+O34+O17 -> 207235.4 | P70: =SUM(Q70:S70) -> 557375.34 | Q70: =+Q52+Q48+Q44+Q34+Q17 -> 194782.35 | R70: =+R52+R48+R44+R34+R17 -> 196108.88 | S70: =+S52+S48+S44+S34+S17 -> 166484.11
B73: Net operating profit / (loss) | C73: =SUM(C13+C14)-C70 -> -2867808.1 | D73: =SUM(E73:G73) -> -847906.39 | E73: =SUM(E13+E14)-E70 -> -287714.64 | F73: =SUM(F13+F14)-F70 -> -248204.21 | G73: =SUM(G13+G14)-G70 -> -311987.54 | H73: =SUM(I73:K73) -> -784028 | I73: =SUM(I13+I14)-I70 -> -265698.89 | J73: =SUM(J13+J14)-J70 -> -260034.29 | K73: =SUM(K13+K14)-K70 -> -258294.82 | L73: =SUM(M73:O73) -> -678498.42 | M73: =SUM(M13+M14)-M70 -> -216610.41 | N73: =SUM(N13+N14)-N70 -> -254652.61 | O73: =SUM(O13+O14)-O70 -> -207235.4 | P73: =SUM(Q73:S73) -> -557375.34 | Q73: =SUM(Q13+Q14)-Q70 -> -194782.35 | R73: =SUM(R13+R14)-R70 -> -196108.88 | S73: =SUM(S13+S14)-S70 -> -166484.11
C75: =SUM(D75:S75)-P75-L75-H75-D75 -> 0
B76: Exchange Gain or Loss | C76: =SUM(D76:S76)-P76-L76-H76-D76 -> -1090.21 | D76: =SUM(E76:G76) -> -1090.21 | E76: 147.97 | F76: -1238.18 | G76: 0 | H76: =SUM(I76:K76) -> -0.05 | I76: 0.02 | J76: -0.02 | K76: -0.05 | L76: =SUM(M76:O76) -> 0.04 | M76: 0.03 | N76: 0 | O76: 0.01 | P76: =SUM(Q76:S76) -> 0.01 | R76: 0.01
C77: =SUM(D77:S77)-P77-L77-H77-D77 -> 0
B78: Gain Or Loss on Disposal | C78: =SUM(D78:S78)-P78-L78-H78-D78 -> 0 | D78: =SUM(E78:G78) -> 0
C80: =SUM(D80:S80)-P80-L80-H80-D80 -> 0
B81: Investor's Profit sharing (Unrealized) | C81: =SUM(D81:S81)-P81-L81-H81-D81 -> 0 | D81: =SUM(E81:G81) -> 0 | F81: 0 | G81: 0 | H81: =SUM(I81:K81) -> 0 | J81: 0 | K81: 0 | L81: =SUM(M81:O81) -> 0 | M81: 0 | N81: 0 | O81: 0 | P81: =SUM(Q81:S81) -> 0 | R81: 0 | S81: 0
C82: =SUM(D82:S82)-P82-L82-H82-D82 -> 0
B83: Short term financing expense (Al-Raeda) | C83: =SUM(D83:S83)-P83-L83-H83-D83 -> 0 | D83: =SUM(E83:G83) -> 0 | H83: =SUM(I83:K83) -> 0 | L83: =SUM(M83:O83) -> 0 | M83: 0 | N83: 0 | O83: 0 | P83: =SUM(Q83:S83) -> 0 | Q83: 0 | R83: 0 | S83: 0
C84: =SUM(D84:S84)-P84-L84-H84-D84 -> 0
B85: Financing expense (Arbah) | C85: =SUM(D85:S85)-P85-L85-H85-D85 -> 0 | D85: =SUM(E85:G85) -> 0
C86: =SUM(D86:S86)-P86-L86-H86-D86 -> 0
B87: Financing expense (STV) | C87: =SUM(D87:S87)-P87-L87-H87-D87 -> -69147.2 | D87: =SUM(E87:G87) -> -69147.2 | E87: -17850.5 | F87: -51296.7
C88: =SUM(D88:S88)-P88-L88-H88-D88 -> 0
B89: Financing Processing Fee Expense | C89: =SUM(D89:S89)-P89-L89-H89-D89 -> 0 | D89: =SUM(E89:G89) -> 0
C90: =SUM(D90:S90)-P90-L90-H90-D90 -> 0
B91: Fundraising Expense | C91: =SUM(D91:S91)-P91-L91-H91-D91 -> -3757.95 | D91: =SUM(E91:G91) -> -3757.95 | E91: -1252.65 | F91: -1252.65 | G91: -1252.65 | H91: =SUM(I91:K91) -> 0 | L91: =SUM(M91:O91) -> 0 | M91: 0 | N91: 0 | O91: 0 | P91: =SUM(Q91:S91) -> 0 | Q91: 0 | R91: 0 | S91: 0
C92: =SUM(D92:S92)-P92-L92-H92-D92 -> 0
B93: Non-operating Income/(Expenses) | C93: =SUM(D93:S93)-P93-L93-H93-D93 -> 0 | D93: =SUM(E93:G93) -> 0 | E93: 0 | F93: 0 | G93: 0 | H93: =SUM(I93:K93) -> 0 | I93: 0 | J93: 0 | K93: 0 | L93: =SUM(M93:O93) -> 0 | M93: 0 | N93: 0 | O93: 0 | P93: =SUM(Q93:S93) -> 0 | Q93: 0 | R93: 0 | S93: 0
C94: =SUM(D94:S94)-P94-L94-H94-D94 -> 0
B95: Zakat / Income Tax | C95: =SUM(D95:S95)-P95-L95-H95-D95 -> 0 | D95: =SUM(E95:G95) -> 0 | E95: 0 | F95: 0 | G95: 0 | H95: 0 | I95: 0 | J95: 0 | K95: 0 | L95: 0 | M95: 0 | N95: 0 | O95: 0 | P95: 0 | Q95: 0 | R95: 0 | S95: 0
B97: Net income / (loss) | C97: =+C73+C83+C93+C95+C81+C76+C91+C87 -> -2941803.5 | D97: =+D73+D83+D93+D95+D81+D76+D91+D89+D87+D85 -> -921901.75 | E97: =+E73+E83+E93+E95+E81+E76+E91+E89+E87+E85 -> -306669.82 | F97: =+F73+F83+F93+F95+F81+F76+F91+F89+F87+F85 -> -301991.74 | G97: =+G73+G83+G93+G95+G81+G76+G91 -> -313240.19 | H97: =+H73+#REF!+H83+H93+H95 -> #REF! | I97: =+I73+I83+I93+I95+I81+I76 -> -265698.87 | J97: =+J73+J83+J93+J95+J81+J76 -> -260034.31 | K97: =+K73+K83+K93+K95+K81+K76 -> -258294.87 | L97: =+L73+L83+L93+L95+L81+L76 -> -678498.38 | M97: =+M73+M83+M93+M95+M81+M76 -> -216610.38 | N97: =+N73+N83+N93+N95+N81+N76 -> -254652.61 | O97: =+O73+O83+O93+O95+O81+O76 -> -207235.39 | P97: =+P73+P83+P93+P95+P81+P76 -> -557375.33 | ... S97: =+S73+S83+S93+S95+S81+S76 -> -166484.11

Sheet BS Dec USA
B6: STATEMENT OF FINANCIAL POSITION (US SAR) | C6: 45657 | D6: 45626 | E6: 45596 | F6: 45565 | G6: 45535 | H6: 45504 | I6: 45473 | J6: 45443 | K6: 45412 | L6: 45382 | M6: 45350 | N6: 45322
B7: As of 31st December 2024
B8: ASSETS
B10: Cash and Bank Balances | C10: =SUM(C11:C25) -> 2008252.4 | D10: =SUM(D11:D25) -> 2359619.8 | E10: =SUM(E11:E25) -> 2572070.2 | F10: =SUM(F11:F25) -> 2993836.8 | G10: =SUM(G11:G25) -> 3243627.6 | H10: =SUM(H11:H25) -> 3565406.1 | I10: =SUM(I11:I25) -> 2938541.7 | J10: =SUM(J11:J25) -> 1566648 | ... N10: =SUM(N11:N25) -> 4667300
B11: ALINMA BILDNW FEE | I11: 0 | J11: 0 | K11: 0 | L11: 0 | M11: 0 | N11: 0
B12: ALINMA BILDNW PROFIT | I12: 0 | J12: 0 | K12: 0 | L12: 0 | M12: 0 | N12: 0
B13: ALINMA CLIENT PROFIT | I13: 0 | J13: 0 | K13: 0 | L13: 0 | M13: 0 | N13: 0
B14: ALINMA DINAR DEALs PROFIT | I14: 0 | J14: 0 | K14: 0 | L14: 0 | M14: 0 | N14: 0
B15: ALINMA DINAR DEALs VAT | I15: 0 | J15: 0 | K15: 0 | L15: 0 | M15: 0 | N15: 0
B16: ALINMA EQUITY | I16: 0 | J16: 0 | K16: 0 | L16: 0 | M16: 0 | N16: 0
B17: ALINMA USD | I17: 0 | J17: 0 | K17: 0 | L17: 0 | M17: 0 | N17: 0
B18: ALINMA VAT | I18: 0 | J18: 0 | K18: 0 | L18: 0 | M18: 0 | N18: 0
B19: ALINMA-DEBT | I19: 0 | J19: 0 | K19: 0 | L19: 0 | M19: 0 | N19: 0
B20: ANB-BILDNW TRADINGCOMPANY | I20: 0 | J20: 0 | K20: 0 | L20: 0 | M20: 0 | N20: 0
B21: Riyad Bank | I21: 0 | J21: 0 | K21: 0 | L21: 0 | M21: 0 | N21: 0
B22: US Checking Account | C22: 2008252.4 | D22: 2359619.8 | E22: 2572070.2 | F22: 2993836.8 | G22: 3243627.6 | H22: 3565406.1 | I22: 2938541.7 | J22: 1566648 | K22: 1911675.5 | L22: 2135188.9 | M22: 2290858.8 | N22: 4663542
B23: ANB Tanmeya Debt A/C
B24: Simplifi
B25: Petty Cash | C25: 0 | F25: 0 | G25: 0 | H25: 0 | I25: 0 | J25: 0 | K25: 0 | L25: 0 | M25: 0 | N25: 3758
B27: Trade Receivables (net) | C27: =SUM(C28:C29) -> 0 | D27: =SUM(D28:D29) -> 0 | E27: =SUM(E28:E29) -> 0 | F27: =SUM(F28:F29) -> 0 | H27: =SUM(H28:H29) -> 0 | I27: =SUM(I28:I29) -> 0 | J27: =SUM(J28:J29) -> 0 | K27: =SUM(K28:K29) -> 0 | L27: =SUM(L28:L29) -> 0 | M27: =SUM(M28:M29) -> 0 | N27: =SUM(N28:N29) -> 0
B28: Trade Receivables - Gross | J28: 0 | K28: 0 | L28: 0 | M28: 0 | N28: 0
B29: Provision for doubtful Accounts | C29: 0 | D29: 0 | E29: 0 | F29: 0 | H29: 0 | I29: 0 | J29: 0 | K29: 0 | L29: 0 | M29: 0 | N29: 0
B31: Prepaid Expenses & Other recievables | C31: =SUM(C32:C43) -> 131186.62 | D31: =SUM(D32:D43) -> 131131.33 | E31: =SUM(E32:E43) -> 142099.49 | F31: =SUM(F32:F43) -> 123074.57 | G31: =SUM(G32:G43) -> 48284.73 | H31: =SUM(H32:H43) -> 1679.89 | I31: =SUM(I32:I43) -> 5808.05 | J31: =SUM(J32:J43) -> 9936.21 | ... N31: =SUM(N32:N43) -> -2192.15
B32: Prepaid Vendors | I32: 0 | J32: 0 | K32: 0 | L32: 0 | M32: 0 | N32: 0
B33: Prepaid Accommodation Rent Expense | I33: 0 | J33: 0 | K33: 0 | L33: 0 | M33: 0 | N33: 0
B34: Prepaid Financing Expense | C34: 71402.05 | D34: 72654.7 | E34: 73907.35 | F34: 75160 | G34: 0 | H34: 0 | I34: 0 | J34: 0 | K34: 0 | L34: 0 | M34: 0 | N34: 0
B35: Prepaid Govt. Legal Expense | I35: 0 | J35: 0 | K35: 0 | L35: 0 | M35: 0 | N35: 0
B36: Prepaid IT Subscriptions Expense | C36: 15798.79 | D36: 10246.98 | E36: 14090.17 | I36: 0 | J36: 0 | K36: 0 | L36: 0 | M36: 0 | N36: 0
B37: Prepaid Office Rent Expense | I37: 0 | J37: 0 | K37: 0 | L37: 0 | M37: 0 | N37: 0
B38: Prepaid Other Expense | C38: 6155.23 | D38: 10399.1 | E38: 14642.97 | F38: 6576.57 | G38: 10704.73 | H38: 1679.89 | I38: 5808.05 | J38: 9936.21 | K38: 14064.37 | L38: -6576.45 | M38: -4384.3 | N38: -2192.15
B39: Fund Raising Expense receivable | C39: 37580 | D39: 37580 | E39: 37580 | F39: 37580 | G39: 37580
B40: Employee Receivable | C40: 250.55 | D40: 250.55 | E40: 1879 | F40: 3758 | G40: 0 | H40: 0 | I40: 0 | J40: 0 | K40: 0 | L40: 0 | M40: 0 | N40: 0
B41: Security deposits | I41: 0 | J41: 0 | K41: 0 | L41: 0 | M41: 0 | N41: 0
B42: Other Receivable
B43: Input VAT | I43: 0 | J43: 0 | K43: 0 | L43: 0 | M43: 0 | N43: 0
B44: Profit Reserve Account (Depsoit)
B46: TOTAL CURRENT ASSETS | C46: =+C31+C10+C27 -> 2139439.1 | D46: =+D31+D10+D27 -> 2490751.1 | E46: =+E31+E10+E27 -> 2714169.7 | F46: =+F31+F10+F27 -> 3116911.4 | G46: =+G31+G10+G27 -> 3291912.4 | H46: =+H31+H10+H27 -> 3567086 | I46: =+I31+I10+I27 -> 2944349.7 | J46: =+J31+J10+J27 -> 1576584.2 | ... N46: =+N31+N10+N27 -> 4665107.8
B49: Fixed Assets (net) | C49: =SUM(C50:C56) -> 10767.83 | D49: =SUM(D50:D57) -> 11366.03 | E49: =SUM(E50:E57) -> 11964.23 | F49: =SUM(F50:F57) -> 12562.43 | G49: =SUM(G50:G57) -> 13160.63 | H49: =SUM(H50:H57) -> 13758.83 | I49: =SUM(I50:I57) -> 0 | J49: =SUM(J50:J57) -> 0 | K49: =SUM(K50:K57) -> 0 | ... N49: =SUM(N50:N57) -> 0
B50: Accumulated Depreciation - Furniture & Fixture | J50: 0 | K50: 0 | L50: 0 | M50: 0 | N50: 0
B51: Accumulated Depreciation - Motor Vehicle | J51: 0 | K51: 0 | L51: 0 | M51: 0 | N51: 0
B52: Accumulated Depreciation - Office Equipment's | C52: -3589.2 | D52: -2991 | E52: -2392.8 | F52: -1794.6 | G52: -1196.4 | H52: -598.2 | J52: 0 | K52: 0 | L52: 0 | M52: 0 | N52: 0
B53: Fixed Assets not in use
B54: Furniture & Fixture | J54: 0 | K54: 0 | L54: 0 | M54: 0 | N54: 0
B55: Motor Vehicle | J55: 0 | K55: 0 | L55: 0 | M55: 0 | N55: 0
B56: Office Equipment | C56: 14357.03 | D56: 14357.03 | E56: 14357.03 | F56: 14357.03 | G56: 14357.03 | H56: 14357.03 | I56: 0 | J56: 0 | K56: 0 | L56: 0 | M56: 0 | N56: 0
B57: Capital Work in Progress
B59: Intercompany | C59: =SUM(C60:C63) -> 24466079 | D59: =SUM(D60:D63) -> 24466079 | E59: =SUM(E60:E63) -> 25029779 | F59: =SUM(F60:F63) -> 25029779 | G59: =SUM(G60:G63) -> 25029779 | H59: =SUM(H60:H63) -> 25029779 | I59: =SUM(I60:I63) -> 25027660 | J59: =SUM(J60:J63) -> 20906385 | ... N59: =SUM(N60:N63) -> 18651585
B60: Buildnow Inc. (US)
B61: Buildnow Tech BD | C61: 2686.97 | D61: 2686.97 | E61: 2686.97 | F61: 2686.97 | G61: 2686.97 | H61: 2686.97 | I61: 567.46 | J61: 567.46 | K61: 567.46 | L61: 567.46 | M61: 567.46 | N61: 567.46
B62: Buildnow Trading Co (KSA) | C62: 24463392 | D62: 24463392 | E62: 25027092 | F62: 25027092 | G62: 25027092 | H62: 25027092 | I62: 25027092 | J62: 20905818 | K62: 20905818 | L62: 20905818 | M62: 20905818 | N62: 18651018
B63: MISA KSA
B65: Investment in Subsidiaries | C65: =SUM(C66:C67) -> 3720.42 | D65: =SUM(D66:D67) -> 3720.42 | E65: =SUM(E66:E67) -> 3720.42 | F65: =SUM(F66:F67) -> 3720.42 | G65: =SUM(G66:G67) -> 3720.42 | H65: =SUM(H66:H67) -> 3720.42 | I65: =SUM(I66:I67) -> 3720.42 | J65: =SUM(J66:J67) -> 3720.42 | ... N65: =SUM(N66:N67) -> 3720.42
B66: Buildnow BD Technology Subsidiary | C66: 3720.42 | D66: 3720.42 | E66: 3720.42 | F66: 3720.42 | G66: 3720.42 | H66: 3720.42 | I66: 3720.42 | J66: 3720.42 | K66: 3720.42 | L66: 3720.42 | M66: 3720.42 | N66: 3720.42
B69: TOTAL NON CURRENT ASSETS | C69: =+C59+C49+C65 -> 24480568 | D69: =+D59+D49+D65 -> 24481166 | E69: =+E59+E49+E65 -> 25045464 | F69: =+F59+F49+F65 -> 25046062 | G69: =+G59+G49+G65 -> 25046661 | H69: =+H59+H49+H65 -> 25047259 | I69: =+I59+I49+I65 -> 25031380 | J69: =+J59+J49+J65 -> 20910106 | ... N69: =+N59+N49+N65 -> 18655306
B72: TOTAL ASSETS | C72: =+C69+C46 -> 26620007 | D72: =+D69+D46 -> 26971917 | E72: =+E69+E46 -> 27759634 | F72: =+F69+F46 -> 28162974 | G72: =+G69+G46 -> 28338573 | H72: =+H69+H46 -> 28614345 | I72: =+I69+I46 -> 27975730 | J72: =+J69+J46 -> 22486690 | ... N72: =+N69+N46 -> 23320413
B75: LIABILITIES & OWNER'S EQUITY
B77: Other Payables and Accruals | C77: =SUM(C78:C94) -> 17851.76 | D77: =SUM(D78:D92) -> 70460.21 | E77: =SUM(E78:E92) -> 1.28 | F77: =SUM(F78:F92) -> 105132.96 | G77: =SUM(G78:G92) -> 18039.65 | H77: =SUM(H78:H92) -> 70384.81 | I77: =SUM(I78:I92) -> 175571.02 | J77: =SUM(J78:J92) -> 90420.31 | K77: =SUM(K78:K92) -> 184923.33 | L77: =SUM(L78:L92) -> 180560.52 | M77: =SUM(M78:M93) -> 143640.25 | N77: =SUM(N78:N92) -> 71364.71
B78: Zakat Provision | I78: 0 | J78: 0 | K78: 0 | L78: 0 | M78: 0 | N78: 0
B79: Misc. Payables | I79: 0 | J79: 0 | K79: 0 | L79: 0 | M79: 0 | N79: 0
B80: Other Payables | I80: 0 | J80: 0 | K80: 0 | L80: 0 | M80: 0 | N80: 0
B81: Unearned Revenue | I81: 0 | J81: 0 | K81: 0 | L81: 0 | M81: 0 | N81: 0
B82: Employee Payable | I82: 0 | J82: 0 | K82: 0 | L82: 0 | M82: 0 | N82: 0
B83: Accounts Payable | I83: 0 | J83: 0 | K83: 0 | L83: 0 | M83: 0 | N83: 0
B84: Accrued Expenses | I84: 0 | J84: 0 | K84: 0 | L84: 0 | M84: 0 | N84: 0
B85: VAT Payable (GAZT) | I85: 0 | J85: 0 | K85: 0 | L85: 0 | M85: 0 | N85: 0
B86: Accrued Investor Profit | C86: 17850.5 | I86: 0 | J86: 0 | K86: 0 | L86: 0 | M86: 0 | N86: 0
B87: Accrued Investor Profit (Unrealized) | I87: 0 | J87: 0 | K87: 0 | L87: 0 | M87: 0 | N87: 0
B88: Leave Pay Payable
B89: Salary Control Account | C89: 1.26 | D89: 70460.21 | E89: 1.28 | F89: 105132.96 | G89: 18039.65 | H89: 35871.36 | I89: 141057.57 | J89: 55906.86 | K89: 150409.88 | L89: 146047.07 | M89: 109126.8 | N89: 36851.26
B90: Consultancy Fee Payable | H90: 34513.45 | I90: 34513.45 | J90: 34513.45 | K90: 34513.45 | L90: 34513.45 | M90: 34513.45 | N90: 34513.45
B91: Output VAT | I91: 0 | J91: 0 | K91: 0 | L91: 0 | M91: 0 | N91: 0
B92: GOSI Payable | I92: 0 | J92: 0 | K92: 0 | L92: 0 | M92: 0 | N92: 0
B93: Dividend Payable (Investor)
B94: Debt Settlement Payable
B96: Short term Financing | C96: =SUM(C97:C100) -> 0 | D96: =SUM(D97:D98) -> 0 | E96: =SUM(E97:E98) -> 0 | F96: =SUM(F97:F98) -> 0 | H96: =SUM(H97:H98) -> 0 | I96: =SUM(I97:I98) -> 0 | J96: =SUM(J97:J98) -> 0 | K96: =SUM(K97:K98) -> 0 | L96: =SUM(L97:L98) -> 0 | M96: =SUM(M97:M98) -> 0 | N96: =+N98+N97 -> 0
B97: Interest payable (Al-Raeda) | I97: 0 | J97: 0 | K97: 0 | L97: 0 | M97: 0 | N97: 0
B98: Short-term Financing (Al Raedah) | I98: 0 | J98: 0 | K98: 0 | L98: 0 | M98: 0 | N98: 0
B99: Arbah Murabaha Facility
B102: TOTAL CURRENT LIABILITIES | C102: =+C96+C77 -> 17851.76 | D102: =+D96+D77 -> 70460.21 | E102: =+E96+E77 -> 1.28 | F102: =+F96+F77 -> 105132.96 | G102: =+G96+G77 -> 18039.65 | H102: =+H96+H77 -> 70384.81 | I102: =+I96+I77 -> 175571.02 | J102: =+J96+J77 -> 90420.31 | ... N102: =+N96+N77 -> 71364.71
B105: Related parties | C105: 269850.36 | D105: 262482.35 | E105: 254966.35 | F105: 239934.35 | G105: 236927.95 | H105: 200320.35 | I105: 200320.35 | J105: 200320.35 | K105: 200320.35 | L105: 200320.35 | M105: 200320.35 | N105: 200320.35
B107: External Debt Investor | C107: 5056800 | D107: 5056800 | E107: 5620500 | F107: 5620500 | G107: 5620500 | H107: 5620500 | I107: 5620500 | J107: 0 | K107: 0 | L107: 0 | M107: 0 | N107: 0
B109: End of Service Indemnity | D109: 0 | E109: 0 | F109: 0 | H109: 0 | I109: 0 | J109: 0 | K109: 0 | L109: 0
B111: TOTAL LONG-TERM LIABILITIES | C111: =+C109+C105+C107 -> 5326650.4 | D111: =+D109+D105+D107 -> 5319282.3 | E111: =+E109+E105+E107 -> 5875466.3 | F111: =+F109+F105+F107 -> 5860434.3 | G111: =+G109+G105+G107 -> 5857428 | H111: =+H109+H105+H107 -> 5820820.3 | I111: =+I109+I105+I107 -> 5820820.3 | J111: =+J109+J105 -> 200320.35 | K111: =+K109+K105 -> 200320.35 | L111: =+L109+L105 -> 200320.35 | M111: =+M109+M105 -> 200320.35 | N111: =+N109+N105 -> 200320.35
B114: Equity Financing | C114: 25257006 | D114: 25257006 | E114: 25257006 | F114: 25257006 | G114: 25257006 | H114: 25257006 | I114: 24254910 | J114: 24254910 | K114: 24254910 | L114: 24254910 | M114: 24254910 | N114: 24254910
B116: Contribution from Owners | C116: 0 | D116: 0 | E116: 0 | F116: 0 | H116: 0 | I116: 0 | J116: 0 | K116: 0 | L116: 0 | M116: 0 | N116: 0
B118: Statutory Reserve | C118: 0 | D118: 0 | E118: 0 | F118: 0 | I118: 0 | J118: 0 | K118: 0 | L118: 0
B120: Profit & Loss for the period | C120: -2941803.5 | D120: -2635133.7 | E120: -2333142 | F120: -2019901.8 | G120: -1754202.9 | H120: -1494168.6 | I120: -1235873.7 | J120: -1019263.3 | K120: -764610.72 | L120: -557375.33 | M120: -362592.98 | N120: -166484.11
B122: Retained Earnings/(Accumulated Losses) | C122: -1039698 | D122: -1039698 | E122: -1039698 | F122: -1039698 | G122: -1039698 | H122: -1039698 | I122: -1039698 | J122: -1039698 | K122: -1039698 | L122: -1039698 | M122: -1039698 | N122: -1039698
B124: TOTAL OWNER'S EQUITY | C124: =+C114+C118+C120+C122 -> 21275505 | D124: =+D114+D118+D120+D122 -> 21582174 | E124: =+E114+E118+E120+E122 -> 21884166 | F124: =+F114+F118+F120+F122 -> 22197406 | G124: =+G114+G118+G120+G122 -> 22463105 | H124: =+H114+H118+H120+H122 -> 22723140 | I124: =+I114+I118+I120+I122 -> 21979339 | J124: =+J114+J118+J120+J122 -> 22195949 | ... N124: =+N114+N118+N120+N122 -> 23048728
B127: TOTAL LIABILITIES & EQUITY | C127: =+C124+C102+C111 -> 26620007 | D127: =+D124+D102+D111 -> 26971917 | E127: =+E124+E102+E111 -> 27759634 | F127: =+F124+F102+F111 -> 28162974 | G127: =+G124+G102+G111 -> 28338573 | H127: =+H124+H102+H111 -> 28614345 | I127: =+I124+I102+I111 -> 27975730 | J127: =+J124+J102+J111 -> 22486690 | ... N127: =+N124+N102+N111 -> 23320413
C128: =+C127-C72 -> 0 | D128: =+D127-D72 -> 0 | E128: =+E127-E72 -> 0 | F128: =+F127-F72 -> 0 | G128: =+G127-G72 -> 0 | H128: =+H127-H72 -> 0 | I128: =+I127-I72 -> 0 | J128: =+J127-J72 -> 0 | ... N128: =+N127-N72 -> 0

Sheet Sheet3

Sheet IS Dec Consolidated
C2: =C63/3.75 -> 26271.371 | E2: 45321 | F2: =EDATE(E2,1) -> 45351 | G2: =EDATE(F2,1) -> 45380 | H2: =EDATE(G2,1) -> 45411 | I2: =EDATE(H2,1) -> 45441 | J2: =EDATE(I2,1) -> 45472 | K2: =EDATE(J2,1) -> 45502 | L2: =EDATE(K2,1) -> 45533 | M2: =EDATE(L2,1) -> 45564 | ... P2: =EDATE(O2,1) -> 45655
C3: =C2/40 -> 656.78427 | E3: 12 | F3: =E3-1 -> 11 | G3: =F3-1 -> 10 | H3: =G3-1 -> 9 | I3: =H3-1 -> 8 | J3: =I3-1 -> 7 | K3: =J3-1 -> 6 | L3: =K3-1 -> 5 | M3: =L3-1 -> 4 | ... P3: =O3-1 -> 1
E4: {=INDEX($E$6:$P$6,,MATCH(E3,$E$5:$P$5,FALSE))} -> -3864.75 | F4: {=INDEX($E$6:$P$6,,MATCH(F3,$E$5:$P$5,FALSE))} -> -15356.85 | G4: {=INDEX($E$6:$P$6,,MATCH(G3,$E$5:$P$5,FALSE))} -> -86801.8 | H4: {=INDEX($E$6:$P$6,,MATCH(H3,$E$5:$P$5,FALSE))} -> -37530.76 | I4: {=INDEX($E$6:$P$6,,MATCH(I3,$E$5:$P$5,FALSE))} -> -80455.25 | J4: {=INDEX($E$6:$P$6,,MATCH(J3,$E$5:$P$5,FALSE))} -> -55373.37 | K4: {=INDEX($E$6:$P$6,,MATCH(K3,$E$5:$P$5,FALSE))} -> -74578.66 | L4: {=INDEX($E$6:$P$6,,MATCH(L3,$E$5:$P$5,FALSE))} -> -122563.93 | ... P4: {=INDEX($E$6:$P$6,,MATCH(P3,$E$5:$P$5,FALSE))} -> -218169.59
E5: 1 | F5: 2 | G5: 3 | H5: 4 | I5: 5 | J5: 6 | K5: 7 | L5: 8 | M5: 9 | N5: 10 | O5: 11 | P5: 12
E6: =SUM(E53:E63,E68:E69)*-1 -> -218169.59 | F6: =SUM(F53:F63,F68:F69)*-1 -> -61700.21 | G6: =SUM(G53:G63,G68:G69)*-1 -> -60767.06 | H6: =SUM(I53:I63,I68:I69)*-1 -> -68531.35 | I6: =SUM(J53:J63,J68:J69)*-1 -> -122563.93 | J6: =SUM(K53:K63,K68:K69)*-1 -> -74578.66 | K6: =SUM(M53:M63,M68:M69)*-1 -> -55373.37 | L6: =SUM(N53:N63,N68:N69)*-1 -> -80455.25 | M6: =SUM(O53:O63,O68:O69)*-1 -> -37530.76 | N6: =SUM(Q53:Q63,Q68:Q69)*-1 -> -86801.8 | O6: =SUM(R53:R63,R68:R69)*-1 -> -15356.85 | P6: =SUM(S53:S63,S68:S69)*-1 -> -3864.75
B7: INCOME STATEMENT (US SAR) | C7: YTD | D7: Q4 - A | E7: MTD | F7: MTD | G7: MTD | H7: Q3 - A | I7: MTD | J7: MTD | K7: MTD | L7: Q2 - A | M7: MTD | N7: MTD | O7: MTD | P7: Q1 A | Q7: MTD | R7: MTD | S7: MTD
B8: FOR THE PERIOD 31st December 2024 | D8: 2024 | E8: 45657 | F8: 45626 | G8: 45596 | H8: 2024 | I8: 45565 | J8: 45535 | K8: 45504 | L8: 2024 | M8: 45473 | N8: 45443 | O8: 45412 | P8: 2024 | Q8: 45382 | R8: 45350 | S8: 45322
B10: Sales | C10: =G10+H10+L10+P10+F10+E10 -> 76420880 | D10: =SUM(E10:G10) -> 21384440 | E10: ='IS Dec KSA'!E10+'IS Dec USA'!E10 -> 10080211 | F10: ='IS Dec KSA'!F10+'IS Dec USA'!F10 -> 7198821.6 | G10: ='IS Dec KSA'!G10+'IS Dec USA'!G10 -> 4105407 | H10: =I10+J10+K10 -> 18352785 | I10: ='IS Dec KSA'!I10+'IS Dec USA'!I10 -> 4309452.5 | J10: ='IS Dec KSA'!J10+'IS Dec USA'!J10 -> 6772612 | K10: ='IS Dec KSA'!K10+'IS Dec USA'!K10 -> 7270720.4 | L10: =SUM(M10:O10) -> 19534533 | M10: ='IS Dec KSA'!M10+'IS Dec USA'!M10 -> 6957712.6 | N10: ='IS Dec KSA'!N10+'IS Dec USA'!N10 -> 7682337.2 | O10: ='IS Dec KSA'!O10+'IS Dec USA'!O10 -> 4894483.3 | P10: =SUM(Q10:S10) -> 17149122 | Q10: ='IS Dec KSA'!Q10+'IS Dec USA'!Q10 -> 9910492.9 | R10: ='IS Dec KSA'!R10+'IS Dec USA'!R10 -> 4805893.4 | S10: ='IS Dec KSA'!S10+'IS Dec USA'!S10 -> 2432735.6
B11: Cost of Goods Sold | C11: =G11+H11+L11+P11+F11+E11 -> 69127802 | D11: =SUM(E11:G11) -> 19099399 | E11: ='IS Dec KSA'!E11+'IS Dec USA'!E11 -> 9065157.9 | F11: ='IS Dec KSA'!F11+'IS Dec USA'!F11 -> 6363435 | G11: ='IS Dec KSA'!G11+'IS Dec USA'!G11 -> 3670806.6 | H11: =I11+J11+K11 -> 16705223 | I11: ='IS Dec KSA'!I11+'IS Dec USA'!I11 -> 3901380 | J11: ='IS Dec KSA'!J11+'IS Dec USA'!J11 -> 6268336 | K11: ='IS Dec KSA'!K11+'IS Dec USA'!K11 -> 6535506.8 | L11: =SUM(M11:O11) -> 17712883 | M11: ='IS Dec KSA'!M11+'IS Dec USA'!M11 -> 6212033.5 | N11: ='IS Dec KSA'!N11+'IS Dec USA'!N11 -> 6980089.4 | O11: ='IS Dec KSA'!O11+'IS Dec USA'!O11 -> 4520760 | P11: =SUM(Q11:S11) -> 15610297 | Q11: ='IS Dec KSA'!Q11+'IS Dec USA'!Q11 -> 9054208.4 | R11: ='IS Dec KSA'!R11+'IS Dec USA'!R11 -> 4407294 | S11: ='IS Dec KSA'!S11+'IS Dec USA'!S11 -> 2148794.4
B12: Purchase Discounts | C12: =G12+H12+L12+P12+F12+E12 -> -93226.45 | D12: =SUM(E12:G12) -> -1236.25 | E12: ='IS Dec KSA'!E12+'IS Dec USA'!E12 -> 0 | F12: ='IS Dec KSA'!F12+'IS Dec USA'!F12 -> 0 | G12: ='IS Dec KSA'!G12+'IS Dec USA'!G12 -> -1236.25 | H12: =I12+J12+K12 -> -54172.81 | I12: ='IS Dec KSA'!I12+'IS Dec USA'!I12 -> -6670 | J12: ='IS Dec KSA'!J12+'IS Dec USA'!J12 -> -7915.43 | K12: ='IS Dec KSA'!K12+'IS Dec USA'!K12 -> -39587.38 | L12: =SUM(M12:O12) -> -18295.8 | M12: ='IS Dec KSA'!M12+'IS Dec USA'!M12 -> 0 | N12: ='IS Dec KSA'!N12+'IS Dec USA'!N12 -> -5820.46 | O12: ='IS Dec KSA'!O12+'IS Dec USA'!O12 -> -12475.34 | P12: =SUM(Q12:S12) -> -19521.59 | Q12: ='IS Dec KSA'!Q12+'IS Dec USA'!Q12 -> -11033.03 | R12: ='IS Dec KSA'!R12+'IS Dec USA'!R12 -> -8488.56 | S12: ='IS Dec KSA'!S12+'IS Dec USA'!S12 -> 0
B13: Gross Profit / (Loss) | C13: =G13+H13+L13+P13+F13+E13 -> 7386304.4 | D13: =SUM(E13:G13) -> 2286276.6 | E13: ='IS Dec KSA'!E13+'IS Dec USA'!E13 -> 1015053.3 | F13: ='IS Dec KSA'!F13+'IS Dec USA'!F13 -> 835386.63 | G13: ='IS Dec KSA'!G13+'IS Dec USA'!G13 -> 435836.72 | H13: =I13+J13+K13 -> 1701735 | I13: ='IS Dec KSA'!I13+'IS Dec USA'!I13 -> 414742.55 | J13: ='IS Dec KSA'!J13+'IS Dec USA'!J13 -> 512191.45 | K13: ='IS Dec KSA'!K13+'IS Dec USA'!K13 -> 774800.95 | L13: =SUM(M13:O13) -> 1839946.1 | M13: ='IS Dec KSA'!M13+'IS Dec USA'!M13 -> 745679.15 | N13: ='IS Dec KSA'!N13+'IS Dec USA'!N13 -> 708068.27 | O13: ='IS Dec KSA'!O13+'IS Dec USA'!O13 -> 386198.65 | P13: =SUM(Q13:S13) -> 1558346.7 | Q13: ='IS Dec KSA'!Q13+'IS Dec USA'!Q13 -> 867317.58 | R13: ='IS Dec KSA'!R13+'IS Dec USA'!R13 -> 407087.92 | S13: ='IS Dec KSA'!S13+'IS Dec USA'!S13 -> 283941.25
B14: Consultation Income | C14: =G14+H14+L14+P14+F14+E14 -> 293478.27 | D14: =SUM(E14:G14) -> 26086.96 | E14: ='IS Dec KSA'!E14+'IS Dec USA'!E14 -> 26086.96 | F14: ='IS Dec KSA'!F14+'IS Dec USA'!F14 -> 0 | G14: ='IS Dec KSA'!G14+'IS Dec USA'!G14 -> 0 | H14: =I14+J14+K14 -> 143478.26 | I14: ='IS Dec KSA'!I14+'IS Dec USA'!I14 -> 0 | J14: ='IS Dec KSA'!J14+'IS Dec USA'!J14 -> 0 | K14: ='IS Dec KSA'!K14+'IS Dec USA'!K14 -> 143478.26 | L14: =SUM(M14:O14) -> 0 | M14: ='IS Dec KSA'!M14+'IS Dec USA'!M14 -> 0 | N14: ='IS Dec KSA'!N14+'IS Dec USA'!N14 -> 0 | O14: ='IS Dec KSA'!O14+'IS Dec USA'!O14 -> 0 | P14: =SUM(Q14:S14) -> 123913.05 | Q14: ='IS Dec KSA'!Q14+'IS Dec USA'!Q14 -> 19565.22 | R14: ='IS Dec KSA'!R14+'IS Dec USA'!R14 -> 104347.83 | S14: ='IS Dec KSA'!S14+'IS Dec USA'!S14 -> 0
B15: Gross Income | C15: =G15+H15+L15+P15+F15+E15 -> 7679782.6 | D15: =SUM(E15:G15) -> 2312363.6 | E15: =+E14+E13 -> 1041140.2 | F15: =+F14+F13 -> 835386.63 | G15: =+G14+G13 -> 435836.72 | H15: =+H14+H13 -> 1845213.2 | I15: =+I14+I13 -> 414742.55 | J15: =+J14+J13 -> 512191.45 | K15: =+K14+K13 -> 918279.21 | L15: =+L14+L13 -> 1839946.1 | ... S15: =+S14+S13 -> 283941.25
B17: General and Administrative Expenses | C17: =SUM(C18:C33) -> 1182570.3 | D17: =SUM(D18:D33) -> 588110.79 | E17: =SUM(E18:E33) -> 326464.28 | F17: =SUM(F18:F33) -> 118090.11 | G17: =SUM(G18:G33) -> 143556.4 | H17: =SUM(H18:H33) -> 222605.63 | I17: =SUM(I18:I33) -> 99971.72 | J17: =SUM(J18:J33) -> 54605.6 | ... S17: =SUM(S18:S33) -> 64127.9
B18: Bad Debt | C18: =G18+H18+L18+P18+F18+E18 -> 203016.64 | D18: =SUM(E18:G18) -> 203011.78 | E18: ='IS Dec KSA'!E18+'IS Dec USA'!E18 -> 203009.5 | F18: ='IS Dec KSA'!F18+'IS Dec USA'!F18 -> 0.37 | G18: ='IS Dec KSA'!G18+'IS Dec USA'!G18 -> 1.91 | H18: =I18+J18+K18 -> 2.67 | I18: ='IS Dec KSA'!I18+'IS Dec USA'!I18 -> 0.5 | J18: ='IS Dec KSA'!J18+'IS Dec USA'!J18 -> 0.4 | K18: ='IS Dec KSA'!K18+'IS Dec USA'!K18 -> 1.77 | L18: =SUM(M18:O18) -> 0.63 | M18: ='IS Dec KSA'!M18+'IS Dec USA'!M18 -> 0 | N18: ='IS Dec KSA'!N18+'IS Dec USA'!N18 -> 0.63 | O18: ='IS Dec KSA'!O18+'IS Dec USA'!O18 -> 0 | P18: =SUM(Q18:S18) -> 1.56 | Q18: ='IS Dec KSA'!Q18+'IS Dec USA'!Q18 -> 0.51 | R18: ='IS Dec KSA'!R18+'IS Dec USA'!R18 -> 0.27 | S18: ='IS Dec KSA'!S18+'IS Dec USA'!S18 -> 0.78
B19: Bank Fees and Charges | C19: =G19+H19+L19+P19+F19+E19 -> 24338.49 | D19: =SUM(E19:G19) -> 5748.42 | E19: ='IS Dec KSA'!E19+'IS Dec USA'!E19 -> 2381.41 | F19: ='IS Dec KSA'!F19+'IS Dec USA'!F19 -> 868.91 | G19: ='IS Dec KSA'!G19+'IS Dec USA'!G19 -> 2498.1 | H19: =I19+J19+K19 -> 5553.18 | I19: ='IS Dec KSA'!I19+'IS Dec USA'!I19 -> 916.73 | J19: ='IS Dec KSA'!J19+'IS Dec USA'!J19 -> 1735.73 | K19: ='IS Dec KSA'!K19+'IS Dec USA'!K19 -> 2900.72 | L19: =SUM(M19:O19) -> 7303.74 | M19: ='IS Dec KSA'!M19+'IS Dec USA'!M19 -> 1444.7 | N19: ='IS Dec KSA'!N19+'IS Dec USA'!N19 -> 3296.92 | O19: ='IS Dec KSA'!O19+'IS Dec USA'!O19 -> 2562.12 | P19: =SUM(Q19:S19) -> 5733.15 | Q19: ='IS Dec KSA'!Q19+'IS Dec USA'!Q19 -> 1642.49 | R19: ='IS Dec KSA'!R19+'IS Dec USA'!R19 -> 2076.03 | S19: ='IS Dec KSA'!S19+'IS Dec USA'!S19 -> 2014.63
B20: Office Supplies | C20: =G20+H20+L20+P20+F20+E20 -> 54128.03 | D20: =SUM(E20:G20) -> 2690.87 | E20: ='IS Dec KSA'!E20+'IS Dec USA'!E20 -> 819.32 | F20: ='IS Dec KSA'!F20+'IS Dec USA'!F20 -> 669.05 | G20: ='IS Dec KSA'!G20+'IS Dec USA'!G20 -> 1202.5 | H20: =I20+J20+K20 -> 11522.46 | I20: ='IS Dec KSA'!I20+'IS Dec USA'!I20 -> 4877.46 | J20: ='IS Dec KSA'!J20+'IS Dec USA'!J20 -> 6110.09 | K20: ='IS Dec KSA'!K20+'IS Dec USA'!K20 -> 534.91 | L20: =SUM(M20:O20) -> 24158.2 | M20: ='IS Dec KSA'!M20+'IS Dec USA'!M20 -> 682.6 | N20: ='IS Dec KSA'!N20+'IS Dec USA'!N20 -> 7993.77 | O20: ='IS Dec KSA'!O20+'IS Dec USA'!O20 -> 15481.83 | P20: =SUM(Q20:S20) -> 15756.5 | Q20: ='IS Dec KSA'!Q20+'IS Dec USA'!Q20 -> 2319 | R20: ='IS Dec KSA'!R20+'IS Dec USA'!R20 -> 6937.47 | S20: ='IS Dec KSA'!S20+'IS Dec USA'!S20 -> 6500.03
B21: Office Utilities - Electricity/Water/Janitorial | C21: =G21+H21+L21+P21+F21+E21 -> 24609.21 | D21: =SUM(E21:G21) -> 13664.34 | E21: ='IS Dec KSA'!E21+'IS Dec USA'!E21 -> 4705.55 | F21: ='IS Dec KSA'!F21+'IS Dec USA'!F21 -> 1182.28 | G21: ='IS Dec KSA'!G21+'IS Dec USA'!G21 -> 7776.51 | H21: =I21+J21+K21 -> 6139.69 | I21: ='IS Dec KSA'!I21+'IS Dec USA'!I21 -> 282 | J21: ='IS Dec KSA'!J21+'IS Dec USA'!J21 -> 4257.65 | K21: ='IS Dec KSA'!K21+'IS Dec USA'!K21 -> 1600.04 | L21: =SUM(M21:O21) -> 3342.28 | M21: ='IS Dec KSA'!M21+'IS Dec USA'!M21 -> 983.6 | N21: ='IS Dec KSA'!N21+'IS Dec USA'!N21 -> 1889.74 | O21: ='IS Dec KSA'!O21+'IS Dec USA'!O21 -> 468.94 | P21: =SUM(Q21:S21) -> 1462.9 | Q21: ='IS Dec KSA'!Q21+'IS Dec USA'!Q21 -> 824.4 | R21: ='IS Dec KSA'!R21+'IS Dec USA'!R21 -> 454 | S21: ='IS Dec KSA'!S21+'IS Dec USA'!S21 -> 184.5
B22: Office Expenses | C22: =G22+H22+L22+P22+F22+E22 -> 3444.41 | D22: =SUM(E22:G22) -> 1 | E22: ='IS Dec KSA'!E22+'IS Dec USA'!E22 -> 0 | F22: ='IS Dec KSA'!F22+'IS Dec USA'!F22 -> 0 | G22: ='IS Dec KSA'!G22+'IS Dec USA'!G22 -> 1 | H22: =I22+J22+K22 -> 0 | I22: ='IS Dec KSA'!I22+'IS Dec USA'!I22 -> 0 | J22: ='IS Dec KSA'!J22+'IS Dec USA'!J22 -> 0 | K22: ='IS Dec KSA'!K22+'IS Dec USA'!K22 -> 0 | L22: =SUM(M22:O22) -> 0 | M22: ='IS Dec KSA'!M22+'IS Dec USA'!M22 -> 0 | N22: ='IS Dec KSA'!N22+'IS Dec USA'!N22 -> 0 | O22: ='IS Dec KSA'!O22+'IS Dec USA'!O22 -> 0 | P22: =SUM(Q22:S22) -> 3443.41 | Q22: ='IS Dec KSA'!Q22+'IS Dec USA'!Q22 -> 0 | R22: ='IS Dec KSA'!R22+'IS Dec USA'!R22 -> 3443.41 | S22: ='IS Dec KSA'!S22+'IS Dec USA'!S22 -> 0
B23: Travel Expense | C23: =G23+H23+L23+P23+F23+E23 -> 38163.24 | D23: =SUM(E23:G23) -> 3750 | E23: ='IS Dec KSA'!E23+'IS Dec USA'!E23 -> 3750 | F23: ='IS Dec KSA'!F23+'IS Dec USA'!F23 -> 0 | G23: ='IS Dec KSA'!G23+'IS Dec USA'!G23 -> 0 | H23: =I23+J23+K23 -> 18156.74 | I23: ='IS Dec KSA'!I23+'IS Dec USA'!I23 -> 2446.84 | J23: ='IS Dec KSA'!J23+'IS Dec USA'!J23 -> 0 | K23: ='IS Dec KSA'!K23+'IS Dec USA'!K23 -> 15709.9 | L23: =SUM(M23:O23) -> 8606.53 | M23: ='IS Dec KSA'!M23+'IS Dec USA'!M23 -> 308.16 | N23: ='IS Dec KSA'!N23+'IS Dec USA'!N23 -> 8025.25 | O23: ='IS Dec KSA'!O23+'IS Dec USA'!O23 -> 273.12 | P23: =SUM(Q23:S23) -> 7649.97 | Q23: ='IS Dec KSA'!Q23+'IS Dec USA'!Q23 -> 814.47 | R23: ='IS Dec KSA'!R23+'IS Dec USA'!R23 -> 6835.5 | S23: ='IS Dec KSA'!S23+'IS Dec USA'!S23 -> 0
B24: Printing and Stationery | C24: =G24+H24+L24+P24+F24+E24 -> 4591.36 | D24: =SUM(E24:G24) -> 1056.29 | E24: ='IS Dec KSA'!E24+'IS Dec USA'!E24 -> 241 | F24: ='IS Dec KSA'!F24+'IS Dec USA'!F24 -> 675.29 | G24: ='IS Dec KSA'!G24+'IS Dec USA'!G24 -> 140 | H24: =I24+J24+K24 -> 2690.93 | I24: ='IS Dec KSA'!I24+'IS Dec USA'!I24 -> 990.06 | J24: ='IS Dec KSA'!J24+'IS Dec USA'!J24 -> 0 | K24: ='IS Dec KSA'!K24+'IS Dec USA'!K24 -> 1700.87 | L24: =SUM(M24:O24) -> 69.57 | M24: ='IS Dec KSA'!M24+'IS Dec USA'!M24 -> 69.57 | N24: ='IS Dec KSA'!N24+'IS Dec USA'!N24 -> 0 | O24: ='IS Dec KSA'!O24+'IS Dec USA'!O24 -> 0 | P24: =SUM(Q24:S24) -> 774.57 | Q24: ='IS Dec KSA'!Q24+'IS Dec USA'!Q24 -> 0 | R24: ='IS Dec KSA'!R24+'IS Dec USA'!R24 -> 774.57 | S24: ='IS Dec KSA'!S24+'IS Dec USA'!S24 -> 0
B25: Rent Expense (G&A) | C25: =G25+H25+L25+P25+F25+E25 -> 127377.94 | D25: =SUM(E25:G25) -> 48093.19 | E25: ='IS Dec KSA'!E25+'IS Dec USA'!E25 -> 32096.09 | F25: ='IS Dec KSA'!F25+'IS Dec USA'!F25 -> 7998.55 | G25: ='IS Dec KSA'!G25+'IS Dec USA'!G25 -> 7998.55 | H25: =I25+J25+K25 -> 23995.64 | I25: ='IS Dec KSA'!I25+'IS Dec USA'!I25 -> 7998.55 | J25: ='IS Dec KSA'!J25+'IS Dec USA'!J25 -> 7998.55 | K25: ='IS Dec KSA'!K25+'IS Dec USA'!K25 -> 7998.54 | L25: =SUM(M25:O25) -> 23899.98 | M25: ='IS Dec KSA'!M25+'IS Dec USA'!M25 -> 7966.66 | N25: ='IS Dec KSA'!N25+'IS Dec USA'!N25 -> 7966.66 | O25: ='IS Dec KSA'!O25+'IS Dec USA'!O25 -> 7966.66 | P25: =SUM(Q25:S25) -> 31389.13 | Q25: ='IS Dec KSA'!Q25+'IS Dec USA'!Q25 -> 10162.66 | R25: ='IS Dec KSA'!R25+'IS Dec USA'!R25 -> 10162.66 | S25: ='IS Dec KSA'!S25+'IS Dec USA'!S25 -> 11063.81
B26: Meals and Entertainment | C26: =G26+H26+L26+P26+F26+E26 -> 91973.44 | D26: =SUM(E26:G26) -> 48368.41 | E26: ='IS Dec KSA'!E26+'IS Dec USA'!E26 -> 3897.75 | F26: ='IS Dec KSA'!F26+'IS Dec USA'!F26 -> 25111.76 | G26: ='IS Dec KSA'!G26+'IS Dec USA'!G26 -> 19358.9 | H26: =I26+J26+K26 -> 22739.23 | I26: ='IS Dec KSA'!I26+'IS Dec USA'!I26 -> 8471.34 | J26: ='IS Dec KSA'!J26+'IS Dec USA'!J26 -> 6298.48 | K26: ='IS Dec KSA'!K26+'IS Dec USA'!K26 -> 7969.41 | L26: =SUM(M26:O26) -> 8918.73 | M26: ='IS Dec KSA'!M26+'IS Dec USA'!M26 -> 3696.52 | N26: ='IS Dec KSA'!N26+'IS Dec USA'!N26 -> 3183.82 | O26: ='IS Dec KSA'!O26+'IS Dec USA'!O26 -> 2038.39 | P26: =SUM(Q26:S26) -> 11947.07 | Q26: ='IS Dec KSA'!Q26+'IS Dec USA'!Q26 -> 1173.66 | R26: ='IS Dec KSA'!R26+'IS Dec USA'!R26 -> 3677.22 | S26: ='IS Dec KSA'!S26+'IS Dec USA'!S26 -> 7096.19
B27: Audit & Consultancy expense | C27: =G27+H27+L27+P27+F27+E27 -> 42500 | D27: =SUM(E27:G27) -> 17500 | E27: ='IS Dec KSA'!E27+'IS Dec USA'!E27 -> 17500 | F27: ='IS Dec KSA'!F27+'IS Dec USA'!F27 -> 0 | G27: ='IS Dec KSA'!G27+'IS Dec USA'!G27 -> 0 | H27: =I27+J27+K27 -> 0 | I27: ='IS Dec KSA'!I27+'IS Dec USA'!I27 -> 0 | J27: ='IS Dec KSA'!J27+'IS Dec USA'!J27 -> 0 | K27: ='IS Dec KSA'!K27+'IS Dec USA'!K27 -> 0 | L27: =SUM(M27:O27) -> 12500 | M27: ='IS Dec KSA'!M27+'IS Dec USA'!M27 -> 12500 | N27: ='IS Dec KSA'!N27+'IS Dec USA'!N27 -> 0 | O27: ='IS Dec KSA'!O27+'IS Dec USA'!O27 -> 0 | P27: =SUM(Q27:S27) -> 12500 | Q27: ='IS Dec KSA'!Q27+'IS Dec USA'!Q27 -> 0 | R27: ='IS Dec KSA'!R27+'IS Dec USA'!R27 -> 0 | S27: ='IS Dec KSA'!S27+'IS Dec USA'!S27 -> 12500
B28: Communication Exp - Mobile & Internet | C28: =G28+H28+L28+P28+F28+E28 -> 25607.52 | D28: =SUM(E28:G28) -> 8450.21 | E28: ='IS Dec KSA'!E28+'IS Dec USA'!E28 -> 2142.64 | F28: ='IS Dec KSA'!F28+'IS Dec USA'!F28 -> 2122.61 | G28: ='IS Dec KSA'!G28+'IS Dec USA'!G28 -> 4184.96 | H28: =I28+J28+K28 -> 4191.5 | I28: ='IS Dec KSA'!I28+'IS Dec USA'!I28 -> 288.54 | J28: ='IS Dec KSA'!J28+'IS Dec USA'!J28 -> 1922.61 | K28: ='IS Dec KSA'!K28+'IS Dec USA'!K28 -> 1980.35 | L28: =SUM(M28:O28) -> 7104.36 | M28: ='IS Dec KSA'!M28+'IS Dec USA'!M28 -> 2045.28 | N28: ='IS Dec KSA'!N28+'IS Dec USA'!N28 -> 2927.6 | O28: ='IS Dec KSA'!O28+'IS Dec USA'!O28 -> 2131.48 | P28: =SUM(Q28:S28) -> 5861.45 | Q28: ='IS Dec KSA'!Q28+'IS Dec USA'!Q28 -> 2016.21 | R28: ='IS Dec KSA'!R28+'IS Dec USA'!R28 -> 1922.61 | S28: ='IS Dec KSA'!S28+'IS Dec USA'!S28 -> 1922.63
B29: Subscriptions & Memberships | C29: =G29+H29+L29+P29+F29+E29 -> 472140.14 | D29: =SUM(E29:G29) -> 171131.28 | E29: ='IS Dec KSA'!E29+'IS Dec USA'!E29 -> 51500.23 | F29: ='IS Dec KSA'!F29+'IS Dec USA'!F29 -> 75292.78 | G29: ='IS Dec KSA'!G29+'IS Dec USA'!G29 -> 44338.27 | H29: =I29+J29+K29 -> 121579.29 | I29: ='IS Dec KSA'!I29+'IS Dec USA'!I29 -> 67561.27 | J29: ='IS Dec KSA'!J29+'IS Dec USA'!J29 -> 26386.19 | K29: ='IS Dec KSA'!K29+'IS Dec USA'!K29 -> 27631.83 | L29: =SUM(M29:O29) -> 99523.89 | M29: ='IS Dec KSA'!M29+'IS Dec USA'!M29 -> 26720.77 | N29: ='IS Dec KSA'!N29+'IS Dec USA'!N29 -> 39015.77 | O29: ='IS Dec KSA'!O29+'IS Dec USA'!O29 -> 33787.35 | P29: =SUM(Q29:S29) -> 79905.68 | Q29: ='IS Dec KSA'!Q29+'IS Dec USA'!Q29 -> 30359.81 | R29: ='IS Dec KSA'!R29+'IS Dec USA'!R29 -> 26700.54 | S29: ='IS Dec KSA'!S29+'IS Dec USA'!S29 -> 22845.33
... B31: Low Value Assets | C31: =G31+H31+L31+P31+F31+E31 -> 13174.86 | D31: =SUM(E31:G31) -> 7036.43 | E31: ='IS Dec KSA'!E31+'IS Dec USA'!E31 -> 2420.55 | F31: ='IS Dec KSA'!F31+'IS Dec USA'!F31 -> 4168.5 | G31: ='IS Dec KSA'!G31+'IS Dec USA'!G31 -> 447.38 | H31: =I31+J31+K31 -> 6138.43 | I31: ='IS Dec KSA'!I31+'IS Dec USA'!I31 -> 6138.43 | J31: ='IS Dec KSA'!J31+'IS Dec USA'!J31 -> 0 | K31: ='IS Dec KSA'!K31+'IS Dec USA'!K31 -> 0 | L31: =SUM(M31:O31) -> 0 | M31: ='IS Dec KSA'!M31+'IS Dec USA'!M31 -> 0 | N31: ='IS Dec KSA'!N31+'IS Dec USA'!N31 -> 0 | O31: ='IS Dec KSA'!O31+'IS Dec USA'!O31 -> 0 | P31: =SUM(Q31:S31) -> 0 | Q31: ='IS Dec KSA'!Q31+'IS Dec USA'!Q31 -> 0 | R31: ='IS Dec KSA'!R31+'IS Dec USA'!R31 -> 0 | S31: ='IS Dec KSA'!S31+'IS Dec USA'!S31 -> 0
B32: Charity | C32: =G32+H32+L32+P32+F32+E32 -> 10000 | D32: =SUM(E32:G32) -> 10000 | E32: ='IS Dec KSA'!E32+'IS Dec USA'!E32 -> 2000 | F32: ='IS Dec KSA'!F32+'IS Dec USA'!F32 -> 0 | G32: ='IS Dec KSA'!G32+'IS Dec USA'!G32 -> 8000
B33: Witholding Tax | C33: =G33+H33+L33+P33+F33+E33 -> 47608.81 | D33: =SUM(E33:G33) -> 47608.81 | E33: ='IS Dec KSA'!E33+'IS Dec USA'!E33 -> 0 | F33: ='IS Dec KSA'!F33+'IS Dec USA'!F33 -> 0 | G33: ='IS Dec KSA'!G33+'IS Dec USA'!G33 -> 47608.81
B34: Selling Expenses | C34: =SUM(C35:C43) -> 771628.36 | D34: =SUM(E34:G34) -> 263087.79 | E34: =SUM(E35:E43) -> 88341.5 | F34: =SUM(F35:F43) -> 99215.19 | G34: =SUM(G35:G43) -> 75531.1 | H34: =SUM(H35:H43) -> 217926.39 | I34: =SUM(I35:I43) -> 110136.53 | J34: =SUM(J35:J43) -> 52412.66 | K34: =SUM(K35:K43) -> 55377.2 | L34: =SUM(L35:L43) -> 174055.86 | ... S34: =SUM(S35:S43) -> 29131.09
B35: Business travel expenses | C35: =G35+H35+L35+P35+F35+E35 -> 110575.44 | D35: =SUM(E35:G35) -> 61398.61 | E35: ='IS Dec KSA'!E35+'IS Dec USA'!E35 -> 18308.59 | F35: ='IS Dec KSA'!F35+'IS Dec USA'!F35 -> 18913.71 | G35: ='IS Dec KSA'!G35+'IS Dec USA'!G35 -> 24176.31 | H35: =I35+J35+K35 -> 15855.33 | I35: ='IS Dec KSA'!I35+'IS Dec USA'!I35 -> 4564.64 | J35: ='IS Dec KSA'!J35+'IS Dec USA'!J35 -> 690 | K35: ='IS Dec KSA'!K35+'IS Dec USA'!K35 -> 10600.69 | L35: =SUM(M35:O35) -> 21622.38 | M35: ='IS Dec KSA'!M35+'IS Dec USA'!M35 -> 2500 | N35: ='IS Dec KSA'!N35+'IS Dec USA'!N35 -> 2912.45 | O35: ='IS Dec KSA'!O35+'IS Dec USA'!O35 -> 16209.93 | P35: =SUM(Q35:S35) -> 11699.12 | Q35: ='IS Dec KSA'!Q35+'IS Dec USA'!Q35 -> 7809.92 | R35: ='IS Dec KSA'!R35+'IS Dec USA'!R35 -> 3889.2 | S35: ='IS Dec KSA'!S35+'IS Dec USA'!S35 -> 0
B36: Collection Commission | C36: =G36+H36+L36+P36+F36+E36 -> 61150.53 | D36: =SUM(E36:G36) -> 8117.57 | E36: ='IS Dec KSA'!E36+'IS Dec USA'!E36 -> 4797.13 | F36: ='IS Dec KSA'!F36+'IS Dec USA'!F36 -> 0 | G36: ='IS Dec KSA'!G36+'IS Dec USA'!G36 -> 3320.44 | H36: =I36+J36+K36 -> 17715.01 | I36: ='IS Dec KSA'!I36+'IS Dec USA'!I36 -> 3388.45 | J36: ='IS Dec KSA'!J36+'IS Dec USA'!J36 -> 11016.84 | K36: ='IS Dec KSA'!K36+'IS Dec USA'!K36 -> 3309.72 | L36: =SUM(M36:O36) -> 17647.36 | M36: ='IS Dec KSA'!M36+'IS Dec USA'!M36 -> 10814.05 | N36: ='IS Dec KSA'!N36+'IS Dec USA'!N36 -> 4426.28 | O36: ='IS Dec KSA'!O36+'IS Dec USA'!O36 -> 2407.03 | P36: =SUM(Q36:S36) -> 17670.59 | Q36: ='IS Dec KSA'!Q36+'IS Dec USA'!Q36 -> 6731.53 | R36: ='IS Dec KSA'!R36+'IS Dec USA'!R36 -> 1817.82 | S36: ='IS Dec KSA'!S36+'IS Dec USA'!S36 -> 9121.24
B37: Dinar commission | C37: =G37+H37+L37+P37+F37+E37 -> 8543.48 | D37: =SUM(E37:G37) -> 0 | E37: ='IS Dec KSA'!E37+'IS Dec USA'!E37 -> 0 | F37: ='IS Dec KSA'!F37+'IS Dec USA'!F37 -> 0 | G37: ='IS Dec KSA'!G37+'IS Dec USA'!G37 -> 0 | H37: =I37+J37+K37 -> 2869.57 | I37: ='IS Dec KSA'!I37+'IS Dec USA'!I37 -> 0 | J37: ='IS Dec KSA'!J37+'IS Dec USA'!J37 -> 1304.35 | K37: ='IS Dec KSA'!K37+'IS Dec USA'!K37 -> 1565.22 | L37: =SUM(M37:O37) -> 391.3 | M37: ='IS Dec KSA'!M37+'IS Dec USA'!M37 -> 0 | N37: ='IS Dec KSA'!N37+'IS Dec USA'!N37 -> 0 | O37: ='IS Dec KSA'!O37+'IS Dec USA'!O37 -> 391.3 | P37: =SUM(Q37:S37) -> 5282.61 | Q37: ='IS Dec KSA'!Q37+'IS Dec USA'!Q37 -> 2086.96 | R37: ='IS Dec KSA'!R37+'IS Dec USA'!R37 -> 0 | S37: ='IS Dec KSA'!S37+'IS Dec USA'!S37 -> 3195.65
B38: New customer commission | C38: =G38+H38+L38+P38+F38+E38 -> 44606.18 | D38: =SUM(E38:G38) -> 13166.48 | E38: ='IS Dec KSA'!E38+'IS Dec USA'!E38 -> 5000 | F38: ='IS Dec KSA'!F38+'IS Dec USA'!F38 -> 8166.48 | G38: ='IS Dec KSA'!G38+'IS Dec USA'!G38 -> 0 | H38: =I38+J38+K38 -> 9439.7 | I38: ='IS Dec KSA'!I38+'IS Dec USA'!I38 -> 1500 | J38: ='IS Dec KSA'!J38+'IS Dec USA'!J38 -> 5939.7 | K38: ='IS Dec KSA'!K38+'IS Dec USA'!K38 -> 2000 | L38: =SUM(M38:O38) -> 13000 | M38: ='IS Dec KSA'!M38+'IS Dec USA'!M38 -> 7000 | N38: ='IS Dec KSA'!N38+'IS Dec USA'!N38 -> 3000 | O38: ='IS Dec KSA'!O38+'IS Dec USA'!O38 -> 3000 | P38: =SUM(Q38:S38) -> 9000 | Q38: ='IS Dec KSA'!Q38+'IS Dec USA'!Q38 -> 2000 | R38: ='IS Dec KSA'!R38+'IS Dec USA'!R38 -> 1000 | S38: ='IS Dec KSA'!S38+'IS Dec USA'!S38 -> 6000
B39: Cash Purchase - Backend Margin | C39: =G39+H39+L39+P39+F39+E39 -> 4457.77 | D39: =SUM(E39:G39) -> 687.5 | E39: ='IS Dec KSA'!E39+'IS Dec USA'!E39 -> 107.5 | F39: ='IS Dec KSA'!F39+'IS Dec USA'!F39 -> 0 | G39: ='IS Dec KSA'!G39+'IS Dec USA'!G39 -> 580 | H39: =I39+J39+K39 -> 481.81 | I39: ='IS Dec KSA'!I39+'IS Dec USA'!I39 -> 481.81 | J39: ='IS Dec KSA'!J39+'IS Dec USA'!J39 -> 0 | K39: ='IS Dec KSA'!K39+'IS Dec USA'!K39 -> 0 | L39: =SUM(M39:O39) -> 3288.46 | M39: ='IS Dec KSA'!M39+'IS Dec USA'!M39 -> 506.13 | N39: ='IS Dec KSA'!N39+'IS Dec USA'!N39 -> 2782.33 | O39: ='IS Dec KSA'!O39+'IS Dec USA'!O39 -> 0 | P39: =SUM(Q39:S39) -> 0 | Q39: ='IS Dec KSA'!Q39+'IS Dec USA'!Q39 -> 0 | R39: ='IS Dec KSA'!R39+'IS Dec USA'!R39 -> 0 | S39: ='IS Dec KSA'!S39+'IS Dec USA'!S39 -> 0
B40: Cash Sale Commission | C40: =G40+H40+L40+P40+F40+E40 -> 21797.18 | D40: =SUM(E40:G40) -> 240 | E40: ='IS Dec KSA'!E40+'IS Dec USA'!E40 -> 0 | F40: ='IS Dec KSA'!F40+'IS Dec USA'!F40 -> 120 | G40: ='IS Dec KSA'!G40+'IS Dec USA'!G40 -> 120 | H40: =I40+J40+K40 -> 4162.38 | I40: ='IS Dec KSA'!I40+'IS Dec USA'!I40 -> 720 | J40: ='IS Dec KSA'!J40+'IS Dec USA'!J40 -> 3442.38 | K40: ='IS Dec KSA'!K40+'IS Dec USA'!K40 -> 0 | L40: =SUM(M40:O40) -> 17394.8 | M40: ='IS Dec KSA'!M40+'IS Dec USA'!M40 -> 6744.8 | N40: ='IS Dec KSA'!N40+'IS Dec USA'!N40 -> 10650 | O40: ='IS Dec KSA'!O40+'IS Dec USA'!O40 -> 0 | P40: =SUM(Q40:S40) -> 0 | Q40: ='IS Dec KSA'!Q40+'IS Dec USA'!Q40 -> 0 | R40: ='IS Dec KSA'!R40+'IS Dec USA'!R40 -> 0 | S40: ='IS Dec KSA'!S40+'IS Dec USA'!S40 -> 0
B41: Fuel/Mileage Expenses | C41: =G41+H41+L41+P41+F41+E41 -> 42649.18 | D41: =SUM(E41:G41) -> 12753.84 | E41: ='IS Dec KSA'!E41+'IS Dec USA'!E41 -> 4340.78 | F41: ='IS Dec KSA'!F41+'IS Dec USA'!F41 -> 3114.39 | G41: ='IS Dec KSA'!G41+'IS Dec USA'!G41 -> 5298.67 | H41: =I41+J41+K41 -> 10160.15 | I41: ='IS Dec KSA'!I41+'IS Dec USA'!I41 -> 4905.08 | J41: ='IS Dec KSA'!J41+'IS Dec USA'!J41 -> 1943.42 | K41: ='IS Dec KSA'!K41+'IS Dec USA'!K41 -> 3311.65 | L41: =SUM(M41:O41) -> 12392.19 | M41: ='IS Dec KSA'!M41+'IS Dec USA'!M41 -> 4093.31 | N41: ='IS Dec KSA'!N41+'IS Dec USA'!N41 -> 5875.86 | O41: ='IS Dec KSA'!O41+'IS Dec USA'!O41 -> 2423.02 | P41: =SUM(Q41:S41) -> 7343 | Q41: ='IS Dec KSA'!Q41+'IS Dec USA'!Q41 -> 4287.21 | R41: ='IS Dec KSA'!R41+'IS Dec USA'!R41 -> 1634.11 | S41: ='IS Dec KSA'!S41+'IS Dec USA'!S41 -> 1421.68
B42: Marketing & Advertising | C42: =G42+H42+L42+P42+F42+E42 -> 259041.14 | D42: =SUM(E42:G42) -> 89059.37 | E42: ='IS Dec KSA'!E42+'IS Dec USA'!E42 -> 29899.36 | F42: ='IS Dec KSA'!F42+'IS Dec USA'!F42 -> 43012.47 | G42: ='IS Dec KSA'!G42+'IS Dec USA'!G42 -> 16147.54 | H42: =I42+J42+K42 -> 101413.6 | I42: ='IS Dec KSA'!I42+'IS Dec USA'!I42 -> 75984.45 | J42: ='IS Dec KSA'!J42+'IS Dec USA'!J42 -> 9457.6 | K42: ='IS Dec KSA'!K42+'IS Dec USA'!K42 -> 15971.55 | L42: =SUM(M42:O42) -> 37892.56 | M42: ='IS Dec KSA'!M42+'IS Dec USA'!M42 -> 10375.74 | N42: ='IS Dec KSA'!N42+'IS Dec USA'!N42 -> 16091.45 | O42: ='IS Dec KSA'!O42+'IS Dec USA'!O42 -> 11425.37 | P42: =SUM(Q42:S42) -> 30675.61 | Q42: ='IS Dec KSA'!Q42+'IS Dec USA'!Q42 -> 11188.12 | R42: ='IS Dec KSA'!R42+'IS Dec USA'!R42 -> 10094.97 | S42: ='IS Dec KSA'!S42+'IS Dec USA'!S42 -> 9392.52
B43: Trade Credit Insurance | C43: =G43+H43+L43+P43+F43+E43 -> 218807.46 | D43: =SUM(E43:G43) -> 77664.42 | E43: ='IS Dec KSA'!E43+'IS Dec USA'!E43 -> 25888.14 | F43: ='IS Dec KSA'!F43+'IS Dec USA'!F43 -> 25888.14 | G43: ='IS Dec KSA'!G43+'IS Dec USA'!G43 -> 25888.14 | H43: =I43+J43+K43 -> 55828.84 | I43: ='IS Dec KSA'!I43+'IS Dec USA'!I43 -> 18592.1 | J43: ='IS Dec KSA'!J43+'IS Dec USA'!J43 -> 18618.37 | K43: ='IS Dec KSA'!K43+'IS Dec USA'!K43 -> 18618.37 | L43: =SUM(M43:O43) -> 50426.81 | M43: ='IS Dec KSA'!M43+'IS Dec USA'!M43 -> 16795.28 | N43: ='IS Dec KSA'!N43+'IS Dec USA'!N43 -> 16808.98 | O43: ='IS Dec KSA'!O43+'IS Dec USA'!O43 -> 16822.55 | P43: =SUM(Q43:S43) -> 34887.39 | Q43: ='IS Dec KSA'!Q43+'IS Dec USA'!Q43 -> 16822.55 | R43: ='IS Dec KSA'!R43+'IS Dec USA'!R43 -> 18064.84 | S43: ='IS Dec KSA'!S43+'IS Dec USA'!S43 -> 0
B44: Legal & Consultation Expenses | C44: =SUM(C45:C47) -> 912663.56 | D44: =SUM(E44:G44) -> 424971.86 | E44: =SUM(E45:E47) -> 241058.12 | F44: =SUM(F45:F47) -> 50847.84 | G44: =SUM(G45:G47) -> 133065.9 | H44: =SUM(H45:H47) -> 210063.36 | I44: =SUM(I45:I47) -> 55589.37 | J44: =SUM(J45:J47) -> 99963.44 | K44: =SUM(K45:K47) -> 54510.55 | L44: =SUM(L45:L47) -> 111316.31 | ... S44: =SUM(S45:S47) -> 58736.14
B45: Consultant Expense | C45: =G45+H45+L45+P45+F45+E45 -> 515896.63 | D45: =SUM(E45:G45) -> 201530.87 | E45: ='IS Dec KSA'!E45+'IS Dec USA'!E45 -> 74891.99 | F45: ='IS Dec KSA'!F45+'IS Dec USA'!F45 -> 22525.54 | G45: ='IS Dec KSA'!G45+'IS Dec USA'!G45 -> 104113.34 | H45: =I45+J45+K45 -> 118778.72 | I45: ='IS Dec KSA'!I45+'IS Dec USA'!I45 -> 26304.29 | J45: ='IS Dec KSA'!J45+'IS Dec USA'!J45 -> 45311.9 | K45: ='IS Dec KSA'!K45+'IS Dec USA'!K45 -> 47162.53 | L45: =SUM(M45:O45) -> 76365.61 | M45: ='IS Dec KSA'!M45+'IS Dec USA'!M45 -> 22845.6 | N45: ='IS Dec KSA'!N45+'IS Dec USA'!N45 -> 26569.25 | O45: ='IS Dec KSA'!O45+'IS Dec USA'!O45 -> 26950.76 | P45: =SUM(Q45:S45) -> 119221.43 | Q45: ='IS Dec KSA'!Q45+'IS Dec USA'!Q45 -> 21297.91 | R45: ='IS Dec KSA'!R45+'IS Dec USA'!R45 -> 49882.6 | S45: ='IS Dec KSA'!S45+'IS Dec USA'!S45 -> 48040.92
B46: Government & Compliance Expense | C46: =G46+H46+L46+P46+F46+E46 -> 29073.83 | D46: =SUM(E46:G46) -> 7668.36 | E46: ='IS Dec KSA'!E46+'IS Dec USA'!E46 -> 1332.26 | F46: ='IS Dec KSA'!F46+'IS Dec USA'!F46 -> 3174.35 | G46: ='IS Dec KSA'!G46+'IS Dec USA'!G46 -> 3161.75 | H46: =I46+J46+K46 -> 9461.39 | I46: ='IS Dec KSA'!I46+'IS Dec USA'!I46 -> 1380.25 | J46: ='IS Dec KSA'!J46+'IS Dec USA'!J46 -> 5155.14 | K46: ='IS Dec KSA'!K46+'IS Dec USA'!K46 -> 2926 | L46: =SUM(M46:O46) -> 3638.5 | M46: ='IS Dec KSA'!M46+'IS Dec USA'!M46 -> 1201.75 | N46: ='IS Dec KSA'!N46+'IS Dec USA'!N46 -> 1656.75 | O46: ='IS Dec KSA'!O46+'IS Dec USA'!O46 -> 780 | P46: =SUM(Q46:S46) -> 8305.58 | Q46: ='IS Dec KSA'!Q46+'IS Dec USA'!Q46 -> 1253.5 | R46: ='IS Dec KSA'!R46+'IS Dec USA'!R46 -> 4165.59 | S46: ='IS Dec KSA'!S46+'IS Dec USA'!S46 -> 2886.49
B47: Legal | C47: =G47+H47+L47+P47+F47+E47 -> 367693.1 | D47: =SUM(E47:G47) -> 215772.63 | E47: ='IS Dec KSA'!E47+'IS Dec USA'!E47 -> 164833.87 | F47: ='IS Dec KSA'!F47+'IS Dec USA'!F47 -> 25147.95 | G47: ='IS Dec KSA'!G47+'IS Dec USA'!G47 -> 25790.81 | H47: =I47+J47+K47 -> 81823.25 | I47: ='IS Dec KSA'!I47+'IS Dec USA'!I47 -> 27904.83 | J47: ='IS Dec KSA'!J47+'IS Dec USA'!J47 -> 49496.4 | K47: ='IS Dec KSA'!K47+'IS Dec USA'!K47 -> 4422.02 | L47: =SUM(M47:O47) -> 31312.2 | M47: ='IS Dec KSA'!M47+'IS Dec USA'!M47 -> 9744.74 | N47: ='IS Dec KSA'!N47+'IS Dec USA'!N47 -> 9744.74 | O47: ='IS Dec KSA'!O47+'IS Dec USA'!O47 -> 11822.72 | P47: =SUM(Q47:S47) -> 38785.02 | Q47: ='IS Dec KSA'!Q47+'IS Dec USA'!Q47 -> 7808.73 | R47: ='IS Dec KSA'!R47+'IS Dec USA'!R47 -> 23167.56 | S47: ='IS Dec KSA'!S47+'IS Dec USA'!S47 -> 7808.73
B48: Depreciation Expenses | C48: =SUM(C49:C51) -> 88776.89 | D48: =SUM(E48:G48) -> 24991.62 | E48: =SUM(E49:E51) -> 8478.56 | F48: =SUM(F49:F51) -> 7889.45 | G48: =SUM(G49:G51) -> 8623.61 | H48: =SUM(H49:H51) -> 24491.16 | I48: =SUM(I49:I51) -> 8533.21 | J48: =SUM(J49:J51) -> 8623.1 | K48: =SUM(K49:K51) -> 7334.85 | L48: =SUM(L49:L51) -> 20209.95 | ... S48: =SUM(S49:S51) -> 6000.35
B49: Depreciation - Furniture & Fixture | C49: =G49+H49+L49+P49+F49+E49 -> 15221.76 | D49: =SUM(E49:G49) -> 3943.41 | E49: ='IS Dec KSA'!E49+'IS Dec USA'!E49 -> 1314.47 | F49: ='IS Dec KSA'!F49+'IS Dec USA'!F49 -> 1314.47 | G49: ='IS Dec KSA'!G49+'IS Dec USA'!G49 -> 1314.47 | H49: =I49+J49+K49 -> 3864.57 | I49: ='IS Dec KSA'!I49+'IS Dec USA'!I49 -> 1314.47 | J49: ='IS Dec KSA'!J49+'IS Dec USA'!J49 -> 1314.47 | K49: ='IS Dec KSA'!K49+'IS Dec USA'!K49 -> 1235.63 | L49: =SUM(M49:O49) -> 3706.89 | M49: ='IS Dec KSA'!M49+'IS Dec USA'!M49 -> 1235.63 | N49: ='IS Dec KSA'!N49+'IS Dec USA'!N49 -> 1235.63 | O49: ='IS Dec KSA'!O49+'IS Dec USA'!O49 -> 1235.63 | P49: =SUM(Q49:S49) -> 3706.89 | Q49: ='IS Dec KSA'!Q49+'IS Dec USA'!Q49 -> 1235.63 | R49: ='IS Dec KSA'!R49+'IS Dec USA'!R49 -> 1235.63 | S49: ='IS Dec KSA'!S49+'IS Dec USA'!S49 -> 1235.63
B50: Depreciation - Motor Vehicle | C50: =G50+H50+L50+P50+F50+E50 -> 14526.77 | D50: =SUM(E50:G50) -> 5039.55 | E50: ='IS Dec KSA'!E50+'IS Dec USA'!E50 -> 1679.85 | F50: ='IS Dec KSA'!F50+'IS Dec USA'!F50 -> 1679.85 | G50: ='IS Dec KSA'!G50+'IS Dec USA'!G50 -> 1679.85 | H50: =I50+J50+K50 -> 4235.06 | I50: ='IS Dec KSA'!I50+'IS Dec USA'!I50 -> 1679.85 | J50: ='IS Dec KSA'!J50+'IS Dec USA'!J50 -> 1679.85 | K50: ='IS Dec KSA'!K50+'IS Dec USA'!K50 -> 875.36 | L50: =SUM(M50:O50) -> 2626.08 | M50: ='IS Dec KSA'!M50+'IS Dec USA'!M50 -> 875.36 | N50: ='IS Dec KSA'!N50+'IS Dec USA'!N50 -> 875.36 | O50: ='IS Dec KSA'!O50+'IS Dec USA'!O50 -> 875.36 | P50: =SUM(Q50:S50) -> 2626.08 | Q50: ='IS Dec KSA'!Q50+'IS Dec USA'!Q50 -> 875.36 | R50: ='IS Dec KSA'!R50+'IS Dec USA'!R50 -> 875.36 | S50: ='IS Dec KSA'!S50+'IS Dec USA'!S50 -> 875.36
B51: Depreciation - Office Equipment's | C51: =G51+H51+L51+P51+F51+E51 -> 59028.36 | D51: =SUM(E51:G51) -> 16008.66 | E51: ='IS Dec KSA'!E51+'IS Dec USA'!E51 -> 5484.24 | F51: ='IS Dec KSA'!F51+'IS Dec USA'!F51 -> 4895.13 | G51: ='IS Dec KSA'!G51+'IS Dec USA'!G51 -> 5629.29 | H51: =I51+J51+K51 -> 16391.53 | I51: ='IS Dec KSA'!I51+'IS Dec USA'!I51 -> 5538.89 | J51: ='IS Dec KSA'!J51+'IS Dec USA'!J51 -> 5628.78 | K51: ='IS Dec KSA'!K51+'IS Dec USA'!K51 -> 5223.86 | L51: =SUM(M51:O51) -> 13876.98 | M51: ='IS Dec KSA'!M51+'IS Dec USA'!M51 -> 4625.66 | N51: ='IS Dec KSA'!N51+'IS Dec USA'!N51 -> 4625.66 | O51: ='IS Dec KSA'!O51+'IS Dec USA'!O51 -> 4625.66 | P51: =SUM(Q51:S51) -> 12751.19 | Q51: ='IS Dec KSA'!Q51+'IS Dec USA'!Q51 -> 4625.66 | R51: ='IS Dec KSA'!R51+'IS Dec USA'!R51 -> 4236.17 | S51: ='IS Dec KSA'!S51+'IS Dec USA'!S51 -> 3889.36
B52: Personnel Expenses | C52: =SUM(C53:C69) -> 5782386.2 | D52: =SUM(E52:G52) -> 1817654.3 | E52: =SUM(E53:E69) -> 715590.13 | F52: =SUM(F53:F69) -> 549140.42 | G52: =SUM(G53:G69) -> 552923.79 | H52: =SUM(H53:H69) -> 1624050.6 | I52: =SUM(I53:I69) -> 548004.74 | J52: =SUM(J53:J69) -> 590153.44 | K52: =SUM(K53:K69) -> 485892.39 | L52: =SUM(L53:L69) -> 1355517.6 | ... S52: =SUM(S53:S69) -> 260401.59
B53: Employee Insurance | C53: =G53+H53+L53+P53+F53+E53 -> 155647.64 | D53: =SUM(E53:G53) -> 55475.28 | E53: ='IS Dec KSA'!E53+'IS Dec USA'!E53 -> 19139.83 | F53: ='IS Dec KSA'!F53+'IS Dec USA'!F53 -> 18825.08 | G53: ='IS Dec KSA'!G53+'IS Dec USA'!G53 -> 17510.37 | H53: =I53+J53+K53 -> 49398.66 | I53: ='IS Dec KSA'!I53+'IS Dec USA'!I53 -> 17220.59 | J53: ='IS Dec KSA'!J53+'IS Dec USA'!J53 -> 16380.48 | K53: ='IS Dec KSA'!K53+'IS Dec USA'!K53 -> 15797.59 | L53: =SUM(M53:O53) -> 37231.82 | M53: ='IS Dec KSA'!M53+'IS Dec USA'!M53 -> 12374.81 | N53: ='IS Dec KSA'!N53+'IS Dec USA'!N53 -> 12614.48 | O53: ='IS Dec KSA'!O53+'IS Dec USA'!O53 -> 12242.53 | P53: =SUM(Q53:S53) -> 13541.88 | Q53: ='IS Dec KSA'!Q53+'IS Dec USA'!Q53 -> 5797.64 | R53: ='IS Dec KSA'!R53+'IS Dec USA'!R53 -> 4107.86 | S53: ='IS Dec KSA'!S53+'IS Dec USA'!S53 -> 3636.38
B54: Leave Pay Expense | C54: =G54+H54+L54+P54+F54+E54 -> 71427.81 | D54: =SUM(E54:G54) -> 58357.68 | E54: ='IS Dec KSA'!E54+'IS Dec USA'!E54 -> 47874.96 | F54: ='IS Dec KSA'!F54+'IS Dec USA'!F54 -> 4523.71 | G54: ='IS Dec KSA'!G54+'IS Dec USA'!G54 -> 5959.01 | H54: =I54+J54+K54 -> 11233.13 | I54: ='IS Dec KSA'!I54+'IS Dec USA'!I54 -> 2420 | J54: ='IS Dec KSA'!J54+'IS Dec USA'!J54 -> 4613.13 | K54: ='IS Dec KSA'!K54+'IS Dec USA'!K54 -> 4200 | L54: =SUM(M54:O54) -> 1837 | M54: ='IS Dec KSA'!M54+'IS Dec USA'!M54 -> 0 | N54: ='IS Dec KSA'!N54+'IS Dec USA'!N54 -> 1837 | O54: ='IS Dec KSA'!O54+'IS Dec USA'!O54 -> 0 | P54: =SUM(Q54:S54) -> 0 | Q54: ='IS Dec KSA'!Q54+'IS Dec USA'!Q54 -> 0 | R54: ='IS Dec KSA'!R54+'IS Dec USA'!R54 -> 0 | S54: ='IS Dec KSA'!S54+'IS Dec USA'!S54 -> 0
B55: Employee Referral Allowance | C55: =G55+H55+L55+P55+F55+E55 -> 13059.86 | D55: =SUM(E55:G55) -> 3000 | E55: ='IS Dec KSA'!E55+'IS Dec USA'!E55 -> 0 | F55: ='IS Dec KSA'!F55+'IS Dec USA'!F55 -> 3000 | G55: ='IS Dec KSA'!G55+'IS Dec USA'!G55 -> 0 | H55: =I55+J55+K55 -> 0 | I55: ='IS Dec KSA'!I55+'IS Dec USA'!I55 -> 0 | J55: ='IS Dec KSA'!J55+'IS Dec USA'!J55 -> 0 | K55: ='IS Dec KSA'!K55+'IS Dec USA'!K55 -> 0 | L55: =SUM(M55:O55) -> 5059.86 | M55: ='IS Dec KSA'!M55+'IS Dec USA'!M55 -> 0 | N55: ='IS Dec KSA'!N55+'IS Dec USA'!N55 -> 682.08 | O55: ='IS Dec KSA'!O55+'IS Dec USA'!O55 -> 4377.78 | P55: =SUM(Q55:S55) -> 5000 | Q55: ='IS Dec KSA'!Q55+'IS Dec USA'!Q55 -> 0 | R55: ='IS Dec KSA'!R55+'IS Dec USA'!R55 -> 5000 | S55: ='IS Dec KSA'!S55+'IS Dec USA'!S55 -> 0
B56: Maintenance Allowance | C56: =G56+H56+L56+P56+F56+E56 -> 50915.87 | D56: =SUM(E56:G56) -> 16500 | E56: ='IS Dec KSA'!E56+'IS Dec USA'!E56 -> 9000 | F56: ='IS Dec KSA'!F56+'IS Dec USA'!F56 -> 3210.43 | G56: ='IS Dec KSA'!G56+'IS Dec USA'!G56 -> 4289.57 | H56: =I56+J56+K56 -> 7891 | I56: ='IS Dec KSA'!I56+'IS Dec USA'!I56 -> 3000 | J56: ='IS Dec KSA'!J56+'IS Dec USA'!J56 -> 1391 | K56: ='IS Dec KSA'!K56+'IS Dec USA'!K56 -> 3500 | L56: =SUM(M56:O56) -> 14714 | M56: ='IS Dec KSA'!M56+'IS Dec USA'!M56 -> 4000 | N56: ='IS Dec KSA'!N56+'IS Dec USA'!N56 -> 7214 | O56: ='IS Dec KSA'!O56+'IS Dec USA'!O56 -> 3500 | P56: =SUM(Q56:S56) -> 11810.87 | Q56: ='IS Dec KSA'!Q56+'IS Dec USA'!Q56 -> 6810.87 | R56: ='IS Dec KSA'!R56+'IS Dec USA'!R56 -> 2500 | S56: ='IS Dec KSA'!S56+'IS Dec USA'!S56 -> 2500
B57: Employee Related Govt Fees | C57: =G57+H57+L57+P57+F57+E57 -> 168634.61 | D57: =SUM(E57:G57) -> 37229.03 | E57: ='IS Dec KSA'!E57+'IS Dec USA'!E57 -> 22339.49 | F57: ='IS Dec KSA'!F57+'IS Dec USA'!F57 -> 5739.54 | G57: ='IS Dec KSA'!G57+'IS Dec USA'!G57 -> 9150 | H57: =I57+J57+K57 -> 71666.75 | I57: ='IS Dec KSA'!I57+'IS Dec USA'!I57 -> 19950 | J57: ='IS Dec KSA'!J57+'IS Dec USA'!J57 -> 19250 | K57: ='IS Dec KSA'!K57+'IS Dec USA'!K57 -> 32466.75 | L57: =SUM(M57:O57) -> 42651.83 | M57: ='IS Dec KSA'!M57+'IS Dec USA'!M57 -> 17938 | N57: ='IS Dec KSA'!N57+'IS Dec USA'!N57 -> 18013 | O57: ='IS Dec KSA'!O57+'IS Dec USA'!O57 -> 6700.83 | P57: =SUM(Q57:S57) -> 17087 | Q57: ='IS Dec KSA'!Q57+'IS Dec USA'!Q57 -> 17087 | R57: ='IS Dec KSA'!R57+'IS Dec USA'!R57 -> 0 | S57: ='IS Dec KSA'!S57+'IS Dec USA'!S57 -> 0
B58: Telecom Allowance | C58: =G58+H58+L58+P58+F58+E58 -> 16448.46 | D58: =SUM(E58:G58) -> 6787.9 | E58: ='IS Dec KSA'!E58+'IS Dec USA'!E58 -> 3400 | F58: ='IS Dec KSA'!F58+'IS Dec USA'!F58 -> 1493.95 | G58: ='IS Dec KSA'!G58+'IS Dec USA'!G58 -> 1893.95 | H58: =I58+J58+K58 -> 3081.85 | I58: ='IS Dec KSA'!I58+'IS Dec USA'!I58 -> 1293.95 | J58: ='IS Dec KSA'!J58+'IS Dec USA'!J58 -> 93.95 | K58: ='IS Dec KSA'!K58+'IS Dec USA'!K58 -> 1693.95 | L58: =SUM(M58:O58) -> 3578.13 | M58: ='IS Dec KSA'!M58+'IS Dec USA'!M58 -> 1093.95 | N58: ='IS Dec KSA'!N58+'IS Dec USA'!N58 -> 1284.18 | O58: ='IS Dec KSA'!O58+'IS Dec USA'!O58 -> 1200 | P58: =SUM(Q58:S58) -> 3000.58 | Q58: ='IS Dec KSA'!Q58+'IS Dec USA'!Q58 -> 1400 | R58: ='IS Dec KSA'!R58+'IS Dec USA'!R58 -> 800.58 | S58: ='IS Dec KSA'!S58+'IS Dec USA'!S58 -> 800
B59: US Employer Taxes | C59: =G59+H59+L59+P59+F59+E59 -> 35255.31 | D59: =SUM(E59:G59) -> 12383.44 | E59: ='IS Dec KSA'!E59+'IS Dec USA'!E59 -> 3054.31 | F59: ='IS Dec KSA'!F59+'IS Dec USA'!F59 -> 3445.67 | G59: ='IS Dec KSA'!G59+'IS Dec USA'!G59 -> 5883.46 | H59: =I59+J59+K59 -> 14128.5 | I59: ='IS Dec KSA'!I59+'IS Dec USA'!I59 -> 4584.32 | J59: ='IS Dec KSA'!J59+'IS Dec USA'!J59 -> 4830.81 | K59: ='IS Dec KSA'!K59+'IS Dec USA'!K59 -> 4713.37 | L59: =SUM(M59:O59) -> 8743.37 | M59: ='IS Dec KSA'!M59+'IS Dec USA'!M59 -> 4247.67 | N59: ='IS Dec KSA'!N59+'IS Dec USA'!N59 -> 4495.7 | O59: ='IS Dec KSA'!O59+'IS Dec USA'!O59 -> 0 | P59: =SUM(Q59:S59) -> 0 | Q59: ='IS Dec KSA'!Q59+'IS Dec USA'!Q59 -> 0 | R59: ='IS Dec KSA'!R59+'IS Dec USA'!R59 -> 0 | S59: ='IS Dec KSA'!S59+'IS Dec USA'!S59 -> 0
B60: GOSI | C60: =G60+H60+L60+P60+F60+E60 -> 167751.58 | D60: =SUM(E60:G60) -> 51066.62 | E60: ='IS Dec KSA'!E60+'IS Dec USA'!E60 -> 17220.56 | F60: ='IS Dec KSA'!F60+'IS Dec USA'!F60 -> 17776.14 | G60: ='IS Dec KSA'!G60+'IS Dec USA'!G60 -> 16069.92 | H60: =I60+J60+K60 -> 47360.02 | I60: ='IS Dec KSA'!I60+'IS Dec USA'!I60 -> 15944.87 | J60: ='IS Dec KSA'!J60+'IS Dec USA'!J60 -> 15669.64 | K60: ='IS Dec KSA'!K60+'IS Dec USA'!K60 -> 15745.51 | L60: =SUM(M60:O60) -> 42946.21 | M60: ='IS Dec KSA'!M60+'IS Dec USA'!M60 -> 14900.91 | N60: ='IS Dec KSA'!N60+'IS Dec USA'!N60 -> 14377.1 | O60: ='IS Dec KSA'!O60+'IS Dec USA'!O60 -> 13668.2 | P60: =SUM(Q60:S60) -> 26378.73 | Q60: ='IS Dec KSA'!Q60+'IS Dec USA'!Q60 -> 13429.24 | R60: ='IS Dec KSA'!R60+'IS Dec USA'!R60 -> 8948.41 | S60: ='IS Dec KSA'!S60+'IS Dec USA'!S60 -> 4001.08
B61: HUMAN RESOUACES DEVELOPMENT FUND | C61: =G61+H61+L61+P61+F61+E61 -> -81000 | D61: =SUM(E61:G61) -> -30000 | E61: ='IS Dec KSA'!E61+'IS Dec USA'!E61 -> -15000 | F61: ='IS Dec KSA'!F61+'IS Dec USA'!F61 -> 0 | G61: ='IS Dec KSA'!G61+'IS Dec USA'!G61 -> -15000 | H61: =I61+J61+K61 -> -15000 | I61: ='IS Dec KSA'!I61+'IS Dec USA'!I61 -> -3000 | J61: ='IS Dec KSA'!J61+'IS Dec USA'!J61 -> -6000 | K61: ='IS Dec KSA'!K61+'IS Dec USA'!K61 -> -6000 | L61: =SUM(M61:O61) -> -12000 | M61: ='IS Dec KSA'!M61+'IS Dec USA'!M61 -> 0 | N61: ='IS Dec KSA'!N61+'IS Dec USA'!N61 -> -6000 | O61: ='IS Dec KSA'!O61+'IS Dec USA'!O61 -> -6000 | P61: =SUM(Q61:S61) -> -24000 | Q61: ='IS Dec KSA'!Q61+'IS Dec USA'!Q61 -> -6000 | R61: ='IS Dec KSA'!R61+'IS Dec USA'!R61 -> -6000 | S61: ='IS Dec KSA'!S61+'IS Dec USA'!S61 -> -12000
B62: Recruitments & Visas | C62: =G62+H62+L62+P62+F62+E62 -> 55227.62 | D62: =SUM(E62:G62) -> 5853.29 | E62: ='IS Dec KSA'!E62+'IS Dec USA'!E62 -> 0 | F62: ='IS Dec KSA'!F62+'IS Dec USA'!F62 -> 0 | G62: ='IS Dec KSA'!G62+'IS Dec USA'!G62 -> 5853.29 | H62: =I62+J62+K62 -> 44447.04 | I62: ='IS Dec KSA'!I62+'IS Dec USA'!I62 -> 950.37 | J62: ='IS Dec KSA'!J62+'IS Dec USA'!J62 -> 43496.67 | K62: ='IS Dec KSA'!K62+'IS Dec USA'!K62 -> 0 | L62: =SUM(M62:O62) -> 0 | M62: ='IS Dec KSA'!M62+'IS Dec USA'!M62 -> 0 | N62: ='IS Dec KSA'!N62+'IS Dec USA'!N62 -> 0 | O62: ='IS Dec KSA'!O62+'IS Dec USA'!O62 -> 0 | P62: =SUM(Q62:S62) -> 4927.29 | Q62: ='IS Dec KSA'!Q62+'IS Dec USA'!Q62 -> 0 | R62: ='IS Dec KSA'!R62+'IS Dec USA'!R62 -> 0 | S62: ='IS Dec KSA'!S62+'IS Dec USA'!S62 -> 4927.29
B63: Bonus | C63: =G63+H63+L63+P63+F63+E63 -> 98517.64 | D63: =SUM(E63:G63) -> 5839.23 | E63: ='IS Dec KSA'!E63+'IS Dec USA'!E63 -> 2739 | F63: ='IS Dec KSA'!F63+'IS Dec USA'!F63 -> 0 | G63: ='IS Dec KSA'!G63+'IS Dec USA'!G63 -> 3100.23 | H63: =I63+J63+K63 -> 18380.97 | I63: ='IS Dec KSA'!I63+'IS Dec USA'!I63 -> 1000 | J63: ='IS Dec KSA'!J63+'IS Dec USA'!J63 -> 14750.37 | K63: ='IS Dec KSA'!K63+'IS Dec USA'!K63 -> 2630.6 | L63: =SUM(M63:O63) -> 26020.39 | M63: ='IS Dec KSA'!M63+'IS Dec USA'!M63 -> 82.68 | N63: ='IS Dec KSA'!N63+'IS Dec USA'!N63 -> 25937.71 | O63: ='IS Dec KSA'!O63+'IS Dec USA'!O63 -> 0 | P63: =SUM(Q63:S63) -> 48277.05 | Q63: ='IS Dec KSA'!Q63+'IS Dec USA'!Q63 -> 48277.05 | R63: ='IS Dec KSA'!R63+'IS Dec USA'!R63 -> 0 | S63: ='IS Dec KSA'!S63+'IS Dec USA'!S63 -> 0
B64: Salaries - Basic | C64: =G64+H64+L64+P64+F64+E64 -> 4141100.9 | D64: =SUM(E64:G64) -> 1220657.1 | E64: ='IS Dec KSA'!E64+'IS Dec USA'!E64 -> 414829.56 | F64: ='IS Dec KSA'!F64+'IS Dec USA'!F64 -> 392289.44 | G64: ='IS Dec KSA'!G64+'IS Dec USA'!G64 -> 413538.15 | H64: =I64+J64+K64 -> 1150987.6 | I64: ='IS Dec KSA'!I64+'IS Dec USA'!I64 -> 399852.05 | J64: ='IS Dec KSA'!J64+'IS Dec USA'!J64 -> 395538.62 | K64: ='IS Dec KSA'!K64+'IS Dec USA'!K64 -> 355596.89 | L64: =SUM(M64:O64) -> 1024570.3 | M64: ='IS Dec KSA'!M64+'IS Dec USA'!M64 -> 353787.79 | N64: ='IS Dec KSA'!N64+'IS Dec USA'!N64 -> 355254.11 | O64: ='IS Dec KSA'!O64+'IS Dec USA'!O64 -> 315528.44 | P64: =SUM(Q64:S64) -> 744885.87 | Q64: ='IS Dec KSA'!Q64+'IS Dec USA'!Q64 -> 304075.07 | R64: ='IS Dec KSA'!R64+'IS Dec USA'!R64 -> 231802.68 | S64: ='IS Dec KSA'!S64+'IS Dec USA'!S64 -> 209008.12
... B69: Staff Education/Growth Allowance | C69: =G69+H69+L69+P69+F69+E69 -> 3571.25 | D69: =SUM(E69:G69) -> 37.54 | E69: ='IS Dec KSA'!E69+'IS Dec USA'!E69 -> 0 | F69: ='IS Dec KSA'!F69+'IS Dec USA'!F69 -> 37.54 | G69: ='IS Dec KSA'!G69+'IS Dec USA'!G69 -> 0 | H69: =I69+J69+K69 -> 956.94 | I69: ='IS Dec KSA'!I69+'IS Dec USA'!I69 -> 0 | J69: ='IS Dec KSA'!J69+'IS Dec USA'!J69 -> 1126.05 | K69: ='IS Dec KSA'!K69+'IS Dec USA'!K69 -> -169.11 | L69: =SUM(M69:O69) -> 2576.77 | M69: ='IS Dec KSA'!M69+'IS Dec USA'!M69 -> 735.35 | N69: ='IS Dec KSA'!N69+'IS Dec USA'!N69 -> 0 | O69: ='IS Dec KSA'!O69+'IS Dec USA'!O69 -> 1841.42 | P69: =SUM(Q69:S69) -> 0 | Q69: ='IS Dec KSA'!Q69+'IS Dec USA'!Q69 -> 0 | R69: ='IS Dec KSA'!R69+'IS Dec USA'!R69 -> 0 | S69: ='IS Dec KSA'!S69+'IS Dec USA'!S69 -> 0
B70: Operating expenses | C70: =+C52+C48+C44+C34+C17 -> 8738025.3 | D70: =SUM(E70:G70) -> 3118816.4 | E70: =+E52+E48+E44+E34+E17 -> 1379932.6 | F70: =+F52+F48+F44+F34+F17 -> 825183.01 | G70: =+G52+G48+G44+G34+G17 -> 913700.8 | H70: =+H52+H48+H44+H34+H17 -> 2299137.1 | I70: =+I52+I48+I44+I34+I17 -> 822235.57 | J70: =+J52+J48+J44+J34+J17 -> 805758.24 | K70: =+K52+K48+K44+K34+K17 -> 671143.3 | L70: =+L52+L48+L44+L34+L17 -> 1856528.2 | ... S70: =+S52+S48+S44+S34+S17 -> 418397.07
B73: Net operating profit / (loss) | C73: =G73+H73+L73+P73+F73+E73 -> -1058242.7 | D73: =SUM(E73:G73) -> -806452.83 | E73: =SUM(E13+E14)-E70 -> -338792.37 | F73: =SUM(F13+F14)-F70 -> 10203.62 | G73: =SUM(G13+G14)-G70 -> -477864.08 | H73: =H15-H70 -> -453923.9 | I73: =I15-I70 -> -407493.02 | J73: =J15-J70 -> -293566.79 | K73: =K15-K70 -> 247135.91 | L73: =L15-L70 -> -16582.14 | M73: =M15-M70 -> 125154.65 | N73: =N15-N70 -> 36772.27 | O73: =O15-O70 -> -178509.06 | ... S73: =S15-S70 -> -134455.82
B76: Exchange Gain or Loss | C76: =G76+H76+L76+P76+F76+E76 -> -52218.42 | D76: =SUM(E76:G76) -> -50256.23 | E76: ='IS Dec KSA'!E76+'IS Dec USA'!E76 -> -49317.86 | F76: ='IS Dec KSA'!F76+'IS Dec USA'!F76 -> -1238.18 | G76: ='IS Dec KSA'!G76+'IS Dec USA'!G76 -> 299.81 | H76: =I76+J76+K76 -> -1737.49 | I76: ='IS Dec KSA'!I76+'IS Dec USA'!I76 -> 0.02 | J76: ='IS Dec KSA'!J76+'IS Dec USA'!J76 -> -1737.46 | K76: ='IS Dec KSA'!K76+'IS Dec USA'!K76 -> -0.05 | L76: =SUM(M76:O76) -> -224.71 | M76: ='IS Dec KSA'!M76+'IS Dec USA'!M76 -> 0.03 | N76: ='IS Dec KSA'!N76+'IS Dec USA'!N76 -> 0 | O76: ='IS Dec KSA'!O76+'IS Dec USA'!O76 -> -224.74 | P76: =SUM(Q76:S76) -> 0.01 | Q76: ='IS Dec KSA'!Q76+'IS Dec USA'!Q76 -> 0 | R76: ='IS Dec KSA'!R76+'IS Dec USA'!R76 -> 0.01 | S76: ='IS Dec KSA'!S76+'IS Dec USA'!S76 -> 0
B78: Gain Or Loss on Disposal | C78: =G78+H78+L78+P78+F78+E78 -> 6362.26 | D78: =SUM(E78:G78) -> 6362.26 | E78: ='IS Dec KSA'!E78+'IS Dec USA'!E78 -> 6362.26
B81: Investor's Profit sharing (Unrealized) | C81: =G81+H81+L81+P81+F81+E81 -> -706164.61 | D81: =SUM(E81:G81) -> 440000 | E81: ='IS Dec KSA'!E81+'IS Dec USA'!E81 -> 475000 | F81: ='IS Dec KSA'!F81+'IS Dec USA'!F81 -> -20000 | G81: ='IS Dec KSA'!G81+'IS Dec USA'!G81 -> -15000 | H81: =I81+J81+K81 -> -369927.06 | I81: ='IS Dec KSA'!I81+'IS Dec USA'!I81 -> -90000 | J81: ='IS Dec KSA'!J81+'IS Dec USA'!J81 -> -108312.47 | K81: ='IS Dec KSA'!K81+'IS Dec USA'!K81 -> -171614.59 | L81: =SUM(M81:O81) -> -430787.54 | M81: ='IS Dec KSA'!M81+'IS Dec USA'!M81 -> -164188.26 | N81: ='IS Dec KSA'!N81+'IS Dec USA'!N81 -> -170587.62 | O81: ='IS Dec KSA'!O81+'IS Dec USA'!O81 -> -96011.66 | P81: =SUM(Q81:S81) -> -345450.01 | Q81: ='IS Dec KSA'!Q81+'IS Dec USA'!Q81 -> -184731.71 | R81: ='IS Dec KSA'!R81+'IS Dec USA'!R81 -> -92622.21 | S81: ='IS Dec KSA'!S81+'IS Dec USA'!S81 -> -68096.09
B83: Short term financing expense (Al-Raeda) | C83: =G83+H83+L83+P83+F83+E83 -> -365252.64 | D83: =SUM(E83:G83) -> -90849.99 | E83: ='IS Dec KSA'!E83+'IS Dec USA'!E83 -> -30283.33 | F83: ='IS Dec KSA'!F83+'IS Dec USA'!F83 -> -30283.33 | G83: ='IS Dec KSA'!G83+'IS Dec USA'!G83 -> -30283.33 | H83: =I83+J83+K83 -> -90849.99 | I83: ='IS Dec KSA'!I83+'IS Dec USA'!I83 -> -30283.33 | J83: ='IS Dec KSA'!J83+'IS Dec USA'!J83 -> -30283.33 | K83: ='IS Dec KSA'!K83+'IS Dec USA'!K83 -> -30283.33 | L83: =SUM(M83:O83) -> -90849.99 | M83: ='IS Dec KSA'!M83+'IS Dec USA'!M83 -> -30283.33 | N83: ='IS Dec KSA'!N83+'IS Dec USA'!N83 -> -30283.33 | O83: ='IS Dec KSA'!O83+'IS Dec USA'!O83 -> -30283.33 | P83: =SUM(Q83:S83) -> -92702.67 | Q83: ='IS Dec KSA'!Q83+'IS Dec USA'!Q83 -> -30283.33 | R83: ='IS Dec KSA'!R83+'IS Dec USA'!R83 -> -30283.33 | S83: ='IS Dec KSA'!S83+'IS Dec USA'!S83 -> -32136.01
B85: Financing expense (Arbah) | C85: =G85+H85+L85+P85+F85+E85 -> -497027.78 | D85: =SUM(E85:G85) -> -497027.78 | E85: ='IS Dec KSA'!E85+'IS Dec USA'!E85 -> -255965.28 | F85: ='IS Dec KSA'!F85+'IS Dec USA'!F85 -> -118416.67 | G85: ='IS Dec KSA'!G85+'IS Dec USA'!G85 -> -122645.83
B87: Financing expense (STV) | C87: =G87+H87+L87+P87+F87+E87 -> -69147.2 | D87: =SUM(E87:G87) -> -69147.2 | E87: ='IS Dec KSA'!E87+'IS Dec USA'!E87 -> -17850.5 | F87: ='IS Dec KSA'!F87+'IS Dec USA'!F87 -> -51296.7
B89: Financing Processing Fee Expense | C89: =G89+H89+L89+P89+F89+E89 -> -102500 | D89: =SUM(E89:G89) -> -102500 | E89: ='IS Dec KSA'!E89+'IS Dec USA'!E89 -> 0 | F89: ='IS Dec KSA'!F89+'IS Dec USA'!F89 -> -50000 | G89: ='IS Dec KSA'!G89+'IS Dec USA'!G89 -> -52500
B91: Fundraising Expense | C91: =G91+H91+L91+P91+F91+E91 -> -9313.5 | D91: =SUM(E91:G91) -> -7091.28 | E91: ='IS Dec KSA'!E91+'IS Dec USA'!E91 -> -2363.76 | F91: ='IS Dec KSA'!F91+'IS Dec USA'!F91 -> -2363.76 | G91: ='IS Dec KSA'!G91+'IS Dec USA'!G91 -> -2363.76 | H91: =I91+J91+K91 -> -2222.22 | I91: ='IS Dec KSA'!I91+'IS Dec USA'!I91 -> -1111.11 | J91: ='IS Dec KSA'!J91+'IS Dec USA'!J91 -> -1111.11 | K91: ='IS Dec KSA'!K91+'IS Dec USA'!K91 -> 0 | L91: =SUM(M91:O91) -> 0 | M91: ='IS Dec KSA'!M91+'IS Dec USA'!M91 -> 0 | N91: ='IS Dec KSA'!N91+'IS Dec USA'!N91 -> 0 | O91: ='IS Dec KSA'!O91+'IS Dec USA'!O91 -> 0 | P91: =SUM(Q91:S91) -> 0 | Q91: ='IS Dec KSA'!Q91+'IS Dec USA'!Q91 -> 0 | R91: ='IS Dec KSA'!R91+'IS Dec USA'!R91 -> 0 | S91: ='IS Dec KSA'!S91+'IS Dec USA'!S91 -> 0
B93: Non-operating Income/(Expenses) | C93: =G93+H93+L93+P93+F93+E93 -> 0 | D93: =SUM(E93:G93) -> 0 | E93: 0 | F93: 0 | G93: 0 | H93: =I93+J93+K93 -> 0 | I93: ='IS Dec KSA'!I93+'IS Dec USA'!I93 -> 0 | J93: ='IS Dec KSA'!J93+'IS Dec USA'!J93 -> 0 | K93: ='IS Dec KSA'!K93+'IS Dec USA'!K93 -> 0 | L93: =SUM(M93:O93) -> 0 | M93: ='IS Dec KSA'!M93+'IS Dec USA'!M93 -> 0 | N93: ='IS Dec KSA'!N93+'IS Dec USA'!N93 -> 0 | O93: ='IS Dec KSA'!O93+'IS Dec USA'!O93 -> 0 | P93: =SUM(Q93:S93) -> 0 | Q93: ='IS Dec KSA'!Q93+'IS Dec USA'!Q93 -> 0 | R93: ='IS Dec KSA'!R93+'IS Dec USA'!R93 -> 0 | S93: ='IS Dec KSA'!S93+'IS Dec USA'!S93 -> 0
B95: Zakat / Income Tax | C95: =G95+H95+L95+P95+F95+E95 -> 5910.49 | D95: =SUM(E95:G95) -> 0 | E95: 0 | F95: 0 | G95: 0 | H95: =I95+J95+K95 -> 0 | I95: ='IS Dec KSA'!I95+'IS Dec USA'!I95 -> 0 | J95: ='IS Dec KSA'!J95+'IS Dec USA'!J95 -> 0 | K95: ='IS Dec KSA'!K95+'IS Dec USA'!K95 -> 0 | L95: =SUM(M95:O95) -> 5910.49 | M95: ='IS Dec KSA'!M95+'IS Dec USA'!M95 -> 0 | N95: ='IS Dec KSA'!N95+'IS Dec USA'!N95 -> 5910.49 | O95: ='IS Dec KSA'!O95+'IS Dec USA'!O95 -> 0 | P95: =SUM(Q95:S95) -> 0 | Q95: ='IS Dec KSA'!Q95+'IS Dec USA'!Q95 -> 0 | R95: ='IS Dec KSA'!R95+'IS Dec USA'!R95 -> 0 | S95: ='IS Dec KSA'!S95+'IS Dec USA'!S95 -> 0
B97: Net income / (loss) | C97: =+C73+C81+C83+C93+C95+C76+C85+C89+C91+C87+C78 -> -2847594.1 | D97: =+D73+D81+D83+D93+D95+D76+D85+D89+D91+D87+D78 -> -1176963.1 | E97: =+E73+E81+E83+E93+E95+E76+E85+E89+E91+E87+E78 -> -213210.84 | F97: =+F73+F81+F83+F93+F95+F76+F85+F89+F91+F87+F78 -> -263395.02 | G97: =+G73+G81+G83+G93+G95+G76+G85+G89+G91+G87+G78 -> -700357.19 | H97: =+H73+H81+H83+H93+H95+H76+H85+H89+H91+H87+H78 -> -918660.66 | I97: =+I73+I81+I83+I93+I95+I76+I85+I89+I91+I87+I78 -> -528887.44 | J97: =+J73+J81+J83+J93+J95+J76+J85+J89+J91+J87+J78 -> -435011.16 | ... S97: =+S73+S81+S83+S93+S95+S76+S85+S89+S91+S87+S78 -> -234687.92

Sheet BS Dec Consolidated
C1: 45321 | D1: =EDATE(C1,1) -> 45351 | E1: =EDATE(D1,1) -> 45380 | F1: =EDATE(E1,1) -> 45411 | G1: =EDATE(F1,1) -> 45441 | H1: =EDATE(G1,1) -> 45472 | I1: =EDATE(H1,1) -> 45502 | J1: =EDATE(I1,1) -> 45533 | K1: =EDATE(J1,1) -> 45564 | ... N1: =EDATE(M1,1) -> 45655
C2: 12 | D2: =C2-1 -> 11 | E2: =D2-1 -> 10 | F2: =E2-1 -> 9 | G2: =F2-1 -> 8 | H2: =G2-1 -> 7 | I2: =H2-1 -> 6 | J2: =I2-1 -> 5 | K2: =J2-1 -> 4 | ... N2: =M2-1 -> 1
C3: {=INDEX($C$5:$N$5,,MATCH(C2,$C$4:$N$4,FALSE))} -> 33406.83 | D3: {=INDEX($C$5:$N$5,,MATCH(D2,$C$4:$N$4,FALSE))} -> 33406.83 | E3: {=INDEX($C$5:$N$5,,MATCH(E2,$C$4:$N$4,FALSE))} -> 33406.83 | F3: {=INDEX($C$5:$N$5,,MATCH(F2,$C$4:$N$4,FALSE))} -> 33406.83 | G3: {=INDEX($C$5:$N$5,,MATCH(G2,$C$4:$N$4,FALSE))} -> 33406.83 | H3: {=INDEX($C$5:$N$5,,MATCH(H2,$C$4:$N$4,FALSE))} -> 33406.83 | I3: {=INDEX($C$5:$N$5,,MATCH(I2,$C$4:$N$4,FALSE))} -> 33406.83 | J3: {=INDEX($C$5:$N$5,,MATCH(J2,$C$4:$N$4,FALSE))} -> 33406.83 | ... N3: {=INDEX($C$5:$N$5,,MATCH(N2,$C$4:$N$4,FALSE))} -> -406009
C4: 1 | D4: 2 | E4: 3 | F4: 4 | G4: 5 | H4: 6 | I4: 7 | J4: 8 | K4: 9 | L4: 10 | M4: 11 | N4: 12
C5: =C29 -> -406009 | D5: =D109 -> 33406.83 | E5: =E109 -> 33406.83 | F5: =F109 -> 33406.83 | G5: =G109 -> 33406.83 | H5: =H109 -> 33406.83 | I5: =I109 -> 33406.83 | J5: =J109 -> 33406.83 | K5: =K109 -> 33406.83 | ... N5: =N109 -> 33406.83
B6: STATEMENT OF FINANCIAL POSITION (US SAR) | C6: 45657 | D6: 45626 | E6: 45596 | F6: 45565 | G6: 45535 | H6: 45504 | I6: 45473 | J6: 45443 | K6: 45412 | L6: 45382 | M6: 45350 | N6: 45322
B7: AS OF 31st Dec 2024
B8: ASSETS | C8: =C29-D29 -> -203009
B10: Cash and Bank Balances | C10: =SUM(C11:C25) -> 12456987 | D10: =SUM(D11:D25) -> 15983087 | E10: =SUM(E11:E25) -> 17152411 | F10: =SUM(F11:F25) -> 7073737 | G10: =SUM(G11:G25) -> 5011742.4 | H10: =SUM(H11:H25) -> 8545313.1 | I10: =SUM(I11:I25) -> 10870209 | J10: =SUM(J11:J25) -> 4780224.5 | ... N10: =SUM(N11:N25) -> 9223746.7
B11: ALINMA BILDNW FEE | C11: ='BS Dec KSA'!C11+'BS Dec USA'!C11 -> 0 | D11: ='BS Dec KSA'!D11+'BS Dec USA'!D11 -> 0 | E11: ='BS Dec KSA'!E11+'BS Dec USA'!E11 -> 0 | F11: ='BS Dec KSA'!F11+'BS Dec USA'!F11 -> 0 | G11: ='BS Dec KSA'!G11+'BS Dec USA'!G11 -> 0 | H11: ='BS Dec KSA'!H11+'BS Dec USA'!H11 -> 75.7 | I11: ='BS Dec KSA'!I11+'BS Dec USA'!I11 -> 75.7 | J11: ='BS Dec KSA'!J11+'BS Dec USA'!J11 -> 75.7 | ... N11: ='BS Dec KSA'!N11+'BS Dec USA'!N11 -> 26646.61
B12: ALINMA BILDNW PROFIT | C12: ='BS Dec KSA'!C12+'BS Dec USA'!C12 -> 140103.67 | D12: ='BS Dec KSA'!D12+'BS Dec USA'!D12 -> 140103.67 | E12: ='BS Dec KSA'!E12+'BS Dec USA'!E12 -> 140103.67 | F12: ='BS Dec KSA'!F12+'BS Dec USA'!F12 -> 0 | G12: ='BS Dec KSA'!G12+'BS Dec USA'!G12 -> 0 | H12: ='BS Dec KSA'!H12+'BS Dec USA'!H12 -> 569757.95 | I12: ='BS Dec KSA'!I12+'BS Dec USA'!I12 -> 0 | J12: ='BS Dec KSA'!J12+'BS Dec USA'!J12 -> 0 | ... N12: ='BS Dec KSA'!N12+'BS Dec USA'!N12 -> 408472.76
B13: ALINMA CLIENT PROFIT | C13: ='BS Dec KSA'!C13+'BS Dec USA'!C13 -> 166842.98 | D13: ='BS Dec KSA'!D13+'BS Dec USA'!D13 -> 166834.93 | E13: ='BS Dec KSA'!E13+'BS Dec USA'!E13 -> 166834.93 | F13: ='BS Dec KSA'!F13+'BS Dec USA'!F13 -> 339620.94 | G13: ='BS Dec KSA'!G13+'BS Dec USA'!G13 -> 339620.94 | H13: ='BS Dec KSA'!H13+'BS Dec USA'!H13 -> -8.05 | I13: ='BS Dec KSA'!I13+'BS Dec USA'!I13 -> 1708.15 | J13: ='BS Dec KSA'!J13+'BS Dec USA'!J13 -> 1708.15 | ... N13: ='BS Dec KSA'!N13+'BS Dec USA'!N13 -> 188464.65
B14: ALINMA DINAR DEALs PROFIT | C14: ='BS Dec KSA'!C14+'BS Dec USA'!C14 -> 30000 | D14: ='BS Dec KSA'!D14+'BS Dec USA'!D14 -> 0 | E14: ='BS Dec KSA'!E14+'BS Dec USA'!E14 -> 0 | F14: ='BS Dec KSA'!F14+'BS Dec USA'!F14 -> 0 | G14: ='BS Dec KSA'!G14+'BS Dec USA'!G14 -> 0 | H14: ='BS Dec KSA'!H14+'BS Dec USA'!H14 -> 165000 | I14: ='BS Dec KSA'!I14+'BS Dec USA'!I14 -> 0 | J14: ='BS Dec KSA'!J14+'BS Dec USA'!J14 -> 0 | ... N14: ='BS Dec KSA'!N14+'BS Dec USA'!N14 -> 0
B15: ALINMA DINAR DEALs VAT | C15: ='BS Dec KSA'!C15+'BS Dec USA'!C15 -> 0 | D15: ='BS Dec KSA'!D15+'BS Dec USA'!D15 -> 0 | E15: ='BS Dec KSA'!E15+'BS Dec USA'!E15 -> 0 | F15: ='BS Dec KSA'!F15+'BS Dec USA'!F15 -> 0 | G15: ='BS Dec KSA'!G15+'BS Dec USA'!G15 -> 0 | H15: ='BS Dec KSA'!H15+'BS Dec USA'!H15 -> 0 | I15: ='BS Dec KSA'!I15+'BS Dec USA'!I15 -> 0 | J15: ='BS Dec KSA'!J15+'BS Dec USA'!J15 -> 0 | ... N15: ='BS Dec KSA'!N15+'BS Dec USA'!N15 -> 0
B16: ALINMA EQUITY | C16: ='BS Dec KSA'!C16+'BS Dec USA'!C16 -> 1315636.9 | D16: ='BS Dec KSA'!D16+'BS Dec USA'!D16 -> 2292020.2 | E16: ='BS Dec KSA'!E16+'BS Dec USA'!E16 -> 1849786.1 | F16: ='BS Dec KSA'!F16+'BS Dec USA'!F16 -> 88790.6 | G16: ='BS Dec KSA'!G16+'BS Dec USA'!G16 -> 1257082.2 | H16: ='BS Dec KSA'!H16+'BS Dec USA'!H16 -> 46543.89 | I16: ='BS Dec KSA'!I16+'BS Dec USA'!I16 -> 168320.11 | J16: ='BS Dec KSA'!J16+'BS Dec USA'!J16 -> 23714.23 | ... N16: ='BS Dec KSA'!N16+'BS Dec USA'!N16 -> 1030009.5
B17: ALINMA USD | C17: ='BS Dec KSA'!C17+'BS Dec USA'!C17 -> 0 | D17: ='BS Dec KSA'!D17+'BS Dec USA'!D17 -> 0 | E17: ='BS Dec KSA'!E17+'BS Dec USA'!E17 -> 0 | F17: ='BS Dec KSA'!F17+'BS Dec USA'!F17 -> 0 | G17: ='BS Dec KSA'!G17+'BS Dec USA'!G17 -> 0 | H17: ='BS Dec KSA'!H17+'BS Dec USA'!H17 -> 356567.64 | I17: ='BS Dec KSA'!I17+'BS Dec USA'!I17 -> 686567.64 | J17: ='BS Dec KSA'!J17+'BS Dec USA'!J17 -> 1186567.6 | ... N17: ='BS Dec KSA'!N17+'BS Dec USA'!N17 -> 0.44
B18: ALINMA VAT | C18: ='BS Dec KSA'!C18+'BS Dec USA'!C18 -> 131821.9 | D18: ='BS Dec KSA'!D18+'BS Dec USA'!D18 -> 100685.09 | E18: ='BS Dec KSA'!E18+'BS Dec USA'!E18 -> 88071.43 | F18: ='BS Dec KSA'!F18+'BS Dec USA'!F18 -> 67480.41 | G18: ='BS Dec KSA'!G18+'BS Dec USA'!G18 -> 29428.08 | H18: ='BS Dec KSA'!H18+'BS Dec USA'!H18 -> 29383.75 | I18: ='BS Dec KSA'!I18+'BS Dec USA'!I18 -> 29383.75 | J18: ='BS Dec KSA'!J18+'BS Dec USA'!J18 -> 39479.28 | ... N18: ='BS Dec KSA'!N18+'BS Dec USA'!N18 -> 19246.15
B19: ALINMA-DEBT | C19: ='BS Dec KSA'!C19+'BS Dec USA'!C19 -> 8593232.1 | D19: ='BS Dec KSA'!D19+'BS Dec USA'!D19 -> 10906870 | E19: ='BS Dec KSA'!E19+'BS Dec USA'!E19 -> 12317444 | F19: ='BS Dec KSA'!F19+'BS Dec USA'!F19 -> 3467930 | G19: ='BS Dec KSA'!G19+'BS Dec USA'!G19 -> 135882.26 | H19: ='BS Dec KSA'!H19+'BS Dec USA'!H19 -> 3806484.8 | I19: ='BS Dec KSA'!I19+'BS Dec USA'!I19 -> 7042461.1 | J19: ='BS Dec KSA'!J19+'BS Dec USA'!J19 -> 1958900.2 | ... N19: ='BS Dec KSA'!N19+'BS Dec USA'!N19 -> 2883475.3
B20: ANB-BILDNW TRADINGCOMPANY | C20: ='BS Dec KSA'!C20+'BS Dec USA'!C20 -> 6 | D20: ='BS Dec KSA'!D20+'BS Dec USA'!D20 -> 6 | E20: ='BS Dec KSA'!E20+'BS Dec USA'!E20 -> 6 | F20: ='BS Dec KSA'!F20+'BS Dec USA'!F20 -> 6 | G20: ='BS Dec KSA'!G20+'BS Dec USA'!G20 -> 6 | H20: ='BS Dec KSA'!H20+'BS Dec USA'!H20 -> 6 | I20: ='BS Dec KSA'!I20+'BS Dec USA'!I20 -> 6 | J20: ='BS Dec KSA'!J20+'BS Dec USA'!J20 -> 6 | ... N20: ='BS Dec KSA'!N20+'BS Dec USA'!N20 -> 6
B21: Riyad Bank | C21: ='BS Dec KSA'!C21+'BS Dec USA'!C21 -> 30.48 | D21: ='BS Dec KSA'!D21+'BS Dec USA'!D21 -> 30.48 | E21: ='BS Dec KSA'!E21+'BS Dec USA'!E21 -> 30.48 | F21: ='BS Dec KSA'!F21+'BS Dec USA'!F21 -> 30.48 | G21: ='BS Dec KSA'!G21+'BS Dec USA'!G21 -> 30.48 | H21: ='BS Dec KSA'!H21+'BS Dec USA'!H21 -> 30.48 | I21: ='BS Dec KSA'!I21+'BS Dec USA'!I21 -> 30.48 | J21: ='BS Dec KSA'!J21+'BS Dec USA'!J21 -> 30.48 | ... N21: ='BS Dec KSA'!N21+'BS Dec USA'!N21 -> 30.48
B22: US Checking Account | C22: ='BS Dec KSA'!C22+'BS Dec USA'!C22 -> 2008252.4 | D22: ='BS Dec KSA'!D22+'BS Dec USA'!D22 -> 2359619.8 | E22: ='BS Dec KSA'!E22+'BS Dec USA'!E22 -> 2572070.2 | F22: ='BS Dec KSA'!F22+'BS Dec USA'!F22 -> 2993836.8 | G22: ='BS Dec KSA'!G22+'BS Dec USA'!G22 -> 3243627.6 | H22: ='BS Dec KSA'!H22+'BS Dec USA'!H22 -> 3565406.1 | I22: ='BS Dec KSA'!I22+'BS Dec USA'!I22 -> 2938541.7 | J22: ='BS Dec KSA'!J22+'BS Dec USA'!J22 -> 1566648 | ... N22: ='BS Dec KSA'!N22+'BS Dec USA'!N22 -> 4663542
... B25: Petty Cash | C25: ='BS Dec KSA'!C25+'BS Dec USA'!C25 -> 26143.5 | D25: ='BS Dec KSA'!D25+'BS Dec USA'!D25 -> 8999.5 | E25: ='BS Dec KSA'!E25+'BS Dec USA'!E25 -> 4999.5 | F25: ='BS Dec KSA'!F25+'BS Dec USA'!F25 -> 102977 | G25: ='BS Dec KSA'!G25+'BS Dec USA'!G25 -> 3000 | H25: ='BS Dec KSA'!H25+'BS Dec USA'!H25 -> 3000 | I25: ='BS Dec KSA'!I25+'BS Dec USA'!I25 -> 3000 | J25: ='BS Dec KSA'!J25+'BS Dec USA'!J25 -> 3000 | ... N25: ='BS Dec KSA'!N25+'BS Dec USA'!N25 -> 3758
B27: Trade Receivables (net) | C27: =SUM(C28:C29) -> 39178410 | D27: =SUM(D28:D29) -> 35535924 | E27: =SUM(E28:E29) -> 33632759 | F27: =SUM(F28:F29) -> 34548085 | G27: =SUM(G28:G29) -> 37084008 | H27: =SUM(H28:H29) -> 34268040 | I27: =SUM(I28:I29) -> 31927623 | J27: =SUM(J28:J29) -> 31054504 | ... N27: =SUM(N28:N29) -> 25019982
B28: Trade Receivables - Gross | C28: ='BS Dec KSA'!C28+'BS Dec USA'!C28 -> 39584419 | D28: ='BS Dec KSA'!D28+'BS Dec USA'!D28 -> 35738924 | E28: ='BS Dec KSA'!E28+'BS Dec USA'!E28 -> 33835759 | F28: ='BS Dec KSA'!F28+'BS Dec USA'!F28 -> 34751085 | G28: ='BS Dec KSA'!G28+'BS Dec USA'!G28 -> 37287008 | H28: ='BS Dec KSA'!H28+'BS Dec USA'!H28 -> 34471040 | I28: ='BS Dec KSA'!I28+'BS Dec USA'!I28 -> 32130623 | J28: ='BS Dec KSA'!J28+'BS Dec USA'!J28 -> 31257504 | ... N28: ='BS Dec KSA'!N28+'BS Dec USA'!N28 -> 25222982
B29: Provision for doubtful Accounts | C29: ='BS Dec KSA'!C29+'BS Dec USA'!C29 -> -406009 | D29: ='BS Dec KSA'!D29+'BS Dec USA'!D29 -> -203000 | E29: ='BS Dec KSA'!E29+'BS Dec USA'!E29 -> -203000 | F29: ='BS Dec KSA'!F29+'BS Dec USA'!F29 -> -203000 | G29: ='BS Dec KSA'!G29+'BS Dec USA'!G29 -> -203000 | H29: ='BS Dec KSA'!H29+'BS Dec USA'!H29 -> -203000 | I29: ='BS Dec KSA'!I29+'BS Dec USA'!I29 -> -203000 | J29: ='BS Dec KSA'!J29+'BS Dec USA'!J29 -> -203000 | ... N29: ='BS Dec KSA'!N29+'BS Dec USA'!N29 -> -203000
B31: Prepaid Expenses & Other recievables | C31: =SUM(C32:C44) -> 1394850.2 | D31: =SUM(D32:D44) -> 1370961.1 | E31: =SUM(E32:E44) -> 887519.67 | F31: =SUM(F32:F43) -> 489615.79 | G31: =SUM(G32:G43) -> 502238.68 | H31: =SUM(H32:H43) -> 354588.47 | I31: =SUM(I32:I43) -> 318307.75 | J31: =SUM(J32:J43) -> 362968.6 | K31: =SUM(K32:K43) -> 333037.43 | L31: =SUM(L32:L43) -> -1232590 | M31: =SUM(M32:M43) -> 279587.24 | N31: =SUM(N32:N43) -> 202111.25
B32: Prepaid Vendors | C32: ='BS Dec KSA'!C32+'BS Dec USA'!C32 -> 0 | D32: ='BS Dec KSA'!D32+'BS Dec USA'!D32 -> -8.05 | E32: ='BS Dec KSA'!E32+'BS Dec USA'!E32 -> -8.05 | F32: ='BS Dec KSA'!F32+'BS Dec USA'!F32 -> -18293.05 | G32: ='BS Dec KSA'!G32+'BS Dec USA'!G32 -> 17091.95 | H32: ='BS Dec KSA'!H32+'BS Dec USA'!H32 -> 17091.95 | I32: ='BS Dec KSA'!I32+'BS Dec USA'!I32 -> -8.05 | J32: ='BS Dec KSA'!J32+'BS Dec USA'!J32 -> -8.05 | ... N32: ='BS Dec KSA'!N32+'BS Dec USA'!N32 -> -8.05
B33: Prepaid Accommodation Rent Expense | C33: ='BS Dec KSA'!C33+'BS Dec USA'!C33 -> 0 | D33: ='BS Dec KSA'!D33+'BS Dec USA'!D33 -> -10666.63 | E33: ='BS Dec KSA'!E33+'BS Dec USA'!E33 -> -8533.3 | F33: ='BS Dec KSA'!F33+'BS Dec USA'!F33 -> -6399.97 | G33: ='BS Dec KSA'!G33+'BS Dec USA'!G33 -> -4266.64 | H33: ='BS Dec KSA'!H33+'BS Dec USA'!H33 -> -2133.31 | I33: ='BS Dec KSA'!I33+'BS Dec USA'!I33 -> 0.02 | J33: ='BS Dec KSA'!J33+'BS Dec USA'!J33 -> 2133.35 | ... N33: ='BS Dec KSA'!N33+'BS Dec USA'!N33 -> 2258.67
B34: Prepaid Financing Expense | C34: ='BS Dec KSA'!C34+'BS Dec USA'!C34 -> 105846.5 | D34: ='BS Dec KSA'!D34+'BS Dec USA'!D34 -> 108210.26 | E34: ='BS Dec KSA'!E34+'BS Dec USA'!E34 -> 110574.02 | F34: ='BS Dec KSA'!F34+'BS Dec USA'!F34 -> 112937.78 | G34: ='BS Dec KSA'!G34+'BS Dec USA'!G34 -> 38888.89 | H34: ='BS Dec KSA'!H34+'BS Dec USA'!H34 -> 0 | I34: ='BS Dec KSA'!I34+'BS Dec USA'!I34 -> 0 | J34: ='BS Dec KSA'!J34+'BS Dec USA'!J34 -> 0 | ... N34: ='BS Dec KSA'!N34+'BS Dec USA'!N34 -> 0
B35: Prepaid Govt. Legal Expense | C35: ='BS Dec KSA'!C35+'BS Dec USA'!C35 -> 32500 | D35: ='BS Dec KSA'!D35+'BS Dec USA'!D35 -> 37916.67 | E35: ='BS Dec KSA'!E35+'BS Dec USA'!E35 -> 43333.34 | F35: ='BS Dec KSA'!F35+'BS Dec USA'!F35 -> 48750.01 | G35: ='BS Dec KSA'!G35+'BS Dec USA'!G35 -> 54166.68 | H35: ='BS Dec KSA'!H35+'BS Dec USA'!H35 -> 45.84 | I35: ='BS Dec KSA'!I35+'BS Dec USA'!I35 -> 91.67 | J35: ='BS Dec KSA'!J35+'BS Dec USA'!J35 -> 5554.17 | ... N35: ='BS Dec KSA'!N35+'BS Dec USA'!N35 -> 27404.17
B36: Prepaid IT Subscriptions Expense | C36: ='BS Dec KSA'!C36+'BS Dec USA'!C36 -> 86253.89 | D36: ='BS Dec KSA'!D36+'BS Dec USA'!D36 -> 17646.8 | E36: ='BS Dec KSA'!E36+'BS Dec USA'!E36 -> 22497.49 | F36: ='BS Dec KSA'!F36+'BS Dec USA'!F36 -> 11165.72 | G36: ='BS Dec KSA'!G36+'BS Dec USA'!G36 -> 13924.12 | H36: ='BS Dec KSA'!H36+'BS Dec USA'!H36 -> 7232.52 | I36: ='BS Dec KSA'!I36+'BS Dec USA'!I36 -> 9203.42 | J36: ='BS Dec KSA'!J36+'BS Dec USA'!J36 -> 11174.32 | ... N36: ='BS Dec KSA'!N36+'BS Dec USA'!N36 -> 17311.4
B37: Prepaid Office Rent Expense | C37: ='BS Dec KSA'!C37+'BS Dec USA'!C37 -> 126562.51 | D37: ='BS Dec KSA'!D37+'BS Dec USA'!D37 -> 156525.23 | E37: ='BS Dec KSA'!E37+'BS Dec USA'!E37 -> 11730.45 | F37: ='BS Dec KSA'!F37+'BS Dec USA'!F37 -> 17595.67 | G37: ='BS Dec KSA'!G37+'BS Dec USA'!G37 -> 23460.89 | H37: ='BS Dec KSA'!H37+'BS Dec USA'!H37 -> -5865.19 | I37: ='BS Dec KSA'!I37+'BS Dec USA'!I37 -> 0.02 | J37: ='BS Dec KSA'!J37+'BS Dec USA'!J37 -> 5833.35 | ... N37: ='BS Dec KSA'!N37+'BS Dec USA'!N37 -> 29166.67
B38: Prepaid Other Expense | C38: ='BS Dec KSA'!C38+'BS Dec USA'!C38 -> 81571.68 | D38: ='BS Dec KSA'!D38+'BS Dec USA'!D38 -> 119029.72 | E38: ='BS Dec KSA'!E38+'BS Dec USA'!E38 -> 104858.01 | F38: ='BS Dec KSA'!F38+'BS Dec USA'!F38 -> 127693.99 | G38: ='BS Dec KSA'!G38+'BS Dec USA'!G38 -> 157481.75 | H38: ='BS Dec KSA'!H38+'BS Dec USA'!H38 -> 175591.4 | I38: ='BS Dec KSA'!I38+'BS Dec USA'!I38 -> 116712.16 | J38: ='BS Dec KSA'!J38+'BS Dec USA'!J38 -> 133215.14 | ... N38: ='BS Dec KSA'!N38+'BS Dec USA'!N38 -> 7289.16
B39: Fund Raising Expense receivable | C39: ='BS Dec KSA'!C39+'BS Dec USA'!C39 -> 37580 | D39: ='BS Dec KSA'!D39+'BS Dec USA'!D39 -> 37580 | E39: ='BS Dec KSA'!E39+'BS Dec USA'!E39 -> 37580 | F39: ='BS Dec KSA'!F39+'BS Dec USA'!F39 -> 37580 | G39: ='BS Dec KSA'!G39+'BS Dec USA'!G39 -> 37580 | H39: ='BS Dec KSA'!H39+'BS Dec USA'!H39 -> 0 | I39: ='BS Dec KSA'!I39+'BS Dec USA'!I39 -> 0 | J39: ='BS Dec KSA'!J39+'BS Dec USA'!J39 -> 0 | ... N39: ='BS Dec KSA'!N39+'BS Dec USA'!N39 -> 0
B40: Employee Receivable | C40: ='BS Dec KSA'!C40+'BS Dec USA'!C40 -> 150941.43 | D40: ='BS Dec KSA'!D40+'BS Dec USA'!D40 -> 131132.87 | E40: ='BS Dec KSA'!E40+'BS Dec USA'!E40 -> 128909.83 | F40: ='BS Dec KSA'!F40+'BS Dec USA'!F40 -> 103152.9 | G40: ='BS Dec KSA'!G40+'BS Dec USA'!G40 -> 108416.5 | H40: ='BS Dec KSA'!H40+'BS Dec USA'!H40 -> 107216.1 | I40: ='BS Dec KSA'!I40+'BS Dec USA'!I40 -> 138558.16 | J40: ='BS Dec KSA'!J40+'BS Dec USA'!J40 -> 152088.92 | ... N40: ='BS Dec KSA'!N40+'BS Dec USA'!N40 -> 70092.47
B41: Security deposits | C41: ='BS Dec KSA'!C41+'BS Dec USA'!C41 -> 2000 | D41: ='BS Dec KSA'!D41+'BS Dec USA'!D41 -> 2000 | E41: ='BS Dec KSA'!E41+'BS Dec USA'!E41 -> 2000 | F41: ='BS Dec KSA'!F41+'BS Dec USA'!F41 -> 2000 | G41: ='BS Dec KSA'!G41+'BS Dec USA'!G41 -> 2000 | H41: ='BS Dec KSA'!H41+'BS Dec USA'!H41 -> 1500 | I41: ='BS Dec KSA'!I41+'BS Dec USA'!I41 -> 1500 | J41: ='BS Dec KSA'!J41+'BS Dec USA'!J41 -> 1500 | ... N41: ='BS Dec KSA'!N41+'BS Dec USA'!N41 -> 1500
B42: Other Receivable | C42: ='BS Dec KSA'!C42+'BS Dec USA'!C42 -> 0 | D42: ='BS Dec KSA'!D42+'BS Dec USA'!D42 -> 0 | E42: ='BS Dec KSA'!E42+'BS Dec USA'!E42 -> 0 | F42: ='BS Dec KSA'!F42+'BS Dec USA'!F42 -> 0 | G42: ='BS Dec KSA'!G42+'BS Dec USA'!G42 -> 0 | H42: ='BS Dec KSA'!H42+'BS Dec USA'!H42 -> 500 | I42: ='BS Dec KSA'!I42+'BS Dec USA'!I42 -> 0 | J42: ='BS Dec KSA'!J42+'BS Dec USA'!J42 -> 0 | ... N42: ='BS Dec KSA'!N42+'BS Dec USA'!N42 -> 0
B43: Input VAT | C43: ='BS Dec KSA'!C43+'BS Dec USA'!C43 -> 28469.18 | D43: ='BS Dec KSA'!D43+'BS Dec USA'!D43 -> 28469.18 | E43: ='BS Dec KSA'!E43+'BS Dec USA'!E43 -> 53952.88 | F43: ='BS Dec KSA'!F43+'BS Dec USA'!F43 -> 53432.74 | G43: ='BS Dec KSA'!G43+'BS Dec USA'!G43 -> 53494.54 | H43: ='BS Dec KSA'!H43+'BS Dec USA'!H43 -> 53409.16 | I43: ='BS Dec KSA'!I43+'BS Dec USA'!I43 -> 52250.35 | J43: ='BS Dec KSA'!J43+'BS Dec USA'!J43 -> 51477.4 | ... N43: ='BS Dec KSA'!N43+'BS Dec USA'!N43 -> 47096.76
B44: Profit Reserve Account (Deposit) | C44: ='BS Dec KSA'!C44+'BS Dec USA'!C44 -> 743125 | D44: ='BS Dec KSA'!D44+'BS Dec USA'!D44 -> 743125 | E44: ='BS Dec KSA'!E44+'BS Dec USA'!E44 -> 380625
K45: ='BS Dec KSA'!K45+'BS Dec USA'!K45 -> 0
B46: TOTAL CURRENT ASSETS | C46: =+C31+C10+C27 -> 53030248 | D46: =+D31+D10+D27 -> 52889972 | E46: =+E31+E10+E27 -> 51672691 | F46: =+F31+F10+F27 -> 42111438 | G46: =+G31+G10+G27 -> 42597989 | H46: =+H31+H10+H27 -> 43167942 | I46: =+I31+I10+I27 -> 43116140 | J46: =+J31+J10+J27 -> 36197698 | ... N46: =+N31+N10+N27 -> 34445840
B49: Fixed Assets (net) | C49: =SUM(C50:C57) -> 219131.08 | D49: =SUM(D50:D57) -> 172967.58 | E49: =SUM(E50:E57) -> 157374.09 | F49: =SUM(F50:F57) -> 165997.7 | G49: =SUM(G50:G57) -> 172270.04 | H49: =SUM(H50:H57) -> 122718.59 | I49: =SUM(I50:I57) -> 113097.31 | J49: =SUM(J50:J57) -> 119833.96 | ... N49: =SUM(N50:N57) -> 128719.67
B50: Accumulated Depreciation - Furniture & Fixture | C50: ='BS Dec KSA'!C50+'BS Dec USA'!C50 -> -23841.55 | D50: ='BS Dec KSA'!D50+'BS Dec USA'!D50 -> -22527.08 | E50: ='BS Dec KSA'!E50+'BS Dec USA'!E50 -> -21212.61 | F50: ='BS Dec KSA'!F50+'BS Dec USA'!F50 -> -19898.14 | G50: ='BS Dec KSA'!G50+'BS Dec USA'!G50 -> -18583.67 | H50: ='BS Dec KSA'!H50+'BS Dec USA'!H50 -> -17269.2 | I50: ='BS Dec KSA'!I50+'BS Dec USA'!I50 -> -16033.57 | J50: ='BS Dec KSA'!J50+'BS Dec USA'!J50 -> -14797.94 | ... N50: ='BS Dec KSA'!N50+'BS Dec USA'!N50 -> -9855.42
B51: Accumulated Depreciation - Motor Vehicle | C51: ='BS Dec KSA'!C51+'BS Dec USA'!C51 -> -4022.45 | D51: ='BS Dec KSA'!D51+'BS Dec USA'!D51 -> -24226.6 | E51: ='BS Dec KSA'!E51+'BS Dec USA'!E51 -> -22546.75 | F51: ='BS Dec KSA'!F51+'BS Dec USA'!F51 -> -20866.9 | G51: ='BS Dec KSA'!G51+'BS Dec USA'!G51 -> -19187.05 | H51: ='BS Dec KSA'!H51+'BS Dec USA'!H51 -> -17507.2 | I51: ='BS Dec KSA'!I51+'BS Dec USA'!I51 -> -16631.84 | J51: ='BS Dec KSA'!J51+'BS Dec USA'!J51 -> -15756.48 | ... N51: ='BS Dec KSA'!N51+'BS Dec USA'!N51 -> -12255.04
B52: Accumulated Depreciation - Office Equipment's | C52: ='BS Dec KSA'!C52+'BS Dec USA'!C52 -> -94657.76 | D52: ='BS Dec KSA'!D52+'BS Dec USA'!D52 -> -89173.52 | E52: ='BS Dec KSA'!E52+'BS Dec USA'!E52 -> -84278.39 | F52: ='BS Dec KSA'!F52+'BS Dec USA'!F52 -> -78649.1 | G52: ='BS Dec KSA'!G52+'BS Dec USA'!G52 -> -73110.21 | H52: ='BS Dec KSA'!H52+'BS Dec USA'!H52 -> -67481.43 | I52: ='BS Dec KSA'!I52+'BS Dec USA'!I52 -> -62257.57 | J52: ='BS Dec KSA'!J52+'BS Dec USA'!J52 -> -57631.91 | ... N52: ='BS Dec KSA'!N52+'BS Dec USA'!N52 -> -39518.76
B53: Fixed Assets not in Use | C53: ='BS Dec KSA'!C53+'BS Dec USA'!C53 -> 0 | D53: ='BS Dec KSA'!D53+'BS Dec USA'!D53 -> 0 | E53: ='BS Dec KSA'!E53+'BS Dec USA'!E53 -> 0 | F53: ='BS Dec KSA'!F53+'BS Dec USA'!F53 -> 0 | G53: ='BS Dec KSA'!G53+'BS Dec USA'!G53 -> 0 | H53: ='BS Dec KSA'!H53+'BS Dec USA'!H53 -> 0.1 | I53: ='BS Dec KSA'!I53+'BS Dec USA'!I53 -> 0 | J53: ='BS Dec KSA'!J53+'BS Dec USA'!J53 -> 0 | ... N53: ='BS Dec KSA'!N53+'BS Dec USA'!N53 -> 0
B54: Furniture & Fixture | C54: ='BS Dec KSA'!C54+'BS Dec USA'!C54 -> 47320.87 | D54: ='BS Dec KSA'!D54+'BS Dec USA'!D54 -> 47320.87 | E54: ='BS Dec KSA'!E54+'BS Dec USA'!E54 -> 47320.87 | F54: ='BS Dec KSA'!F54+'BS Dec USA'!F54 -> 47320.87 | G54: ='BS Dec KSA'!G54+'BS Dec USA'!G54 -> 47320.87 | H54: ='BS Dec KSA'!H54+'BS Dec USA'!H54 -> 44482.61 | I54: ='BS Dec KSA'!I54+'BS Dec USA'!I54 -> 44482.61 | J54: ='BS Dec KSA'!J54+'BS Dec USA'!J54 -> 44482.61 | ... N54: ='BS Dec KSA'!N54+'BS Dec USA'!N54 -> 44482.61
B55: Motor Vehicle | C55: ='BS Dec KSA'!C55+'BS Dec USA'!C55 -> 48217.39 | D55: ='BS Dec KSA'!D55+'BS Dec USA'!D55 -> 100739.13 | E55: ='BS Dec KSA'!E55+'BS Dec USA'!E55 -> 100739.13 | F55: ='BS Dec KSA'!F55+'BS Dec USA'!F55 -> 100739.13 | G55: ='BS Dec KSA'!G55+'BS Dec USA'!G55 -> 100739.13 | H55: ='BS Dec KSA'!H55+'BS Dec USA'!H55 -> 52521.74 | I55: ='BS Dec KSA'!I55+'BS Dec USA'!I55 -> 52521.74 | J55: ='BS Dec KSA'!J55+'BS Dec USA'!J55 -> 52521.74 | ... N55: ='BS Dec KSA'!N55+'BS Dec USA'!N55 -> 52521.74
B56: Office Equipment | C56: ='BS Dec KSA'!C56+'BS Dec USA'!C56 -> 154746.26 | D56: ='BS Dec KSA'!D56+'BS Dec USA'!D56 -> 147317.57 | E56: ='BS Dec KSA'!E56+'BS Dec USA'!E56 -> 137351.84 | F56: ='BS Dec KSA'!F56+'BS Dec USA'!F56 -> 137351.84 | G56: ='BS Dec KSA'!G56+'BS Dec USA'!G56 -> 135090.97 | H56: ='BS Dec KSA'!H56+'BS Dec USA'!H56 -> 127971.97 | I56: ='BS Dec KSA'!I56+'BS Dec USA'!I56 -> 111015.94 | J56: ='BS Dec KSA'!J56+'BS Dec USA'!J56 -> 111015.94 | ... N56: ='BS Dec KSA'!N56+'BS Dec USA'!N56 -> 93344.54
B57: Capital Work in Progress | C57: ='BS Dec KSA'!C57+'BS Dec USA'!C57 -> 91368.32 | D57: ='BS Dec KSA'!D57+'BS Dec USA'!D57 -> 13517.21 | E57: ='BS Dec KSA'!E57+'BS Dec USA'!E57 -> 0 | F57: ='BS Dec KSA'!F57+'BS Dec USA'!F57 -> 0 | G57: ='BS Dec KSA'!G57+'BS Dec USA'!G57 -> 0 | H57: ='BS Dec KSA'!H57+'BS Dec USA'!H57 -> 0 | I57: ='BS Dec KSA'!I57+'BS Dec USA'!I57 -> 0 | J57: ='BS Dec KSA'!J57+'BS Dec USA'!J57 -> 0 | ... N57: ='BS Dec KSA'!N57+'BS Dec USA'!N57 -> 0
B59: Intercompany | C59: =SUM(C60:C63) -> 8378.32 | D59: =SUM(D60:D63) -> 55711.81 | E59: =SUM(E60:E63) -> 56927.81 | F59: =SUM(F60:F63) -> 6378.32 | G59: =SUM(G60:G63) -> 6378.32 | H59: =SUM(H60:H63) -> 2878.32 | I59: =SUM(I60:I63) -> 758.81 | J59: =SUM(J60:J63) -> 758.81 | ... N59: =SUM(N60:N63) -> 758.81
B60: Buildnow Inc. (US)
B61: Buildnow Tech BD | C61: ='BS Dec KSA'!C61+'BS Dec USA'!C61 -> 2728.3 | D61: ='BS Dec KSA'!D61+'BS Dec USA'!D61 -> 2728.3 | E61: ='BS Dec KSA'!E61+'BS Dec USA'!E61 -> 2728.3 | F61: ='BS Dec KSA'!F61+'BS Dec USA'!F61 -> 2728.3 | G61: ='BS Dec KSA'!G61+'BS Dec USA'!G61 -> 2728.3 | H61: ='BS Dec KSA'!H61+'BS Dec USA'!H61 -> 2728.3 | I61: ='BS Dec KSA'!I61+'BS Dec USA'!I61 -> 608.79 | J61: ='BS Dec KSA'!J61+'BS Dec USA'!J61 -> 608.79 | ... N61: ='BS Dec KSA'!N61+'BS Dec USA'!N61 -> 608.79
B62: Buildnow Trading Co (KSA) | C62: 0 | D62: 49333.49 | E62: 50549.49 | F62: 0 | G62: 0 | H62: 0 | I62: 0 | J62: 0 | K62: 0 | L62: 0 | M62: 0 | N62: 0
B63: MISA KSA | C63: ='BS Dec KSA'!C63+'BS Dec USA'!C63 -> 5650.02 | D63: ='BS Dec KSA'!D63+'BS Dec USA'!D63 -> 3650.02 | E63: ='BS Dec KSA'!E63+'BS Dec USA'!E63 -> 3650.02 | F63: ='BS Dec KSA'!F63+'BS Dec USA'!F63 -> 3650.02 | G63: ='BS Dec KSA'!G63+'BS Dec USA'!G63 -> 3650.02 | H63: ='BS Dec KSA'!H63+'BS Dec USA'!H63 -> 150.02 | I63: ='BS Dec KSA'!I63+'BS Dec USA'!I63 -> 150.02 | J63: ='BS Dec KSA'!J63+'BS Dec USA'!J63 -> 150.02 | ... N63: ='BS Dec KSA'!N63+'BS Dec USA'!N63 -> 150.02
B65: Investment in Subsidiaries | C65: =SUM(C66:C67) -> 3720.42 | D65: =SUM(D66:D67) -> 3720.42 | E65: =SUM(E66:E67) -> 3720.42 | F65: =SUM(F66:F67) -> 3720.42 | G65: =SUM(G66:G67) -> 3720.42 | H65: =SUM(H66:H67) -> 3720.42 | I65: =SUM(I66:I67) -> 3720.42 | J65: =SUM(J66:J67) -> 3720.42 | ... N65: =SUM(N66:N67) -> 3720.42
B66: Buildnow BD Technology Subsidiary | C66: ='BS Dec KSA'!C66+'BS Dec USA'!C66 -> 3720.42 | D66: ='BS Dec KSA'!D66+'BS Dec USA'!D66 -> 3720.42 | E66: ='BS Dec KSA'!E66+'BS Dec USA'!E66 -> 3720.42 | F66: ='BS Dec KSA'!F66+'BS Dec USA'!F66 -> 3720.42 | G66: ='BS Dec KSA'!G66+'BS Dec USA'!G66 -> 3720.42 | H66: ='BS Dec KSA'!H66+'BS Dec USA'!H66 -> 3720.42 | I66: ='BS Dec KSA'!I66+'BS Dec USA'!I66 -> 3720.42 | J66: ='BS Dec KSA'!J66+'BS Dec USA'!J66 -> 3720.42 | ... N66: ='BS Dec KSA'!N66+'BS Dec USA'!N66 -> 3720.42
B69: TOTAL NON CURRENT ASSETS | C69: =+C59+C49+C65 -> 231229.82 | D69: =+D59+D49+D65 -> 232399.81 | E69: =+E59+E49+E65 -> 218022.32 | F69: =+F59+F49+F65 -> 176096.44 | G69: =+G59+G49+G65 -> 182368.78 | H69: =+H59+H49+H65 -> 129317.33 | I69: =+I59+I49+I65 -> 117576.54 | J69: =+J59+J49+J65 -> 124313.19 | ... N69: =+N59+N49+N65 -> 133198.9
B72: TOTAL ASSETS | C72: =+C69+C46 -> 53261477 | D72: =+D69+D46 -> 53122372 | E72: =+E69+E46 -> 51890713 | F72: =+F69+F46 -> 42287535 | G72: =+G69+G46 -> 42780358 | H72: =+H69+H46 -> 43297259 | I72: =+I69+I46 -> 43233717 | J72: =+J69+J46 -> 36322011 | ... N72: =+N69+N46 -> 34579039
B75: LIABILITIES & OWNER'S EQUITY
B77: Other Payables and Accruals | C77: =SUM(C78:C94) -> 1683798.1 | D77: =SUM(D78:D94) -> 1438053.1 | E77: =SUM(E78:E94) -> 9379299.3 | F77: =SUM(F78:F93) -> 1626345.4 | G77: =SUM(G78:G93) -> 1590287.3 | H77: =SUM(H78:H93) -> 1672255.4 | I77: =SUM(I78:I93) -> 2656046.4 | J77: =SUM(J78:J93) -> 1294748.8 | K77: =SUM(K78:K93) -> 1242624 | L77: =SUM(L78:L93) -> 54276.38 | M77: =SUM(M78:M93) -> 1243053.5 | N77: =SUM(N78:N93) -> 1031185.6
B78: Zakat Provision | C78: ='BS Dec KSA'!C78+'BS Dec USA'!C78 -> 0 | D78: ='BS Dec KSA'!D78+'BS Dec USA'!D78 -> 0 | E78: ='BS Dec KSA'!E78+'BS Dec USA'!E78 -> 0 | F78: ='BS Dec KSA'!F78+'BS Dec USA'!F78 -> 0 | G78: ='BS Dec KSA'!G78+'BS Dec USA'!G78 -> 0 | H78: ='BS Dec KSA'!H78+'BS Dec USA'!H78 -> 0 | I78: ='BS Dec KSA'!I78+'BS Dec USA'!I78 -> 0 | J78: ='BS Dec KSA'!J78+'BS Dec USA'!J78 -> 0 | ... N78: ='BS Dec KSA'!N78+'BS Dec USA'!N78 -> 39481
B79: Misc. Payables | C79: ='BS Dec KSA'!C79+'BS Dec USA'!C79 -> 158987.5 | D79: ='BS Dec KSA'!D79+'BS Dec USA'!D79 -> 158987.5 | E79: ='BS Dec KSA'!E79+'BS Dec USA'!E79 -> 158987.5 | F79: ='BS Dec KSA'!F79+'BS Dec USA'!F79 -> 158987.5 | G79: ='BS Dec KSA'!G79+'BS Dec USA'!G79 -> 158987.5 | H79: ='BS Dec KSA'!H79+'BS Dec USA'!H79 -> 158987.5 | I79: ='BS Dec KSA'!I79+'BS Dec USA'!I79 -> 158987.5 | J79: ='BS Dec KSA'!J79+'BS Dec USA'!J79 -> 158987.5 | ... N79: ='BS Dec KSA'!N79+'BS Dec USA'!N79 -> 158987.5
B80: Other Payables | C80: ='BS Dec KSA'!C80+'BS Dec USA'!C80 -> 139840 | D80: ='BS Dec KSA'!D80+'BS Dec USA'!D80 -> -3255.65 | E80: ='BS Dec KSA'!E80+'BS Dec USA'!E80 -> 81853.05 | F80: ='BS Dec KSA'!F80+'BS Dec USA'!F80 -> 85108.7 | G80: ='BS Dec KSA'!G80+'BS Dec USA'!G80 -> 143804.35 | H80: ='BS Dec KSA'!H80+'BS Dec USA'!H80 -> 143804.35 | I80: ='BS Dec KSA'!I80+'BS Dec USA'!I80 -> 143804.35 | J80: ='BS Dec KSA'!J80+'BS Dec USA'!J80 -> 143804.35 | ... N80: ='BS Dec KSA'!N80+'BS Dec USA'!N80 -> 0
B81: Unearned Revenue | C81: ='BS Dec KSA'!C81+'BS Dec USA'!C81 -> 1373.79 | D81: ='BS Dec KSA'!D81+'BS Dec USA'!D81 -> 1372.92 | E81: ='BS Dec KSA'!E81+'BS Dec USA'!E81 -> 1371.15 | F81: ='BS Dec KSA'!F81+'BS Dec USA'!F81 -> 1370.24 | G81: ='BS Dec KSA'!G81+'BS Dec USA'!G81 -> 0 | H81: ='BS Dec KSA'!H81+'BS Dec USA'!H81 -> 104.1 | I81: ='BS Dec KSA'!I81+'BS Dec USA'!I81 -> 103.24 | J81: ='BS Dec KSA'!J81+'BS Dec USA'!J81 -> 103.24 | ... N81: ='BS Dec KSA'!N81+'BS Dec USA'!N81 -> 102.82
B82: Employee Payable | C82: ='BS Dec KSA'!C82+'BS Dec USA'!C82 -> 0 | D82: ='BS Dec KSA'!D82+'BS Dec USA'!D82 -> 716.48 | E82: ='BS Dec KSA'!E82+'BS Dec USA'!E82 -> 716.48 | F82: ='BS Dec KSA'!F82+'BS Dec USA'!F82 -> 716.48 | G82: ='BS Dec KSA'!G82+'BS Dec USA'!G82 -> 716.48 | H82: ='BS Dec KSA'!H82+'BS Dec USA'!H82 -> 716.48 | I82: ='BS Dec KSA'!I82+'BS Dec USA'!I82 -> 716.48 | J82: ='BS Dec KSA'!J82+'BS Dec USA'!J82 -> 716.48 | ... N82: ='BS Dec KSA'!N82+'BS Dec USA'!N82 -> 716.48
B83: Accounts Payable | C83: ='BS Dec KSA'!C83+'BS Dec USA'!C83 -> 877017.06 | D83: ='BS Dec KSA'!D83+'BS Dec USA'!D83 -> 393994.53 | E83: ='BS Dec KSA'!E83+'BS Dec USA'!E83 -> 109792.73 | F83: ='BS Dec KSA'!F83+'BS Dec USA'!F83 -> 63875.59 | G83: ='BS Dec KSA'!G83+'BS Dec USA'!G83 -> 188753.42 | H83: ='BS Dec KSA'!H83+'BS Dec USA'!H83 -> 207570.12 | I83: ='BS Dec KSA'!I83+'BS Dec USA'!I83 -> 1074112.6 | J83: ='BS Dec KSA'!J83+'BS Dec USA'!J83 -> 0.57 | ... N83: ='BS Dec KSA'!N83+'BS Dec USA'!N83 -> 46713.57
B84: Accrued Expenses | C84: ='BS Dec KSA'!C84+'BS Dec USA'!C84 -> 25866.83 | D84: ='BS Dec KSA'!D84+'BS Dec USA'!D84 -> -1030.15 | E84: ='BS Dec KSA'!E84+'BS Dec USA'!E84 -> -27927.13 | F84: ='BS Dec KSA'!F84+'BS Dec USA'!F84 -> -54824.11 | G84: ='BS Dec KSA'!G84+'BS Dec USA'!G84 -> -81721.09 | H84: ='BS Dec KSA'!H84+'BS Dec USA'!H84 -> -108618.09 | I84: ='BS Dec KSA'!I84+'BS Dec USA'!I84 -> -135515.09 | J84: ='BS Dec KSA'!J84+'BS Dec USA'!J84 -> -162412.08 | ... N84: ='BS Dec KSA'!N84+'BS Dec USA'!N84 -> 0
B85: VAT Payable (GAZT) | C85: ='BS Dec KSA'!C85+'BS Dec USA'!C85 -> 129870.78 | D85: ='BS Dec KSA'!D85+'BS Dec USA'!D85 -> 87148.86 | E85: ='BS Dec KSA'!E85+'BS Dec USA'!E85 -> 137073.2 | F85: ='BS Dec KSA'!F85+'BS Dec USA'!F85 -> 40260.02 | G85: ='BS Dec KSA'!G85+'BS Dec USA'!G85 -> 36509.21 | H85: ='BS Dec KSA'!H85+'BS Dec USA'!H85 -> 223097.27 | I85: ='BS Dec KSA'!I85+'BS Dec USA'!I85 -> 108021.91 | J85: ='BS Dec KSA'!J85+'BS Dec USA'!J85 -> 88598.41 | ... N85: ='BS Dec KSA'!N85+'BS Dec USA'!N85 -> 34553.58
B86: Accrued Investor Profit | C86: ='BS Dec KSA'!C86+'BS Dec USA'!C86 -> 137644.4 | D86: ='BS Dec KSA'!D86+'BS Dec USA'!D86 -> 595802.74 | E86: ='BS Dec KSA'!E86+'BS Dec USA'!E86 -> 576811.58 | F86: ='BS Dec KSA'!F86+'BS Dec USA'!F86 -> 766015.92 | G86: ='BS Dec KSA'!G86+'BS Dec USA'!G86 -> 940141.87 | H86: ='BS Dec KSA'!H86+'BS Dec USA'!H86 -> 840108.03 | I86: ='BS Dec KSA'!I86+'BS Dec USA'!I86 -> 676772.07 | J86: ='BS Dec KSA'!J86+'BS Dec USA'!J86 -> 866837.73 | ... N86: ='BS Dec KSA'!N86+'BS Dec USA'!N86 -> 603768.9
B87: Accrued Investor Profit (Unrealized) | C87: ='BS Dec KSA'!C87+'BS Dec USA'!C87 -> 0 | D87: ='BS Dec KSA'!D87+'BS Dec USA'!D87 -> 0 | E87: ='BS Dec KSA'!E87+'BS Dec USA'!E87 -> 0 | F87: ='BS Dec KSA'!F87+'BS Dec USA'!F87 -> 0 | G87: ='BS Dec KSA'!G87+'BS Dec USA'!G87 -> 0 | H87: ='BS Dec KSA'!H87+'BS Dec USA'!H87 -> 0 | I87: ='BS Dec KSA'!I87+'BS Dec USA'!I87 -> 0 | J87: ='BS Dec KSA'!J87+'BS Dec USA'!J87 -> 0 | ... N87: ='BS Dec KSA'!N87+'BS Dec USA'!N87 -> 0
B88: Leave Pay Payable | C88: ='BS Dec KSA'!C88+'BS Dec USA'!C88 -> 47874.96 | D88: ='BS Dec KSA'!D88+'BS Dec USA'!D88 -> 0 | E88: ='BS Dec KSA'!E88+'BS Dec USA'!E88 -> 0 | F88: ='BS Dec KSA'!F88+'BS Dec USA'!F88 -> 0 | G88: ='BS Dec KSA'!G88+'BS Dec USA'!G88 -> 0 | H88: ='BS Dec KSA'!H88+'BS Dec USA'!H88 -> 0 | I88: ='BS Dec KSA'!I88+'BS Dec USA'!I88 -> 0 | J88: ='BS Dec KSA'!J88+'BS Dec USA'!J88 -> 0 | ... N88: ='BS Dec KSA'!N88+'BS Dec USA'!N88 -> 0
B89: Salary Control Account | C89: ='BS Dec KSA'!C89+'BS Dec USA'!C89 -> 31872.44 | D89: ='BS Dec KSA'!D89+'BS Dec USA'!D89 -> 70460.19 | E89: ='BS Dec KSA'!E89+'BS Dec USA'!E89 -> 9601.28 | F89: ='BS Dec KSA'!F89+'BS Dec USA'!F89 -> 209632.96 | G89: ='BS Dec KSA'!G89+'BS Dec USA'!G89 -> 104539.66 | H89: ='BS Dec KSA'!H89+'BS Dec USA'!H89 -> 73371.37 | I89: ='BS Dec KSA'!I89+'BS Dec USA'!I89 -> 151557.58 | J89: ='BS Dec KSA'!J89+'BS Dec USA'!J89 -> 66406.87 | ... N89: ='BS Dec KSA'!N89+'BS Dec USA'!N89 -> 36851.26
... B93: Dividend Payable (Investor) | C93: ='BS Dec KSA'!C93+'BS Dec USA'!C93 -> 30938.46 | D93: ='BS Dec KSA'!D93+'BS Dec USA'!D93 -> 30938.46 | E93: ='BS Dec KSA'!E93+'BS Dec USA'!E93 -> 30938.46 | F93: ='BS Dec KSA'!F93+'BS Dec USA'!F93 -> 255821.07 | G93: ='BS Dec KSA'!G93+'BS Dec USA'!G93 -> 0 | H93: ='BS Dec KSA'!H93+'BS Dec USA'!H93 -> 0 | I93: ='BS Dec KSA'!I93+'BS Dec USA'!I93 -> 345874.68 | J93: ='BS Dec KSA'!J93+'BS Dec USA'!J93 -> 1722.47 | ... N93: ='BS Dec KSA'!N93+'BS Dec USA'!N93 -> 0
B94: Debt Settlement Payable | C94: ='BS Dec KSA'!C94+'BS Dec USA'!C94 -> 0 | D94: ='BS Dec KSA'!D94+'BS Dec USA'!D94 -> 0 | E94: ='BS Dec KSA'!E94+'BS Dec USA'!E94 -> 8199734.7
B96: Short term Financing | C96: =SUM(C97:C99) -> 22530283 | D96: =SUM(D97:D99) -> 22530283 | E96: =SUM(E97:E99) -> 12530283 | F96: =SUM(F97:F98) -> 2030283.3 | G96: =SUM(G97:G98) -> 2030283.3 | H96: =SUM(H97:H98) -> 2030283.3 | I96: =SUM(I97:I98) -> 2030283.3 | J96: =SUM(J97:J98) -> 2030283.3 | K96: =SUM(K97:K98) -> 2030283.3 | L96: =SUM(L97:L98) -> 2030283.3 | M96: =SUM(M97:M98) -> 2030283.3 | N96: =+N98+N97 -> 2030283.3
B97: Interest payable (Al-Raeda) | C97: ='BS Dec KSA'!C97+'BS Dec USA'!C97 -> 30283.31 | D97: ='BS Dec KSA'!D97+'BS Dec USA'!D97 -> 30283.31 | E97: ='BS Dec KSA'!E97+'BS Dec USA'!E97 -> 30283.31 | F97: ='BS Dec KSA'!F97+'BS Dec USA'!F97 -> 30283.31 | G97: ='BS Dec KSA'!G97+'BS Dec USA'!G97 -> 30283.31 | H97: ='BS Dec KSA'!H97+'BS Dec USA'!H97 -> 30283.31 | I97: ='BS Dec KSA'!I97+'BS Dec USA'!I97 -> 30283.31 | J97: ='BS Dec KSA'!J97+'BS Dec USA'!J97 -> 30283.31 | ... N97: ='BS Dec KSA'!N97+'BS Dec USA'!N97 -> 30283.31
B98: Short-term Financing (Al Raedah) | C98: ='BS Dec KSA'!C98+'BS Dec USA'!C98 -> 2000000 | D98: ='BS Dec KSA'!D98+'BS Dec USA'!D98 -> 2000000 | E98: ='BS Dec KSA'!E98+'BS Dec USA'!E98 -> 2000000 | F98: ='BS Dec KSA'!F98+'BS Dec USA'!F98 -> 2000000 | G98: ='BS Dec KSA'!G98+'BS Dec USA'!G98 -> 2000000 | H98: ='BS Dec KSA'!H98+'BS Dec USA'!H98 -> 2000000 | I98: ='BS Dec KSA'!I98+'BS Dec USA'!I98 -> 2000000 | J98: ='BS Dec KSA'!J98+'BS Dec USA'!J98 -> 2000000 | ... N98: ='BS Dec KSA'!N98+'BS Dec USA'!N98 -> 2000000
B99: Arbah Murabaha Facility | C99: ='BS Dec KSA'!C99+'BS Dec USA'!C99 -> 20500000 | D99: ='BS Dec KSA'!D99+'BS Dec USA'!D99 -> 20500000 | E99: ='BS Dec KSA'!E99+'BS Dec USA'!E99 -> 10500000
B102: TOTAL CURRENT LIABILITIES | C102: =+C96+C77 -> 24214081 | D102: =+D96+D77 -> 23968336 | E102: =+E96+E77 -> 21909583 | F102: =+F96+F77 -> 3656628.7 | G102: =+G96+G77 -> 3620570.6 | H102: =+H96+H77 -> 3702538.7 | I102: =+I96+I77 -> 4686329.7 | J102: =+J96+J77 -> 3325032.1 | ... N102: =+N96+N77 -> 3061468.9
B105: Related parties | C105: 0 | D105: 0 | E105: 0 | F105: 7949418.5 | G105: 7949412.1 | H105: 7949334.5 | I105: 7949334.5 | J105: 7950109.3 | K105: 7950109.3 | L105: 7950109.3 | M105: 7950109.3 | N105: 7209302.1
B107: External Debt Investor | C107: ='BS Dec KSA'!C107+'BS Dec USA'!C107 -> 6243367.2 | D107: ='BS Dec KSA'!D107+'BS Dec USA'!D107 -> 6243367.2 | E107: ='BS Dec KSA'!E107+'BS Dec USA'!E107 -> 6807067.2 | F107: ='BS Dec KSA'!F107+'BS Dec USA'!F107 -> 6807067.2 | G107: ='BS Dec KSA'!G107+'BS Dec USA'!G107 -> 6807067.2 | H107: ='BS Dec KSA'!H107+'BS Dec USA'!H107 -> 6807067.2 | I107: ='BS Dec KSA'!I107+'BS Dec USA'!I107 -> 6807067.2 | J107: ='BS Dec KSA'!J107+'BS Dec USA'!J107 -> 1186567.2 | ... N107: ='BS Dec KSA'!N107+'BS Dec USA'!N107 -> 0
B109: End of Service Indemnity | C109: ='BS Dec KSA'!C109+'BS Dec USA'!C109 -> 139978.12 | D109: ='BS Dec KSA'!D109+'BS Dec USA'!D109 -> 33406.83 | E109: ='BS Dec KSA'!E109+'BS Dec USA'!E109 -> 33406.83 | F109: ='BS Dec KSA'!F109+'BS Dec USA'!F109 -> 33406.83 | G109: ='BS Dec KSA'!G109+'BS Dec USA'!G109 -> 33406.83 | H109: ='BS Dec KSA'!H109+'BS Dec USA'!H109 -> 33406.83 | I109: ='BS Dec KSA'!I109+'BS Dec USA'!I109 -> 33406.83 | J109: ='BS Dec KSA'!J109+'BS Dec USA'!J109 -> 33406.83 | ... N109: ='BS Dec KSA'!N109+'BS Dec USA'!N109 -> 33406.83
B111: TOTAL LONG-TERM LIABILITIES | C111: =+C109+C105+C107 -> 6383345.3 | D111: =+D109+D105+D107 -> 6276774 | E111: =+E109+E105+E107 -> 6840474 | F111: =+F109+F105+F107 -> 14789893 | G111: =+G109+G105+G107 -> 14789886 | H111: =+H109+H105+H107 -> 14789809 | I111: =+I109+I105+I107 -> 14789809 | J111: =+J109+J105+J107 -> 9170083.4 | ... M111: =+M109+M105+M107 -> 7983516.2 | N111: =+N109+N105 -> 7242709
B114: Equity Financing | C114: ='BS Dec KSA'!C114+'BS Dec USA'!C114 -> 25257006 | D114: ='BS Dec KSA'!D114+'BS Dec USA'!D114 -> 25257006 | E114: ='BS Dec KSA'!E114+'BS Dec USA'!E114 -> 25257006 | F114: ='BS Dec KSA'!F114+'BS Dec USA'!F114 -> 25257006 | G114: ='BS Dec KSA'!G114+'BS Dec USA'!G114 -> 25257006 | H114: ='BS Dec KSA'!H114+'BS Dec USA'!H114 -> 25257006 | I114: ='BS Dec KSA'!I114+'BS Dec USA'!I114 -> 24254910 | J114: ='BS Dec KSA'!J114+'BS Dec USA'!J114 -> 24254910 | ... N114: ='BS Dec KSA'!N114+'BS Dec USA'!N114 -> 24254910
B116: Contribution from Owners | C116: ='BS Dec KSA'!C116+'BS Dec USA'!C116 -> 25000 | D116: ='BS Dec KSA'!D116+'BS Dec USA'!D116 -> 25000 | E116: ='BS Dec KSA'!E116+'BS Dec USA'!E116 -> 25000 | F116: ='BS Dec KSA'!F116+'BS Dec USA'!F116 -> 25000 | G116: ='BS Dec KSA'!G116+'BS Dec USA'!G116 -> 25000 | H116: ='BS Dec KSA'!H116+'BS Dec USA'!H116 -> 25000 | I116: ='BS Dec KSA'!I116+'BS Dec USA'!I116 -> 25000 | J116: ='BS Dec KSA'!J116+'BS Dec USA'!J116 -> 25000 | ... N116: ='BS Dec KSA'!N116+'BS Dec USA'!N116 -> 25000
B118: Statutory Reserve | C118: ='BS Dec KSA'!C118+'BS Dec USA'!C118 -> 7500 | D118: ='BS Dec KSA'!D118+'BS Dec USA'!D118 -> 7500 | E118: ='BS Dec KSA'!E118+'BS Dec USA'!E118 -> 7500 | F118: ='BS Dec KSA'!F118+'BS Dec USA'!F118 -> 7500 | G118: ='BS Dec KSA'!G118+'BS Dec USA'!G118 -> 7500 | H118: ='BS Dec KSA'!H118+'BS Dec USA'!H118 -> 7500 | I118: ='BS Dec KSA'!I118+'BS Dec USA'!I118 -> 7500 | J118: ='BS Dec KSA'!J118+'BS Dec USA'!J118 -> 7500 | ... N118: ='BS Dec KSA'!N118+'BS Dec USA'!N118 -> 7500
B120: Profit & Loss for the period | C120: ='BS Dec KSA'!C120+'BS Dec USA'!C120 -> -2847594 | D120: ='BS Dec KSA'!D120+'BS Dec USA'!D120 -> -2634383.2 | E120: ='BS Dec KSA'!E120+'BS Dec USA'!E120 -> -2370988.2 | F120: ='BS Dec KSA'!F120+'BS Dec USA'!F120 -> -1670631 | G120: ='BS Dec KSA'!G120+'BS Dec USA'!G120 -> -1141743.6 | H120: ='BS Dec KSA'!H120+'BS Dec USA'!H120 -> -706732.4 | I120: ='BS Dec KSA'!I120+'BS Dec USA'!I120 -> -751970.34 | J120: ='BS Dec KSA'!J120+'BS Dec USA'!J120 -> -682653.43 | ... N120: ='BS Dec KSA'!N120+'BS Dec USA'!N120 -> -234687.92
B122: Retained Earnings/(Accumulated Losses) | C122: ='BS Dec KSA'!C122+'BS Dec USA'!C122 -> 222138.28 | D122: ='BS Dec KSA'!D122+'BS Dec USA'!D122 -> 222138.28 | E122: ='BS Dec KSA'!E122+'BS Dec USA'!E122 -> 222138.28 | F122: ='BS Dec KSA'!F122+'BS Dec USA'!F122 -> 222138.28 | G122: ='BS Dec KSA'!G122+'BS Dec USA'!G122 -> 222138.28 | H122: ='BS Dec KSA'!H122+'BS Dec USA'!H122 -> 222138.28 | I122: ='BS Dec KSA'!I122+'BS Dec USA'!I122 -> 222138.28 | J122: ='BS Dec KSA'!J122+'BS Dec USA'!J122 -> 222138.28 | ... N122: ='BS Dec KSA'!N122+'BS Dec USA'!N122 -> 222138.28
B124: TOTAL OWNER'S EQUITY | C124: =+C114+C118+C120+C122+C116 -> 22664050 | D124: =+D114+D118+D120+D122+D116 -> 22877261 | E124: =+E114+E118+E120+E122+E116 -> 23140656 | F124: =+F114+F118+F120+F122+F116 -> 23841013 | G124: =+G114+G118+G120+G122+G116 -> 24369901 | H124: =+H114+H118+H120+H122+H116 -> 24804912 | I124: =+I114+I118+I120+I122+I116 -> 23757578 | J124: =+J114+J118+J120+J122+J116 -> 23826895 | ... N124: =+N114+N118+N120+N122+N116 -> 24274861
B127: TOTAL LIABILITIES & EQUITY | C127: =+C124+C102+C111 -> 53261477 | D127: =+D124+D102+D111 -> 53122372 | E127: =+E124+E102+E111 -> 51890713 | F127: =+F124+F102+F111 -> 42287535 | G127: =+G124+G102+G111 -> 42780358 | H127: =+H124+H102+H111 -> 43297259 | I127: =+I124+I102+I111 -> 43233717 | J127: =+J124+J102+J111 -> 36322011 | ... N127: =+N124+N102+N111 -> 34579039
C128: =+C127-C72 -> -0.36 | D128: =+D127-D72 -> 0 | E128: =+E127-E72 -> 0 | F128: =+F127-F72 -> 0 | G128: =+G127-G72 -> 0 | H128: =+H127-H72 -> 0 | I128: =+I127-I72 -> 0 | J128: =+J127-J72 -> 0 | ... N128: =+N127-N72 -> 0

Sheet Cash Flow Consolidated
A1: Account | B1: Total
A2: Beginning Cash Balance | B2: ='BS Dec Consolidated'!D10 -> 15983087
A4: Cash Flow from Operating Activities
A5: Accounts Payable | B5: 483022.53
A6: Accounts Receivable | B6: -3845495
A7: Accrued Expenses | B7: 26896.98
A8: GOSI Payable | B8: -405.42
A9: Salaries & Wages Payables | B9: -38587.75
A10: Accrued Investor Profit | B10: -476008.84
A11: Employee Advance | B11: -19808.56
A12: Employee Reimbursements | B12: -716.48
A13: End of Service Benefits Payable | B13: 106571.29
A14: GCC VAT Payable | B14: 42721.92
A15: Input VAT | B15: 0
A16: Net Income | B16: -213210.84
... A30: Profit Payable (STV) | B30: 17850.51
A33: Net cash provided by Operating Activities | B33: =SUM(B4:B32) -> -3527269.7 | C33: =B33-[14]CF!$C$56 -> 0
A36: Cash Flow from Investing Activities
A37: Accumulated Depreciation - Furniture & Fixture | B37: 1314.47
A38: Accumulated Depreciation - Motor Vehicle | B38: -20204.15
A39: Accumulated Depreciation - Office Equipment's | B39: 5484.24
A40: Capital Work in Progress | B40: -77851.11
A41: Office Equipment | B41: -7428.69 | C41: =B41 -> -7428.69
A42: Motor Vehicle | B42: 52521.74
A43: Buildnow Inc. (US) | B43: -7500
A44: MISA KSA | B44: -2000
A47: Net cash provided by Investing Activities | B47: =SUM(B37:B45) -> -55663.5
A50: Cash Flow from Financing Activities
A51: STV Debt
A52: Related Party (Loan) US | B52: 49465.83
A53: Related parties Loan KSA | B53: 7368.01
A54: Arbah Murabaha Facility
A57: Net cash provided by Financing Activities | B57: =SUM(B51:B55) -> 56833.84
A60: Net Change in cash | B60: =+B33+B47+B57 -> -3526099.4
A61: Ending Cash Balance | B61: =+B2+B60 -> 12456987
B62: =B61-'BS Dec Consolidated'!C10 -> 0

Sheet AR Aging
A1: Sl. No. | B1: Customer | C1: Current | D1: 1-30 Days | E1: 31-60 Days | F1: 61-90 Days | G1: 91-180 Days | H1: Above 180 Days | I1: Total AR
A2: 1 | B2: Abraj Al Madaen Contracting Company | C2: 0 | D2: 0 | E2: 0 | F2: 0 | G2: 0 | H2: 244984.2 | I2: =SUM(C2:H2) -> 244984.2
A3: =+A2+1 -> 2 | B3: Al Mosleh Corner For Cont. | C3: 351791.97 | D3: 0 | E3: 0 | F3: 0 | G3: 0 | H3: 0 | I3: =SUM(C3:H3) -> 351791.97
A4: =+A3+1 -> 3 | B4: Bait Al Jazira Trading & Contracting | C4: 0 | D4: 0 | E4: 0 | F4: 0 | G4: 0 | H4: 330605.84 | I4: =SUM(C4:H4) -> 330605.84
A5: =+A4+1 -> 4 | B5: Clean Technologies Contracting Co. | C5: 272901.19 | D5: 0 | E5: 0 | F5: 0 | G5: 0 | H5: 0 | I5: =SUM(C5:H5) -> 272901.19
A6: =+A5+1 -> 5 | B6: Dur Arabia Company Limited | C6: 0 | D6: 0 | E6: 0 | F6: 0 | G6: 307888.35 | H6: 0 | I6: =SUM(C6:H6) -> 307888.35
A7: =+A6+1 -> 6 | B7: Factory Ercon Middle East Industries Saudi Co | C7: 1101666.7 | D7: 0 | E7: 0 | F7: 0 | G7: 0 | H7: 0 | I7: =SUM(C7:H7) -> 1101666.7
A8: =+A7+1 -> 7 | B8: Inshaat Al Awtan General Contracting Co | C8: 0 | D8: 0 | E8: 0 | F8: 0 | G8: 0 | H8: 458771.84 | I8: =SUM(C8:H8) -> 458771.84
A9: =+A8+1 -> 8 | B9: Jawahr Al-Hadid Est. | C9: 0 | D9: 0 | E9: 0 | F9: 880187 | G9: 1093211.2 | H9: 0 | I9: =SUM(C9:H9) -> 1973398.2
A10: =+A9+1 -> 9 | B10: Leader Wolf General Contracting | C10: 0 | D10: 0 | E10: 0 | F10: 0 | G10: 0 | H10: 111605.09 | I10: =SUM(C10:H10) -> 111605.09
A11: =+A10+1 -> 10 | B11: Modern Housing Contracting Company | C11: 0 | D11: 0 | E11: 0 | F11: 0 | G11: 636601.91 | H11: 0 | I11: =SUM(C11:H11) -> 636601.91
A12: =+A11+1 -> 11 | B12: Monaqsat Al Khaleej For Communication & Information Technology | C12: 0 | D12: 139937.78 | E12: 0 | F12: 0 | G12: 0 | H12: 0 | I12: =SUM(C12:H12) -> 139937.78
A13: =+A12+1 -> 12 | B13: Nipras Steel Factory | C13: 0 | D13: 0 | E13: 0 | F13: 0 | G13: 0 | H13: 1206185.2 | I13: =SUM(C13:H13) -> 1206185.2
A14: =+A13+1 -> 13 | B14: Rahat's Test Account | C14: 0 | D14: 0 | E14: 0 | F14: 0 | G14: 0 | H14: 12.65 | I14: =SUM(C14:H14) -> 12.65
... A60: =+A59+1 -> 59 | B60: فرع شركة اوفرسيزر كونستركشن كومباني برايفت ليمتد | C60: 0 | D60: 0 | E60: 0 | F60: 0 | G60: 0 | H60: 409500.4 | I60: =SUM(C60:H60) -> 409500.4
C61: =SUM(C2:C60) -> 26921103 | D61: =SUM(D2:D60) -> 2915387.9 | E61: =SUM(E2:E60) -> 1457712.9 | F61: =SUM(F2:F60) -> 880187 | G61: =SUM(G2:G60) -> 3358290.5 | H61: =SUM(H2:H60) -> 4060090 | I61: =SUM(I2:I60) -> 39592772
G63: 0
D64: Receivable Grade | E64: Amount (Mil) | F64: % of Total
D65: Current | E65: =C61/1000000 -> 26.921103 | F65: =E65/$E$71 -> 0.67994996
D66: =D1 -> 1-30 Days | E66: =D61/1000000 -> 2.9153879 | F66: =E66/$E$71 -> 0.073634349
D67: =E1 -> 31-60 Days | E67: =E61/1000000 -> 1.4577129 | F67: =E67/$E$71 -> 0.036817652
D68: =F1 -> 61-90 Days | E68: =F61/1000000 -> 0.880187 | F68: =E68/$E$71 -> 0.022231002
D69: =G1 -> 91-180 Days | E69: =G61/1000000 -> 3.3582905 | F69: =E69/$E$71 -> 0.084820798
D70: =H1 -> Above 180 Days | E70: =H61/1000000 -> 4.06009 | F70: =E70/$E$71 -> 0.10254624
D71: Total | E71: =SUM(E65:E70) -> 39.592772 | F71: =E71/$E$71 -> 1

Sheet Sheet1
C11: Debt | D11: =(37307067-8000000)/3.75 -> 7815217.9
C12: Equity | D12: 6766656.7 | E12: =D11/D12 -> 1.15496

Sheet Dinar Data June FS
A1: Dinar & Cash Sales Projections
A2: Scenario | B2: Dinar & Cash Sales | C2: 45292 | D2: 45323 | E2: 45352 | F2: 45383 | G2: 45413 | H2: 45444 | I2: 45474 | J2: 45505 | K2: 45536 | L2: 45566 | M2: 45597 | N2: 45627 | O2: 45658 | P2: 45689 | Q2: 45717 | R2: 45748 | S2: 45778 | T2: 45809 | U2: 45839 | V2: 45870 | W2: 45901 | X2: 45931 | Y2: 45962 | Z2: 45992 | AA2: 46023 | AB2: 46054 | AC2: 46082 | AD2: 46113 | AE2: 46143 | AF2: 46174 | AG2: 46204 | AH2: 46235 | AI2: 46266 | AJ2: 46296 | AK2: 46327 | AL2: 46357
A3: Best | B3: Dinar deals | C3: 12000000 | D3: 9000000 | E3: 9000000 | F3: 9000000 | G3: 15000000 | H3: 15000000 | I3: 21000000 | J3: 21000000 | K3: 21000000 | L3: 21000000 | M3: 24000000 | N3: 24000000 | O3: 12000000 | P3: 9000000 | Q3: 9000000 | R3: 9000000 | S3: 15000000 | T3: 15000000 | U3: 21000000 | V3: 21000000 | W3: 21000000 | X3: 21000000 | Y3: 24000000 | Z3: 24000000 | AA3: 12000000 | AB3: 9000000 | AC3: 9000000 | AD3: 9000000 | AE3: 15000000 | AF3: 15000000 | AG3: 21000000 | AH3: 21000000 | AI3: 21000000 | AJ3: 21000000 | AK3: 24000000 | AL3: 24000000
A4: Best | B4: Cash deals | C4: 2000000 | D4: 3200000 | E4: 2800000 | F4: 2800000 | G4: 4000000 | H4: 8000000 | I4: 8000000 | J4: 12000000 | K4: 12000000 | L4: 12000000 | M4: 16000000 | N4: 16000000 | O4: 2000000 | P4: 3200000 | Q4: 2800000 | R4: 2800000 | S4: 4000000 | T4: 8000000 | U4: 8000000 | V4: 12000000 | W4: 12000000 | X4: 12000000 | Y4: 16000000 | Z4: 16000000 | AA4: 2000000 | AB4: 3200000 | AC4: 2800000 | AD4: 2800000 | AE4: 4000000 | AF4: 8000000 | AG4: 8000000 | AH4: 12000000 | AI4: 12000000 | AJ4: 12000000 | AK4: 16000000 | AL4: 16000000
A5: Worst | B5: Dinar deals | C5: =C3/4 -> 3000000 | D5: =D3/4 -> 2250000 | E5: =E3/4 -> 2250000 | F5: =F3/4 -> 2250000 | G5: =G3/4 -> 3750000 | H5: =H3/4 -> 3750000 | I5: =I3/4 -> 5250000 | J5: =J3/4 -> 5250000 | ... AL5: =AL3/4 -> 6000000
A6: Worst | B6: Cash deals | C6: =C4/4 -> 500000 | D6: =D4/4 -> 800000 | E6: =E4/4 -> 700000 | F6: =F4/4 -> 700000 | G6: =G4/4 -> 1000000 | H6: =H4/4 -> 2000000 | I6: =I4/4 -> 2000000 | J6: =J4/4 -> 3000000 | ... AL6: =AL4/4 -> 4000000
A7: Base | B7: Dinar deals | C7: =C3/2 -> 6000000 | D7: =D3/2 -> 4500000 | E7: =E3/2 -> 4500000 | F7: =F3/2 -> 4500000 | G7: =G3/2 -> 7500000 | H7: =H3/2 -> 7500000 | I7: =I3/2 -> 10500000 | J7: =J3/2 -> 10500000 | ... AL7: =AL3/2 -> 12000000
A8: Base | B8: Cash deals | C8: =C4/2 -> 1000000 | D8: =D4/2 -> 1600000 | E8: =E4/2 -> 1400000 | F8: =F4/2 -> 1400000 | G8: =G4/2 -> 2000000 | H8: =H4/2 -> 4000000 | I8: =I4/2 -> 4000000 | J8: =J4/2 -> 6000000 | ... AL8: =AL4/2 -> 8000000
B11: Cash Profit Rate | C11: 0.01
B12: Dinar Commission Rate | C12: 0.0125
A15: Dinar & Cash Sales Commission Projections
A16: Scenario | B16: Dinar & Cash Sales | C16: 45292 | D16: 45323 | E16: 45352 | F16: 45383 | G16: 45413 | H16: 45444 | I16: 45474 | J16: 45505 | K16: 45536 | L16: 45566 | M16: 45597 | N16: 45627 | O16: 45658 | P16: 45689 | Q16: 45717 | R16: 45748 | S16: 45778 | T16: 45809 | U16: 45839 | V16: 45870 | W16: 45901 | X16: 45931 | Y16: 45962 | Z16: 45992 | AA16: 46023 | AB16: 46054 | AC16: 46082 | AD16: 46113 | AE16: 46143 | AF16: 46174 | AG16: 46204 | AH16: 46235 | AI16: 46266 | AJ16: 46296 | AK16: 46327 | AL16: 46357
A17: Best | B17: Dinar Commission | C17: =C$3*$C$12 -> 150000 | D17: =D$3*$C$12 -> 112500 | E17: =E$3*$C$12 -> 112500 | F17: =F$3*$C$12 -> 112500 | G17: =G$3*$C$12 -> 187500 | H17: =H$3*$C$12 -> 187500 | I17: =I$3*$C$12 -> 262500 | J17: =J$3*$C$12 -> 262500 | ... AL17: =AL$3*$C$12 -> 300000
A18: Best | B18: Cash Commission | C18: =C$4*$C$11 -> 20000 | D18: =D$4*$C$11 -> 32000 | E18: =E$4*$C$11 -> 28000 | F18: =F$4*$C$11 -> 28000 | G18: =G$4*$C$11 -> 40000 | H18: =H$4*$C$11 -> 80000 | I18: =I$4*$C$11 -> 80000 | J18: =J$4*$C$11 -> 120000 | ... AL18: =AL$4*$C$11 -> 160000
A19: Worst | B19: Dinar Commission | C19: =C$5*$C$12 -> 37500 | D19: =D$5*$C$12 -> 28125 | E19: =E$5*$C$12 -> 28125 | F19: =F$5*$C$12 -> 28125 | G19: =G$5*$C$12 -> 46875 | H19: =H$5*$C$12 -> 46875 | I19: =I$5*$C$12 -> 65625 | J19: =J$5*$C$12 -> 65625 | ... AL19: =AL$5*$C$12 -> 75000
A20: Worst | B20: Cash Commission | C20: =C$6*$C$11 -> 5000 | D20: =D$6*$C$11 -> 8000 | E20: =E$6*$C$11 -> 7000 | F20: =F$6*$C$11 -> 7000 | G20: =G$6*$C$11 -> 10000 | H20: =H$6*$C$11 -> 20000 | I20: =I$6*$C$11 -> 20000 | J20: =J$6*$C$11 -> 30000 | ... AL20: =AL$6*$C$11 -> 40000
A21: Base | B21: Dinar Commission | C21: =C$7*$C$12 -> 75000 | D21: =D$7*$C$12 -> 56250 | E21: =E$7*$C$12 -> 56250 | F21: =F$7*$C$12 -> 56250 | G21: =G$7*$C$12 -> 93750 | H21: =H$7*$C$12 -> 93750 | I21: =I$7*$C$12 -> 131250 | J21: =J$7*$C$12 -> 131250 | ... AL21: =AL$7*$C$12 -> 150000
A22: Base | B22: Cash Commission | C22: =C$8*$C$11 -> 10000 | D22: =D$8*$C$11 -> 16000 | E22: =E$8*$C$11 -> 14000 | F22: =F$8*$C$11 -> 14000 | G22: =G$8*$C$11 -> 20000 | H22: =H$8*$C$11 -> 40000 | I22: =I$8*$C$11 -> 40000 | J22: =J$8*$C$11 -> 60000 | ... AL22: =AL$8*$C$11 -> 80000
C25: =+C22+C8 -> 1010000 | D25: =+D22+D8 -> 1616000 | E25: =+E22+E8 -> 1414000 | F25: =+F22+F8 -> 1414000 | G25: =+G22+G8 -> 2020000 | H25: =+H22+H8 -> 4040000 | I25: =+I22+I8 -> 4040000 | J25: =+J22+J8 -> 6060000 | ... N25: =+N22+N8 -> 8080000
B26: Revenue | C26: =+C25/115*100 -> 878260.87 | D26: =+D25/115*100 -> 1405217.4 | E26: =+E25/115*100 -> 1229565.2 | F26: =+F25/115*100 -> 1229565.2 | G26: =+G25/115*100 -> 1756521.7 | H26: =+H25/115*100 -> 3513043.5 | I26: =+I25/115*100 -> 3513043.5 | J26: =+J25/115*100 -> 5269565.2 | ... N26: =+N25/115*100 -> 7026087
B27: COGS | C27: =+C8/115*100 -> 869565.22 | D27: =+D8/115*100 -> 1391304.3 | E27: =+E8/115*100 -> 1217391.3 | F27: =+F8/115*100 -> 1217391.3 | G27: =+G8/115*100 -> 1739130.4 | H27: =+H8/115*100 -> 3478260.9 | I27: =+I8/115*100 -> 3478260.9 | J27: =+J8/115*100 -> 5217391.3 | ... N27: =+N8/115*100 -> 6956521.7 | O27: =SUM(C27:N27) -> 42956522 | P27: 87976757 | Q27: =+O27+P27 -> 1.3093328e+08
D28: 1492147.5
D29: =+D26+D28 -> 2897364.9
